Workbook
Name ch1_cats: OFFSET(Calc_Charts!$A$66,0,0,MAX(1,COUNTIF(Calc_Charts!$B$66:$B$90,">0")),1)
Name ch1_seg01: OFFSET(Calc_Charts!$C$66,0,0,MAX(1,COUNTIF(Calc_Charts!$B$66:$B$90,">0")),1)
Name ch1_seg02: OFFSET(Calc_Charts!$D$66,0,0,MAX(1,COUNTIF(Calc_Charts!$B$66:$B$90,">0")),1)
Name ch1_seg03: OFFSET(Calc_Charts!$E$66,0,0,MAX(1,COUNTIF(Calc_Charts!$B$66:$B$90,">0")),1)
Name ch1_seg04: OFFSET(Calc_Charts!$F$66,0,0,MAX(1,COUNTIF(Calc_Charts!$B$66:$B$90,">0")),1)
Name ch1_seg05: OFFSET(Calc_Charts!$G$66,0,0,MAX(1,COUNTIF(Calc_Charts!$B$66:$B$90,">0")),1)
Name ch1_seg06: OFFSET(Calc_Charts!$H$66,0,0,MAX(1,COUNTIF(Calc_Charts!$B$66:$B$90,">0")),1)
Name ch1_seg07: OFFSET(Calc_Charts!$I$66,0,0,MAX(1,COUNTIF(Calc_Charts!$B$66:$B$90,">0")),1)
Name ch1_seg08: OFFSET(Calc_Charts!$J$66,0,0,MAX(1,COUNTIF(Calc_Charts!$B$66:$B$90,">0")),1)
Name ch1_seg09: OFFSET(Calc_Charts!$K$66,0,0,MAX(1,COUNTIF(Calc_Charts!$B$66:$B$90,">0")),1)
Name ch1_seg10: OFFSET(Calc_Charts!$L$66,0,0,MAX(1,COUNTIF(Calc_Charts!$B$66:$B$90,">0")),1)
Name ch1_seg11: OFFSET(Calc_Charts!$M$66,0,0,MAX(1,COUNTIF(Calc_Charts!$B$66:$B$90,">0")),1)
Name ch1_seg12: OFFSET(Calc_Charts!$N$66,0,0,MAX(1,COUNTIF(Calc_Charts!$B$66:$B$90,">0")),1)
Name ch1_seg13: OFFSET(Calc_Charts!$O$66,0,0,MAX(1,COUNTIF(Calc_Charts!$B$66:$B$90,">0")),1)
Name ch1_seg14: OFFSET(Calc_Charts!$P$66,0,0,MAX(1,COUNTIF(Calc_Charts!$B$66:$B$90,">0")),1)
Name ch1_seg15: OFFSET(Calc_Charts!$Q$66,0,0,MAX(1,COUNTIF(Calc_Charts!$B$66:$B$90,">0")),1)
Name ch1_seg16: OFFSET(Calc_Charts!$R$66,0,0,MAX(1,COUNTIF(Calc_Charts!$B$66:$B$90,">0")),1)
Name ch1_seg17: OFFSET(Calc_Charts!$S$66,0,0,MAX(1,COUNTIF(Calc_Charts!$B$66:$B$90,">0")),1)
Name ch1_seg18: OFFSET(Calc_Charts!$T$66,0,0,MAX(1,COUNTIF(Calc_Charts!$B$66:$B$90,">0")),1)
Name ch1_seg19: OFFSET(Calc_Charts!$U$66,0,0,MAX(1,COUNTIF(Calc_Charts!$B$66:$B$90,">0")),1)
Name ch1_seg20: OFFSET(Calc_Charts!$V$66,0,0,MAX(1,COUNTIF(Calc_Charts!$B$66:$B$90,">0")),1)
Name ch1_seg21: OFFSET(Calc_Charts!$W$66,0,0,MAX(1,COUNTIF(Calc_Charts!$B$66:$B$90,">0")),1)
Name ch1_seg22: OFFSET(Calc_Charts!$X$66,0,0,MAX(1,COUNTIF(Calc_Charts!$B$66:$B$90,">0")),1)
Name ch1_seg23: OFFSET(Calc_Charts!$Y$66,0,0,MAX(1,COUNTIF(Calc_Charts!$B$66:$B$90,">0")),1)
Name ch1_seg24: OFFSET(Calc_Charts!$Z$66,0,0,MAX(1,COUNTIF(Calc_Charts!$B$66:$B$90,">0")),1)
Name ch1_seg25: OFFSET(Calc_Charts!$AA$66,0,0,MAX(1,COUNTIF(Calc_Charts!$B$66:$B$90,">0")),1)
Name ch1_vals: OFFSET(Calc_Charts!$B$66,0,0,MAX(1,COUNTIF(Calc_Charts!$B$66:$B$90,">0")),1)
Name ch3_cats: OFFSET(Calc_Charts!$A$96,0,0,MAX(1,COUNTIF(Calc_Charts!$B$96:$B$120,">0")),1)
Name ch3_seg01: OFFSET(Calc_Charts!$C$96,0,0,MAX(1,COUNTIF(Calc_Charts!$B$96:$B$120,">0")),1)
Name ch3_seg02: OFFSET(Calc_Charts!$D$96,0,0,MAX(1,COUNTIF(Calc_Charts!$B$96:$B$120,">0")),1)
Name ch3_seg03: OFFSET(Calc_Charts!$E$96,0,0,MAX(1,COUNTIF(Calc_Charts!$B$96:$B$120,">0")),1)
Name ch3_seg04: OFFSET(Calc_Charts!$F$96,0,0,MAX(1,COUNTIF(Calc_Charts!$B$96:$B$120,">0")),1)
Name ch3_seg05: OFFSET(Calc_Charts!$G$96,0,0,MAX(1,COUNTIF(Calc_Charts!$B$96:$B$120,">0")),1)
Name ch3_seg06: OFFSET(Calc_Charts!$H$96,0,0,MAX(1,COUNTIF(Calc_Charts!$B$96:$B$120,">0")),1)
Name ch3_seg07: OFFSET(Calc_Charts!$I$96,0,0,MAX(1,COUNTIF(Calc_Charts!$B$96:$B$120,">0")),1)
Name ch3_seg08: OFFSET(Calc_Charts!$J$96,0,0,MAX(1,COUNTIF(Calc_Charts!$B$96:$B$120,">0")),1)
Name ch3_seg09: OFFSET(Calc_Charts!$K$96,0,0,MAX(1,COUNTIF(Calc_Charts!$B$96:$B$120,">0")),1)
Name ch3_seg10: OFFSET(Calc_Charts!$L$96,0,0,MAX(1,COUNTIF(Calc_Charts!$B$96:$B$120,">0")),1)
Name ch3_seg11: OFFSET(Calc_Charts!$M$96,0,0,MAX(1,COUNTIF(Calc_Charts!$B$96:$B$120,">0")),1)
Name ch3_seg12: OFFSET(Calc_Charts!$N$96,0,0,MAX(1,COUNTIF(Calc_Charts!$B$96:$B$120,">0")),1)
Name ch3_seg13: OFFSET(Calc_Charts!$O$96,0,0,MAX(1,COUNTIF(Calc_Charts!$B$96:$B$120,">0")),1)
Name ch3_seg14: OFFSET(Calc_Charts!$P$96,0,0,MAX(1,COUNTIF(Calc_Charts!$B$96:$B$120,">0")),1)
Name ch3_seg15: OFFSET(Calc_Charts!$Q$96,0,0,MAX(1,COUNTIF(Calc_Charts!$B$96:$B$120,">0")),1)
Name ch3_seg16: OFFSET(Calc_Charts!$R$96,0,0,MAX(1,COUNTIF(Calc_Charts!$B$96:$B$120,">0")),1)
Name ch3_seg17: OFFSET(Calc_Charts!$S$96,0,0,MAX(1,COUNTIF(Calc_Charts!$B$96:$B$120,">0")),1)
Name ch3_seg18: OFFSET(Calc_Charts!$T$96,0,0,MAX(1,COUNTIF(Calc_Charts!$B$96:$B$120,">0")),1)
Name ch3_seg19: OFFSET(Calc_Charts!$U$96,0,0,MAX(1,COUNTIF(Calc_Charts!$B$96:$B$120,">0")),1)
Name ch3_seg20: OFFSET(Calc_Charts!$V$96,0,0,MAX(1,COUNTIF(Calc_Charts!$B$96:$B$120,">0")),1)
Name ch3_seg21: OFFSET(Calc_Charts!$W$96,0,0,MAX(1,COUNTIF(Calc_Charts!$B$96:$B$120,">0")),1)
Name ch3_seg22: OFFSET(Calc_Charts!$X$96,0,0,MAX(1,COUNTIF(Calc_Charts!$B$96:$B$120,">0")),1)
Name ch3_seg23: OFFSET(Calc_Charts!$Y$96,0,0,MAX(1,COUNTIF(Calc_Charts!$B$96:$B$120,">0")),1)
Name ch3_seg24: OFFSET(Calc_Charts!$Z$96,0,0,MAX(1,COUNTIF(Calc_Charts!$B$96:$B$120,">0")),1)
Name ch3_seg25: OFFSET(Calc_Charts!$AA$96,0,0,MAX(1,COUNTIF(Calc_Charts!$B$96:$B$120,">0")),1)
Name ch3_vals: OFFSET(Calc_Charts!$B$96,0,0,MAX(1,COUNTIF(Calc_Charts!$B$96:$B$120,">0")),1)
Name ch5_after: OFFSET(Calc_Charts!$B$126,0,0,MAX(1,COUNTIF(Calc_Charts!$D$126:$D$150,">0")),1)
Name ch5_before: OFFSET(Calc_Charts!$C$126,0,0,MAX(1,COUNTIF(Calc_Charts!$D$126:$D$150,">0")),1)
Name ch5_cats: OFFSET(Calc_Charts!$A$126,0,0,MAX(1,COUNTIF(Calc_Charts!$D$126:$D$150,">0")),1)
Name ch5_seg01: OFFSET(Calc_Charts!$B$156,0,0,MAX(1,COUNTIF(Calc_Charts!$D$126:$D$150,">0")),1)
Name ch5_seg02: OFFSET(Calc_Charts!$C$156,0,0,MAX(1,COUNTIF(Calc_Charts!$D$126:$D$150,">0")),1)
Name ch5_seg03: OFFSET(Calc_Charts!$D$156,0,0,MAX(1,COUNTIF(Calc_Charts!$D$126:$D$150,">0")),1)

Sheet Dashboard
A1: DG Service-Call Dashboard Explore sheet: use slicers there for slice-and-dice; refresh pivot after new data.
A3: From | B3: 46174
A4: To | B4: 46218
A5: Period | B5: =Calc_Charts!$B$262 -> Jun 1 to Jul 15
A6: Checks needing review | B6: =COUNTIF('Data Checks'!C:C,"Review") -> 1
A124: Timeline - pick cause OR group:
A125: Timeline cause | B125: Communication problem
A126: Date basis | B126: Commission date

Sheet Explore
A1: Slice-and-dice. Slicers filter the chart and table live. Right-click Refresh after adding Summary rows.
A58: Row Labels | B58: Count of Work Order
A59: False Alarm | B59: 1
A60: Grand Total | B60: 1

Sheet Data Checks
A1: Check | B1: Count | C1: Status | D1: What to fix | E1: Formula scope
A2: Heatmap classified line reconciliation | B2: =SUM('Heatmap Calc'!$B$5:$T$30) -> 80 | C2: =IF(B2=SUMPRODUCT(--(Summary!$E$2:$E$240<>""),--ISNUMBER(MATCH(Summary!$E$2:$E$240,Settings!$A$4:$A$29,0)),--(Summary!$A$2:$A$240>=IF(Dashboard!$B$3="",0,Dashboard!$B$3)),--(Summary!$A$2:$A$240<IF(Dashboard!$B$4="",2958465,Dashboard!$B$4+1))),"OK","Review") -> OK | D2: Heatmap sum must equal classified Summary lines in the active Dashboard date window. | E2: Heatmap Calc vs Summary
A3: Root causes not in Settings | B3: =SUMPRODUCT(--(Summary!$E$2:$E$240<>""),--ISNA(MATCH(Summary!$E$2:$E$240,Settings!$A$4:$A$104,0))) -> 0 | C3: =IF(B3=0,"OK","Review") -> OK | D3: Pick a valid Root Cause from the dropdown. | E3: Summary vs Settings
A4: Clean-point daily chart reconciliation | B4: =SUM('Timeline Calc'!B8:B191) -> 4 | C4: =IF(B4=IF(ISNUMBER(MATCH(tl_cause,Settings!$B$4:$B$83,0)),COUNTIFS(Summary!$K$2:$K$240,tl_cause,Summary!$A$2:$A$240,">="&IF(Dashboard!$B$3="",0,Dashboard!$B$3),Summary!$A$2:$A$240,"<"&IF(Dashboard!$B$4="",2958465,Dashboard!$B$4+1)),COUNTIFS(Summary!$E$2:$E$240,tl_cause,Summary!$A$2:$A$240,">="&IF(Dashboard!$B$3="",0,Dashboard!$B$3),Summary!$A$2:$A$240,"<"&IF(Dashboard!$B$4="",2958465,Dashboard!$B$4+1))),"OK","Review") -> OK | D4: Timeline sum must equal selected cause/group rows in the Dashboard call-date window; basis only changes plotted dates. | E4: Timeline Calc vs Summary
A5: Explore pivot grand total reconciliation | B5: =GETPIVOTDATA("Work Order",Explore!$A$58) -> 1 | C5: =IF(B5=SUMPRODUCT(--(Summary!$E$2:$E$240<>"")),"OK","Review") -> Review | D5: Clear Explore slicers and refresh pivot if this shows Review. | E5: Explore Pivot vs Summary

Sheet Heatmap Calc
A1: Cause x week heatmap - source range for the linked picture on Dashboard. Format HERE, not on the picture.
A3: ="Issues by root cause x "&LOWER(hm_basis)&" week ("&Dashboard!$B$5&")" -> Issues by root cause x call date week (Jun 1 to Jul 15)
B4: =$B$41 -> 46174.419 | C4: =B4+7 -> 46181.419 | D4: =C4+7 -> 46188.419 | E4: =D4+7 -> 46195.419 | F4: =E4+7 -> 46202.419 | G4: =F4+7 -> 46209.419 | H4: =G4+7 -> 46216.419 | I4: =H4+7 -> 46223.419 | J4: =I4+7 -> 46230.419 | ... T4: =S4+7 -> 46300.419
A5: =IF(Settings!A4="","",Settings!A4) -> Ref. leak/ Low charge | B5: =IF($A5="","",IF(hm_basis="Call date",COUNTIFS(Summary!$E$2:$E$240,$A5,Summary!$A$2:$A$240,">="&B4,Summary!$A$2:$A$240,"<"&B4+7,Summary!$A$2:$A$240,">="&IF(Dashboard!$B$3="",0,Dashboard!$B$3),Summary!$A$2:$A$240,"<"&IF(Dashboard!$B$4="",2958465,Dashboard!$B$4+1)),COUNTIFS(Summary!$E$2:$E$240,$A5,Summary!$D$2:$D$240,">="&B4,Summary!$D$2:$D$240,"<"&B4+7,Summary!$A$2:$A$240,">="&IF(Dashboard!$B$3="",0,Dashboard!$B$3),Summary!$A$2:$A$240,"<"&IF(Dashboard!$B$4="",2958465,Dashboard!$B$4+1)))) -> 2 | C5: =IF($A5="","",IF(hm_basis="Call date",COUNTIFS(Summary!$E$2:$E$240,$A5,Summary!$A$2:$A$240,">="&C4,Summary!$A$2:$A$240,"<"&C4+7,Summary!$A$2:$A$240,">="&IF(Dashboard!$B$3="",0,Dashboard!$B$3),Summary!$A$2:$A$240,"<"&IF(Dashboard!$B$4="",2958465,Dashboard!$B$4+1)),COUNTIFS(Summary!$E$2:$E$240,$A5,Summary!$D$2:$D$240,">="&C4,Summary!$D$2:$D$240,"<"&C4+7,Summary!$A$2:$A$240,">="&IF(Dashboard!$B$3="",0,Dashboard!$B$3),Summary!$A$2:$A$240,"<"&IF(Dashboard!$B$4="",2958465,Dashboard!$B$4+1)))) -> 0 | D5: =IF($A5="","",IF(hm_basis="Call date",COUNTIFS(Summary!$E$2:$E$240,$A5,Summary!$A$2:$A$240,">="&D4,Summary!$A$2:$A$240,"<"&D4+7,Summary!$A$2:$A$240,">="&IF(Dashboard!$B$3="",0,Dashboard!$B$3),Summary!$A$2:$A$240,"<"&IF(Dashboard!$B$4="",2958465,Dashboard!$B$4+1)),COUNTIFS(Summary!$E$2:$E$240,$A5,Summary!$D$2:$D$240,">="&D4,Summary!$D$2:$D$240,"<"&D4+7,Summary!$A$2:$A$240,">="&IF(Dashboard!$B$3="",0,Dashboard!$B$3),Summary!$A$2:$A$240,"<"&IF(Dashboard!$B$4="",2958465,Dashboard!$B$4+1)))) -> 0 | E5: =IF($A5="","",IF(hm_basis="Call date",COUNTIFS(Summary!$E$2:$E$240,$A5,Summary!$A$2:$A$240,">="&E4,Summary!$A$2:$A$240,"<"&E4+7,Summary!$A$2:$A$240,">="&IF(Dashboard!$B$3="",0,Dashboard!$B$3),Summary!$A$2:$A$240,"<"&IF(Dashboard!$B$4="",2958465,Dashboard!$B$4+1)),COUNTIFS(Summary!$E$2:$E$240,$A5,Summary!$D$2:$D$240,">="&E4,Summary!$D$2:$D$240,"<"&E4+7,Summary!$A$2:$A$240,">="&IF(Dashboard!$B$3="",0,Dashboard!$B$3),Summary!$A$2:$A$240,"<"&IF(Dashboard!$B$4="",2958465,Dashboard!$B$4+1)))) -> 0 | F5: =IF($A5="","",IF(hm_basis="Call date",COUNTIFS(Summary!$E$2:$E$240,$A5,Summary!$A$2:$A$240,">="&F4,Summary!$A$2:$A$240,"<"&F4+7,Summary!$A$2:$A$240,">="&IF(Dashboard!$B$3="",0,Dashboard!$B$3),Summary!$A$2:$A$240,"<"&IF(Dashboard!$B$4="",2958465,Dashboard!$B$4+1)),COUNTIFS(Summary!$E$2:$E$240,$A5,Summary!$D$2:$D$240,">="&F4,Summary!$D$2:$D$240,"<"&F4+7,Summary!$A$2:$A$240,">="&IF(Dashboard!$B$3="",0,Dashboard!$B$3),Summary!$A$2:$A$240,"<"&IF(Dashboard!$B$4="",2958465,Dashboard!$B$4+1)))) -> 0 | G5: =IF($A5="","",IF(hm_basis="Call date",COUNTIFS(Summary!$E$2:$E$240,$A5,Summary!$A$2:$A$240,">="&G4,Summary!$A$2:$A$240,"<"&G4+7,Summary!$A$2:$A$240,">="&IF(Dashboard!$B$3="",0,Dashboard!$B$3),Summary!$A$2:$A$240,"<"&IF(Dashboard!$B$4="",2958465,Dashboard!$B$4+1)),COUNTIFS(Summary!$E$2:$E$240,$A5,Summary!$D$2:$D$240,">="&G4,Summary!$D$2:$D$240,"<"&G4+7,Summary!$A$2:$A$240,">="&IF(Dashboard!$B$3="",0,Dashboard!$B$3),Summary!$A$2:$A$240,"<"&IF(Dashboard!$B$4="",2958465,Dashboard!$B$4+1)))) -> 2 | H5: =IF($A5="","",IF(hm_basis="Call date",COUNTIFS(Summary!$E$2:$E$240,$A5,Summary!$A$2:$A$240,">="&H4,Summary!$A$2:$A$240,"<"&H4+7,Summary!$A$2:$A$240,">="&IF(Dashboard!$B$3="",0,Dashboard!$B$3),Summary!$A$2:$A$240,"<"&IF(Dashboard!$B$4="",2958465,Dashboard!$B$4+1)),COUNTIFS(Summary!$E$2:$E$240,$A5,Summary!$D$2:$D$240,">="&H4,Summary!$D$2:$D$240,"<"&H4+7,Summary!$A$2:$A$240,">="&IF(Dashboard!$B$3="",0,Dashboard!$B$3),Summary!$A$2:$A$240,"<"&IF(Dashboard!$B$4="",2958465,Dashboard!$B$4+1)))) -> 0 | I5: =IF($A5="","",IF(hm_basis="Call date",COUNTIFS(Summary!$E$2:$E$240,$A5,Summary!$A$2:$A$240,">="&I4,Summary!$A$2:$A$240,"<"&I4+7,Summary!$A$2:$A$240,">="&IF(Dashboard!$B$3="",0,Dashboard!$B$3),Summary!$A$2:$A$240,"<"&IF(Dashboard!$B$4="",2958465,Dashboard!$B$4+1)),COUNTIFS(Summary!$E$2:$E$240,$A5,Summary!$D$2:$D$240,">="&I4,Summary!$D$2:$D$240,"<"&I4+7,Summary!$A$2:$A$240,">="&IF(Dashboard!$B$3="",0,Dashboard!$B$3),Summary!$A$2:$A$240,"<"&IF(Dashboard!$B$4="",2958465,Dashboard!$B$4+1)))) -> 0 | ... T5: =IF($A5="","",IF(hm_basis="Call date",COUNTIFS(Summary!$E$2:$E$240,$A5,Summary!$A$2:$A$240,">="&T4,Summary!$A$2:$A$240,"<"&T4+7,Summary!$A$2:$A$240,">="&IF(Dashboard!$B$3="",0,Dashboard!$B$3),Summary!$A$2:$A$240,"<"&IF(Dashboard!$B$4="",2958465,Dashboard!$B$4+1)),COUNTIFS(Summary!$E$2:$E$240,$A5,Summary!$D$2:$D$240,">="&T4,Summary!$D$2:$D$240,"<"&T4+7,Summary!$A$2:$A$240,">="&IF(Dashboard!$B$3="",0,Dashboard!$B$3),Summary!$A$2:$A$240,"<"&IF(Dashboard!$B$4="",2958465,Dashboard!$B$4+1)))) -> 0
A6: =IF(Settings!A5="","",Settings!A5) -> Door Torque | B6: =IF($A6="","",IF(hm_basis="Call date",COUNTIFS(Summary!$E$2:$E$240,$A6,Summary!$A$2:$A$240,">="&B4,Summary!$A$2:$A$240,"<"&B4+7,Summary!$A$2:$A$240,">="&IF(Dashboard!$B$3="",0,Dashboard!$B$3),Summary!$A$2:$A$240,"<"&IF(Dashboard!$B$4="",2958465,Dashboard!$B$4+1)),COUNTIFS(Summary!$E$2:$E$240,$A6,Summary!$D$2:$D$240,">="&B4,Summary!$D$2:$D$240,"<"&B4+7,Summary!$A$2:$A$240,">="&IF(Dashboard!$B$3="",0,Dashboard!$B$3),Summary!$A$2:$A$240,"<"&IF(Dashboard!$B$4="",2958465,Dashboard!$B$4+1)))) -> 0 | C6: =IF($A6="","",IF(hm_basis="Call date",COUNTIFS(Summary!$E$2:$E$240,$A6,Summary!$A$2:$A$240,">="&C4,Summary!$A$2:$A$240,"<"&C4+7,Summary!$A$2:$A$240,">="&IF(Dashboard!$B$3="",0,Dashboard!$B$3),Summary!$A$2:$A$240,"<"&IF(Dashboard!$B$4="",2958465,Dashboard!$B$4+1)),COUNTIFS(Summary!$E$2:$E$240,$A6,Summary!$D$2:$D$240,">="&C4,Summary!$D$2:$D$240,"<"&C4+7,Summary!$A$2:$A$240,">="&IF(Dashboard!$B$3="",0,Dashboard!$B$3),Summary!$A$2:$A$240,"<"&IF(Dashboard!$B$4="",2958465,Dashboard!$B$4+1)))) -> 2 | D6: =IF($A6="","",IF(hm_basis="Call date",COUNTIFS(Summary!$E$2:$E$240,$A6,Summary!$A$2:$A$240,">="&D4,Summary!$A$2:$A$240,"<"&D4+7,Summary!$A$2:$A$240,">="&IF(Dashboard!$B$3="",0,Dashboard!$B$3),Summary!$A$2:$A$240,"<"&IF(Dashboard!$B$4="",2958465,Dashboard!$B$4+1)),COUNTIFS(Summary!$E$2:$E$240,$A6,Summary!$D$2:$D$240,">="&D4,Summary!$D$2:$D$240,"<"&D4+7,Summary!$A$2:$A$240,">="&IF(Dashboard!$B$3="",0,Dashboard!$B$3),Summary!$A$2:$A$240,"<"&IF(Dashboard!$B$4="",2958465,Dashboard!$B$4+1)))) -> 0 | E6: =IF($A6="","",IF(hm_basis="Call date",COUNTIFS(Summary!$E$2:$E$240,$A6,Summary!$A$2:$A$240,">="&E4,Summary!$A$2:$A$240,"<"&E4+7,Summary!$A$2:$A$240,">="&IF(Dashboard!$B$3="",0,Dashboard!$B$3),Summary!$A$2:$A$240,"<"&IF(Dashboard!$B$4="",2958465,Dashboard!$B$4+1)),COUNTIFS(Summary!$E$2:$E$240,$A6,Summary!$D$2:$D$240,">="&E4,Summary!$D$2:$D$240,"<"&E4+7,Summary!$A$2:$A$240,">="&IF(Dashboard!$B$3="",0,Dashboard!$B$3),Summary!$A$2:$A$240,"<"&IF(Dashboard!$B$4="",2958465,Dashboard!$B$4+1)))) -> 2 | F6: =IF($A6="","",IF(hm_basis="Call date",COUNTIFS(Summary!$E$2:$E$240,$A6,Summary!$A$2:$A$240,">="&F4,Summary!$A$2:$A$240,"<"&F4+7,Summary!$A$2:$A$240,">="&IF(Dashboard!$B$3="",0,Dashboard!$B$3),Summary!$A$2:$A$240,"<"&IF(Dashboard!$B$4="",2958465,Dashboard!$B$4+1)),COUNTIFS(Summary!$E$2:$E$240,$A6,Summary!$D$2:$D$240,">="&F4,Summary!$D$2:$D$240,"<"&F4+7,Summary!$A$2:$A$240,">="&IF(Dashboard!$B$3="",0,Dashboard!$B$3),Summary!$A$2:$A$240,"<"&IF(Dashboard!$B$4="",2958465,Dashboard!$B$4+1)))) -> 0 | G6: =IF($A6="","",IF(hm_basis="Call date",COUNTIFS(Summary!$E$2:$E$240,$A6,Summary!$A$2:$A$240,">="&G4,Summary!$A$2:$A$240,"<"&G4+7,Summary!$A$2:$A$240,">="&IF(Dashboard!$B$3="",0,Dashboard!$B$3),Summary!$A$2:$A$240,"<"&IF(Dashboard!$B$4="",2958465,Dashboard!$B$4+1)),COUNTIFS(Summary!$E$2:$E$240,$A6,Summary!$D$2:$D$240,">="&G4,Summary!$D$2:$D$240,"<"&G4+7,Summary!$A$2:$A$240,">="&IF(Dashboard!$B$3="",0,Dashboard!$B$3),Summary!$A$2:$A$240,"<"&IF(Dashboard!$B$4="",2958465,Dashboard!$B$4+1)))) -> 3 | H6: =IF($A6="","",IF(hm_basis="Call date",COUNTIFS(Summary!$E$2:$E$240,$A6,Summary!$A$2:$A$240,">="&H4,Summary!$A$2:$A$240,"<"&H4+7,Summary!$A$2:$A$240,">="&IF(Dashboard!$B$3="",0,Dashboard!$B$3),Summary!$A$2:$A$240,"<"&IF(Dashboard!$B$4="",2958465,Dashboard!$B$4+1)),COUNTIFS(Summary!$E$2:$E$240,$A6,Summary!$D$2:$D$240,">="&H4,Summary!$D$2:$D$240,"<"&H4+7,Summary!$A$2:$A$240,">="&IF(Dashboard!$B$3="",0,Dashboard!$B$3),Summary!$A$2:$A$240,"<"&IF(Dashboard!$B$4="",2958465,Dashboard!$B$4+1)))) -> 0 | I6: =IF($A6="","",IF(hm_basis="Call date",COUNTIFS(Summary!$E$2:$E$240,$A6,Summary!$A$2:$A$240,">="&I4,Summary!$A$2:$A$240,"<"&I4+7,Summary!$A$2:$A$240,">="&IF(Dashboard!$B$3="",0,Dashboard!$B$3),Summary!$A$2:$A$240,"<"&IF(Dashboard!$B$4="",2958465,Dashboard!$B$4+1)),COUNTIFS(Summary!$E$2:$E$240,$A6,Summary!$D$2:$D$240,">="&I4,Summary!$D$2:$D$240,"<"&I4+7,Summary!$A$2:$A$240,">="&IF(Dashboard!$B$3="",0,Dashboard!$B$3),Summary!$A$2:$A$240,"<"&IF(Dashboard!$B$4="",2958465,Dashboard!$B$4+1)))) -> 0 | ... T6: =IF($A6="","",IF(hm_basis="Call date",COUNTIFS(Summary!$E$2:$E$240,$A6,Summary!$A$2:$A$240,">="&T4,Summary!$A$2:$A$240,"<"&T4+7,Summary!$A$2:$A$240,">="&IF(Dashboard!$B$3="",0,Dashboard!$B$3),Summary!$A$2:$A$240,"<"&IF(Dashboard!$B$4="",2958465,Dashboard!$B$4+1)),COUNTIFS(Summary!$E$2:$E$240,$A6,Summary!$D$2:$D$240,">="&T4,Summary!$D$2:$D$240,"<"&T4+7,Summary!$A$2:$A$240,">="&IF(Dashboard!$B$3="",0,Dashboard!$B$3),Summary!$A$2:$A$240,"<"&IF(Dashboard!$B$4="",2958465,Dashboard!$B$4+1)))) -> 0
A7: =IF(Settings!A6="","",Settings!A6) -> Door Gasket | B7: =IF($A7="","",IF(hm_basis="Call date",COUNTIFS(Summary!$E$2:$E$240,$A7,Summary!$A$2:$A$240,">="&B4,Summary!$A$2:$A$240,"<"&B4+7,Summary!$A$2:$A$240,">="&IF(Dashboard!$B$3="",0,Dashboard!$B$3),Summary!$A$2:$A$240,"<"&IF(Dashboard!$B$4="",2958465,Dashboard!$B$4+1)),COUNTIFS(Summary!$E$2:$E$240,$A7,Summary!$D$2:$D$240,">="&B4,Summary!$D$2:$D$240,"<"&B4+7,Summary!$A$2:$A$240,">="&IF(Dashboard!$B$3="",0,Dashboard!$B$3),Summary!$A$2:$A$240,"<"&IF(Dashboard!$B$4="",2958465,Dashboard!$B$4+1)))) -> 0 | C7: =IF($A7="","",IF(hm_basis="Call date",COUNTIFS(Summary!$E$2:$E$240,$A7,Summary!$A$2:$A$240,">="&C4,Summary!$A$2:$A$240,"<"&C4+7,Summary!$A$2:$A$240,">="&IF(Dashboard!$B$3="",0,Dashboard!$B$3),Summary!$A$2:$A$240,"<"&IF(Dashboard!$B$4="",2958465,Dashboard!$B$4+1)),COUNTIFS(Summary!$E$2:$E$240,$A7,Summary!$D$2:$D$240,">="&C4,Summary!$D$2:$D$240,"<"&C4+7,Summary!$A$2:$A$240,">="&IF(Dashboard!$B$3="",0,Dashboard!$B$3),Summary!$A$2:$A$240,"<"&IF(Dashboard!$B$4="",2958465,Dashboard!$B$4+1)))) -> 2 | D7: =IF($A7="","",IF(hm_basis="Call date",COUNTIFS(Summary!$E$2:$E$240,$A7,Summary!$A$2:$A$240,">="&D4,Summary!$A$2:$A$240,"<"&D4+7,Summary!$A$2:$A$240,">="&IF(Dashboard!$B$3="",0,Dashboard!$B$3),Summary!$A$2:$A$240,"<"&IF(Dashboard!$B$4="",2958465,Dashboard!$B$4+1)),COUNTIFS(Summary!$E$2:$E$240,$A7,Summary!$D$2:$D$240,">="&D4,Summary!$D$2:$D$240,"<"&D4+7,Summary!$A$2:$A$240,">="&IF(Dashboard!$B$3="",0,Dashboard!$B$3),Summary!$A$2:$A$240,"<"&IF(Dashboard!$B$4="",2958465,Dashboard!$B$4+1)))) -> 0 | E7: =IF($A7="","",IF(hm_basis="Call date",COUNTIFS(Summary!$E$2:$E$240,$A7,Summary!$A$2:$A$240,">="&E4,Summary!$A$2:$A$240,"<"&E4+7,Summary!$A$2:$A$240,">="&IF(Dashboard!$B$3="",0,Dashboard!$B$3),Summary!$A$2:$A$240,"<"&IF(Dashboard!$B$4="",2958465,Dashboard!$B$4+1)),COUNTIFS(Summary!$E$2:$E$240,$A7,Summary!$D$2:$D$240,">="&E4,Summary!$D$2:$D$240,"<"&E4+7,Summary!$A$2:$A$240,">="&IF(Dashboard!$B$3="",0,Dashboard!$B$3),Summary!$A$2:$A$240,"<"&IF(Dashboard!$B$4="",2958465,Dashboard!$B$4+1)))) -> 1 | F7: =IF($A7="","",IF(hm_basis="Call date",COUNTIFS(Summary!$E$2:$E$240,$A7,Summary!$A$2:$A$240,">="&F4,Summary!$A$2:$A$240,"<"&F4+7,Summary!$A$2:$A$240,">="&IF(Dashboard!$B$3="",0,Dashboard!$B$3),Summary!$A$2:$A$240,"<"&IF(Dashboard!$B$4="",2958465,Dashboard!$B$4+1)),COUNTIFS(Summary!$E$2:$E$240,$A7,Summary!$D$2:$D$240,">="&F4,Summary!$D$2:$D$240,"<"&F4+7,Summary!$A$2:$A$240,">="&IF(Dashboard!$B$3="",0,Dashboard!$B$3),Summary!$A$2:$A$240,"<"&IF(Dashboard!$B$4="",2958465,Dashboard!$B$4+1)))) -> 0 | G7: =IF($A7="","",IF(hm_basis="Call date",COUNTIFS(Summary!$E$2:$E$240,$A7,Summary!$A$2:$A$240,">="&G4,Summary!$A$2:$A$240,"<"&G4+7,Summary!$A$2:$A$240,">="&IF(Dashboard!$B$3="",0,Dashboard!$B$3),Summary!$A$2:$A$240,"<"&IF(Dashboard!$B$4="",2958465,Dashboard!$B$4+1)),COUNTIFS(Summary!$E$2:$E$240,$A7,Summary!$D$2:$D$240,">="&G4,Summary!$D$2:$D$240,"<"&G4+7,Summary!$A$2:$A$240,">="&IF(Dashboard!$B$3="",0,Dashboard!$B$3),Summary!$A$2:$A$240,"<"&IF(Dashboard!$B$4="",2958465,Dashboard!$B$4+1)))) -> 0 | H7: =IF($A7="","",IF(hm_basis="Call date",COUNTIFS(Summary!$E$2:$E$240,$A7,Summary!$A$2:$A$240,">="&H4,Summary!$A$2:$A$240,"<"&H4+7,Summary!$A$2:$A$240,">="&IF(Dashboard!$B$3="",0,Dashboard!$B$3),Summary!$A$2:$A$240,"<"&IF(Dashboard!$B$4="",2958465,Dashboard!$B$4+1)),COUNTIFS(Summary!$E$2:$E$240,$A7,Summary!$D$2:$D$240,">="&H4,Summary!$D$2:$D$240,"<"&H4+7,Summary!$A$2:$A$240,">="&IF(Dashboard!$B$3="",0,Dashboard!$B$3),Summary!$A$2:$A$240,"<"&IF(Dashboard!$B$4="",2958465,Dashboard!$B$4+1)))) -> 0 | I7: =IF($A7="","",IF(hm_basis="Call date",COUNTIFS(Summary!$E$2:$E$240,$A7,Summary!$A$2:$A$240,">="&I4,Summary!$A$2:$A$240,"<"&I4+7,Summary!$A$2:$A$240,">="&IF(Dashboard!$B$3="",0,Dashboard!$B$3),Summary!$A$2:$A$240,"<"&IF(Dashboard!$B$4="",2958465,Dashboard!$B$4+1)),COUNTIFS(Summary!$E$2:$E$240,$A7,Summary!$D$2:$D$240,">="&I4,Summary!$D$2:$D$240,"<"&I4+7,Summary!$A$2:$A$240,">="&IF(Dashboard!$B$3="",0,Dashboard!$B$3),Summary!$A$2:$A$240,"<"&IF(Dashboard!$B$4="",2958465,Dashboard!$B$4+1)))) -> 0 | ... T7: =IF($A7="","",IF(hm_basis="Call date",COUNTIFS(Summary!$E$2:$E$240,$A7,Summary!$A$2:$A$240,">="&T4,Summary!$A$2:$A$240,"<"&T4+7,Summary!$A$2:$A$240,">="&IF(Dashboard!$B$3="",0,Dashboard!$B$3),Summary!$A$2:$A$240,"<"&IF(Dashboard!$B$4="",2958465,Dashboard!$B$4+1)),COUNTIFS(Summary!$E$2:$E$240,$A7,Summary!$D$2:$D$240,">="&T4,Summary!$D$2:$D$240,"<"&T4+7,Summary!$A$2:$A$240,">="&IF(Dashboard!$B$3="",0,Dashboard!$B$3),Summary!$A$2:$A$240,"<"&IF(Dashboard!$B$4="",2958465,Dashboard!$B$4+1)))) -> 0
A8: =IF(Settings!A7="","",Settings!A7) -> Door frame heater | B8: =IF($A8="","",IF(hm_basis="Call date",COUNTIFS(Summary!$E$2:$E$240,$A8,Summary!$A$2:$A$240,">="&B4,Summary!$A$2:$A$240,"<"&B4+7,Summary!$A$2:$A$240,">="&IF(Dashboard!$B$3="",0,Dashboard!$B$3),Summary!$A$2:$A$240,"<"&IF(Dashboard!$B$4="",2958465,Dashboard!$B$4+1)),COUNTIFS(Summary!$E$2:$E$240,$A8,Summary!$D$2:$D$240,">="&B4,Summary!$D$2:$D$240,"<"&B4+7,Summary!$A$2:$A$240,">="&IF(Dashboard!$B$3="",0,Dashboard!$B$3),Summary!$A$2:$A$240,"<"&IF(Dashboard!$B$4="",2958465,Dashboard!$B$4+1)))) -> 1 | C8: =IF($A8="","",IF(hm_basis="Call date",COUNTIFS(Summary!$E$2:$E$240,$A8,Summary!$A$2:$A$240,">="&C4,Summary!$A$2:$A$240,"<"&C4+7,Summary!$A$2:$A$240,">="&IF(Dashboard!$B$3="",0,Dashboard!$B$3),Summary!$A$2:$A$240,"<"&IF(Dashboard!$B$4="",2958465,Dashboard!$B$4+1)),COUNTIFS(Summary!$E$2:$E$240,$A8,Summary!$D$2:$D$240,">="&C4,Summary!$D$2:$D$240,"<"&C4+7,Summary!$A$2:$A$240,">="&IF(Dashboard!$B$3="",0,Dashboard!$B$3),Summary!$A$2:$A$240,"<"&IF(Dashboard!$B$4="",2958465,Dashboard!$B$4+1)))) -> 1 | D8: =IF($A8="","",IF(hm_basis="Call date",COUNTIFS(Summary!$E$2:$E$240,$A8,Summary!$A$2:$A$240,">="&D4,Summary!$A$2:$A$240,"<"&D4+7,Summary!$A$2:$A$240,">="&IF(Dashboard!$B$3="",0,Dashboard!$B$3),Summary!$A$2:$A$240,"<"&IF(Dashboard!$B$4="",2958465,Dashboard!$B$4+1)),COUNTIFS(Summary!$E$2:$E$240,$A8,Summary!$D$2:$D$240,">="&D4,Summary!$D$2:$D$240,"<"&D4+7,Summary!$A$2:$A$240,">="&IF(Dashboard!$B$3="",0,Dashboard!$B$3),Summary!$A$2:$A$240,"<"&IF(Dashboard!$B$4="",2958465,Dashboard!$B$4+1)))) -> 0 | E8: =IF($A8="","",IF(hm_basis="Call date",COUNTIFS(Summary!$E$2:$E$240,$A8,Summary!$A$2:$A$240,">="&E4,Summary!$A$2:$A$240,"<"&E4+7,Summary!$A$2:$A$240,">="&IF(Dashboard!$B$3="",0,Dashboard!$B$3),Summary!$A$2:$A$240,"<"&IF(Dashboard!$B$4="",2958465,Dashboard!$B$4+1)),COUNTIFS(Summary!$E$2:$E$240,$A8,Summary!$D$2:$D$240,">="&E4,Summary!$D$2:$D$240,"<"&E4+7,Summary!$A$2:$A$240,">="&IF(Dashboard!$B$3="",0,Dashboard!$B$3),Summary!$A$2:$A$240,"<"&IF(Dashboard!$B$4="",2958465,Dashboard!$B$4+1)))) -> 0 | F8: =IF($A8="","",IF(hm_basis="Call date",COUNTIFS(Summary!$E$2:$E$240,$A8,Summary!$A$2:$A$240,">="&F4,Summary!$A$2:$A$240,"<"&F4+7,Summary!$A$2:$A$240,">="&IF(Dashboard!$B$3="",0,Dashboard!$B$3),Summary!$A$2:$A$240,"<"&IF(Dashboard!$B$4="",2958465,Dashboard!$B$4+1)),COUNTIFS(Summary!$E$2:$E$240,$A8,Summary!$D$2:$D$240,">="&F4,Summary!$D$2:$D$240,"<"&F4+7,Summary!$A$2:$A$240,">="&IF(Dashboard!$B$3="",0,Dashboard!$B$3),Summary!$A$2:$A$240,"<"&IF(Dashboard!$B$4="",2958465,Dashboard!$B$4+1)))) -> 1 | G8: =IF($A8="","",IF(hm_basis="Call date",COUNTIFS(Summary!$E$2:$E$240,$A8,Summary!$A$2:$A$240,">="&G4,Summary!$A$2:$A$240,"<"&G4+7,Summary!$A$2:$A$240,">="&IF(Dashboard!$B$3="",0,Dashboard!$B$3),Summary!$A$2:$A$240,"<"&IF(Dashboard!$B$4="",2958465,Dashboard!$B$4+1)),COUNTIFS(Summary!$E$2:$E$240,$A8,Summary!$D$2:$D$240,">="&G4,Summary!$D$2:$D$240,"<"&G4+7,Summary!$A$2:$A$240,">="&IF(Dashboard!$B$3="",0,Dashboard!$B$3),Summary!$A$2:$A$240,"<"&IF(Dashboard!$B$4="",2958465,Dashboard!$B$4+1)))) -> 0 | H8: =IF($A8="","",IF(hm_basis="Call date",COUNTIFS(Summary!$E$2:$E$240,$A8,Summary!$A$2:$A$240,">="&H4,Summary!$A$2:$A$240,"<"&H4+7,Summary!$A$2:$A$240,">="&IF(Dashboard!$B$3="",0,Dashboard!$B$3),Summary!$A$2:$A$240,"<"&IF(Dashboard!$B$4="",2958465,Dashboard!$B$4+1)),COUNTIFS(Summary!$E$2:$E$240,$A8,Summary!$D$2:$D$240,">="&H4,Summary!$D$2:$D$240,"<"&H4+7,Summary!$A$2:$A$240,">="&IF(Dashboard!$B$3="",0,Dashboard!$B$3),Summary!$A$2:$A$240,"<"&IF(Dashboard!$B$4="",2958465,Dashboard!$B$4+1)))) -> 0 | I8: =IF($A8="","",IF(hm_basis="Call date",COUNTIFS(Summary!$E$2:$E$240,$A8,Summary!$A$2:$A$240,">="&I4,Summary!$A$2:$A$240,"<"&I4+7,Summary!$A$2:$A$240,">="&IF(Dashboard!$B$3="",0,Dashboard!$B$3),Summary!$A$2:$A$240,"<"&IF(Dashboard!$B$4="",2958465,Dashboard!$B$4+1)),COUNTIFS(Summary!$E$2:$E$240,$A8,Summary!$D$2:$D$240,">="&I4,Summary!$D$2:$D$240,"<"&I4+7,Summary!$A$2:$A$240,">="&IF(Dashboard!$B$3="",0,Dashboard!$B$3),Summary!$A$2:$A$240,"<"&IF(Dashboard!$B$4="",2958465,Dashboard!$B$4+1)))) -> 0 | ... T8: =IF($A8="","",IF(hm_basis="Call date",COUNTIFS(Summary!$E$2:$E$240,$A8,Summary!$A$2:$A$240,">="&T4,Summary!$A$2:$A$240,"<"&T4+7,Summary!$A$2:$A$240,">="&IF(Dashboard!$B$3="",0,Dashboard!$B$3),Summary!$A$2:$A$240,"<"&IF(Dashboard!$B$4="",2958465,Dashboard!$B$4+1)),COUNTIFS(Summary!$E$2:$E$240,$A8,Summary!$D$2:$D$240,">="&T4,Summary!$D$2:$D$240,"<"&T4+7,Summary!$A$2:$A$240,">="&IF(Dashboard!$B$3="",0,Dashboard!$B$3),Summary!$A$2:$A$240,"<"&IF(Dashboard!$B$4="",2958465,Dashboard!$B$4+1)))) -> 0
A9: =IF(Settings!A8="","",Settings!A8) -> Door Torsion rod | B9: =IF($A9="","",IF(hm_basis="Call date",COUNTIFS(Summary!$E$2:$E$240,$A9,Summary!$A$2:$A$240,">="&B4,Summary!$A$2:$A$240,"<"&B4+7,Summary!$A$2:$A$240,">="&IF(Dashboard!$B$3="",0,Dashboard!$B$3),Summary!$A$2:$A$240,"<"&IF(Dashboard!$B$4="",2958465,Dashboard!$B$4+1)),COUNTIFS(Summary!$E$2:$E$240,$A9,Summary!$D$2:$D$240,">="&B4,Summary!$D$2:$D$240,"<"&B4+7,Summary!$A$2:$A$240,">="&IF(Dashboard!$B$3="",0,Dashboard!$B$3),Summary!$A$2:$A$240,"<"&IF(Dashboard!$B$4="",2958465,Dashboard!$B$4+1)))) -> 0 | C9: =IF($A9="","",IF(hm_basis="Call date",COUNTIFS(Summary!$E$2:$E$240,$A9,Summary!$A$2:$A$240,">="&C4,Summary!$A$2:$A$240,"<"&C4+7,Summary!$A$2:$A$240,">="&IF(Dashboard!$B$3="",0,Dashboard!$B$3),Summary!$A$2:$A$240,"<"&IF(Dashboard!$B$4="",2958465,Dashboard!$B$4+1)),COUNTIFS(Summary!$E$2:$E$240,$A9,Summary!$D$2:$D$240,">="&C4,Summary!$D$2:$D$240,"<"&C4+7,Summary!$A$2:$A$240,">="&IF(Dashboard!$B$3="",0,Dashboard!$B$3),Summary!$A$2:$A$240,"<"&IF(Dashboard!$B$4="",2958465,Dashboard!$B$4+1)))) -> 0 | D9: =IF($A9="","",IF(hm_basis="Call date",COUNTIFS(Summary!$E$2:$E$240,$A9,Summary!$A$2:$A$240,">="&D4,Summary!$A$2:$A$240,"<"&D4+7,Summary!$A$2:$A$240,">="&IF(Dashboard!$B$3="",0,Dashboard!$B$3),Summary!$A$2:$A$240,"<"&IF(Dashboard!$B$4="",2958465,Dashboard!$B$4+1)),COUNTIFS(Summary!$E$2:$E$240,$A9,Summary!$D$2:$D$240,">="&D4,Summary!$D$2:$D$240,"<"&D4+7,Summary!$A$2:$A$240,">="&IF(Dashboard!$B$3="",0,Dashboard!$B$3),Summary!$A$2:$A$240,"<"&IF(Dashboard!$B$4="",2958465,Dashboard!$B$4+1)))) -> 0 | E9: =IF($A9="","",IF(hm_basis="Call date",COUNTIFS(Summary!$E$2:$E$240,$A9,Summary!$A$2:$A$240,">="&E4,Summary!$A$2:$A$240,"<"&E4+7,Summary!$A$2:$A$240,">="&IF(Dashboard!$B$3="",0,Dashboard!$B$3),Summary!$A$2:$A$240,"<"&IF(Dashboard!$B$4="",2958465,Dashboard!$B$4+1)),COUNTIFS(Summary!$E$2:$E$240,$A9,Summary!$D$2:$D$240,">="&E4,Summary!$D$2:$D$240,"<"&E4+7,Summary!$A$2:$A$240,">="&IF(Dashboard!$B$3="",0,Dashboard!$B$3),Summary!$A$2:$A$240,"<"&IF(Dashboard!$B$4="",2958465,Dashboard!$B$4+1)))) -> 0 | F9: =IF($A9="","",IF(hm_basis="Call date",COUNTIFS(Summary!$E$2:$E$240,$A9,Summary!$A$2:$A$240,">="&F4,Summary!$A$2:$A$240,"<"&F4+7,Summary!$A$2:$A$240,">="&IF(Dashboard!$B$3="",0,Dashboard!$B$3),Summary!$A$2:$A$240,"<"&IF(Dashboard!$B$4="",2958465,Dashboard!$B$4+1)),COUNTIFS(Summary!$E$2:$E$240,$A9,Summary!$D$2:$D$240,">="&F4,Summary!$D$2:$D$240,"<"&F4+7,Summary!$A$2:$A$240,">="&IF(Dashboard!$B$3="",0,Dashboard!$B$3),Summary!$A$2:$A$240,"<"&IF(Dashboard!$B$4="",2958465,Dashboard!$B$4+1)))) -> 1 | G9: =IF($A9="","",IF(hm_basis="Call date",COUNTIFS(Summary!$E$2:$E$240,$A9,Summary!$A$2:$A$240,">="&G4,Summary!$A$2:$A$240,"<"&G4+7,Summary!$A$2:$A$240,">="&IF(Dashboard!$B$3="",0,Dashboard!$B$3),Summary!$A$2:$A$240,"<"&IF(Dashboard!$B$4="",2958465,Dashboard!$B$4+1)),COUNTIFS(Summary!$E$2:$E$240,$A9,Summary!$D$2:$D$240,">="&G4,Summary!$D$2:$D$240,"<"&G4+7,Summary!$A$2:$A$240,">="&IF(Dashboard!$B$3="",0,Dashboard!$B$3),Summary!$A$2:$A$240,"<"&IF(Dashboard!$B$4="",2958465,Dashboard!$B$4+1)))) -> 0 | H9: =IF($A9="","",IF(hm_basis="Call date",COUNTIFS(Summary!$E$2:$E$240,$A9,Summary!$A$2:$A$240,">="&H4,Summary!$A$2:$A$240,"<"&H4+7,Summary!$A$2:$A$240,">="&IF(Dashboard!$B$3="",0,Dashboard!$B$3),Summary!$A$2:$A$240,"<"&IF(Dashboard!$B$4="",2958465,Dashboard!$B$4+1)),COUNTIFS(Summary!$E$2:$E$240,$A9,Summary!$D$2:$D$240,">="&H4,Summary!$D$2:$D$240,"<"&H4+7,Summary!$A$2:$A$240,">="&IF(Dashboard!$B$3="",0,Dashboard!$B$3),Summary!$A$2:$A$240,"<"&IF(Dashboard!$B$4="",2958465,Dashboard!$B$4+1)))) -> 0 | I9: =IF($A9="","",IF(hm_basis="Call date",COUNTIFS(Summary!$E$2:$E$240,$A9,Summary!$A$2:$A$240,">="&I4,Summary!$A$2:$A$240,"<"&I4+7,Summary!$A$2:$A$240,">="&IF(Dashboard!$B$3="",0,Dashboard!$B$3),Summary!$A$2:$A$240,"<"&IF(Dashboard!$B$4="",2958465,Dashboard!$B$4+1)),COUNTIFS(Summary!$E$2:$E$240,$A9,Summary!$D$2:$D$240,">="&I4,Summary!$D$2:$D$240,"<"&I4+7,Summary!$A$2:$A$240,">="&IF(Dashboard!$B$3="",0,Dashboard!$B$3),Summary!$A$2:$A$240,"<"&IF(Dashboard!$B$4="",2958465,Dashboard!$B$4+1)))) -> 0 | ... T9: =IF($A9="","",IF(hm_basis="Call date",COUNTIFS(Summary!$E$2:$E$240,$A9,Summary!$A$2:$A$240,">="&T4,Summary!$A$2:$A$240,"<"&T4+7,Summary!$A$2:$A$240,">="&IF(Dashboard!$B$3="",0,Dashboard!$B$3),Summary!$A$2:$A$240,"<"&IF(Dashboard!$B$4="",2958465,Dashboard!$B$4+1)),COUNTIFS(Summary!$E$2:$E$240,$A9,Summary!$D$2:$D$240,">="&T4,Summary!$D$2:$D$240,"<"&T4+7,Summary!$A$2:$A$240,">="&IF(Dashboard!$B$3="",0,Dashboard!$B$3),Summary!$A$2:$A$240,"<"&IF(Dashboard!$B$4="",2958465,Dashboard!$B$4+1)))) -> 0
A10: =IF(Settings!A9="","",Settings!A9) -> Door not closed (Overnight) | B10: =IF($A10="","",IF(hm_basis="Call date",COUNTIFS(Summary!$E$2:$E$240,$A10,Summary!$A$2:$A$240,">="&B4,Summary!$A$2:$A$240,"<"&B4+7,Summary!$A$2:$A$240,">="&IF(Dashboard!$B$3="",0,Dashboard!$B$3),Summary!$A$2:$A$240,"<"&IF(Dashboard!$B$4="",2958465,Dashboard!$B$4+1)),COUNTIFS(Summary!$E$2:$E$240,$A10,Summary!$D$2:$D$240,">="&B4,Summary!$D$2:$D$240,"<"&B4+7,Summary!$A$2:$A$240,">="&IF(Dashboard!$B$3="",0,Dashboard!$B$3),Summary!$A$2:$A$240,"<"&IF(Dashboard!$B$4="",2958465,Dashboard!$B$4+1)))) -> 1 | C10: =IF($A10="","",IF(hm_basis="Call date",COUNTIFS(Summary!$E$2:$E$240,$A10,Summary!$A$2:$A$240,">="&C4,Summary!$A$2:$A$240,"<"&C4+7,Summary!$A$2:$A$240,">="&IF(Dashboard!$B$3="",0,Dashboard!$B$3),Summary!$A$2:$A$240,"<"&IF(Dashboard!$B$4="",2958465,Dashboard!$B$4+1)),COUNTIFS(Summary!$E$2:$E$240,$A10,Summary!$D$2:$D$240,">="&C4,Summary!$D$2:$D$240,"<"&C4+7,Summary!$A$2:$A$240,">="&IF(Dashboard!$B$3="",0,Dashboard!$B$3),Summary!$A$2:$A$240,"<"&IF(Dashboard!$B$4="",2958465,Dashboard!$B$4+1)))) -> 1 | D10: =IF($A10="","",IF(hm_basis="Call date",COUNTIFS(Summary!$E$2:$E$240,$A10,Summary!$A$2:$A$240,">="&D4,Summary!$A$2:$A$240,"<"&D4+7,Summary!$A$2:$A$240,">="&IF(Dashboard!$B$3="",0,Dashboard!$B$3),Summary!$A$2:$A$240,"<"&IF(Dashboard!$B$4="",2958465,Dashboard!$B$4+1)),COUNTIFS(Summary!$E$2:$E$240,$A10,Summary!$D$2:$D$240,">="&D4,Summary!$D$2:$D$240,"<"&D4+7,Summary!$A$2:$A$240,">="&IF(Dashboard!$B$3="",0,Dashboard!$B$3),Summary!$A$2:$A$240,"<"&IF(Dashboard!$B$4="",2958465,Dashboard!$B$4+1)))) -> 4 | E10: =IF($A10="","",IF(hm_basis="Call date",COUNTIFS(Summary!$E$2:$E$240,$A10,Summary!$A$2:$A$240,">="&E4,Summary!$A$2:$A$240,"<"&E4+7,Summary!$A$2:$A$240,">="&IF(Dashboard!$B$3="",0,Dashboard!$B$3),Summary!$A$2:$A$240,"<"&IF(Dashboard!$B$4="",2958465,Dashboard!$B$4+1)),COUNTIFS(Summary!$E$2:$E$240,$A10,Summary!$D$2:$D$240,">="&E4,Summary!$D$2:$D$240,"<"&E4+7,Summary!$A$2:$A$240,">="&IF(Dashboard!$B$3="",0,Dashboard!$B$3),Summary!$A$2:$A$240,"<"&IF(Dashboard!$B$4="",2958465,Dashboard!$B$4+1)))) -> 2 | F10: =IF($A10="","",IF(hm_basis="Call date",COUNTIFS(Summary!$E$2:$E$240,$A10,Summary!$A$2:$A$240,">="&F4,Summary!$A$2:$A$240,"<"&F4+7,Summary!$A$2:$A$240,">="&IF(Dashboard!$B$3="",0,Dashboard!$B$3),Summary!$A$2:$A$240,"<"&IF(Dashboard!$B$4="",2958465,Dashboard!$B$4+1)),COUNTIFS(Summary!$E$2:$E$240,$A10,Summary!$D$2:$D$240,">="&F4,Summary!$D$2:$D$240,"<"&F4+7,Summary!$A$2:$A$240,">="&IF(Dashboard!$B$3="",0,Dashboard!$B$3),Summary!$A$2:$A$240,"<"&IF(Dashboard!$B$4="",2958465,Dashboard!$B$4+1)))) -> 4 | G10: =IF($A10="","",IF(hm_basis="Call date",COUNTIFS(Summary!$E$2:$E$240,$A10,Summary!$A$2:$A$240,">="&G4,Summary!$A$2:$A$240,"<"&G4+7,Summary!$A$2:$A$240,">="&IF(Dashboard!$B$3="",0,Dashboard!$B$3),Summary!$A$2:$A$240,"<"&IF(Dashboard!$B$4="",2958465,Dashboard!$B$4+1)),COUNTIFS(Summary!$E$2:$E$240,$A10,Summary!$D$2:$D$240,">="&G4,Summary!$D$2:$D$240,"<"&G4+7,Summary!$A$2:$A$240,">="&IF(Dashboard!$B$3="",0,Dashboard!$B$3),Summary!$A$2:$A$240,"<"&IF(Dashboard!$B$4="",2958465,Dashboard!$B$4+1)))) -> 1 | H10: =IF($A10="","",IF(hm_basis="Call date",COUNTIFS(Summary!$E$2:$E$240,$A10,Summary!$A$2:$A$240,">="&H4,Summary!$A$2:$A$240,"<"&H4+7,Summary!$A$2:$A$240,">="&IF(Dashboard!$B$3="",0,Dashboard!$B$3),Summary!$A$2:$A$240,"<"&IF(Dashboard!$B$4="",2958465,Dashboard!$B$4+1)),COUNTIFS(Summary!$E$2:$E$240,$A10,Summary!$D$2:$D$240,">="&H4,Summary!$D$2:$D$240,"<"&H4+7,Summary!$A$2:$A$240,">="&IF(Dashboard!$B$3="",0,Dashboard!$B$3),Summary!$A$2:$A$240,"<"&IF(Dashboard!$B$4="",2958465,Dashboard!$B$4+1)))) -> 0 | I10: =IF($A10="","",IF(hm_basis="Call date",COUNTIFS(Summary!$E$2:$E$240,$A10,Summary!$A$2:$A$240,">="&I4,Summary!$A$2:$A$240,"<"&I4+7,Summary!$A$2:$A$240,">="&IF(Dashboard!$B$3="",0,Dashboard!$B$3),Summary!$A$2:$A$240,"<"&IF(Dashboard!$B$4="",2958465,Dashboard!$B$4+1)),COUNTIFS(Summary!$E$2:$E$240,$A10,Summary!$D$2:$D$240,">="&I4,Summary!$D$2:$D$240,"<"&I4+7,Summary!$A$2:$A$240,">="&IF(Dashboard!$B$3="",0,Dashboard!$B$3),Summary!$A$2:$A$240,"<"&IF(Dashboard!$B$4="",2958465,Dashboard!$B$4+1)))) -> 0 | ... T10: =IF($A10="","",IF(hm_basis="Call date",COUNTIFS(Summary!$E$2:$E$240,$A10,Summary!$A$2:$A$240,">="&T4,Summary!$A$2:$A$240,"<"&T4+7,Summary!$A$2:$A$240,">="&IF(Dashboard!$B$3="",0,Dashboard!$B$3),Summary!$A$2:$A$240,"<"&IF(Dashboard!$B$4="",2958465,Dashboard!$B$4+1)),COUNTIFS(Summary!$E$2:$E$240,$A10,Summary!$D$2:$D$240,">="&T4,Summary!$D$2:$D$240,"<"&T4+7,Summary!$A$2:$A$240,">="&IF(Dashboard!$B$3="",0,Dashboard!$B$3),Summary!$A$2:$A$240,"<"&IF(Dashboard!$B$4="",2958465,Dashboard!$B$4+1)))) -> 0
A11: =IF(Settings!A10="","",Settings!A10) -> Door - general | B11: =IF($A11="","",IF(hm_basis="Call date",COUNTIFS(Summary!$E$2:$E$240,$A11,Summary!$A$2:$A$240,">="&B4,Summary!$A$2:$A$240,"<"&B4+7,Summary!$A$2:$A$240,">="&IF(Dashboard!$B$3="",0,Dashboard!$B$3),Summary!$A$2:$A$240,"<"&IF(Dashboard!$B$4="",2958465,Dashboard!$B$4+1)),COUNTIFS(Summary!$E$2:$E$240,$A11,Summary!$D$2:$D$240,">="&B4,Summary!$D$2:$D$240,"<"&B4+7,Summary!$A$2:$A$240,">="&IF(Dashboard!$B$3="",0,Dashboard!$B$3),Summary!$A$2:$A$240,"<"&IF(Dashboard!$B$4="",2958465,Dashboard!$B$4+1)))) -> 0 | C11: =IF($A11="","",IF(hm_basis="Call date",COUNTIFS(Summary!$E$2:$E$240,$A11,Summary!$A$2:$A$240,">="&C4,Summary!$A$2:$A$240,"<"&C4+7,Summary!$A$2:$A$240,">="&IF(Dashboard!$B$3="",0,Dashboard!$B$3),Summary!$A$2:$A$240,"<"&IF(Dashboard!$B$4="",2958465,Dashboard!$B$4+1)),COUNTIFS(Summary!$E$2:$E$240,$A11,Summary!$D$2:$D$240,">="&C4,Summary!$D$2:$D$240,"<"&C4+7,Summary!$A$2:$A$240,">="&IF(Dashboard!$B$3="",0,Dashboard!$B$3),Summary!$A$2:$A$240,"<"&IF(Dashboard!$B$4="",2958465,Dashboard!$B$4+1)))) -> 0 | D11: =IF($A11="","",IF(hm_basis="Call date",COUNTIFS(Summary!$E$2:$E$240,$A11,Summary!$A$2:$A$240,">="&D4,Summary!$A$2:$A$240,"<"&D4+7,Summary!$A$2:$A$240,">="&IF(Dashboard!$B$3="",0,Dashboard!$B$3),Summary!$A$2:$A$240,"<"&IF(Dashboard!$B$4="",2958465,Dashboard!$B$4+1)),COUNTIFS(Summary!$E$2:$E$240,$A11,Summary!$D$2:$D$240,">="&D4,Summary!$D$2:$D$240,"<"&D4+7,Summary!$A$2:$A$240,">="&IF(Dashboard!$B$3="",0,Dashboard!$B$3),Summary!$A$2:$A$240,"<"&IF(Dashboard!$B$4="",2958465,Dashboard!$B$4+1)))) -> 0 | E11: =IF($A11="","",IF(hm_basis="Call date",COUNTIFS(Summary!$E$2:$E$240,$A11,Summary!$A$2:$A$240,">="&E4,Summary!$A$2:$A$240,"<"&E4+7,Summary!$A$2:$A$240,">="&IF(Dashboard!$B$3="",0,Dashboard!$B$3),Summary!$A$2:$A$240,"<"&IF(Dashboard!$B$4="",2958465,Dashboard!$B$4+1)),COUNTIFS(Summary!$E$2:$E$240,$A11,Summary!$D$2:$D$240,">="&E4,Summary!$D$2:$D$240,"<"&E4+7,Summary!$A$2:$A$240,">="&IF(Dashboard!$B$3="",0,Dashboard!$B$3),Summary!$A$2:$A$240,"<"&IF(Dashboard!$B$4="",2958465,Dashboard!$B$4+1)))) -> 0 | F11: =IF($A11="","",IF(hm_basis="Call date",COUNTIFS(Summary!$E$2:$E$240,$A11,Summary!$A$2:$A$240,">="&F4,Summary!$A$2:$A$240,"<"&F4+7,Summary!$A$2:$A$240,">="&IF(Dashboard!$B$3="",0,Dashboard!$B$3),Summary!$A$2:$A$240,"<"&IF(Dashboard!$B$4="",2958465,Dashboard!$B$4+1)),COUNTIFS(Summary!$E$2:$E$240,$A11,Summary!$D$2:$D$240,">="&F4,Summary!$D$2:$D$240,"<"&F4+7,Summary!$A$2:$A$240,">="&IF(Dashboard!$B$3="",0,Dashboard!$B$3),Summary!$A$2:$A$240,"<"&IF(Dashboard!$B$4="",2958465,Dashboard!$B$4+1)))) -> 0 | G11: =IF($A11="","",IF(hm_basis="Call date",COUNTIFS(Summary!$E$2:$E$240,$A11,Summary!$A$2:$A$240,">="&G4,Summary!$A$2:$A$240,"<"&G4+7,Summary!$A$2:$A$240,">="&IF(Dashboard!$B$3="",0,Dashboard!$B$3),Summary!$A$2:$A$240,"<"&IF(Dashboard!$B$4="",2958465,Dashboard!$B$4+1)),COUNTIFS(Summary!$E$2:$E$240,$A11,Summary!$D$2:$D$240,">="&G4,Summary!$D$2:$D$240,"<"&G4+7,Summary!$A$2:$A$240,">="&IF(Dashboard!$B$3="",0,Dashboard!$B$3),Summary!$A$2:$A$240,"<"&IF(Dashboard!$B$4="",2958465,Dashboard!$B$4+1)))) -> 0 | H11: =IF($A11="","",IF(hm_basis="Call date",COUNTIFS(Summary!$E$2:$E$240,$A11,Summary!$A$2:$A$240,">="&H4,Summary!$A$2:$A$240,"<"&H4+7,Summary!$A$2:$A$240,">="&IF(Dashboard!$B$3="",0,Dashboard!$B$3),Summary!$A$2:$A$240,"<"&IF(Dashboard!$B$4="",2958465,Dashboard!$B$4+1)),COUNTIFS(Summary!$E$2:$E$240,$A11,Summary!$D$2:$D$240,">="&H4,Summary!$D$2:$D$240,"<"&H4+7,Summary!$A$2:$A$240,">="&IF(Dashboard!$B$3="",0,Dashboard!$B$3),Summary!$A$2:$A$240,"<"&IF(Dashboard!$B$4="",2958465,Dashboard!$B$4+1)))) -> 1 | I11: =IF($A11="","",IF(hm_basis="Call date",COUNTIFS(Summary!$E$2:$E$240,$A11,Summary!$A$2:$A$240,">="&I4,Summary!$A$2:$A$240,"<"&I4+7,Summary!$A$2:$A$240,">="&IF(Dashboard!$B$3="",0,Dashboard!$B$3),Summary!$A$2:$A$240,"<"&IF(Dashboard!$B$4="",2958465,Dashboard!$B$4+1)),COUNTIFS(Summary!$E$2:$E$240,$A11,Summary!$D$2:$D$240,">="&I4,Summary!$D$2:$D$240,"<"&I4+7,Summary!$A$2:$A$240,">="&IF(Dashboard!$B$3="",0,Dashboard!$B$3),Summary!$A$2:$A$240,"<"&IF(Dashboard!$B$4="",2958465,Dashboard!$B$4+1)))) -> 0 | ... T11: =IF($A11="","",IF(hm_basis="Call date",COUNTIFS(Summary!$E$2:$E$240,$A11,Summary!$A$2:$A$240,">="&T4,Summary!$A$2:$A$240,"<"&T4+7,Summary!$A$2:$A$240,">="&IF(Dashboard!$B$3="",0,Dashboard!$B$3),Summary!$A$2:$A$240,"<"&IF(Dashboard!$B$4="",2958465,Dashboard!$B$4+1)),COUNTIFS(Summary!$E$2:$E$240,$A11,Summary!$D$2:$D$240,">="&T4,Summary!$D$2:$D$240,"<"&T4+7,Summary!$A$2:$A$240,">="&IF(Dashboard!$B$3="",0,Dashboard!$B$3),Summary!$A$2:$A$240,"<"&IF(Dashboard!$B$4="",2958465,Dashboard!$B$4+1)))) -> 0
A12: =IF(Settings!A11="","",Settings!A11) -> Drain tube blocked | B12: =IF($A12="","",IF(hm_basis="Call date",COUNTIFS(Summary!$E$2:$E$240,$A12,Summary!$A$2:$A$240,">="&B4,Summary!$A$2:$A$240,"<"&B4+7,Summary!$A$2:$A$240,">="&IF(Dashboard!$B$3="",0,Dashboard!$B$3),Summary!$A$2:$A$240,"<"&IF(Dashboard!$B$4="",2958465,Dashboard!$B$4+1)),COUNTIFS(Summary!$E$2:$E$240,$A12,Summary!$D$2:$D$240,">="&B4,Summary!$D$2:$D$240,"<"&B4+7,Summary!$A$2:$A$240,">="&IF(Dashboard!$B$3="",0,Dashboard!$B$3),Summary!$A$2:$A$240,"<"&IF(Dashboard!$B$4="",2958465,Dashboard!$B$4+1)))) -> 0 | C12: =IF($A12="","",IF(hm_basis="Call date",COUNTIFS(Summary!$E$2:$E$240,$A12,Summary!$A$2:$A$240,">="&C4,Summary!$A$2:$A$240,"<"&C4+7,Summary!$A$2:$A$240,">="&IF(Dashboard!$B$3="",0,Dashboard!$B$3),Summary!$A$2:$A$240,"<"&IF(Dashboard!$B$4="",2958465,Dashboard!$B$4+1)),COUNTIFS(Summary!$E$2:$E$240,$A12,Summary!$D$2:$D$240,">="&C4,Summary!$D$2:$D$240,"<"&C4+7,Summary!$A$2:$A$240,">="&IF(Dashboard!$B$3="",0,Dashboard!$B$3),Summary!$A$2:$A$240,"<"&IF(Dashboard!$B$4="",2958465,Dashboard!$B$4+1)))) -> 1 | D12: =IF($A12="","",IF(hm_basis="Call date",COUNTIFS(Summary!$E$2:$E$240,$A12,Summary!$A$2:$A$240,">="&D4,Summary!$A$2:$A$240,"<"&D4+7,Summary!$A$2:$A$240,">="&IF(Dashboard!$B$3="",0,Dashboard!$B$3),Summary!$A$2:$A$240,"<"&IF(Dashboard!$B$4="",2958465,Dashboard!$B$4+1)),COUNTIFS(Summary!$E$2:$E$240,$A12,Summary!$D$2:$D$240,">="&D4,Summary!$D$2:$D$240,"<"&D4+7,Summary!$A$2:$A$240,">="&IF(Dashboard!$B$3="",0,Dashboard!$B$3),Summary!$A$2:$A$240,"<"&IF(Dashboard!$B$4="",2958465,Dashboard!$B$4+1)))) -> 0 | E12: =IF($A12="","",IF(hm_basis="Call date",COUNTIFS(Summary!$E$2:$E$240,$A12,Summary!$A$2:$A$240,">="&E4,Summary!$A$2:$A$240,"<"&E4+7,Summary!$A$2:$A$240,">="&IF(Dashboard!$B$3="",0,Dashboard!$B$3),Summary!$A$2:$A$240,"<"&IF(Dashboard!$B$4="",2958465,Dashboard!$B$4+1)),COUNTIFS(Summary!$E$2:$E$240,$A12,Summary!$D$2:$D$240,">="&E4,Summary!$D$2:$D$240,"<"&E4+7,Summary!$A$2:$A$240,">="&IF(Dashboard!$B$3="",0,Dashboard!$B$3),Summary!$A$2:$A$240,"<"&IF(Dashboard!$B$4="",2958465,Dashboard!$B$4+1)))) -> 0 | F12: =IF($A12="","",IF(hm_basis="Call date",COUNTIFS(Summary!$E$2:$E$240,$A12,Summary!$A$2:$A$240,">="&F4,Summary!$A$2:$A$240,"<"&F4+7,Summary!$A$2:$A$240,">="&IF(Dashboard!$B$3="",0,Dashboard!$B$3),Summary!$A$2:$A$240,"<"&IF(Dashboard!$B$4="",2958465,Dashboard!$B$4+1)),COUNTIFS(Summary!$E$2:$E$240,$A12,Summary!$D$2:$D$240,">="&F4,Summary!$D$2:$D$240,"<"&F4+7,Summary!$A$2:$A$240,">="&IF(Dashboard!$B$3="",0,Dashboard!$B$3),Summary!$A$2:$A$240,"<"&IF(Dashboard!$B$4="",2958465,Dashboard!$B$4+1)))) -> 0 | G12: =IF($A12="","",IF(hm_basis="Call date",COUNTIFS(Summary!$E$2:$E$240,$A12,Summary!$A$2:$A$240,">="&G4,Summary!$A$2:$A$240,"<"&G4+7,Summary!$A$2:$A$240,">="&IF(Dashboard!$B$3="",0,Dashboard!$B$3),Summary!$A$2:$A$240,"<"&IF(Dashboard!$B$4="",2958465,Dashboard!$B$4+1)),COUNTIFS(Summary!$E$2:$E$240,$A12,Summary!$D$2:$D$240,">="&G4,Summary!$D$2:$D$240,"<"&G4+7,Summary!$A$2:$A$240,">="&IF(Dashboard!$B$3="",0,Dashboard!$B$3),Summary!$A$2:$A$240,"<"&IF(Dashboard!$B$4="",2958465,Dashboard!$B$4+1)))) -> 2 | H12: =IF($A12="","",IF(hm_basis="Call date",COUNTIFS(Summary!$E$2:$E$240,$A12,Summary!$A$2:$A$240,">="&H4,Summary!$A$2:$A$240,"<"&H4+7,Summary!$A$2:$A$240,">="&IF(Dashboard!$B$3="",0,Dashboard!$B$3),Summary!$A$2:$A$240,"<"&IF(Dashboard!$B$4="",2958465,Dashboard!$B$4+1)),COUNTIFS(Summary!$E$2:$E$240,$A12,Summary!$D$2:$D$240,">="&H4,Summary!$D$2:$D$240,"<"&H4+7,Summary!$A$2:$A$240,">="&IF(Dashboard!$B$3="",0,Dashboard!$B$3),Summary!$A$2:$A$240,"<"&IF(Dashboard!$B$4="",2958465,Dashboard!$B$4+1)))) -> 0 | I12: =IF($A12="","",IF(hm_basis="Call date",COUNTIFS(Summary!$E$2:$E$240,$A12,Summary!$A$2:$A$240,">="&I4,Summary!$A$2:$A$240,"<"&I4+7,Summary!$A$2:$A$240,">="&IF(Dashboard!$B$3="",0,Dashboard!$B$3),Summary!$A$2:$A$240,"<"&IF(Dashboard!$B$4="",2958465,Dashboard!$B$4+1)),COUNTIFS(Summary!$E$2:$E$240,$A12,Summary!$D$2:$D$240,">="&I4,Summary!$D$2:$D$240,"<"&I4+7,Summary!$A$2:$A$240,">="&IF(Dashboard!$B$3="",0,Dashboard!$B$3),Summary!$A$2:$A$240,"<"&IF(Dashboard!$B$4="",2958465,Dashboard!$B$4+1)))) -> 0 | ... T12: =IF($A12="","",IF(hm_basis="Call date",COUNTIFS(Summary!$E$2:$E$240,$A12,Summary!$A$2:$A$240,">="&T4,Summary!$A$2:$A$240,"<"&T4+7,Summary!$A$2:$A$240,">="&IF(Dashboard!$B$3="",0,Dashboard!$B$3),Summary!$A$2:$A$240,"<"&IF(Dashboard!$B$4="",2958465,Dashboard!$B$4+1)),COUNTIFS(Summary!$E$2:$E$240,$A12,Summary!$D$2:$D$240,">="&T4,Summary!$D$2:$D$240,"<"&T4+7,Summary!$A$2:$A$240,">="&IF(Dashboard!$B$3="",0,Dashboard!$B$3),Summary!$A$2:$A$240,"<"&IF(Dashboard!$B$4="",2958465,Dashboard!$B$4+1)))) -> 0
A13: =IF(Settings!A12="","",Settings!A12) -> Wrong / Loose wiring | B13: =IF($A13="","",IF(hm_basis="Call date",COUNTIFS(Summary!$E$2:$E$240,$A13,Summary!$A$2:$A$240,">="&B4,Summary!$A$2:$A$240,"<"&B4+7,Summary!$A$2:$A$240,">="&IF(Dashboard!$B$3="",0,Dashboard!$B$3),Summary!$A$2:$A$240,"<"&IF(Dashboard!$B$4="",2958465,Dashboard!$B$4+1)),COUNTIFS(Summary!$E$2:$E$240,$A13,Summary!$D$2:$D$240,">="&B4,Summary!$D$2:$D$240,"<"&B4+7,Summary!$A$2:$A$240,">="&IF(Dashboard!$B$3="",0,Dashboard!$B$3),Summary!$A$2:$A$240,"<"&IF(Dashboard!$B$4="",2958465,Dashboard!$B$4+1)))) -> 0 | C13: =IF($A13="","",IF(hm_basis="Call date",COUNTIFS(Summary!$E$2:$E$240,$A13,Summary!$A$2:$A$240,">="&C4,Summary!$A$2:$A$240,"<"&C4+7,Summary!$A$2:$A$240,">="&IF(Dashboard!$B$3="",0,Dashboard!$B$3),Summary!$A$2:$A$240,"<"&IF(Dashboard!$B$4="",2958465,Dashboard!$B$4+1)),COUNTIFS(Summary!$E$2:$E$240,$A13,Summary!$D$2:$D$240,">="&C4,Summary!$D$2:$D$240,"<"&C4+7,Summary!$A$2:$A$240,">="&IF(Dashboard!$B$3="",0,Dashboard!$B$3),Summary!$A$2:$A$240,"<"&IF(Dashboard!$B$4="",2958465,Dashboard!$B$4+1)))) -> 1 | D13: =IF($A13="","",IF(hm_basis="Call date",COUNTIFS(Summary!$E$2:$E$240,$A13,Summary!$A$2:$A$240,">="&D4,Summary!$A$2:$A$240,"<"&D4+7,Summary!$A$2:$A$240,">="&IF(Dashboard!$B$3="",0,Dashboard!$B$3),Summary!$A$2:$A$240,"<"&IF(Dashboard!$B$4="",2958465,Dashboard!$B$4+1)),COUNTIFS(Summary!$E$2:$E$240,$A13,Summary!$D$2:$D$240,">="&D4,Summary!$D$2:$D$240,"<"&D4+7,Summary!$A$2:$A$240,">="&IF(Dashboard!$B$3="",0,Dashboard!$B$3),Summary!$A$2:$A$240,"<"&IF(Dashboard!$B$4="",2958465,Dashboard!$B$4+1)))) -> 0 | E13: =IF($A13="","",IF(hm_basis="Call date",COUNTIFS(Summary!$E$2:$E$240,$A13,Summary!$A$2:$A$240,">="&E4,Summary!$A$2:$A$240,"<"&E4+7,Summary!$A$2:$A$240,">="&IF(Dashboard!$B$3="",0,Dashboard!$B$3),Summary!$A$2:$A$240,"<"&IF(Dashboard!$B$4="",2958465,Dashboard!$B$4+1)),COUNTIFS(Summary!$E$2:$E$240,$A13,Summary!$D$2:$D$240,">="&E4,Summary!$D$2:$D$240,"<"&E4+7,Summary!$A$2:$A$240,">="&IF(Dashboard!$B$3="",0,Dashboard!$B$3),Summary!$A$2:$A$240,"<"&IF(Dashboard!$B$4="",2958465,Dashboard!$B$4+1)))) -> 0 | F13: =IF($A13="","",IF(hm_basis="Call date",COUNTIFS(Summary!$E$2:$E$240,$A13,Summary!$A$2:$A$240,">="&F4,Summary!$A$2:$A$240,"<"&F4+7,Summary!$A$2:$A$240,">="&IF(Dashboard!$B$3="",0,Dashboard!$B$3),Summary!$A$2:$A$240,"<"&IF(Dashboard!$B$4="",2958465,Dashboard!$B$4+1)),COUNTIFS(Summary!$E$2:$E$240,$A13,Summary!$D$2:$D$240,">="&F4,Summary!$D$2:$D$240,"<"&F4+7,Summary!$A$2:$A$240,">="&IF(Dashboard!$B$3="",0,Dashboard!$B$3),Summary!$A$2:$A$240,"<"&IF(Dashboard!$B$4="",2958465,Dashboard!$B$4+1)))) -> 1 | G13: =IF($A13="","",IF(hm_basis="Call date",COUNTIFS(Summary!$E$2:$E$240,$A13,Summary!$A$2:$A$240,">="&G4,Summary!$A$2:$A$240,"<"&G4+7,Summary!$A$2:$A$240,">="&IF(Dashboard!$B$3="",0,Dashboard!$B$3),Summary!$A$2:$A$240,"<"&IF(Dashboard!$B$4="",2958465,Dashboard!$B$4+1)),COUNTIFS(Summary!$E$2:$E$240,$A13,Summary!$D$2:$D$240,">="&G4,Summary!$D$2:$D$240,"<"&G4+7,Summary!$A$2:$A$240,">="&IF(Dashboard!$B$3="",0,Dashboard!$B$3),Summary!$A$2:$A$240,"<"&IF(Dashboard!$B$4="",2958465,Dashboard!$B$4+1)))) -> 0 | H13: =IF($A13="","",IF(hm_basis="Call date",COUNTIFS(Summary!$E$2:$E$240,$A13,Summary!$A$2:$A$240,">="&H4,Summary!$A$2:$A$240,"<"&H4+7,Summary!$A$2:$A$240,">="&IF(Dashboard!$B$3="",0,Dashboard!$B$3),Summary!$A$2:$A$240,"<"&IF(Dashboard!$B$4="",2958465,Dashboard!$B$4+1)),COUNTIFS(Summary!$E$2:$E$240,$A13,Summary!$D$2:$D$240,">="&H4,Summary!$D$2:$D$240,"<"&H4+7,Summary!$A$2:$A$240,">="&IF(Dashboard!$B$3="",0,Dashboard!$B$3),Summary!$A$2:$A$240,"<"&IF(Dashboard!$B$4="",2958465,Dashboard!$B$4+1)))) -> 0 | I13: =IF($A13="","",IF(hm_basis="Call date",COUNTIFS(Summary!$E$2:$E$240,$A13,Summary!$A$2:$A$240,">="&I4,Summary!$A$2:$A$240,"<"&I4+7,Summary!$A$2:$A$240,">="&IF(Dashboard!$B$3="",0,Dashboard!$B$3),Summary!$A$2:$A$240,"<"&IF(Dashboard!$B$4="",2958465,Dashboard!$B$4+1)),COUNTIFS(Summary!$E$2:$E$240,$A13,Summary!$D$2:$D$240,">="&I4,Summary!$D$2:$D$240,"<"&I4+7,Summary!$A$2:$A$240,">="&IF(Dashboard!$B$3="",0,Dashboard!$B$3),Summary!$A$2:$A$240,"<"&IF(Dashboard!$B$4="",2958465,Dashboard!$B$4+1)))) -> 0 | ... T13: =IF($A13="","",IF(hm_basis="Call date",COUNTIFS(Summary!$E$2:$E$240,$A13,Summary!$A$2:$A$240,">="&T4,Summary!$A$2:$A$240,"<"&T4+7,Summary!$A$2:$A$240,">="&IF(Dashboard!$B$3="",0,Dashboard!$B$3),Summary!$A$2:$A$240,"<"&IF(Dashboard!$B$4="",2958465,Dashboard!$B$4+1)),COUNTIFS(Summary!$E$2:$E$240,$A13,Summary!$D$2:$D$240,">="&T4,Summary!$D$2:$D$240,"<"&T4+7,Summary!$A$2:$A$240,">="&IF(Dashboard!$B$3="",0,Dashboard!$B$3),Summary!$A$2:$A$240,"<"&IF(Dashboard!$B$4="",2958465,Dashboard!$B$4+1)))) -> 0
A14: =IF(Settings!A13="","",Settings!A13) -> Communication problem | B14: =IF($A14="","",IF(hm_basis="Call date",COUNTIFS(Summary!$E$2:$E$240,$A14,Summary!$A$2:$A$240,">="&B4,Summary!$A$2:$A$240,"<"&B4+7,Summary!$A$2:$A$240,">="&IF(Dashboard!$B$3="",0,Dashboard!$B$3),Summary!$A$2:$A$240,"<"&IF(Dashboard!$B$4="",2958465,Dashboard!$B$4+1)),COUNTIFS(Summary!$E$2:$E$240,$A14,Summary!$D$2:$D$240,">="&B4,Summary!$D$2:$D$240,"<"&B4+7,Summary!$A$2:$A$240,">="&IF(Dashboard!$B$3="",0,Dashboard!$B$3),Summary!$A$2:$A$240,"<"&IF(Dashboard!$B$4="",2958465,Dashboard!$B$4+1)))) -> 0 | C14: =IF($A14="","",IF(hm_basis="Call date",COUNTIFS(Summary!$E$2:$E$240,$A14,Summary!$A$2:$A$240,">="&C4,Summary!$A$2:$A$240,"<"&C4+7,Summary!$A$2:$A$240,">="&IF(Dashboard!$B$3="",0,Dashboard!$B$3),Summary!$A$2:$A$240,"<"&IF(Dashboard!$B$4="",2958465,Dashboard!$B$4+1)),COUNTIFS(Summary!$E$2:$E$240,$A14,Summary!$D$2:$D$240,">="&C4,Summary!$D$2:$D$240,"<"&C4+7,Summary!$A$2:$A$240,">="&IF(Dashboard!$B$3="",0,Dashboard!$B$3),Summary!$A$2:$A$240,"<"&IF(Dashboard!$B$4="",2958465,Dashboard!$B$4+1)))) -> 1 | D14: =IF($A14="","",IF(hm_basis="Call date",COUNTIFS(Summary!$E$2:$E$240,$A14,Summary!$A$2:$A$240,">="&D4,Summary!$A$2:$A$240,"<"&D4+7,Summary!$A$2:$A$240,">="&IF(Dashboard!$B$3="",0,Dashboard!$B$3),Summary!$A$2:$A$240,"<"&IF(Dashboard!$B$4="",2958465,Dashboard!$B$4+1)),COUNTIFS(Summary!$E$2:$E$240,$A14,Summary!$D$2:$D$240,">="&D4,Summary!$D$2:$D$240,"<"&D4+7,Summary!$A$2:$A$240,">="&IF(Dashboard!$B$3="",0,Dashboard!$B$3),Summary!$A$2:$A$240,"<"&IF(Dashboard!$B$4="",2958465,Dashboard!$B$4+1)))) -> 2 | E14: =IF($A14="","",IF(hm_basis="Call date",COUNTIFS(Summary!$E$2:$E$240,$A14,Summary!$A$2:$A$240,">="&E4,Summary!$A$2:$A$240,"<"&E4+7,Summary!$A$2:$A$240,">="&IF(Dashboard!$B$3="",0,Dashboard!$B$3),Summary!$A$2:$A$240,"<"&IF(Dashboard!$B$4="",2958465,Dashboard!$B$4+1)),COUNTIFS(Summary!$E$2:$E$240,$A14,Summary!$D$2:$D$240,">="&E4,Summary!$D$2:$D$240,"<"&E4+7,Summary!$A$2:$A$240,">="&IF(Dashboard!$B$3="",0,Dashboard!$B$3),Summary!$A$2:$A$240,"<"&IF(Dashboard!$B$4="",2958465,Dashboard!$B$4+1)))) -> 0 | F14: =IF($A14="","",IF(hm_basis="Call date",COUNTIFS(Summary!$E$2:$E$240,$A14,Summary!$A$2:$A$240,">="&F4,Summary!$A$2:$A$240,"<"&F4+7,Summary!$A$2:$A$240,">="&IF(Dashboard!$B$3="",0,Dashboard!$B$3),Summary!$A$2:$A$240,"<"&IF(Dashboard!$B$4="",2958465,Dashboard!$B$4+1)),COUNTIFS(Summary!$E$2:$E$240,$A14,Summary!$D$2:$D$240,">="&F4,Summary!$D$2:$D$240,"<"&F4+7,Summary!$A$2:$A$240,">="&IF(Dashboard!$B$3="",0,Dashboard!$B$3),Summary!$A$2:$A$240,"<"&IF(Dashboard!$B$4="",2958465,Dashboard!$B$4+1)))) -> 1 | G14: =IF($A14="","",IF(hm_basis="Call date",COUNTIFS(Summary!$E$2:$E$240,$A14,Summary!$A$2:$A$240,">="&G4,Summary!$A$2:$A$240,"<"&G4+7,Summary!$A$2:$A$240,">="&IF(Dashboard!$B$3="",0,Dashboard!$B$3),Summary!$A$2:$A$240,"<"&IF(Dashboard!$B$4="",2958465,Dashboard!$B$4+1)),COUNTIFS(Summary!$E$2:$E$240,$A14,Summary!$D$2:$D$240,">="&G4,Summary!$D$2:$D$240,"<"&G4+7,Summary!$A$2:$A$240,">="&IF(Dashboard!$B$3="",0,Dashboard!$B$3),Summary!$A$2:$A$240,"<"&IF(Dashboard!$B$4="",2958465,Dashboard!$B$4+1)))) -> 0 | H14: =IF($A14="","",IF(hm_basis="Call date",COUNTIFS(Summary!$E$2:$E$240,$A14,Summary!$A$2:$A$240,">="&H4,Summary!$A$2:$A$240,"<"&H4+7,Summary!$A$2:$A$240,">="&IF(Dashboard!$B$3="",0,Dashboard!$B$3),Summary!$A$2:$A$240,"<"&IF(Dashboard!$B$4="",2958465,Dashboard!$B$4+1)),COUNTIFS(Summary!$E$2:$E$240,$A14,Summary!$D$2:$D$240,">="&H4,Summary!$D$2:$D$240,"<"&H4+7,Summary!$A$2:$A$240,">="&IF(Dashboard!$B$3="",0,Dashboard!$B$3),Summary!$A$2:$A$240,"<"&IF(Dashboard!$B$4="",2958465,Dashboard!$B$4+1)))) -> 0 | I14: =IF($A14="","",IF(hm_basis="Call date",COUNTIFS(Summary!$E$2:$E$240,$A14,Summary!$A$2:$A$240,">="&I4,Summary!$A$2:$A$240,"<"&I4+7,Summary!$A$2:$A$240,">="&IF(Dashboard!$B$3="",0,Dashboard!$B$3),Summary!$A$2:$A$240,"<"&IF(Dashboard!$B$4="",2958465,Dashboard!$B$4+1)),COUNTIFS(Summary!$E$2:$E$240,$A14,Summary!$D$2:$D$240,">="&I4,Summary!$D$2:$D$240,"<"&I4+7,Summary!$A$2:$A$240,">="&IF(Dashboard!$B$3="",0,Dashboard!$B$3),Summary!$A$2:$A$240,"<"&IF(Dashboard!$B$4="",2958465,Dashboard!$B$4+1)))) -> 0 | ... T14: =IF($A14="","",IF(hm_basis="Call date",COUNTIFS(Summary!$E$2:$E$240,$A14,Summary!$A$2:$A$240,">="&T4,Summary!$A$2:$A$240,"<"&T4+7,Summary!$A$2:$A$240,">="&IF(Dashboard!$B$3="",0,Dashboard!$B$3),Summary!$A$2:$A$240,"<"&IF(Dashboard!$B$4="",2958465,Dashboard!$B$4+1)),COUNTIFS(Summary!$E$2:$E$240,$A14,Summary!$D$2:$D$240,">="&T4,Summary!$D$2:$D$240,"<"&T4+7,Summary!$A$2:$A$240,">="&IF(Dashboard!$B$3="",0,Dashboard!$B$3),Summary!$A$2:$A$240,"<"&IF(Dashboard!$B$4="",2958465,Dashboard!$B$4+1)))) -> 0
A15: =IF(Settings!A14="","",Settings!A14) -> High Store RH | B15: =IF($A15="","",IF(hm_basis="Call date",COUNTIFS(Summary!$E$2:$E$240,$A15,Summary!$A$2:$A$240,">="&B4,Summary!$A$2:$A$240,"<"&B4+7,Summary!$A$2:$A$240,">="&IF(Dashboard!$B$3="",0,Dashboard!$B$3),Summary!$A$2:$A$240,"<"&IF(Dashboard!$B$4="",2958465,Dashboard!$B$4+1)),COUNTIFS(Summary!$E$2:$E$240,$A15,Summary!$D$2:$D$240,">="&B4,Summary!$D$2:$D$240,"<"&B4+7,Summary!$A$2:$A$240,">="&IF(Dashboard!$B$3="",0,Dashboard!$B$3),Summary!$A$2:$A$240,"<"&IF(Dashboard!$B$4="",2958465,Dashboard!$B$4+1)))) -> 0 | C15: =IF($A15="","",IF(hm_basis="Call date",COUNTIFS(Summary!$E$2:$E$240,$A15,Summary!$A$2:$A$240,">="&C4,Summary!$A$2:$A$240,"<"&C4+7,Summary!$A$2:$A$240,">="&IF(Dashboard!$B$3="",0,Dashboard!$B$3),Summary!$A$2:$A$240,"<"&IF(Dashboard!$B$4="",2958465,Dashboard!$B$4+1)),COUNTIFS(Summary!$E$2:$E$240,$A15,Summary!$D$2:$D$240,">="&C4,Summary!$D$2:$D$240,"<"&C4+7,Summary!$A$2:$A$240,">="&IF(Dashboard!$B$3="",0,Dashboard!$B$3),Summary!$A$2:$A$240,"<"&IF(Dashboard!$B$4="",2958465,Dashboard!$B$4+1)))) -> 1 | D15: =IF($A15="","",IF(hm_basis="Call date",COUNTIFS(Summary!$E$2:$E$240,$A15,Summary!$A$2:$A$240,">="&D4,Summary!$A$2:$A$240,"<"&D4+7,Summary!$A$2:$A$240,">="&IF(Dashboard!$B$3="",0,Dashboard!$B$3),Summary!$A$2:$A$240,"<"&IF(Dashboard!$B$4="",2958465,Dashboard!$B$4+1)),COUNTIFS(Summary!$E$2:$E$240,$A15,Summary!$D$2:$D$240,">="&D4,Summary!$D$2:$D$240,"<"&D4+7,Summary!$A$2:$A$240,">="&IF(Dashboard!$B$3="",0,Dashboard!$B$3),Summary!$A$2:$A$240,"<"&IF(Dashboard!$B$4="",2958465,Dashboard!$B$4+1)))) -> 0 | E15: =IF($A15="","",IF(hm_basis="Call date",COUNTIFS(Summary!$E$2:$E$240,$A15,Summary!$A$2:$A$240,">="&E4,Summary!$A$2:$A$240,"<"&E4+7,Summary!$A$2:$A$240,">="&IF(Dashboard!$B$3="",0,Dashboard!$B$3),Summary!$A$2:$A$240,"<"&IF(Dashboard!$B$4="",2958465,Dashboard!$B$4+1)),COUNTIFS(Summary!$E$2:$E$240,$A15,Summary!$D$2:$D$240,">="&E4,Summary!$D$2:$D$240,"<"&E4+7,Summary!$A$2:$A$240,">="&IF(Dashboard!$B$3="",0,Dashboard!$B$3),Summary!$A$2:$A$240,"<"&IF(Dashboard!$B$4="",2958465,Dashboard!$B$4+1)))) -> 1 | F15: =IF($A15="","",IF(hm_basis="Call date",COUNTIFS(Summary!$E$2:$E$240,$A15,Summary!$A$2:$A$240,">="&F4,Summary!$A$2:$A$240,"<"&F4+7,Summary!$A$2:$A$240,">="&IF(Dashboard!$B$3="",0,Dashboard!$B$3),Summary!$A$2:$A$240,"<"&IF(Dashboard!$B$4="",2958465,Dashboard!$B$4+1)),COUNTIFS(Summary!$E$2:$E$240,$A15,Summary!$D$2:$D$240,">="&F4,Summary!$D$2:$D$240,"<"&F4+7,Summary!$A$2:$A$240,">="&IF(Dashboard!$B$3="",0,Dashboard!$B$3),Summary!$A$2:$A$240,"<"&IF(Dashboard!$B$4="",2958465,Dashboard!$B$4+1)))) -> 1 | G15: =IF($A15="","",IF(hm_basis="Call date",COUNTIFS(Summary!$E$2:$E$240,$A15,Summary!$A$2:$A$240,">="&G4,Summary!$A$2:$A$240,"<"&G4+7,Summary!$A$2:$A$240,">="&IF(Dashboard!$B$3="",0,Dashboard!$B$3),Summary!$A$2:$A$240,"<"&IF(Dashboard!$B$4="",2958465,Dashboard!$B$4+1)),COUNTIFS(Summary!$E$2:$E$240,$A15,Summary!$D$2:$D$240,">="&G4,Summary!$D$2:$D$240,"<"&G4+7,Summary!$A$2:$A$240,">="&IF(Dashboard!$B$3="",0,Dashboard!$B$3),Summary!$A$2:$A$240,"<"&IF(Dashboard!$B$4="",2958465,Dashboard!$B$4+1)))) -> 5 | H15: =IF($A15="","",IF(hm_basis="Call date",COUNTIFS(Summary!$E$2:$E$240,$A15,Summary!$A$2:$A$240,">="&H4,Summary!$A$2:$A$240,"<"&H4+7,Summary!$A$2:$A$240,">="&IF(Dashboard!$B$3="",0,Dashboard!$B$3),Summary!$A$2:$A$240,"<"&IF(Dashboard!$B$4="",2958465,Dashboard!$B$4+1)),COUNTIFS(Summary!$E$2:$E$240,$A15,Summary!$D$2:$D$240,">="&H4,Summary!$D$2:$D$240,"<"&H4+7,Summary!$A$2:$A$240,">="&IF(Dashboard!$B$3="",0,Dashboard!$B$3),Summary!$A$2:$A$240,"<"&IF(Dashboard!$B$4="",2958465,Dashboard!$B$4+1)))) -> 1 | I15: =IF($A15="","",IF(hm_basis="Call date",COUNTIFS(Summary!$E$2:$E$240,$A15,Summary!$A$2:$A$240,">="&I4,Summary!$A$2:$A$240,"<"&I4+7,Summary!$A$2:$A$240,">="&IF(Dashboard!$B$3="",0,Dashboard!$B$3),Summary!$A$2:$A$240,"<"&IF(Dashboard!$B$4="",2958465,Dashboard!$B$4+1)),COUNTIFS(Summary!$E$2:$E$240,$A15,Summary!$D$2:$D$240,">="&I4,Summary!$D$2:$D$240,"<"&I4+7,Summary!$A$2:$A$240,">="&IF(Dashboard!$B$3="",0,Dashboard!$B$3),Summary!$A$2:$A$240,"<"&IF(Dashboard!$B$4="",2958465,Dashboard!$B$4+1)))) -> 0 | ... T15: =IF($A15="","",IF(hm_basis="Call date",COUNTIFS(Summary!$E$2:$E$240,$A15,Summary!$A$2:$A$240,">="&T4,Summary!$A$2:$A$240,"<"&T4+7,Summary!$A$2:$A$240,">="&IF(Dashboard!$B$3="",0,Dashboard!$B$3),Summary!$A$2:$A$240,"<"&IF(Dashboard!$B$4="",2958465,Dashboard!$B$4+1)),COUNTIFS(Summary!$E$2:$E$240,$A15,Summary!$D$2:$D$240,">="&T4,Summary!$D$2:$D$240,"<"&T4+7,Summary!$A$2:$A$240,">="&IF(Dashboard!$B$3="",0,Dashboard!$B$3),Summary!$A$2:$A$240,"<"&IF(Dashboard!$B$4="",2958465,Dashboard!$B$4+1)))) -> 0
A16: =IF(Settings!A15="","",Settings!A15) -> Enclosure Seal | B16: =IF($A16="","",IF(hm_basis="Call date",COUNTIFS(Summary!$E$2:$E$240,$A16,Summary!$A$2:$A$240,">="&B4,Summary!$A$2:$A$240,"<"&B4+7,Summary!$A$2:$A$240,">="&IF(Dashboard!$B$3="",0,Dashboard!$B$3),Summary!$A$2:$A$240,"<"&IF(Dashboard!$B$4="",2958465,Dashboard!$B$4+1)),COUNTIFS(Summary!$E$2:$E$240,$A16,Summary!$D$2:$D$240,">="&B4,Summary!$D$2:$D$240,"<"&B4+7,Summary!$A$2:$A$240,">="&IF(Dashboard!$B$3="",0,Dashboard!$B$3),Summary!$A$2:$A$240,"<"&IF(Dashboard!$B$4="",2958465,Dashboard!$B$4+1)))) -> 0 | C16: =IF($A16="","",IF(hm_basis="Call date",COUNTIFS(Summary!$E$2:$E$240,$A16,Summary!$A$2:$A$240,">="&C4,Summary!$A$2:$A$240,"<"&C4+7,Summary!$A$2:$A$240,">="&IF(Dashboard!$B$3="",0,Dashboard!$B$3),Summary!$A$2:$A$240,"<"&IF(Dashboard!$B$4="",2958465,Dashboard!$B$4+1)),COUNTIFS(Summary!$E$2:$E$240,$A16,Summary!$D$2:$D$240,">="&C4,Summary!$D$2:$D$240,"<"&C4+7,Summary!$A$2:$A$240,">="&IF(Dashboard!$B$3="",0,Dashboard!$B$3),Summary!$A$2:$A$240,"<"&IF(Dashboard!$B$4="",2958465,Dashboard!$B$4+1)))) -> 0 | D16: =IF($A16="","",IF(hm_basis="Call date",COUNTIFS(Summary!$E$2:$E$240,$A16,Summary!$A$2:$A$240,">="&D4,Summary!$A$2:$A$240,"<"&D4+7,Summary!$A$2:$A$240,">="&IF(Dashboard!$B$3="",0,Dashboard!$B$3),Summary!$A$2:$A$240,"<"&IF(Dashboard!$B$4="",2958465,Dashboard!$B$4+1)),COUNTIFS(Summary!$E$2:$E$240,$A16,Summary!$D$2:$D$240,">="&D4,Summary!$D$2:$D$240,"<"&D4+7,Summary!$A$2:$A$240,">="&IF(Dashboard!$B$3="",0,Dashboard!$B$3),Summary!$A$2:$A$240,"<"&IF(Dashboard!$B$4="",2958465,Dashboard!$B$4+1)))) -> 0 | E16: =IF($A16="","",IF(hm_basis="Call date",COUNTIFS(Summary!$E$2:$E$240,$A16,Summary!$A$2:$A$240,">="&E4,Summary!$A$2:$A$240,"<"&E4+7,Summary!$A$2:$A$240,">="&IF(Dashboard!$B$3="",0,Dashboard!$B$3),Summary!$A$2:$A$240,"<"&IF(Dashboard!$B$4="",2958465,Dashboard!$B$4+1)),COUNTIFS(Summary!$E$2:$E$240,$A16,Summary!$D$2:$D$240,">="&E4,Summary!$D$2:$D$240,"<"&E4+7,Summary!$A$2:$A$240,">="&IF(Dashboard!$B$3="",0,Dashboard!$B$3),Summary!$A$2:$A$240,"<"&IF(Dashboard!$B$4="",2958465,Dashboard!$B$4+1)))) -> 0 | F16: =IF($A16="","",IF(hm_basis="Call date",COUNTIFS(Summary!$E$2:$E$240,$A16,Summary!$A$2:$A$240,">="&F4,Summary!$A$2:$A$240,"<"&F4+7,Summary!$A$2:$A$240,">="&IF(Dashboard!$B$3="",0,Dashboard!$B$3),Summary!$A$2:$A$240,"<"&IF(Dashboard!$B$4="",2958465,Dashboard!$B$4+1)),COUNTIFS(Summary!$E$2:$E$240,$A16,Summary!$D$2:$D$240,">="&F4,Summary!$D$2:$D$240,"<"&F4+7,Summary!$A$2:$A$240,">="&IF(Dashboard!$B$3="",0,Dashboard!$B$3),Summary!$A$2:$A$240,"<"&IF(Dashboard!$B$4="",2958465,Dashboard!$B$4+1)))) -> 0 | G16: =IF($A16="","",IF(hm_basis="Call date",COUNTIFS(Summary!$E$2:$E$240,$A16,Summary!$A$2:$A$240,">="&G4,Summary!$A$2:$A$240,"<"&G4+7,Summary!$A$2:$A$240,">="&IF(Dashboard!$B$3="",0,Dashboard!$B$3),Summary!$A$2:$A$240,"<"&IF(Dashboard!$B$4="",2958465,Dashboard!$B$4+1)),COUNTIFS(Summary!$E$2:$E$240,$A16,Summary!$D$2:$D$240,">="&G4,Summary!$D$2:$D$240,"<"&G4+7,Summary!$A$2:$A$240,">="&IF(Dashboard!$B$3="",0,Dashboard!$B$3),Summary!$A$2:$A$240,"<"&IF(Dashboard!$B$4="",2958465,Dashboard!$B$4+1)))) -> 0 | H16: =IF($A16="","",IF(hm_basis="Call date",COUNTIFS(Summary!$E$2:$E$240,$A16,Summary!$A$2:$A$240,">="&H4,Summary!$A$2:$A$240,"<"&H4+7,Summary!$A$2:$A$240,">="&IF(Dashboard!$B$3="",0,Dashboard!$B$3),Summary!$A$2:$A$240,"<"&IF(Dashboard!$B$4="",2958465,Dashboard!$B$4+1)),COUNTIFS(Summary!$E$2:$E$240,$A16,Summary!$D$2:$D$240,">="&H4,Summary!$D$2:$D$240,"<"&H4+7,Summary!$A$2:$A$240,">="&IF(Dashboard!$B$3="",0,Dashboard!$B$3),Summary!$A$2:$A$240,"<"&IF(Dashboard!$B$4="",2958465,Dashboard!$B$4+1)))) -> 0 | I16: =IF($A16="","",IF(hm_basis="Call date",COUNTIFS(Summary!$E$2:$E$240,$A16,Summary!$A$2:$A$240,">="&I4,Summary!$A$2:$A$240,"<"&I4+7,Summary!$A$2:$A$240,">="&IF(Dashboard!$B$3="",0,Dashboard!$B$3),Summary!$A$2:$A$240,"<"&IF(Dashboard!$B$4="",2958465,Dashboard!$B$4+1)),COUNTIFS(Summary!$E$2:$E$240,$A16,Summary!$D$2:$D$240,">="&I4,Summary!$D$2:$D$240,"<"&I4+7,Summary!$A$2:$A$240,">="&IF(Dashboard!$B$3="",0,Dashboard!$B$3),Summary!$A$2:$A$240,"<"&IF(Dashboard!$B$4="",2958465,Dashboard!$B$4+1)))) -> 0 | ... T16: =IF($A16="","",IF(hm_basis="Call date",COUNTIFS(Summary!$E$2:$E$240,$A16,Summary!$A$2:$A$240,">="&T4,Summary!$A$2:$A$240,"<"&T4+7,Summary!$A$2:$A$240,">="&IF(Dashboard!$B$3="",0,Dashboard!$B$3),Summary!$A$2:$A$240,"<"&IF(Dashboard!$B$4="",2958465,Dashboard!$B$4+1)),COUNTIFS(Summary!$E$2:$E$240,$A16,Summary!$D$2:$D$240,">="&T4,Summary!$D$2:$D$240,"<"&T4+7,Summary!$A$2:$A$240,">="&IF(Dashboard!$B$3="",0,Dashboard!$B$3),Summary!$A$2:$A$240,"<"&IF(Dashboard!$B$4="",2958465,Dashboard!$B$4+1)))) -> 0
A17: =IF(Settings!A16="","",Settings!A16) -> Component Failure | B17: =IF($A17="","",IF(hm_basis="Call date",COUNTIFS(Summary!$E$2:$E$240,$A17,Summary!$A$2:$A$240,">="&B4,Summary!$A$2:$A$240,"<"&B4+7,Summary!$A$2:$A$240,">="&IF(Dashboard!$B$3="",0,Dashboard!$B$3),Summary!$A$2:$A$240,"<"&IF(Dashboard!$B$4="",2958465,Dashboard!$B$4+1)),COUNTIFS(Summary!$E$2:$E$240,$A17,Summary!$D$2:$D$240,">="&B4,Summary!$D$2:$D$240,"<"&B4+7,Summary!$A$2:$A$240,">="&IF(Dashboard!$B$3="",0,Dashboard!$B$3),Summary!$A$2:$A$240,"<"&IF(Dashboard!$B$4="",2958465,Dashboard!$B$4+1)))) -> 0 | C17: =IF($A17="","",IF(hm_basis="Call date",COUNTIFS(Summary!$E$2:$E$240,$A17,Summary!$A$2:$A$240,">="&C4,Summary!$A$2:$A$240,"<"&C4+7,Summary!$A$2:$A$240,">="&IF(Dashboard!$B$3="",0,Dashboard!$B$3),Summary!$A$2:$A$240,"<"&IF(Dashboard!$B$4="",2958465,Dashboard!$B$4+1)),COUNTIFS(Summary!$E$2:$E$240,$A17,Summary!$D$2:$D$240,">="&C4,Summary!$D$2:$D$240,"<"&C4+7,Summary!$A$2:$A$240,">="&IF(Dashboard!$B$3="",0,Dashboard!$B$3),Summary!$A$2:$A$240,"<"&IF(Dashboard!$B$4="",2958465,Dashboard!$B$4+1)))) -> 0 | D17: =IF($A17="","",IF(hm_basis="Call date",COUNTIFS(Summary!$E$2:$E$240,$A17,Summary!$A$2:$A$240,">="&D4,Summary!$A$2:$A$240,"<"&D4+7,Summary!$A$2:$A$240,">="&IF(Dashboard!$B$3="",0,Dashboard!$B$3),Summary!$A$2:$A$240,"<"&IF(Dashboard!$B$4="",2958465,Dashboard!$B$4+1)),COUNTIFS(Summary!$E$2:$E$240,$A17,Summary!$D$2:$D$240,">="&D4,Summary!$D$2:$D$240,"<"&D4+7,Summary!$A$2:$A$240,">="&IF(Dashboard!$B$3="",0,Dashboard!$B$3),Summary!$A$2:$A$240,"<"&IF(Dashboard!$B$4="",2958465,Dashboard!$B$4+1)))) -> 2 | E17: =IF($A17="","",IF(hm_basis="Call date",COUNTIFS(Summary!$E$2:$E$240,$A17,Summary!$A$2:$A$240,">="&E4,Summary!$A$2:$A$240,"<"&E4+7,Summary!$A$2:$A$240,">="&IF(Dashboard!$B$3="",0,Dashboard!$B$3),Summary!$A$2:$A$240,"<"&IF(Dashboard!$B$4="",2958465,Dashboard!$B$4+1)),COUNTIFS(Summary!$E$2:$E$240,$A17,Summary!$D$2:$D$240,">="&E4,Summary!$D$2:$D$240,"<"&E4+7,Summary!$A$2:$A$240,">="&IF(Dashboard!$B$3="",0,Dashboard!$B$3),Summary!$A$2:$A$240,"<"&IF(Dashboard!$B$4="",2958465,Dashboard!$B$4+1)))) -> 0 | F17: =IF($A17="","",IF(hm_basis="Call date",COUNTIFS(Summary!$E$2:$E$240,$A17,Summary!$A$2:$A$240,">="&F4,Summary!$A$2:$A$240,"<"&F4+7,Summary!$A$2:$A$240,">="&IF(Dashboard!$B$3="",0,Dashboard!$B$3),Summary!$A$2:$A$240,"<"&IF(Dashboard!$B$4="",2958465,Dashboard!$B$4+1)),COUNTIFS(Summary!$E$2:$E$240,$A17,Summary!$D$2:$D$240,">="&F4,Summary!$D$2:$D$240,"<"&F4+7,Summary!$A$2:$A$240,">="&IF(Dashboard!$B$3="",0,Dashboard!$B$3),Summary!$A$2:$A$240,"<"&IF(Dashboard!$B$4="",2958465,Dashboard!$B$4+1)))) -> 0 | G17: =IF($A17="","",IF(hm_basis="Call date",COUNTIFS(Summary!$E$2:$E$240,$A17,Summary!$A$2:$A$240,">="&G4,Summary!$A$2:$A$240,"<"&G4+7,Summary!$A$2:$A$240,">="&IF(Dashboard!$B$3="",0,Dashboard!$B$3),Summary!$A$2:$A$240,"<"&IF(Dashboard!$B$4="",2958465,Dashboard!$B$4+1)),COUNTIFS(Summary!$E$2:$E$240,$A17,Summary!$D$2:$D$240,">="&G4,Summary!$D$2:$D$240,"<"&G4+7,Summary!$A$2:$A$240,">="&IF(Dashboard!$B$3="",0,Dashboard!$B$3),Summary!$A$2:$A$240,"<"&IF(Dashboard!$B$4="",2958465,Dashboard!$B$4+1)))) -> 0 | H17: =IF($A17="","",IF(hm_basis="Call date",COUNTIFS(Summary!$E$2:$E$240,$A17,Summary!$A$2:$A$240,">="&H4,Summary!$A$2:$A$240,"<"&H4+7,Summary!$A$2:$A$240,">="&IF(Dashboard!$B$3="",0,Dashboard!$B$3),Summary!$A$2:$A$240,"<"&IF(Dashboard!$B$4="",2958465,Dashboard!$B$4+1)),COUNTIFS(Summary!$E$2:$E$240,$A17,Summary!$D$2:$D$240,">="&H4,Summary!$D$2:$D$240,"<"&H4+7,Summary!$A$2:$A$240,">="&IF(Dashboard!$B$3="",0,Dashboard!$B$3),Summary!$A$2:$A$240,"<"&IF(Dashboard!$B$4="",2958465,Dashboard!$B$4+1)))) -> 0 | I17: =IF($A17="","",IF(hm_basis="Call date",COUNTIFS(Summary!$E$2:$E$240,$A17,Summary!$A$2:$A$240,">="&I4,Summary!$A$2:$A$240,"<"&I4+7,Summary!$A$2:$A$240,">="&IF(Dashboard!$B$3="",0,Dashboard!$B$3),Summary!$A$2:$A$240,"<"&IF(Dashboard!$B$4="",2958465,Dashboard!$B$4+1)),COUNTIFS(Summary!$E$2:$E$240,$A17,Summary!$D$2:$D$240,">="&I4,Summary!$D$2:$D$240,"<"&I4+7,Summary!$A$2:$A$240,">="&IF(Dashboard!$B$3="",0,Dashboard!$B$3),Summary!$A$2:$A$240,"<"&IF(Dashboard!$B$4="",2958465,Dashboard!$B$4+1)))) -> 0 | ... T17: =IF($A17="","",IF(hm_basis="Call date",COUNTIFS(Summary!$E$2:$E$240,$A17,Summary!$A$2:$A$240,">="&T4,Summary!$A$2:$A$240,"<"&T4+7,Summary!$A$2:$A$240,">="&IF(Dashboard!$B$3="",0,Dashboard!$B$3),Summary!$A$2:$A$240,"<"&IF(Dashboard!$B$4="",2958465,Dashboard!$B$4+1)),COUNTIFS(Summary!$E$2:$E$240,$A17,Summary!$D$2:$D$240,">="&T4,Summary!$D$2:$D$240,"<"&T4+7,Summary!$A$2:$A$240,">="&IF(Dashboard!$B$3="",0,Dashboard!$B$3),Summary!$A$2:$A$240,"<"&IF(Dashboard!$B$4="",2958465,Dashboard!$B$4+1)))) -> 0
A18: =IF(Settings!A17="","",Settings!A17) -> Defrost Sync | B18: =IF($A18="","",IF(hm_basis="Call date",COUNTIFS(Summary!$E$2:$E$240,$A18,Summary!$A$2:$A$240,">="&B4,Summary!$A$2:$A$240,"<"&B4+7,Summary!$A$2:$A$240,">="&IF(Dashboard!$B$3="",0,Dashboard!$B$3),Summary!$A$2:$A$240,"<"&IF(Dashboard!$B$4="",2958465,Dashboard!$B$4+1)),COUNTIFS(Summary!$E$2:$E$240,$A18,Summary!$D$2:$D$240,">="&B4,Summary!$D$2:$D$240,"<"&B4+7,Summary!$A$2:$A$240,">="&IF(Dashboard!$B$3="",0,Dashboard!$B$3),Summary!$A$2:$A$240,"<"&IF(Dashboard!$B$4="",2958465,Dashboard!$B$4+1)))) -> 0 | C18: =IF($A18="","",IF(hm_basis="Call date",COUNTIFS(Summary!$E$2:$E$240,$A18,Summary!$A$2:$A$240,">="&C4,Summary!$A$2:$A$240,"<"&C4+7,Summary!$A$2:$A$240,">="&IF(Dashboard!$B$3="",0,Dashboard!$B$3),Summary!$A$2:$A$240,"<"&IF(Dashboard!$B$4="",2958465,Dashboard!$B$4+1)),COUNTIFS(Summary!$E$2:$E$240,$A18,Summary!$D$2:$D$240,">="&C4,Summary!$D$2:$D$240,"<"&C4+7,Summary!$A$2:$A$240,">="&IF(Dashboard!$B$3="",0,Dashboard!$B$3),Summary!$A$2:$A$240,"<"&IF(Dashboard!$B$4="",2958465,Dashboard!$B$4+1)))) -> 0 | D18: =IF($A18="","",IF(hm_basis="Call date",COUNTIFS(Summary!$E$2:$E$240,$A18,Summary!$A$2:$A$240,">="&D4,Summary!$A$2:$A$240,"<"&D4+7,Summary!$A$2:$A$240,">="&IF(Dashboard!$B$3="",0,Dashboard!$B$3),Summary!$A$2:$A$240,"<"&IF(Dashboard!$B$4="",2958465,Dashboard!$B$4+1)),COUNTIFS(Summary!$E$2:$E$240,$A18,Summary!$D$2:$D$240,">="&D4,Summary!$D$2:$D$240,"<"&D4+7,Summary!$A$2:$A$240,">="&IF(Dashboard!$B$3="",0,Dashboard!$B$3),Summary!$A$2:$A$240,"<"&IF(Dashboard!$B$4="",2958465,Dashboard!$B$4+1)))) -> 0 | E18: =IF($A18="","",IF(hm_basis="Call date",COUNTIFS(Summary!$E$2:$E$240,$A18,Summary!$A$2:$A$240,">="&E4,Summary!$A$2:$A$240,"<"&E4+7,Summary!$A$2:$A$240,">="&IF(Dashboard!$B$3="",0,Dashboard!$B$3),Summary!$A$2:$A$240,"<"&IF(Dashboard!$B$4="",2958465,Dashboard!$B$4+1)),COUNTIFS(Summary!$E$2:$E$240,$A18,Summary!$D$2:$D$240,">="&E4,Summary!$D$2:$D$240,"<"&E4+7,Summary!$A$2:$A$240,">="&IF(Dashboard!$B$3="",0,Dashboard!$B$3),Summary!$A$2:$A$240,"<"&IF(Dashboard!$B$4="",2958465,Dashboard!$B$4+1)))) -> 0 | F18: =IF($A18="","",IF(hm_basis="Call date",COUNTIFS(Summary!$E$2:$E$240,$A18,Summary!$A$2:$A$240,">="&F4,Summary!$A$2:$A$240,"<"&F4+7,Summary!$A$2:$A$240,">="&IF(Dashboard!$B$3="",0,Dashboard!$B$3),Summary!$A$2:$A$240,"<"&IF(Dashboard!$B$4="",2958465,Dashboard!$B$4+1)),COUNTIFS(Summary!$E$2:$E$240,$A18,Summary!$D$2:$D$240,">="&F4,Summary!$D$2:$D$240,"<"&F4+7,Summary!$A$2:$A$240,">="&IF(Dashboard!$B$3="",0,Dashboard!$B$3),Summary!$A$2:$A$240,"<"&IF(Dashboard!$B$4="",2958465,Dashboard!$B$4+1)))) -> 0 | G18: =IF($A18="","",IF(hm_basis="Call date",COUNTIFS(Summary!$E$2:$E$240,$A18,Summary!$A$2:$A$240,">="&G4,Summary!$A$2:$A$240,"<"&G4+7,Summary!$A$2:$A$240,">="&IF(Dashboard!$B$3="",0,Dashboard!$B$3),Summary!$A$2:$A$240,"<"&IF(Dashboard!$B$4="",2958465,Dashboard!$B$4+1)),COUNTIFS(Summary!$E$2:$E$240,$A18,Summary!$D$2:$D$240,">="&G4,Summary!$D$2:$D$240,"<"&G4+7,Summary!$A$2:$A$240,">="&IF(Dashboard!$B$3="",0,Dashboard!$B$3),Summary!$A$2:$A$240,"<"&IF(Dashboard!$B$4="",2958465,Dashboard!$B$4+1)))) -> 0 | H18: =IF($A18="","",IF(hm_basis="Call date",COUNTIFS(Summary!$E$2:$E$240,$A18,Summary!$A$2:$A$240,">="&H4,Summary!$A$2:$A$240,"<"&H4+7,Summary!$A$2:$A$240,">="&IF(Dashboard!$B$3="",0,Dashboard!$B$3),Summary!$A$2:$A$240,"<"&IF(Dashboard!$B$4="",2958465,Dashboard!$B$4+1)),COUNTIFS(Summary!$E$2:$E$240,$A18,Summary!$D$2:$D$240,">="&H4,Summary!$D$2:$D$240,"<"&H4+7,Summary!$A$2:$A$240,">="&IF(Dashboard!$B$3="",0,Dashboard!$B$3),Summary!$A$2:$A$240,"<"&IF(Dashboard!$B$4="",2958465,Dashboard!$B$4+1)))) -> 0 | I18: =IF($A18="","",IF(hm_basis="Call date",COUNTIFS(Summary!$E$2:$E$240,$A18,Summary!$A$2:$A$240,">="&I4,Summary!$A$2:$A$240,"<"&I4+7,Summary!$A$2:$A$240,">="&IF(Dashboard!$B$3="",0,Dashboard!$B$3),Summary!$A$2:$A$240,"<"&IF(Dashboard!$B$4="",2958465,Dashboard!$B$4+1)),COUNTIFS(Summary!$E$2:$E$240,$A18,Summary!$D$2:$D$240,">="&I4,Summary!$D$2:$D$240,"<"&I4+7,Summary!$A$2:$A$240,">="&IF(Dashboard!$B$3="",0,Dashboard!$B$3),Summary!$A$2:$A$240,"<"&IF(Dashboard!$B$4="",2958465,Dashboard!$B$4+1)))) -> 0 | ... T18: =IF($A18="","",IF(hm_basis="Call date",COUNTIFS(Summary!$E$2:$E$240,$A18,Summary!$A$2:$A$240,">="&T4,Summary!$A$2:$A$240,"<"&T4+7,Summary!$A$2:$A$240,">="&IF(Dashboard!$B$3="",0,Dashboard!$B$3),Summary!$A$2:$A$240,"<"&IF(Dashboard!$B$4="",2958465,Dashboard!$B$4+1)),COUNTIFS(Summary!$E$2:$E$240,$A18,Summary!$D$2:$D$240,">="&T4,Summary!$D$2:$D$240,"<"&T4+7,Summary!$A$2:$A$240,">="&IF(Dashboard!$B$3="",0,Dashboard!$B$3),Summary!$A$2:$A$240,"<"&IF(Dashboard!$B$4="",2958465,Dashboard!$B$4+1)))) -> 0
A19: =IF(Settings!A18="","",Settings!A18) -> False Alarm | B19: =IF($A19="","",IF(hm_basis="Call date",COUNTIFS(Summary!$E$2:$E$240,$A19,Summary!$A$2:$A$240,">="&B4,Summary!$A$2:$A$240,"<"&B4+7,Summary!$A$2:$A$240,">="&IF(Dashboard!$B$3="",0,Dashboard!$B$3),Summary!$A$2:$A$240,"<"&IF(Dashboard!$B$4="",2958465,Dashboard!$B$4+1)),COUNTIFS(Summary!$E$2:$E$240,$A19,Summary!$D$2:$D$240,">="&B4,Summary!$D$2:$D$240,"<"&B4+7,Summary!$A$2:$A$240,">="&IF(Dashboard!$B$3="",0,Dashboard!$B$3),Summary!$A$2:$A$240,"<"&IF(Dashboard!$B$4="",2958465,Dashboard!$B$4+1)))) -> 3 | C19: =IF($A19="","",IF(hm_basis="Call date",COUNTIFS(Summary!$E$2:$E$240,$A19,Summary!$A$2:$A$240,">="&C4,Summary!$A$2:$A$240,"<"&C4+7,Summary!$A$2:$A$240,">="&IF(Dashboard!$B$3="",0,Dashboard!$B$3),Summary!$A$2:$A$240,"<"&IF(Dashboard!$B$4="",2958465,Dashboard!$B$4+1)),COUNTIFS(Summary!$E$2:$E$240,$A19,Summary!$D$2:$D$240,">="&C4,Summary!$D$2:$D$240,"<"&C4+7,Summary!$A$2:$A$240,">="&IF(Dashboard!$B$3="",0,Dashboard!$B$3),Summary!$A$2:$A$240,"<"&IF(Dashboard!$B$4="",2958465,Dashboard!$B$4+1)))) -> 1 | D19: =IF($A19="","",IF(hm_basis="Call date",COUNTIFS(Summary!$E$2:$E$240,$A19,Summary!$A$2:$A$240,">="&D4,Summary!$A$2:$A$240,"<"&D4+7,Summary!$A$2:$A$240,">="&IF(Dashboard!$B$3="",0,Dashboard!$B$3),Summary!$A$2:$A$240,"<"&IF(Dashboard!$B$4="",2958465,Dashboard!$B$4+1)),COUNTIFS(Summary!$E$2:$E$240,$A19,Summary!$D$2:$D$240,">="&D4,Summary!$D$2:$D$240,"<"&D4+7,Summary!$A$2:$A$240,">="&IF(Dashboard!$B$3="",0,Dashboard!$B$3),Summary!$A$2:$A$240,"<"&IF(Dashboard!$B$4="",2958465,Dashboard!$B$4+1)))) -> 0 | E19: =IF($A19="","",IF(hm_basis="Call date",COUNTIFS(Summary!$E$2:$E$240,$A19,Summary!$A$2:$A$240,">="&E4,Summary!$A$2:$A$240,"<"&E4+7,Summary!$A$2:$A$240,">="&IF(Dashboard!$B$3="",0,Dashboard!$B$3),Summary!$A$2:$A$240,"<"&IF(Dashboard!$B$4="",2958465,Dashboard!$B$4+1)),COUNTIFS(Summary!$E$2:$E$240,$A19,Summary!$D$2:$D$240,">="&E4,Summary!$D$2:$D$240,"<"&E4+7,Summary!$A$2:$A$240,">="&IF(Dashboard!$B$3="",0,Dashboard!$B$3),Summary!$A$2:$A$240,"<"&IF(Dashboard!$B$4="",2958465,Dashboard!$B$4+1)))) -> 4 | F19: =IF($A19="","",IF(hm_basis="Call date",COUNTIFS(Summary!$E$2:$E$240,$A19,Summary!$A$2:$A$240,">="&F4,Summary!$A$2:$A$240,"<"&F4+7,Summary!$A$2:$A$240,">="&IF(Dashboard!$B$3="",0,Dashboard!$B$3),Summary!$A$2:$A$240,"<"&IF(Dashboard!$B$4="",2958465,Dashboard!$B$4+1)),COUNTIFS(Summary!$E$2:$E$240,$A19,Summary!$D$2:$D$240,">="&F4,Summary!$D$2:$D$240,"<"&F4+7,Summary!$A$2:$A$240,">="&IF(Dashboard!$B$3="",0,Dashboard!$B$3),Summary!$A$2:$A$240,"<"&IF(Dashboard!$B$4="",2958465,Dashboard!$B$4+1)))) -> 1 | G19: =IF($A19="","",IF(hm_basis="Call date",COUNTIFS(Summary!$E$2:$E$240,$A19,Summary!$A$2:$A$240,">="&G4,Summary!$A$2:$A$240,"<"&G4+7,Summary!$A$2:$A$240,">="&IF(Dashboard!$B$3="",0,Dashboard!$B$3),Summary!$A$2:$A$240,"<"&IF(Dashboard!$B$4="",2958465,Dashboard!$B$4+1)),COUNTIFS(Summary!$E$2:$E$240,$A19,Summary!$D$2:$D$240,">="&G4,Summary!$D$2:$D$240,"<"&G4+7,Summary!$A$2:$A$240,">="&IF(Dashboard!$B$3="",0,Dashboard!$B$3),Summary!$A$2:$A$240,"<"&IF(Dashboard!$B$4="",2958465,Dashboard!$B$4+1)))) -> 1 | H19: =IF($A19="","",IF(hm_basis="Call date",COUNTIFS(Summary!$E$2:$E$240,$A19,Summary!$A$2:$A$240,">="&H4,Summary!$A$2:$A$240,"<"&H4+7,Summary!$A$2:$A$240,">="&IF(Dashboard!$B$3="",0,Dashboard!$B$3),Summary!$A$2:$A$240,"<"&IF(Dashboard!$B$4="",2958465,Dashboard!$B$4+1)),COUNTIFS(Summary!$E$2:$E$240,$A19,Summary!$D$2:$D$240,">="&H4,Summary!$D$2:$D$240,"<"&H4+7,Summary!$A$2:$A$240,">="&IF(Dashboard!$B$3="",0,Dashboard!$B$3),Summary!$A$2:$A$240,"<"&IF(Dashboard!$B$4="",2958465,Dashboard!$B$4+1)))) -> 1 | I19: =IF($A19="","",IF(hm_basis="Call date",COUNTIFS(Summary!$E$2:$E$240,$A19,Summary!$A$2:$A$240,">="&I4,Summary!$A$2:$A$240,"<"&I4+7,Summary!$A$2:$A$240,">="&IF(Dashboard!$B$3="",0,Dashboard!$B$3),Summary!$A$2:$A$240,"<"&IF(Dashboard!$B$4="",2958465,Dashboard!$B$4+1)),COUNTIFS(Summary!$E$2:$E$240,$A19,Summary!$D$2:$D$240,">="&I4,Summary!$D$2:$D$240,"<"&I4+7,Summary!$A$2:$A$240,">="&IF(Dashboard!$B$3="",0,Dashboard!$B$3),Summary!$A$2:$A$240,"<"&IF(Dashboard!$B$4="",2958465,Dashboard!$B$4+1)))) -> 0 | ... T19: =IF($A19="","",IF(hm_basis="Call date",COUNTIFS(Summary!$E$2:$E$240,$A19,Summary!$A$2:$A$240,">="&T4,Summary!$A$2:$A$240,"<"&T4+7,Summary!$A$2:$A$240,">="&IF(Dashboard!$B$3="",0,Dashboard!$B$3),Summary!$A$2:$A$240,"<"&IF(Dashboard!$B$4="",2958465,Dashboard!$B$4+1)),COUNTIFS(Summary!$E$2:$E$240,$A19,Summary!$D$2:$D$240,">="&T4,Summary!$D$2:$D$240,"<"&T4+7,Summary!$A$2:$A$240,">="&IF(Dashboard!$B$3="",0,Dashboard!$B$3),Summary!$A$2:$A$240,"<"&IF(Dashboard!$B$4="",2958465,Dashboard!$B$4+1)))) -> 0
A20: =IF(Settings!A19="","",Settings!A19) -> Setpoint change | B20: =IF($A20="","",IF(hm_basis="Call date",COUNTIFS(Summary!$E$2:$E$240,$A20,Summary!$A$2:$A$240,">="&B4,Summary!$A$2:$A$240,"<"&B4+7,Summary!$A$2:$A$240,">="&IF(Dashboard!$B$3="",0,Dashboard!$B$3),Summary!$A$2:$A$240,"<"&IF(Dashboard!$B$4="",2958465,Dashboard!$B$4+1)),COUNTIFS(Summary!$E$2:$E$240,$A20,Summary!$D$2:$D$240,">="&B4,Summary!$D$2:$D$240,"<"&B4+7,Summary!$A$2:$A$240,">="&IF(Dashboard!$B$3="",0,Dashboard!$B$3),Summary!$A$2:$A$240,"<"&IF(Dashboard!$B$4="",2958465,Dashboard!$B$4+1)))) -> 0 | C20: =IF($A20="","",IF(hm_basis="Call date",COUNTIFS(Summary!$E$2:$E$240,$A20,Summary!$A$2:$A$240,">="&C4,Summary!$A$2:$A$240,"<"&C4+7,Summary!$A$2:$A$240,">="&IF(Dashboard!$B$3="",0,Dashboard!$B$3),Summary!$A$2:$A$240,"<"&IF(Dashboard!$B$4="",2958465,Dashboard!$B$4+1)),COUNTIFS(Summary!$E$2:$E$240,$A20,Summary!$D$2:$D$240,">="&C4,Summary!$D$2:$D$240,"<"&C4+7,Summary!$A$2:$A$240,">="&IF(Dashboard!$B$3="",0,Dashboard!$B$3),Summary!$A$2:$A$240,"<"&IF(Dashboard!$B$4="",2958465,Dashboard!$B$4+1)))) -> 1 | D20: =IF($A20="","",IF(hm_basis="Call date",COUNTIFS(Summary!$E$2:$E$240,$A20,Summary!$A$2:$A$240,">="&D4,Summary!$A$2:$A$240,"<"&D4+7,Summary!$A$2:$A$240,">="&IF(Dashboard!$B$3="",0,Dashboard!$B$3),Summary!$A$2:$A$240,"<"&IF(Dashboard!$B$4="",2958465,Dashboard!$B$4+1)),COUNTIFS(Summary!$E$2:$E$240,$A20,Summary!$D$2:$D$240,">="&D4,Summary!$D$2:$D$240,"<"&D4+7,Summary!$A$2:$A$240,">="&IF(Dashboard!$B$3="",0,Dashboard!$B$3),Summary!$A$2:$A$240,"<"&IF(Dashboard!$B$4="",2958465,Dashboard!$B$4+1)))) -> 0 | E20: =IF($A20="","",IF(hm_basis="Call date",COUNTIFS(Summary!$E$2:$E$240,$A20,Summary!$A$2:$A$240,">="&E4,Summary!$A$2:$A$240,"<"&E4+7,Summary!$A$2:$A$240,">="&IF(Dashboard!$B$3="",0,Dashboard!$B$3),Summary!$A$2:$A$240,"<"&IF(Dashboard!$B$4="",2958465,Dashboard!$B$4+1)),COUNTIFS(Summary!$E$2:$E$240,$A20,Summary!$D$2:$D$240,">="&E4,Summary!$D$2:$D$240,"<"&E4+7,Summary!$A$2:$A$240,">="&IF(Dashboard!$B$3="",0,Dashboard!$B$3),Summary!$A$2:$A$240,"<"&IF(Dashboard!$B$4="",2958465,Dashboard!$B$4+1)))) -> 0 | F20: =IF($A20="","",IF(hm_basis="Call date",COUNTIFS(Summary!$E$2:$E$240,$A20,Summary!$A$2:$A$240,">="&F4,Summary!$A$2:$A$240,"<"&F4+7,Summary!$A$2:$A$240,">="&IF(Dashboard!$B$3="",0,Dashboard!$B$3),Summary!$A$2:$A$240,"<"&IF(Dashboard!$B$4="",2958465,Dashboard!$B$4+1)),COUNTIFS(Summary!$E$2:$E$240,$A20,Summary!$D$2:$D$240,">="&F4,Summary!$D$2:$D$240,"<"&F4+7,Summary!$A$2:$A$240,">="&IF(Dashboard!$B$3="",0,Dashboard!$B$3),Summary!$A$2:$A$240,"<"&IF(Dashboard!$B$4="",2958465,Dashboard!$B$4+1)))) -> 0 | G20: =IF($A20="","",IF(hm_basis="Call date",COUNTIFS(Summary!$E$2:$E$240,$A20,Summary!$A$2:$A$240,">="&G4,Summary!$A$2:$A$240,"<"&G4+7,Summary!$A$2:$A$240,">="&IF(Dashboard!$B$3="",0,Dashboard!$B$3),Summary!$A$2:$A$240,"<"&IF(Dashboard!$B$4="",2958465,Dashboard!$B$4+1)),COUNTIFS(Summary!$E$2:$E$240,$A20,Summary!$D$2:$D$240,">="&G4,Summary!$D$2:$D$240,"<"&G4+7,Summary!$A$2:$A$240,">="&IF(Dashboard!$B$3="",0,Dashboard!$B$3),Summary!$A$2:$A$240,"<"&IF(Dashboard!$B$4="",2958465,Dashboard!$B$4+1)))) -> 0 | H20: =IF($A20="","",IF(hm_basis="Call date",COUNTIFS(Summary!$E$2:$E$240,$A20,Summary!$A$2:$A$240,">="&H4,Summary!$A$2:$A$240,"<"&H4+7,Summary!$A$2:$A$240,">="&IF(Dashboard!$B$3="",0,Dashboard!$B$3),Summary!$A$2:$A$240,"<"&IF(Dashboard!$B$4="",2958465,Dashboard!$B$4+1)),COUNTIFS(Summary!$E$2:$E$240,$A20,Summary!$D$2:$D$240,">="&H4,Summary!$D$2:$D$240,"<"&H4+7,Summary!$A$2:$A$240,">="&IF(Dashboard!$B$3="",0,Dashboard!$B$3),Summary!$A$2:$A$240,"<"&IF(Dashboard!$B$4="",2958465,Dashboard!$B$4+1)))) -> 0 | I20: =IF($A20="","",IF(hm_basis="Call date",COUNTIFS(Summary!$E$2:$E$240,$A20,Summary!$A$2:$A$240,">="&I4,Summary!$A$2:$A$240,"<"&I4+7,Summary!$A$2:$A$240,">="&IF(Dashboard!$B$3="",0,Dashboard!$B$3),Summary!$A$2:$A$240,"<"&IF(Dashboard!$B$4="",2958465,Dashboard!$B$4+1)),COUNTIFS(Summary!$E$2:$E$240,$A20,Summary!$D$2:$D$240,">="&I4,Summary!$D$2:$D$240,"<"&I4+7,Summary!$A$2:$A$240,">="&IF(Dashboard!$B$3="",0,Dashboard!$B$3),Summary!$A$2:$A$240,"<"&IF(Dashboard!$B$4="",2958465,Dashboard!$B$4+1)))) -> 0 | ... T20: =IF($A20="","",IF(hm_basis="Call date",COUNTIFS(Summary!$E$2:$E$240,$A20,Summary!$A$2:$A$240,">="&T4,Summary!$A$2:$A$240,"<"&T4+7,Summary!$A$2:$A$240,">="&IF(Dashboard!$B$3="",0,Dashboard!$B$3),Summary!$A$2:$A$240,"<"&IF(Dashboard!$B$4="",2958465,Dashboard!$B$4+1)),COUNTIFS(Summary!$E$2:$E$240,$A20,Summary!$D$2:$D$240,">="&T4,Summary!$D$2:$D$240,"<"&T4+7,Summary!$A$2:$A$240,">="&IF(Dashboard!$B$3="",0,Dashboard!$B$3),Summary!$A$2:$A$240,"<"&IF(Dashboard!$B$4="",2958465,Dashboard!$B$4+1)))) -> 0
A21: =IF(Settings!A20="","",Settings!A20) -> Overstocking | B21: =IF($A21="","",IF(hm_basis="Call date",COUNTIFS(Summary!$E$2:$E$240,$A21,Summary!$A$2:$A$240,">="&B4,Summary!$A$2:$A$240,"<"&B4+7,Summary!$A$2:$A$240,">="&IF(Dashboard!$B$3="",0,Dashboard!$B$3),Summary!$A$2:$A$240,"<"&IF(Dashboard!$B$4="",2958465,Dashboard!$B$4+1)),COUNTIFS(Summary!$E$2:$E$240,$A21,Summary!$D$2:$D$240,">="&B4,Summary!$D$2:$D$240,"<"&B4+7,Summary!$A$2:$A$240,">="&IF(Dashboard!$B$3="",0,Dashboard!$B$3),Summary!$A$2:$A$240,"<"&IF(Dashboard!$B$4="",2958465,Dashboard!$B$4+1)))) -> 0 | C21: =IF($A21="","",IF(hm_basis="Call date",COUNTIFS(Summary!$E$2:$E$240,$A21,Summary!$A$2:$A$240,">="&C4,Summary!$A$2:$A$240,"<"&C4+7,Summary!$A$2:$A$240,">="&IF(Dashboard!$B$3="",0,Dashboard!$B$3),Summary!$A$2:$A$240,"<"&IF(Dashboard!$B$4="",2958465,Dashboard!$B$4+1)),COUNTIFS(Summary!$E$2:$E$240,$A21,Summary!$D$2:$D$240,">="&C4,Summary!$D$2:$D$240,"<"&C4+7,Summary!$A$2:$A$240,">="&IF(Dashboard!$B$3="",0,Dashboard!$B$3),Summary!$A$2:$A$240,"<"&IF(Dashboard!$B$4="",2958465,Dashboard!$B$4+1)))) -> 0 | D21: =IF($A21="","",IF(hm_basis="Call date",COUNTIFS(Summary!$E$2:$E$240,$A21,Summary!$A$2:$A$240,">="&D4,Summary!$A$2:$A$240,"<"&D4+7,Summary!$A$2:$A$240,">="&IF(Dashboard!$B$3="",0,Dashboard!$B$3),Summary!$A$2:$A$240,"<"&IF(Dashboard!$B$4="",2958465,Dashboard!$B$4+1)),COUNTIFS(Summary!$E$2:$E$240,$A21,Summary!$D$2:$D$240,">="&D4,Summary!$D$2:$D$240,"<"&D4+7,Summary!$A$2:$A$240,">="&IF(Dashboard!$B$3="",0,Dashboard!$B$3),Summary!$A$2:$A$240,"<"&IF(Dashboard!$B$4="",2958465,Dashboard!$B$4+1)))) -> 0 | E21: =IF($A21="","",IF(hm_basis="Call date",COUNTIFS(Summary!$E$2:$E$240,$A21,Summary!$A$2:$A$240,">="&E4,Summary!$A$2:$A$240,"<"&E4+7,Summary!$A$2:$A$240,">="&IF(Dashboard!$B$3="",0,Dashboard!$B$3),Summary!$A$2:$A$240,"<"&IF(Dashboard!$B$4="",2958465,Dashboard!$B$4+1)),COUNTIFS(Summary!$E$2:$E$240,$A21,Summary!$D$2:$D$240,">="&E4,Summary!$D$2:$D$240,"<"&E4+7,Summary!$A$2:$A$240,">="&IF(Dashboard!$B$3="",0,Dashboard!$B$3),Summary!$A$2:$A$240,"<"&IF(Dashboard!$B$4="",2958465,Dashboard!$B$4+1)))) -> 1 | F21: =IF($A21="","",IF(hm_basis="Call date",COUNTIFS(Summary!$E$2:$E$240,$A21,Summary!$A$2:$A$240,">="&F4,Summary!$A$2:$A$240,"<"&F4+7,Summary!$A$2:$A$240,">="&IF(Dashboard!$B$3="",0,Dashboard!$B$3),Summary!$A$2:$A$240,"<"&IF(Dashboard!$B$4="",2958465,Dashboard!$B$4+1)),COUNTIFS(Summary!$E$2:$E$240,$A21,Summary!$D$2:$D$240,">="&F4,Summary!$D$2:$D$240,"<"&F4+7,Summary!$A$2:$A$240,">="&IF(Dashboard!$B$3="",0,Dashboard!$B$3),Summary!$A$2:$A$240,"<"&IF(Dashboard!$B$4="",2958465,Dashboard!$B$4+1)))) -> 0 | G21: =IF($A21="","",IF(hm_basis="Call date",COUNTIFS(Summary!$E$2:$E$240,$A21,Summary!$A$2:$A$240,">="&G4,Summary!$A$2:$A$240,"<"&G4+7,Summary!$A$2:$A$240,">="&IF(Dashboard!$B$3="",0,Dashboard!$B$3),Summary!$A$2:$A$240,"<"&IF(Dashboard!$B$4="",2958465,Dashboard!$B$4+1)),COUNTIFS(Summary!$E$2:$E$240,$A21,Summary!$D$2:$D$240,">="&G4,Summary!$D$2:$D$240,"<"&G4+7,Summary!$A$2:$A$240,">="&IF(Dashboard!$B$3="",0,Dashboard!$B$3),Summary!$A$2:$A$240,"<"&IF(Dashboard!$B$4="",2958465,Dashboard!$B$4+1)))) -> 2 | H21: =IF($A21="","",IF(hm_basis="Call date",COUNTIFS(Summary!$E$2:$E$240,$A21,Summary!$A$2:$A$240,">="&H4,Summary!$A$2:$A$240,"<"&H4+7,Summary!$A$2:$A$240,">="&IF(Dashboard!$B$3="",0,Dashboard!$B$3),Summary!$A$2:$A$240,"<"&IF(Dashboard!$B$4="",2958465,Dashboard!$B$4+1)),COUNTIFS(Summary!$E$2:$E$240,$A21,Summary!$D$2:$D$240,">="&H4,Summary!$D$2:$D$240,"<"&H4+7,Summary!$A$2:$A$240,">="&IF(Dashboard!$B$3="",0,Dashboard!$B$3),Summary!$A$2:$A$240,"<"&IF(Dashboard!$B$4="",2958465,Dashboard!$B$4+1)))) -> 0 | I21: =IF($A21="","",IF(hm_basis="Call date",COUNTIFS(Summary!$E$2:$E$240,$A21,Summary!$A$2:$A$240,">="&I4,Summary!$A$2:$A$240,"<"&I4+7,Summary!$A$2:$A$240,">="&IF(Dashboard!$B$3="",0,Dashboard!$B$3),Summary!$A$2:$A$240,"<"&IF(Dashboard!$B$4="",2958465,Dashboard!$B$4+1)),COUNTIFS(Summary!$E$2:$E$240,$A21,Summary!$D$2:$D$240,">="&I4,Summary!$D$2:$D$240,"<"&I4+7,Summary!$A$2:$A$240,">="&IF(Dashboard!$B$3="",0,Dashboard!$B$3),Summary!$A$2:$A$240,"<"&IF(Dashboard!$B$4="",2958465,Dashboard!$B$4+1)))) -> 0 | ... T21: =IF($A21="","",IF(hm_basis="Call date",COUNTIFS(Summary!$E$2:$E$240,$A21,Summary!$A$2:$A$240,">="&T4,Summary!$A$2:$A$240,"<"&T4+7,Summary!$A$2:$A$240,">="&IF(Dashboard!$B$3="",0,Dashboard!$B$3),Summary!$A$2:$A$240,"<"&IF(Dashboard!$B$4="",2958465,Dashboard!$B$4+1)),COUNTIFS(Summary!$E$2:$E$240,$A21,Summary!$D$2:$D$240,">="&T4,Summary!$D$2:$D$240,"<"&T4+7,Summary!$A$2:$A$240,">="&IF(Dashboard!$B$3="",0,Dashboard!$B$3),Summary!$A$2:$A$240,"<"&IF(Dashboard!$B$4="",2958465,Dashboard!$B$4+1)))) -> 0
A22: =IF(Settings!A21="","",Settings!A21) -> Double defrost | B22: =IF($A22="","",IF(hm_basis="Call date",COUNTIFS(Summary!$E$2:$E$240,$A22,Summary!$A$2:$A$240,">="&B4,Summary!$A$2:$A$240,"<"&B4+7,Summary!$A$2:$A$240,">="&IF(Dashboard!$B$3="",0,Dashboard!$B$3),Summary!$A$2:$A$240,"<"&IF(Dashboard!$B$4="",2958465,Dashboard!$B$4+1)),COUNTIFS(Summary!$E$2:$E$240,$A22,Summary!$D$2:$D$240,">="&B4,Summary!$D$2:$D$240,"<"&B4+7,Summary!$A$2:$A$240,">="&IF(Dashboard!$B$3="",0,Dashboard!$B$3),Summary!$A$2:$A$240,"<"&IF(Dashboard!$B$4="",2958465,Dashboard!$B$4+1)))) -> 0 | C22: =IF($A22="","",IF(hm_basis="Call date",COUNTIFS(Summary!$E$2:$E$240,$A22,Summary!$A$2:$A$240,">="&C4,Summary!$A$2:$A$240,"<"&C4+7,Summary!$A$2:$A$240,">="&IF(Dashboard!$B$3="",0,Dashboard!$B$3),Summary!$A$2:$A$240,"<"&IF(Dashboard!$B$4="",2958465,Dashboard!$B$4+1)),COUNTIFS(Summary!$E$2:$E$240,$A22,Summary!$D$2:$D$240,">="&C4,Summary!$D$2:$D$240,"<"&C4+7,Summary!$A$2:$A$240,">="&IF(Dashboard!$B$3="",0,Dashboard!$B$3),Summary!$A$2:$A$240,"<"&IF(Dashboard!$B$4="",2958465,Dashboard!$B$4+1)))) -> 0 | D22: =IF($A22="","",IF(hm_basis="Call date",COUNTIFS(Summary!$E$2:$E$240,$A22,Summary!$A$2:$A$240,">="&D4,Summary!$A$2:$A$240,"<"&D4+7,Summary!$A$2:$A$240,">="&IF(Dashboard!$B$3="",0,Dashboard!$B$3),Summary!$A$2:$A$240,"<"&IF(Dashboard!$B$4="",2958465,Dashboard!$B$4+1)),COUNTIFS(Summary!$E$2:$E$240,$A22,Summary!$D$2:$D$240,">="&D4,Summary!$D$2:$D$240,"<"&D4+7,Summary!$A$2:$A$240,">="&IF(Dashboard!$B$3="",0,Dashboard!$B$3),Summary!$A$2:$A$240,"<"&IF(Dashboard!$B$4="",2958465,Dashboard!$B$4+1)))) -> 0 | E22: =IF($A22="","",IF(hm_basis="Call date",COUNTIFS(Summary!$E$2:$E$240,$A22,Summary!$A$2:$A$240,">="&E4,Summary!$A$2:$A$240,"<"&E4+7,Summary!$A$2:$A$240,">="&IF(Dashboard!$B$3="",0,Dashboard!$B$3),Summary!$A$2:$A$240,"<"&IF(Dashboard!$B$4="",2958465,Dashboard!$B$4+1)),COUNTIFS(Summary!$E$2:$E$240,$A22,Summary!$D$2:$D$240,">="&E4,Summary!$D$2:$D$240,"<"&E4+7,Summary!$A$2:$A$240,">="&IF(Dashboard!$B$3="",0,Dashboard!$B$3),Summary!$A$2:$A$240,"<"&IF(Dashboard!$B$4="",2958465,Dashboard!$B$4+1)))) -> 0 | F22: =IF($A22="","",IF(hm_basis="Call date",COUNTIFS(Summary!$E$2:$E$240,$A22,Summary!$A$2:$A$240,">="&F4,Summary!$A$2:$A$240,"<"&F4+7,Summary!$A$2:$A$240,">="&IF(Dashboard!$B$3="",0,Dashboard!$B$3),Summary!$A$2:$A$240,"<"&IF(Dashboard!$B$4="",2958465,Dashboard!$B$4+1)),COUNTIFS(Summary!$E$2:$E$240,$A22,Summary!$D$2:$D$240,">="&F4,Summary!$D$2:$D$240,"<"&F4+7,Summary!$A$2:$A$240,">="&IF(Dashboard!$B$3="",0,Dashboard!$B$3),Summary!$A$2:$A$240,"<"&IF(Dashboard!$B$4="",2958465,Dashboard!$B$4+1)))) -> 0 | G22: =IF($A22="","",IF(hm_basis="Call date",COUNTIFS(Summary!$E$2:$E$240,$A22,Summary!$A$2:$A$240,">="&G4,Summary!$A$2:$A$240,"<"&G4+7,Summary!$A$2:$A$240,">="&IF(Dashboard!$B$3="",0,Dashboard!$B$3),Summary!$A$2:$A$240,"<"&IF(Dashboard!$B$4="",2958465,Dashboard!$B$4+1)),COUNTIFS(Summary!$E$2:$E$240,$A22,Summary!$D$2:$D$240,">="&G4,Summary!$D$2:$D$240,"<"&G4+7,Summary!$A$2:$A$240,">="&IF(Dashboard!$B$3="",0,Dashboard!$B$3),Summary!$A$2:$A$240,"<"&IF(Dashboard!$B$4="",2958465,Dashboard!$B$4+1)))) -> 0 | H22: =IF($A22="","",IF(hm_basis="Call date",COUNTIFS(Summary!$E$2:$E$240,$A22,Summary!$A$2:$A$240,">="&H4,Summary!$A$2:$A$240,"<"&H4+7,Summary!$A$2:$A$240,">="&IF(Dashboard!$B$3="",0,Dashboard!$B$3),Summary!$A$2:$A$240,"<"&IF(Dashboard!$B$4="",2958465,Dashboard!$B$4+1)),COUNTIFS(Summary!$E$2:$E$240,$A22,Summary!$D$2:$D$240,">="&H4,Summary!$D$2:$D$240,"<"&H4+7,Summary!$A$2:$A$240,">="&IF(Dashboard!$B$3="",0,Dashboard!$B$3),Summary!$A$2:$A$240,"<"&IF(Dashboard!$B$4="",2958465,Dashboard!$B$4+1)))) -> 0 | I22: =IF($A22="","",IF(hm_basis="Call date",COUNTIFS(Summary!$E$2:$E$240,$A22,Summary!$A$2:$A$240,">="&I4,Summary!$A$2:$A$240,"<"&I4+7,Summary!$A$2:$A$240,">="&IF(Dashboard!$B$3="",0,Dashboard!$B$3),Summary!$A$2:$A$240,"<"&IF(Dashboard!$B$4="",2958465,Dashboard!$B$4+1)),COUNTIFS(Summary!$E$2:$E$240,$A22,Summary!$D$2:$D$240,">="&I4,Summary!$D$2:$D$240,"<"&I4+7,Summary!$A$2:$A$240,">="&IF(Dashboard!$B$3="",0,Dashboard!$B$3),Summary!$A$2:$A$240,"<"&IF(Dashboard!$B$4="",2958465,Dashboard!$B$4+1)))) -> 0 | ... R22: =IF($A22="","",IF(hm_basis="Call date",COUNTIFS(Summary!$E$2:$E$240,$A22,Summary!$A$2:$A$240,">="&R4,Summary!$A$2:$A$240,"<"&R4+7,Summary!$A$2:$A$240,">="&IF(Dashboard!$B$3="",0,Dashboard!$B$3),Summary!$A$2:$A$240,"<"&IF(Dashboard!$B$4="",2958465,Dashboard!$B$4+1)),COUNTIFS(Summary!$E$2:$E$240,$A22,Summary!$D$2:$D$240,">="&R4,Summary!$D$2:$D$240,"<"&R4+7,Summary!$A$2:$A$240,">="&IF(Dashboard!$B$3="",0,Dashboard!$B$3),Summary!$A$2:$A$240,"<"&IF(Dashboard!$B$4="",2958465,Dashboard!$B$4+1)))) -> 0 | S22: =IF($A22="","",COUNTIFS(Summary!$E$2:$E$240,$A22,Summary!$A$2:$A$240,">="&Calc_Weekly!$A$123,Summary!$A$2:$A$240,"<"&Calc_Weekly!$A$123+7,Summary!$A$2:$A$240,">="&IF(Dashboard!$B$3="",0,Dashboard!$B$3),Summary!$A$2:$A$240,"<"&IF(Dashboard!$B$4="",2958465,Dashboard!$B$4+1))) -> 0 | T22: =IF($A22="","",COUNTIFS(Summary!$E$2:$E$240,$A22,Summary!$A$2:$A$240,">="&Calc_Weekly!$A$124,Summary!$A$2:$A$240,"<"&Calc_Weekly!$A$124+7,Summary!$A$2:$A$240,">="&IF(Dashboard!$B$3="",0,Dashboard!$B$3),Summary!$A$2:$A$240,"<"&IF(Dashboard!$B$4="",2958465,Dashboard!$B$4+1))) -> 0
A23: =IF(Settings!A22="","",Settings!A22) -> Return Air blocked | B23: =IF($A23="","",COUNTIFS(Summary!$E$2:$E$240,$A23,Summary!$A$2:$A$240,">="&Calc_Weekly!$A$106,Summary!$A$2:$A$240,"<"&Calc_Weekly!$A$106+7,Summary!$A$2:$A$240,">="&IF(Dashboard!$B$3="",0,Dashboard!$B$3),Summary!$A$2:$A$240,"<"&IF(Dashboard!$B$4="",2958465,Dashboard!$B$4+1))) -> 0 | C23: =IF($A23="","",COUNTIFS(Summary!$E$2:$E$240,$A23,Summary!$A$2:$A$240,">="&Calc_Weekly!$A$107,Summary!$A$2:$A$240,"<"&Calc_Weekly!$A$107+7,Summary!$A$2:$A$240,">="&IF(Dashboard!$B$3="",0,Dashboard!$B$3),Summary!$A$2:$A$240,"<"&IF(Dashboard!$B$4="",2958465,Dashboard!$B$4+1))) -> 0 | D23: =IF($A23="","",COUNTIFS(Summary!$E$2:$E$240,$A23,Summary!$A$2:$A$240,">="&Calc_Weekly!$A$108,Summary!$A$2:$A$240,"<"&Calc_Weekly!$A$108+7,Summary!$A$2:$A$240,">="&IF(Dashboard!$B$3="",0,Dashboard!$B$3),Summary!$A$2:$A$240,"<"&IF(Dashboard!$B$4="",2958465,Dashboard!$B$4+1))) -> 0 | E23: =IF($A23="","",COUNTIFS(Summary!$E$2:$E$240,$A23,Summary!$A$2:$A$240,">="&Calc_Weekly!$A$109,Summary!$A$2:$A$240,"<"&Calc_Weekly!$A$109+7,Summary!$A$2:$A$240,">="&IF(Dashboard!$B$3="",0,Dashboard!$B$3),Summary!$A$2:$A$240,"<"&IF(Dashboard!$B$4="",2958465,Dashboard!$B$4+1))) -> 0 | F23: =IF($A23="","",COUNTIFS(Summary!$E$2:$E$240,$A23,Summary!$A$2:$A$240,">="&Calc_Weekly!$A$110,Summary!$A$2:$A$240,"<"&Calc_Weekly!$A$110+7,Summary!$A$2:$A$240,">="&IF(Dashboard!$B$3="",0,Dashboard!$B$3),Summary!$A$2:$A$240,"<"&IF(Dashboard!$B$4="",2958465,Dashboard!$B$4+1))) -> 0 | G23: =IF($A23="","",COUNTIFS(Summary!$E$2:$E$240,$A23,Summary!$A$2:$A$240,">="&Calc_Weekly!$A$111,Summary!$A$2:$A$240,"<"&Calc_Weekly!$A$111+7,Summary!$A$2:$A$240,">="&IF(Dashboard!$B$3="",0,Dashboard!$B$3),Summary!$A$2:$A$240,"<"&IF(Dashboard!$B$4="",2958465,Dashboard!$B$4+1))) -> 0 | H23: =IF($A23="","",COUNTIFS(Summary!$E$2:$E$240,$A23,Summary!$A$2:$A$240,">="&Calc_Weekly!$A$112,Summary!$A$2:$A$240,"<"&Calc_Weekly!$A$112+7,Summary!$A$2:$A$240,">="&IF(Dashboard!$B$3="",0,Dashboard!$B$3),Summary!$A$2:$A$240,"<"&IF(Dashboard!$B$4="",2958465,Dashboard!$B$4+1))) -> 0 | I23: =IF($A23="","",COUNTIFS(Summary!$E$2:$E$240,$A23,Summary!$A$2:$A$240,">="&Calc_Weekly!$A$113,Summary!$A$2:$A$240,"<"&Calc_Weekly!$A$113+7,Summary!$A$2:$A$240,">="&IF(Dashboard!$B$3="",0,Dashboard!$B$3),Summary!$A$2:$A$240,"<"&IF(Dashboard!$B$4="",2958465,Dashboard!$B$4+1))) -> 0 | J23: =IF($A23="","",COUNTIFS(Summary!$E$2:$E$240,$A23,Summary!$A$2:$A$240,">="&Calc_Weekly!$A$114,Summary!$A$2:$A$240,"<"&Calc_Weekly!$A$114+7,Summary!$A$2:$A$240,">="&IF(Dashboard!$B$3="",0,Dashboard!$B$3),Summary!$A$2:$A$240,"<"&IF(Dashboard!$B$4="",2958465,Dashboard!$B$4+1))) -> 0 | K23: =IF($A23="","",COUNTIFS(Summary!$E$2:$E$240,$A23,Summary!$A$2:$A$240,">="&Calc_Weekly!$A$115,Summary!$A$2:$A$240,"<"&Calc_Weekly!$A$115+7,Summary!$A$2:$A$240,">="&IF(Dashboard!$B$3="",0,Dashboard!$B$3),Summary!$A$2:$A$240,"<"&IF(Dashboard!$B$4="",2958465,Dashboard!$B$4+1))) -> 0 | L23: =IF($A23="","",COUNTIFS(Summary!$E$2:$E$240,$A23,Summary!$A$2:$A$240,">="&Calc_Weekly!$A$116,Summary!$A$2:$A$240,"<"&Calc_Weekly!$A$116+7,Summary!$A$2:$A$240,">="&IF(Dashboard!$B$3="",0,Dashboard!$B$3),Summary!$A$2:$A$240,"<"&IF(Dashboard!$B$4="",2958465,Dashboard!$B$4+1))) -> 0 | M23: =IF($A23="","",COUNTIFS(Summary!$E$2:$E$240,$A23,Summary!$A$2:$A$240,">="&Calc_Weekly!$A$117,Summary!$A$2:$A$240,"<"&Calc_Weekly!$A$117+7,Summary!$A$2:$A$240,">="&IF(Dashboard!$B$3="",0,Dashboard!$B$3),Summary!$A$2:$A$240,"<"&IF(Dashboard!$B$4="",2958465,Dashboard!$B$4+1))) -> 0 | N23: =IF($A23="","",COUNTIFS(Summary!$E$2:$E$240,$A23,Summary!$A$2:$A$240,">="&Calc_Weekly!$A$118,Summary!$A$2:$A$240,"<"&Calc_Weekly!$A$118+7,Summary!$A$2:$A$240,">="&IF(Dashboard!$B$3="",0,Dashboard!$B$3),Summary!$A$2:$A$240,"<"&IF(Dashboard!$B$4="",2958465,Dashboard!$B$4+1))) -> 0 | O23: =IF($A23="","",COUNTIFS(Summary!$E$2:$E$240,$A23,Summary!$A$2:$A$240,">="&Calc_Weekly!$A$119,Summary!$A$2:$A$240,"<"&Calc_Weekly!$A$119+7,Summary!$A$2:$A$240,">="&IF(Dashboard!$B$3="",0,Dashboard!$B$3),Summary!$A$2:$A$240,"<"&IF(Dashboard!$B$4="",2958465,Dashboard!$B$4+1))) -> 0 | P23: =IF($A23="","",COUNTIFS(Summary!$E$2:$E$240,$A23,Summary!$A$2:$A$240,">="&Calc_Weekly!$A$120,Summary!$A$2:$A$240,"<"&Calc_Weekly!$A$120+7,Summary!$A$2:$A$240,">="&IF(Dashboard!$B$3="",0,Dashboard!$B$3),Summary!$A$2:$A$240,"<"&IF(Dashboard!$B$4="",2958465,Dashboard!$B$4+1))) -> 0 | Q23: =IF($A23="","",COUNTIFS(Summary!$E$2:$E$240,$A23,Summary!$A$2:$A$240,">="&Calc_Weekly!$A$121,Summary!$A$2:$A$240,"<"&Calc_Weekly!$A$121+7,Summary!$A$2:$A$240,">="&IF(Dashboard!$B$3="",0,Dashboard!$B$3),Summary!$A$2:$A$240,"<"&IF(Dashboard!$B$4="",2958465,Dashboard!$B$4+1))) -> 0 | R23: =IF($A23="","",COUNTIFS(Summary!$E$2:$E$240,$A23,Summary!$A$2:$A$240,">="&Calc_Weekly!$A$122,Summary!$A$2:$A$240,"<"&Calc_Weekly!$A$122+7,Summary!$A$2:$A$240,">="&IF(Dashboard!$B$3="",0,Dashboard!$B$3),Summary!$A$2:$A$240,"<"&IF(Dashboard!$B$4="",2958465,Dashboard!$B$4+1))) -> 0 | S23: =IF($A23="","",COUNTIFS(Summary!$E$2:$E$240,$A23,Summary!$A$2:$A$240,">="&Calc_Weekly!$A$123,Summary!$A$2:$A$240,"<"&Calc_Weekly!$A$123+7,Summary!$A$2:$A$240,">="&IF(Dashboard!$B$3="",0,Dashboard!$B$3),Summary!$A$2:$A$240,"<"&IF(Dashboard!$B$4="",2958465,Dashboard!$B$4+1))) -> 0 | T23: =IF($A23="","",COUNTIFS(Summary!$E$2:$E$240,$A23,Summary!$A$2:$A$240,">="&Calc_Weekly!$A$124,Summary!$A$2:$A$240,"<"&Calc_Weekly!$A$124+7,Summary!$A$2:$A$240,">="&IF(Dashboard!$B$3="",0,Dashboard!$B$3),Summary!$A$2:$A$240,"<"&IF(Dashboard!$B$4="",2958465,Dashboard!$B$4+1))) -> 0
A24: =IF(Settings!A23="","",Settings!A23) -> Unidentified air leak | B24: =IF($A24="","",COUNTIFS(Summary!$E$2:$E$240,$A24,Summary!$A$2:$A$240,">="&Calc_Weekly!$A$106,Summary!$A$2:$A$240,"<"&Calc_Weekly!$A$106+7,Summary!$A$2:$A$240,">="&IF(Dashboard!$B$3="",0,Dashboard!$B$3),Summary!$A$2:$A$240,"<"&IF(Dashboard!$B$4="",2958465,Dashboard!$B$4+1))) -> 0 | C24: =IF($A24="","",COUNTIFS(Summary!$E$2:$E$240,$A24,Summary!$A$2:$A$240,">="&Calc_Weekly!$A$107,Summary!$A$2:$A$240,"<"&Calc_Weekly!$A$107+7,Summary!$A$2:$A$240,">="&IF(Dashboard!$B$3="",0,Dashboard!$B$3),Summary!$A$2:$A$240,"<"&IF(Dashboard!$B$4="",2958465,Dashboard!$B$4+1))) -> 0 | D24: =IF($A24="","",COUNTIFS(Summary!$E$2:$E$240,$A24,Summary!$A$2:$A$240,">="&Calc_Weekly!$A$108,Summary!$A$2:$A$240,"<"&Calc_Weekly!$A$108+7,Summary!$A$2:$A$240,">="&IF(Dashboard!$B$3="",0,Dashboard!$B$3),Summary!$A$2:$A$240,"<"&IF(Dashboard!$B$4="",2958465,Dashboard!$B$4+1))) -> 0 | E24: =IF($A24="","",COUNTIFS(Summary!$E$2:$E$240,$A24,Summary!$A$2:$A$240,">="&Calc_Weekly!$A$109,Summary!$A$2:$A$240,"<"&Calc_Weekly!$A$109+7,Summary!$A$2:$A$240,">="&IF(Dashboard!$B$3="",0,Dashboard!$B$3),Summary!$A$2:$A$240,"<"&IF(Dashboard!$B$4="",2958465,Dashboard!$B$4+1))) -> 0 | F24: =IF($A24="","",COUNTIFS(Summary!$E$2:$E$240,$A24,Summary!$A$2:$A$240,">="&Calc_Weekly!$A$110,Summary!$A$2:$A$240,"<"&Calc_Weekly!$A$110+7,Summary!$A$2:$A$240,">="&IF(Dashboard!$B$3="",0,Dashboard!$B$3),Summary!$A$2:$A$240,"<"&IF(Dashboard!$B$4="",2958465,Dashboard!$B$4+1))) -> 0 | G24: =IF($A24="","",COUNTIFS(Summary!$E$2:$E$240,$A24,Summary!$A$2:$A$240,">="&Calc_Weekly!$A$111,Summary!$A$2:$A$240,"<"&Calc_Weekly!$A$111+7,Summary!$A$2:$A$240,">="&IF(Dashboard!$B$3="",0,Dashboard!$B$3),Summary!$A$2:$A$240,"<"&IF(Dashboard!$B$4="",2958465,Dashboard!$B$4+1))) -> 0 | H24: =IF($A24="","",COUNTIFS(Summary!$E$2:$E$240,$A24,Summary!$A$2:$A$240,">="&Calc_Weekly!$A$112,Summary!$A$2:$A$240,"<"&Calc_Weekly!$A$112+7,Summary!$A$2:$A$240,">="&IF(Dashboard!$B$3="",0,Dashboard!$B$3),Summary!$A$2:$A$240,"<"&IF(Dashboard!$B$4="",2958465,Dashboard!$B$4+1))) -> 0 | I24: =IF($A24="","",COUNTIFS(Summary!$E$2:$E$240,$A24,Summary!$A$2:$A$240,">="&Calc_Weekly!$A$113,Summary!$A$2:$A$240,"<"&Calc_Weekly!$A$113+7,Summary!$A$2:$A$240,">="&IF(Dashboard!$B$3="",0,Dashboard!$B$3),Summary!$A$2:$A$240,"<"&IF(Dashboard!$B$4="",2958465,Dashboard!$B$4+1))) -> 0 | J24: =IF($A24="","",COUNTIFS(Summary!$E$2:$E$240,$A24,Summary!$A$2:$A$240,">="&Calc_Weekly!$A$114,Summary!$A$2:$A$240,"<"&Calc_Weekly!$A$114+7,Summary!$A$2:$A$240,">="&IF(Dashboard!$B$3="",0,Dashboard!$B$3),Summary!$A$2:$A$240,"<"&IF(Dashboard!$B$4="",2958465,Dashboard!$B$4+1))) -> 0 | K24: =IF($A24="","",COUNTIFS(Summary!$E$2:$E$240,$A24,Summary!$A$2:$A$240,">="&Calc_Weekly!$A$115,Summary!$A$2:$A$240,"<"&Calc_Weekly!$A$115+7,Summary!$A$2:$A$240,">="&IF(Dashboard!$B$3="",0,Dashboard!$B$3),Summary!$A$2:$A$240,"<"&IF(Dashboard!$B$4="",2958465,Dashboard!$B$4+1))) -> 0 | L24: =IF($A24="","",COUNTIFS(Summary!$E$2:$E$240,$A24,Summary!$A$2:$A$240,">="&Calc_Weekly!$A$116,Summary!$A$2:$A$240,"<"&Calc_Weekly!$A$116+7,Summary!$A$2:$A$240,">="&IF(Dashboard!$B$3="",0,Dashboard!$B$3),Summary!$A$2:$A$240,"<"&IF(Dashboard!$B$4="",2958465,Dashboard!$B$4+1))) -> 0 | M24: =IF($A24="","",COUNTIFS(Summary!$E$2:$E$240,$A24,Summary!$A$2:$A$240,">="&Calc_Weekly!$A$117,Summary!$A$2:$A$240,"<"&Calc_Weekly!$A$117+7,Summary!$A$2:$A$240,">="&IF(Dashboard!$B$3="",0,Dashboard!$B$3),Summary!$A$2:$A$240,"<"&IF(Dashboard!$B$4="",2958465,Dashboard!$B$4+1))) -> 0 | N24: =IF($A24="","",COUNTIFS(Summary!$E$2:$E$240,$A24,Summary!$A$2:$A$240,">="&Calc_Weekly!$A$118,Summary!$A$2:$A$240,"<"&Calc_Weekly!$A$118+7,Summary!$A$2:$A$240,">="&IF(Dashboard!$B$3="",0,Dashboard!$B$3),Summary!$A$2:$A$240,"<"&IF(Dashboard!$B$4="",2958465,Dashboard!$B$4+1))) -> 0 | O24: =IF($A24="","",COUNTIFS(Summary!$E$2:$E$240,$A24,Summary!$A$2:$A$240,">="&Calc_Weekly!$A$119,Summary!$A$2:$A$240,"<"&Calc_Weekly!$A$119+7,Summary!$A$2:$A$240,">="&IF(Dashboard!$B$3="",0,Dashboard!$B$3),Summary!$A$2:$A$240,"<"&IF(Dashboard!$B$4="",2958465,Dashboard!$B$4+1))) -> 0 | P24: =IF($A24="","",COUNTIFS(Summary!$E$2:$E$240,$A24,Summary!$A$2:$A$240,">="&Calc_Weekly!$A$120,Summary!$A$2:$A$240,"<"&Calc_Weekly!$A$120+7,Summary!$A$2:$A$240,">="&IF(Dashboard!$B$3="",0,Dashboard!$B$3),Summary!$A$2:$A$240,"<"&IF(Dashboard!$B$4="",2958465,Dashboard!$B$4+1))) -> 0 | Q24: =IF($A24="","",COUNTIFS(Summary!$E$2:$E$240,$A24,Summary!$A$2:$A$240,">="&Calc_Weekly!$A$121,Summary!$A$2:$A$240,"<"&Calc_Weekly!$A$121+7,Summary!$A$2:$A$240,">="&IF(Dashboard!$B$3="",0,Dashboard!$B$3),Summary!$A$2:$A$240,"<"&IF(Dashboard!$B$4="",2958465,Dashboard!$B$4+1))) -> 0 | R24: =IF($A24="","",COUNTIFS(Summary!$E$2:$E$240,$A24,Summary!$A$2:$A$240,">="&Calc_Weekly!$A$122,Summary!$A$2:$A$240,"<"&Calc_Weekly!$A$122+7,Summary!$A$2:$A$240,">="&IF(Dashboard!$B$3="",0,Dashboard!$B$3),Summary!$A$2:$A$240,"<"&IF(Dashboard!$B$4="",2958465,Dashboard!$B$4+1))) -> 0 | S24: =IF($A24="","",COUNTIFS(Summary!$E$2:$E$240,$A24,Summary!$A$2:$A$240,">="&Calc_Weekly!$A$123,Summary!$A$2:$A$240,"<"&Calc_Weekly!$A$123+7,Summary!$A$2:$A$240,">="&IF(Dashboard!$B$3="",0,Dashboard!$B$3),Summary!$A$2:$A$240,"<"&IF(Dashboard!$B$4="",2958465,Dashboard!$B$4+1))) -> 0 | T24: =IF($A24="","",COUNTIFS(Summary!$E$2:$E$240,$A24,Summary!$A$2:$A$240,">="&Calc_Weekly!$A$124,Summary!$A$2:$A$240,"<"&Calc_Weekly!$A$124+7,Summary!$A$2:$A$240,">="&IF(Dashboard!$B$3="",0,Dashboard!$B$3),Summary!$A$2:$A$240,"<"&IF(Dashboard!$B$4="",2958465,Dashboard!$B$4+1))) -> 1
A25: =IF(Settings!A24="","",Settings!A24) -> Freedom | B25: =IF($A25="","",COUNTIFS(Summary!$E$2:$E$240,$A25,Summary!$A$2:$A$240,">="&Calc_Weekly!$A$106,Summary!$A$2:$A$240,"<"&Calc_Weekly!$A$106+7,Summary!$A$2:$A$240,">="&IF(Dashboard!$B$3="",0,Dashboard!$B$3),Summary!$A$2:$A$240,"<"&IF(Dashboard!$B$4="",2958465,Dashboard!$B$4+1))) -> 0 | C25: =IF($A25="","",COUNTIFS(Summary!$E$2:$E$240,$A25,Summary!$A$2:$A$240,">="&Calc_Weekly!$A$107,Summary!$A$2:$A$240,"<"&Calc_Weekly!$A$107+7,Summary!$A$2:$A$240,">="&IF(Dashboard!$B$3="",0,Dashboard!$B$3),Summary!$A$2:$A$240,"<"&IF(Dashboard!$B$4="",2958465,Dashboard!$B$4+1))) -> 0 | D25: =IF($A25="","",COUNTIFS(Summary!$E$2:$E$240,$A25,Summary!$A$2:$A$240,">="&Calc_Weekly!$A$108,Summary!$A$2:$A$240,"<"&Calc_Weekly!$A$108+7,Summary!$A$2:$A$240,">="&IF(Dashboard!$B$3="",0,Dashboard!$B$3),Summary!$A$2:$A$240,"<"&IF(Dashboard!$B$4="",2958465,Dashboard!$B$4+1))) -> 0 | E25: =IF($A25="","",COUNTIFS(Summary!$E$2:$E$240,$A25,Summary!$A$2:$A$240,">="&Calc_Weekly!$A$109,Summary!$A$2:$A$240,"<"&Calc_Weekly!$A$109+7,Summary!$A$2:$A$240,">="&IF(Dashboard!$B$3="",0,Dashboard!$B$3),Summary!$A$2:$A$240,"<"&IF(Dashboard!$B$4="",2958465,Dashboard!$B$4+1))) -> 0 | F25: =IF($A25="","",COUNTIFS(Summary!$E$2:$E$240,$A25,Summary!$A$2:$A$240,">="&Calc_Weekly!$A$110,Summary!$A$2:$A$240,"<"&Calc_Weekly!$A$110+7,Summary!$A$2:$A$240,">="&IF(Dashboard!$B$3="",0,Dashboard!$B$3),Summary!$A$2:$A$240,"<"&IF(Dashboard!$B$4="",2958465,Dashboard!$B$4+1))) -> 0 | G25: =IF($A25="","",COUNTIFS(Summary!$E$2:$E$240,$A25,Summary!$A$2:$A$240,">="&Calc_Weekly!$A$111,Summary!$A$2:$A$240,"<"&Calc_Weekly!$A$111+7,Summary!$A$2:$A$240,">="&IF(Dashboard!$B$3="",0,Dashboard!$B$3),Summary!$A$2:$A$240,"<"&IF(Dashboard!$B$4="",2958465,Dashboard!$B$4+1))) -> 0 | H25: =IF($A25="","",COUNTIFS(Summary!$E$2:$E$240,$A25,Summary!$A$2:$A$240,">="&Calc_Weekly!$A$112,Summary!$A$2:$A$240,"<"&Calc_Weekly!$A$112+7,Summary!$A$2:$A$240,">="&IF(Dashboard!$B$3="",0,Dashboard!$B$3),Summary!$A$2:$A$240,"<"&IF(Dashboard!$B$4="",2958465,Dashboard!$B$4+1))) -> 0 | I25: =IF($A25="","",COUNTIFS(Summary!$E$2:$E$240,$A25,Summary!$A$2:$A$240,">="&Calc_Weekly!$A$113,Summary!$A$2:$A$240,"<"&Calc_Weekly!$A$113+7,Summary!$A$2:$A$240,">="&IF(Dashboard!$B$3="",0,Dashboard!$B$3),Summary!$A$2:$A$240,"<"&IF(Dashboard!$B$4="",2958465,Dashboard!$B$4+1))) -> 0 | J25: =IF($A25="","",COUNTIFS(Summary!$E$2:$E$240,$A25,Summary!$A$2:$A$240,">="&Calc_Weekly!$A$114,Summary!$A$2:$A$240,"<"&Calc_Weekly!$A$114+7,Summary!$A$2:$A$240,">="&IF(Dashboard!$B$3="",0,Dashboard!$B$3),Summary!$A$2:$A$240,"<"&IF(Dashboard!$B$4="",2958465,Dashboard!$B$4+1))) -> 0 | K25: =IF($A25="","",COUNTIFS(Summary!$E$2:$E$240,$A25,Summary!$A$2:$A$240,">="&Calc_Weekly!$A$115,Summary!$A$2:$A$240,"<"&Calc_Weekly!$A$115+7,Summary!$A$2:$A$240,">="&IF(Dashboard!$B$3="",0,Dashboard!$B$3),Summary!$A$2:$A$240,"<"&IF(Dashboard!$B$4="",2958465,Dashboard!$B$4+1))) -> 0 | L25: =IF($A25="","",COUNTIFS(Summary!$E$2:$E$240,$A25,Summary!$A$2:$A$240,">="&Calc_Weekly!$A$116,Summary!$A$2:$A$240,"<"&Calc_Weekly!$A$116+7,Summary!$A$2:$A$240,">="&IF(Dashboard!$B$3="",0,Dashboard!$B$3),Summary!$A$2:$A$240,"<"&IF(Dashboard!$B$4="",2958465,Dashboard!$B$4+1))) -> 0 | M25: =IF($A25="","",COUNTIFS(Summary!$E$2:$E$240,$A25,Summary!$A$2:$A$240,">="&Calc_Weekly!$A$117,Summary!$A$2:$A$240,"<"&Calc_Weekly!$A$117+7,Summary!$A$2:$A$240,">="&IF(Dashboard!$B$3="",0,Dashboard!$B$3),Summary!$A$2:$A$240,"<"&IF(Dashboard!$B$4="",2958465,Dashboard!$B$4+1))) -> 0 | N25: =IF($A25="","",COUNTIFS(Summary!$E$2:$E$240,$A25,Summary!$A$2:$A$240,">="&Calc_Weekly!$A$118,Summary!$A$2:$A$240,"<"&Calc_Weekly!$A$118+7,Summary!$A$2:$A$240,">="&IF(Dashboard!$B$3="",0,Dashboard!$B$3),Summary!$A$2:$A$240,"<"&IF(Dashboard!$B$4="",2958465,Dashboard!$B$4+1))) -> 1 | O25: =IF($A25="","",COUNTIFS(Summary!$E$2:$E$240,$A25,Summary!$A$2:$A$240,">="&Calc_Weekly!$A$119,Summary!$A$2:$A$240,"<"&Calc_Weekly!$A$119+7,Summary!$A$2:$A$240,">="&IF(Dashboard!$B$3="",0,Dashboard!$B$3),Summary!$A$2:$A$240,"<"&IF(Dashboard!$B$4="",2958465,Dashboard!$B$4+1))) -> 0 | P25: =IF($A25="","",COUNTIFS(Summary!$E$2:$E$240,$A25,Summary!$A$2:$A$240,">="&Calc_Weekly!$A$120,Summary!$A$2:$A$240,"<"&Calc_Weekly!$A$120+7,Summary!$A$2:$A$240,">="&IF(Dashboard!$B$3="",0,Dashboard!$B$3),Summary!$A$2:$A$240,"<"&IF(Dashboard!$B$4="",2958465,Dashboard!$B$4+1))) -> 0 | Q25: =IF($A25="","",COUNTIFS(Summary!$E$2:$E$240,$A25,Summary!$A$2:$A$240,">="&Calc_Weekly!$A$121,Summary!$A$2:$A$240,"<"&Calc_Weekly!$A$121+7,Summary!$A$2:$A$240,">="&IF(Dashboard!$B$3="",0,Dashboard!$B$3),Summary!$A$2:$A$240,"<"&IF(Dashboard!$B$4="",2958465,Dashboard!$B$4+1))) -> 0 | R25: =IF($A25="","",COUNTIFS(Summary!$E$2:$E$240,$A25,Summary!$A$2:$A$240,">="&Calc_Weekly!$A$122,Summary!$A$2:$A$240,"<"&Calc_Weekly!$A$122+7,Summary!$A$2:$A$240,">="&IF(Dashboard!$B$3="",0,Dashboard!$B$3),Summary!$A$2:$A$240,"<"&IF(Dashboard!$B$4="",2958465,Dashboard!$B$4+1))) -> 0 | S25: =IF($A25="","",COUNTIFS(Summary!$E$2:$E$240,$A25,Summary!$A$2:$A$240,">="&Calc_Weekly!$A$123,Summary!$A$2:$A$240,"<"&Calc_Weekly!$A$123+7,Summary!$A$2:$A$240,">="&IF(Dashboard!$B$3="",0,Dashboard!$B$3),Summary!$A$2:$A$240,"<"&IF(Dashboard!$B$4="",2958465,Dashboard!$B$4+1))) -> 0 | T25: =IF($A25="","",COUNTIFS(Summary!$E$2:$E$240,$A25,Summary!$A$2:$A$240,">="&Calc_Weekly!$A$124,Summary!$A$2:$A$240,"<"&Calc_Weekly!$A$124+7,Summary!$A$2:$A$240,">="&IF(Dashboard!$B$3="",0,Dashboard!$B$3),Summary!$A$2:$A$240,"<"&IF(Dashboard!$B$4="",2958465,Dashboard!$B$4+1))) -> 0
A26: =IF(Settings!A25="","",Settings!A25) -> Heavy case load | B26: =IF($A26="","",COUNTIFS(Summary!$E$2:$E$240,$A26,Summary!$A$2:$A$240,">="&Calc_Weekly!$A$106,Summary!$A$2:$A$240,"<"&Calc_Weekly!$A$106+7,Summary!$A$2:$A$240,">="&IF(Dashboard!$B$3="",0,Dashboard!$B$3),Summary!$A$2:$A$240,"<"&IF(Dashboard!$B$4="",2958465,Dashboard!$B$4+1))) -> 0 | C26: =IF($A26="","",COUNTIFS(Summary!$E$2:$E$240,$A26,Summary!$A$2:$A$240,">="&Calc_Weekly!$A$107,Summary!$A$2:$A$240,"<"&Calc_Weekly!$A$107+7,Summary!$A$2:$A$240,">="&IF(Dashboard!$B$3="",0,Dashboard!$B$3),Summary!$A$2:$A$240,"<"&IF(Dashboard!$B$4="",2958465,Dashboard!$B$4+1))) -> 0 | D26: =IF($A26="","",COUNTIFS(Summary!$E$2:$E$240,$A26,Summary!$A$2:$A$240,">="&Calc_Weekly!$A$108,Summary!$A$2:$A$240,"<"&Calc_Weekly!$A$108+7,Summary!$A$2:$A$240,">="&IF(Dashboard!$B$3="",0,Dashboard!$B$3),Summary!$A$2:$A$240,"<"&IF(Dashboard!$B$4="",2958465,Dashboard!$B$4+1))) -> 0 | E26: =IF($A26="","",COUNTIFS(Summary!$E$2:$E$240,$A26,Summary!$A$2:$A$240,">="&Calc_Weekly!$A$109,Summary!$A$2:$A$240,"<"&Calc_Weekly!$A$109+7,Summary!$A$2:$A$240,">="&IF(Dashboard!$B$3="",0,Dashboard!$B$3),Summary!$A$2:$A$240,"<"&IF(Dashboard!$B$4="",2958465,Dashboard!$B$4+1))) -> 0 | F26: =IF($A26="","",COUNTIFS(Summary!$E$2:$E$240,$A26,Summary!$A$2:$A$240,">="&Calc_Weekly!$A$110,Summary!$A$2:$A$240,"<"&Calc_Weekly!$A$110+7,Summary!$A$2:$A$240,">="&IF(Dashboard!$B$3="",0,Dashboard!$B$3),Summary!$A$2:$A$240,"<"&IF(Dashboard!$B$4="",2958465,Dashboard!$B$4+1))) -> 0 | G26: =IF($A26="","",COUNTIFS(Summary!$E$2:$E$240,$A26,Summary!$A$2:$A$240,">="&Calc_Weekly!$A$111,Summary!$A$2:$A$240,"<"&Calc_Weekly!$A$111+7,Summary!$A$2:$A$240,">="&IF(Dashboard!$B$3="",0,Dashboard!$B$3),Summary!$A$2:$A$240,"<"&IF(Dashboard!$B$4="",2958465,Dashboard!$B$4+1))) -> 0 | H26: =IF($A26="","",COUNTIFS(Summary!$E$2:$E$240,$A26,Summary!$A$2:$A$240,">="&Calc_Weekly!$A$112,Summary!$A$2:$A$240,"<"&Calc_Weekly!$A$112+7,Summary!$A$2:$A$240,">="&IF(Dashboard!$B$3="",0,Dashboard!$B$3),Summary!$A$2:$A$240,"<"&IF(Dashboard!$B$4="",2958465,Dashboard!$B$4+1))) -> 0 | I26: =IF($A26="","",COUNTIFS(Summary!$E$2:$E$240,$A26,Summary!$A$2:$A$240,">="&Calc_Weekly!$A$113,Summary!$A$2:$A$240,"<"&Calc_Weekly!$A$113+7,Summary!$A$2:$A$240,">="&IF(Dashboard!$B$3="",0,Dashboard!$B$3),Summary!$A$2:$A$240,"<"&IF(Dashboard!$B$4="",2958465,Dashboard!$B$4+1))) -> 0 | J26: =IF($A26="","",COUNTIFS(Summary!$E$2:$E$240,$A26,Summary!$A$2:$A$240,">="&Calc_Weekly!$A$114,Summary!$A$2:$A$240,"<"&Calc_Weekly!$A$114+7,Summary!$A$2:$A$240,">="&IF(Dashboard!$B$3="",0,Dashboard!$B$3),Summary!$A$2:$A$240,"<"&IF(Dashboard!$B$4="",2958465,Dashboard!$B$4+1))) -> 0 | K26: =IF($A26="","",COUNTIFS(Summary!$E$2:$E$240,$A26,Summary!$A$2:$A$240,">="&Calc_Weekly!$A$115,Summary!$A$2:$A$240,"<"&Calc_Weekly!$A$115+7,Summary!$A$2:$A$240,">="&IF(Dashboard!$B$3="",0,Dashboard!$B$3),Summary!$A$2:$A$240,"<"&IF(Dashboard!$B$4="",2958465,Dashboard!$B$4+1))) -> 0 | L26: =IF($A26="","",COUNTIFS(Summary!$E$2:$E$240,$A26,Summary!$A$2:$A$240,">="&Calc_Weekly!$A$116,Summary!$A$2:$A$240,"<"&Calc_Weekly!$A$116+7,Summary!$A$2:$A$240,">="&IF(Dashboard!$B$3="",0,Dashboard!$B$3),Summary!$A$2:$A$240,"<"&IF(Dashboard!$B$4="",2958465,Dashboard!$B$4+1))) -> 0 | M26: =IF($A26="","",COUNTIFS(Summary!$E$2:$E$240,$A26,Summary!$A$2:$A$240,">="&Calc_Weekly!$A$117,Summary!$A$2:$A$240,"<"&Calc_Weekly!$A$117+7,Summary!$A$2:$A$240,">="&IF(Dashboard!$B$3="",0,Dashboard!$B$3),Summary!$A$2:$A$240,"<"&IF(Dashboard!$B$4="",2958465,Dashboard!$B$4+1))) -> 0 | N26: =IF($A26="","",COUNTIFS(Summary!$E$2:$E$240,$A26,Summary!$A$2:$A$240,">="&Calc_Weekly!$A$118,Summary!$A$2:$A$240,"<"&Calc_Weekly!$A$118+7,Summary!$A$2:$A$240,">="&IF(Dashboard!$B$3="",0,Dashboard!$B$3),Summary!$A$2:$A$240,"<"&IF(Dashboard!$B$4="",2958465,Dashboard!$B$4+1))) -> 0 | O26: =IF($A26="","",COUNTIFS(Summary!$E$2:$E$240,$A26,Summary!$A$2:$A$240,">="&Calc_Weekly!$A$119,Summary!$A$2:$A$240,"<"&Calc_Weekly!$A$119+7,Summary!$A$2:$A$240,">="&IF(Dashboard!$B$3="",0,Dashboard!$B$3),Summary!$A$2:$A$240,"<"&IF(Dashboard!$B$4="",2958465,Dashboard!$B$4+1))) -> 0 | P26: =IF($A26="","",COUNTIFS(Summary!$E$2:$E$240,$A26,Summary!$A$2:$A$240,">="&Calc_Weekly!$A$120,Summary!$A$2:$A$240,"<"&Calc_Weekly!$A$120+7,Summary!$A$2:$A$240,">="&IF(Dashboard!$B$3="",0,Dashboard!$B$3),Summary!$A$2:$A$240,"<"&IF(Dashboard!$B$4="",2958465,Dashboard!$B$4+1))) -> 0 | Q26: =IF($A26="","",COUNTIFS(Summary!$E$2:$E$240,$A26,Summary!$A$2:$A$240,">="&Calc_Weekly!$A$121,Summary!$A$2:$A$240,"<"&Calc_Weekly!$A$121+7,Summary!$A$2:$A$240,">="&IF(Dashboard!$B$3="",0,Dashboard!$B$3),Summary!$A$2:$A$240,"<"&IF(Dashboard!$B$4="",2958465,Dashboard!$B$4+1))) -> 0 | R26: =IF($A26="","",COUNTIFS(Summary!$E$2:$E$240,$A26,Summary!$A$2:$A$240,">="&Calc_Weekly!$A$122,Summary!$A$2:$A$240,"<"&Calc_Weekly!$A$122+7,Summary!$A$2:$A$240,">="&IF(Dashboard!$B$3="",0,Dashboard!$B$3),Summary!$A$2:$A$240,"<"&IF(Dashboard!$B$4="",2958465,Dashboard!$B$4+1))) -> 0 | S26: =IF($A26="","",COUNTIFS(Summary!$E$2:$E$240,$A26,Summary!$A$2:$A$240,">="&Calc_Weekly!$A$123,Summary!$A$2:$A$240,"<"&Calc_Weekly!$A$123+7,Summary!$A$2:$A$240,">="&IF(Dashboard!$B$3="",0,Dashboard!$B$3),Summary!$A$2:$A$240,"<"&IF(Dashboard!$B$4="",2958465,Dashboard!$B$4+1))) -> 0 | T26: =IF($A26="","",COUNTIFS(Summary!$E$2:$E$240,$A26,Summary!$A$2:$A$240,">="&Calc_Weekly!$A$124,Summary!$A$2:$A$240,"<"&Calc_Weekly!$A$124+7,Summary!$A$2:$A$240,">="&IF(Dashboard!$B$3="",0,Dashboard!$B$3),Summary!$A$2:$A$240,"<"&IF(Dashboard!$B$4="",2958465,Dashboard!$B$4+1))) -> 0
A27: =IF(Settings!A26="","",Settings!A26) -> Installation issue | B27: =IF($A27="","",COUNTIFS(Summary!$E$2:$E$240,$A27,Summary!$A$2:$A$240,">="&Calc_Weekly!$A$106,Summary!$A$2:$A$240,"<"&Calc_Weekly!$A$106+7,Summary!$A$2:$A$240,">="&IF(Dashboard!$B$3="",0,Dashboard!$B$3),Summary!$A$2:$A$240,"<"&IF(Dashboard!$B$4="",2958465,Dashboard!$B$4+1))) -> 0 | C27: =IF($A27="","",COUNTIFS(Summary!$E$2:$E$240,$A27,Summary!$A$2:$A$240,">="&Calc_Weekly!$A$107,Summary!$A$2:$A$240,"<"&Calc_Weekly!$A$107+7,Summary!$A$2:$A$240,">="&IF(Dashboard!$B$3="",0,Dashboard!$B$3),Summary!$A$2:$A$240,"<"&IF(Dashboard!$B$4="",2958465,Dashboard!$B$4+1))) -> 0 | D27: =IF($A27="","",COUNTIFS(Summary!$E$2:$E$240,$A27,Summary!$A$2:$A$240,">="&Calc_Weekly!$A$108,Summary!$A$2:$A$240,"<"&Calc_Weekly!$A$108+7,Summary!$A$2:$A$240,">="&IF(Dashboard!$B$3="",0,Dashboard!$B$3),Summary!$A$2:$A$240,"<"&IF(Dashboard!$B$4="",2958465,Dashboard!$B$4+1))) -> 0 | E27: =IF($A27="","",COUNTIFS(Summary!$E$2:$E$240,$A27,Summary!$A$2:$A$240,">="&Calc_Weekly!$A$109,Summary!$A$2:$A$240,"<"&Calc_Weekly!$A$109+7,Summary!$A$2:$A$240,">="&IF(Dashboard!$B$3="",0,Dashboard!$B$3),Summary!$A$2:$A$240,"<"&IF(Dashboard!$B$4="",2958465,Dashboard!$B$4+1))) -> 0 | F27: =IF($A27="","",COUNTIFS(Summary!$E$2:$E$240,$A27,Summary!$A$2:$A$240,">="&Calc_Weekly!$A$110,Summary!$A$2:$A$240,"<"&Calc_Weekly!$A$110+7,Summary!$A$2:$A$240,">="&IF(Dashboard!$B$3="",0,Dashboard!$B$3),Summary!$A$2:$A$240,"<"&IF(Dashboard!$B$4="",2958465,Dashboard!$B$4+1))) -> 0 | G27: =IF($A27="","",COUNTIFS(Summary!$E$2:$E$240,$A27,Summary!$A$2:$A$240,">="&Calc_Weekly!$A$111,Summary!$A$2:$A$240,"<"&Calc_Weekly!$A$111+7,Summary!$A$2:$A$240,">="&IF(Dashboard!$B$3="",0,Dashboard!$B$3),Summary!$A$2:$A$240,"<"&IF(Dashboard!$B$4="",2958465,Dashboard!$B$4+1))) -> 0 | H27: =IF($A27="","",COUNTIFS(Summary!$E$2:$E$240,$A27,Summary!$A$2:$A$240,">="&Calc_Weekly!$A$112,Summary!$A$2:$A$240,"<"&Calc_Weekly!$A$112+7,Summary!$A$2:$A$240,">="&IF(Dashboard!$B$3="",0,Dashboard!$B$3),Summary!$A$2:$A$240,"<"&IF(Dashboard!$B$4="",2958465,Dashboard!$B$4+1))) -> 0 | I27: =IF($A27="","",COUNTIFS(Summary!$E$2:$E$240,$A27,Summary!$A$2:$A$240,">="&Calc_Weekly!$A$113,Summary!$A$2:$A$240,"<"&Calc_Weekly!$A$113+7,Summary!$A$2:$A$240,">="&IF(Dashboard!$B$3="",0,Dashboard!$B$3),Summary!$A$2:$A$240,"<"&IF(Dashboard!$B$4="",2958465,Dashboard!$B$4+1))) -> 0 | J27: =IF($A27="","",COUNTIFS(Summary!$E$2:$E$240,$A27,Summary!$A$2:$A$240,">="&Calc_Weekly!$A$114,Summary!$A$2:$A$240,"<"&Calc_Weekly!$A$114+7,Summary!$A$2:$A$240,">="&IF(Dashboard!$B$3="",0,Dashboard!$B$3),Summary!$A$2:$A$240,"<"&IF(Dashboard!$B$4="",2958465,Dashboard!$B$4+1))) -> 0 | K27: =IF($A27="","",COUNTIFS(Summary!$E$2:$E$240,$A27,Summary!$A$2:$A$240,">="&Calc_Weekly!$A$115,Summary!$A$2:$A$240,"<"&Calc_Weekly!$A$115+7,Summary!$A$2:$A$240,">="&IF(Dashboard!$B$3="",0,Dashboard!$B$3),Summary!$A$2:$A$240,"<"&IF(Dashboard!$B$4="",2958465,Dashboard!$B$4+1))) -> 0 | L27: =IF($A27="","",COUNTIFS(Summary!$E$2:$E$240,$A27,Summary!$A$2:$A$240,">="&Calc_Weekly!$A$116,Summary!$A$2:$A$240,"<"&Calc_Weekly!$A$116+7,Summary!$A$2:$A$240,">="&IF(Dashboard!$B$3="",0,Dashboard!$B$3),Summary!$A$2:$A$240,"<"&IF(Dashboard!$B$4="",2958465,Dashboard!$B$4+1))) -> 0 | M27: =IF($A27="","",COUNTIFS(Summary!$E$2:$E$240,$A27,Summary!$A$2:$A$240,">="&Calc_Weekly!$A$117,Summary!$A$2:$A$240,"<"&Calc_Weekly!$A$117+7,Summary!$A$2:$A$240,">="&IF(Dashboard!$B$3="",0,Dashboard!$B$3),Summary!$A$2:$A$240,"<"&IF(Dashboard!$B$4="",2958465,Dashboard!$B$4+1))) -> 0 | N27: =IF($A27="","",COUNTIFS(Summary!$E$2:$E$240,$A27,Summary!$A$2:$A$240,">="&Calc_Weekly!$A$118,Summary!$A$2:$A$240,"<"&Calc_Weekly!$A$118+7,Summary!$A$2:$A$240,">="&IF(Dashboard!$B$3="",0,Dashboard!$B$3),Summary!$A$2:$A$240,"<"&IF(Dashboard!$B$4="",2958465,Dashboard!$B$4+1))) -> 0 | O27: =IF($A27="","",COUNTIFS(Summary!$E$2:$E$240,$A27,Summary!$A$2:$A$240,">="&Calc_Weekly!$A$119,Summary!$A$2:$A$240,"<"&Calc_Weekly!$A$119+7,Summary!$A$2:$A$240,">="&IF(Dashboard!$B$3="",0,Dashboard!$B$3),Summary!$A$2:$A$240,"<"&IF(Dashboard!$B$4="",2958465,Dashboard!$B$4+1))) -> 3 | P27: =IF($A27="","",COUNTIFS(Summary!$E$2:$E$240,$A27,Summary!$A$2:$A$240,">="&Calc_Weekly!$A$120,Summary!$A$2:$A$240,"<"&Calc_Weekly!$A$120+7,Summary!$A$2:$A$240,">="&IF(Dashboard!$B$3="",0,Dashboard!$B$3),Summary!$A$2:$A$240,"<"&IF(Dashboard!$B$4="",2958465,Dashboard!$B$4+1))) -> 0 | Q27: =IF($A27="","",COUNTIFS(Summary!$E$2:$E$240,$A27,Summary!$A$2:$A$240,">="&Calc_Weekly!$A$121,Summary!$A$2:$A$240,"<"&Calc_Weekly!$A$121+7,Summary!$A$2:$A$240,">="&IF(Dashboard!$B$3="",0,Dashboard!$B$3),Summary!$A$2:$A$240,"<"&IF(Dashboard!$B$4="",2958465,Dashboard!$B$4+1))) -> 1 | R27: =IF($A27="","",COUNTIFS(Summary!$E$2:$E$240,$A27,Summary!$A$2:$A$240,">="&Calc_Weekly!$A$122,Summary!$A$2:$A$240,"<"&Calc_Weekly!$A$122+7,Summary!$A$2:$A$240,">="&IF(Dashboard!$B$3="",0,Dashboard!$B$3),Summary!$A$2:$A$240,"<"&IF(Dashboard!$B$4="",2958465,Dashboard!$B$4+1))) -> 0 | S27: =IF($A27="","",COUNTIFS(Summary!$E$2:$E$240,$A27,Summary!$A$2:$A$240,">="&Calc_Weekly!$A$123,Summary!$A$2:$A$240,"<"&Calc_Weekly!$A$123+7,Summary!$A$2:$A$240,">="&IF(Dashboard!$B$3="",0,Dashboard!$B$3),Summary!$A$2:$A$240,"<"&IF(Dashboard!$B$4="",2958465,Dashboard!$B$4+1))) -> 0 | T27: =IF($A27="","",COUNTIFS(Summary!$E$2:$E$240,$A27,Summary!$A$2:$A$240,">="&Calc_Weekly!$A$124,Summary!$A$2:$A$240,"<"&Calc_Weekly!$A$124+7,Summary!$A$2:$A$240,">="&IF(Dashboard!$B$3="",0,Dashboard!$B$3),Summary!$A$2:$A$240,"<"&IF(Dashboard!$B$4="",2958465,Dashboard!$B$4+1))) -> 1
A28: =IF(Settings!A27="","",Settings!A27) -> Unknown | B28: =IF($A28="","",COUNTIFS(Summary!$E$2:$E$240,$A28,Summary!$A$2:$A$240,">="&Calc_Weekly!$A$106,Summary!$A$2:$A$240,"<"&Calc_Weekly!$A$106+7,Summary!$A$2:$A$240,">="&IF(Dashboard!$B$3="",0,Dashboard!$B$3),Summary!$A$2:$A$240,"<"&IF(Dashboard!$B$4="",2958465,Dashboard!$B$4+1))) -> 0 | C28: =IF($A28="","",COUNTIFS(Summary!$E$2:$E$240,$A28,Summary!$A$2:$A$240,">="&Calc_Weekly!$A$107,Summary!$A$2:$A$240,"<"&Calc_Weekly!$A$107+7,Summary!$A$2:$A$240,">="&IF(Dashboard!$B$3="",0,Dashboard!$B$3),Summary!$A$2:$A$240,"<"&IF(Dashboard!$B$4="",2958465,Dashboard!$B$4+1))) -> 0 | D28: =IF($A28="","",COUNTIFS(Summary!$E$2:$E$240,$A28,Summary!$A$2:$A$240,">="&Calc_Weekly!$A$108,Summary!$A$2:$A$240,"<"&Calc_Weekly!$A$108+7,Summary!$A$2:$A$240,">="&IF(Dashboard!$B$3="",0,Dashboard!$B$3),Summary!$A$2:$A$240,"<"&IF(Dashboard!$B$4="",2958465,Dashboard!$B$4+1))) -> 0 | E28: =IF($A28="","",COUNTIFS(Summary!$E$2:$E$240,$A28,Summary!$A$2:$A$240,">="&Calc_Weekly!$A$109,Summary!$A$2:$A$240,"<"&Calc_Weekly!$A$109+7,Summary!$A$2:$A$240,">="&IF(Dashboard!$B$3="",0,Dashboard!$B$3),Summary!$A$2:$A$240,"<"&IF(Dashboard!$B$4="",2958465,Dashboard!$B$4+1))) -> 0 | F28: =IF($A28="","",COUNTIFS(Summary!$E$2:$E$240,$A28,Summary!$A$2:$A$240,">="&Calc_Weekly!$A$110,Summary!$A$2:$A$240,"<"&Calc_Weekly!$A$110+7,Summary!$A$2:$A$240,">="&IF(Dashboard!$B$3="",0,Dashboard!$B$3),Summary!$A$2:$A$240,"<"&IF(Dashboard!$B$4="",2958465,Dashboard!$B$4+1))) -> 0 | G28: =IF($A28="","",COUNTIFS(Summary!$E$2:$E$240,$A28,Summary!$A$2:$A$240,">="&Calc_Weekly!$A$111,Summary!$A$2:$A$240,"<"&Calc_Weekly!$A$111+7,Summary!$A$2:$A$240,">="&IF(Dashboard!$B$3="",0,Dashboard!$B$3),Summary!$A$2:$A$240,"<"&IF(Dashboard!$B$4="",2958465,Dashboard!$B$4+1))) -> 0 | H28: =IF($A28="","",COUNTIFS(Summary!$E$2:$E$240,$A28,Summary!$A$2:$A$240,">="&Calc_Weekly!$A$112,Summary!$A$2:$A$240,"<"&Calc_Weekly!$A$112+7,Summary!$A$2:$A$240,">="&IF(Dashboard!$B$3="",0,Dashboard!$B$3),Summary!$A$2:$A$240,"<"&IF(Dashboard!$B$4="",2958465,Dashboard!$B$4+1))) -> 0 | I28: =IF($A28="","",COUNTIFS(Summary!$E$2:$E$240,$A28,Summary!$A$2:$A$240,">="&Calc_Weekly!$A$113,Summary!$A$2:$A$240,"<"&Calc_Weekly!$A$113+7,Summary!$A$2:$A$240,">="&IF(Dashboard!$B$3="",0,Dashboard!$B$3),Summary!$A$2:$A$240,"<"&IF(Dashboard!$B$4="",2958465,Dashboard!$B$4+1))) -> 0 | J28: =IF($A28="","",COUNTIFS(Summary!$E$2:$E$240,$A28,Summary!$A$2:$A$240,">="&Calc_Weekly!$A$114,Summary!$A$2:$A$240,"<"&Calc_Weekly!$A$114+7,Summary!$A$2:$A$240,">="&IF(Dashboard!$B$3="",0,Dashboard!$B$3),Summary!$A$2:$A$240,"<"&IF(Dashboard!$B$4="",2958465,Dashboard!$B$4+1))) -> 0 | K28: =IF($A28="","",COUNTIFS(Summary!$E$2:$E$240,$A28,Summary!$A$2:$A$240,">="&Calc_Weekly!$A$115,Summary!$A$2:$A$240,"<"&Calc_Weekly!$A$115+7,Summary!$A$2:$A$240,">="&IF(Dashboard!$B$3="",0,Dashboard!$B$3),Summary!$A$2:$A$240,"<"&IF(Dashboard!$B$4="",2958465,Dashboard!$B$4+1))) -> 0 | L28: =IF($A28="","",COUNTIFS(Summary!$E$2:$E$240,$A28,Summary!$A$2:$A$240,">="&Calc_Weekly!$A$116,Summary!$A$2:$A$240,"<"&Calc_Weekly!$A$116+7,Summary!$A$2:$A$240,">="&IF(Dashboard!$B$3="",0,Dashboard!$B$3),Summary!$A$2:$A$240,"<"&IF(Dashboard!$B$4="",2958465,Dashboard!$B$4+1))) -> 0 | M28: =IF($A28="","",COUNTIFS(Summary!$E$2:$E$240,$A28,Summary!$A$2:$A$240,">="&Calc_Weekly!$A$117,Summary!$A$2:$A$240,"<"&Calc_Weekly!$A$117+7,Summary!$A$2:$A$240,">="&IF(Dashboard!$B$3="",0,Dashboard!$B$3),Summary!$A$2:$A$240,"<"&IF(Dashboard!$B$4="",2958465,Dashboard!$B$4+1))) -> 0 | N28: =IF($A28="","",COUNTIFS(Summary!$E$2:$E$240,$A28,Summary!$A$2:$A$240,">="&Calc_Weekly!$A$118,Summary!$A$2:$A$240,"<"&Calc_Weekly!$A$118+7,Summary!$A$2:$A$240,">="&IF(Dashboard!$B$3="",0,Dashboard!$B$3),Summary!$A$2:$A$240,"<"&IF(Dashboard!$B$4="",2958465,Dashboard!$B$4+1))) -> 0 | O28: =IF($A28="","",COUNTIFS(Summary!$E$2:$E$240,$A28,Summary!$A$2:$A$240,">="&Calc_Weekly!$A$119,Summary!$A$2:$A$240,"<"&Calc_Weekly!$A$119+7,Summary!$A$2:$A$240,">="&IF(Dashboard!$B$3="",0,Dashboard!$B$3),Summary!$A$2:$A$240,"<"&IF(Dashboard!$B$4="",2958465,Dashboard!$B$4+1))) -> 0 | P28: =IF($A28="","",COUNTIFS(Summary!$E$2:$E$240,$A28,Summary!$A$2:$A$240,">="&Calc_Weekly!$A$120,Summary!$A$2:$A$240,"<"&Calc_Weekly!$A$120+7,Summary!$A$2:$A$240,">="&IF(Dashboard!$B$3="",0,Dashboard!$B$3),Summary!$A$2:$A$240,"<"&IF(Dashboard!$B$4="",2958465,Dashboard!$B$4+1))) -> 0 | Q28: =IF($A28="","",COUNTIFS(Summary!$E$2:$E$240,$A28,Summary!$A$2:$A$240,">="&Calc_Weekly!$A$121,Summary!$A$2:$A$240,"<"&Calc_Weekly!$A$121+7,Summary!$A$2:$A$240,">="&IF(Dashboard!$B$3="",0,Dashboard!$B$3),Summary!$A$2:$A$240,"<"&IF(Dashboard!$B$4="",2958465,Dashboard!$B$4+1))) -> 1 | R28: =IF($A28="","",COUNTIFS(Summary!$E$2:$E$240,$A28,Summary!$A$2:$A$240,">="&Calc_Weekly!$A$122,Summary!$A$2:$A$240,"<"&Calc_Weekly!$A$122+7,Summary!$A$2:$A$240,">="&IF(Dashboard!$B$3="",0,Dashboard!$B$3),Summary!$A$2:$A$240,"<"&IF(Dashboard!$B$4="",2958465,Dashboard!$B$4+1))) -> 3 | S28: =IF($A28="","",COUNTIFS(Summary!$E$2:$E$240,$A28,Summary!$A$2:$A$240,">="&Calc_Weekly!$A$123,Summary!$A$2:$A$240,"<"&Calc_Weekly!$A$123+7,Summary!$A$2:$A$240,">="&IF(Dashboard!$B$3="",0,Dashboard!$B$3),Summary!$A$2:$A$240,"<"&IF(Dashboard!$B$4="",2958465,Dashboard!$B$4+1))) -> 1 | T28: =IF($A28="","",COUNTIFS(Summary!$E$2:$E$240,$A28,Summary!$A$2:$A$240,">="&Calc_Weekly!$A$124,Summary!$A$2:$A$240,"<"&Calc_Weekly!$A$124+7,Summary!$A$2:$A$240,">="&IF(Dashboard!$B$3="",0,Dashboard!$B$3),Summary!$A$2:$A$240,"<"&IF(Dashboard!$B$4="",2958465,Dashboard!$B$4+1))) -> 0
A29: =IF(Settings!A28="","",Settings!A28) -> Program change - Hussmann | B29: =IF($A29="","",COUNTIFS(Summary!$E$2:$E$240,$A29,Summary!$A$2:$A$240,">="&Calc_Weekly!$A$106,Summary!$A$2:$A$240,"<"&Calc_Weekly!$A$106+7,Summary!$A$2:$A$240,">="&IF(Dashboard!$B$3="",0,Dashboard!$B$3),Summary!$A$2:$A$240,"<"&IF(Dashboard!$B$4="",2958465,Dashboard!$B$4+1))) -> 0 | C29: =IF($A29="","",COUNTIFS(Summary!$E$2:$E$240,$A29,Summary!$A$2:$A$240,">="&Calc_Weekly!$A$107,Summary!$A$2:$A$240,"<"&Calc_Weekly!$A$107+7,Summary!$A$2:$A$240,">="&IF(Dashboard!$B$3="",0,Dashboard!$B$3),Summary!$A$2:$A$240,"<"&IF(Dashboard!$B$4="",2958465,Dashboard!$B$4+1))) -> 0 | D29: =IF($A29="","",COUNTIFS(Summary!$E$2:$E$240,$A29,Summary!$A$2:$A$240,">="&Calc_Weekly!$A$108,Summary!$A$2:$A$240,"<"&Calc_Weekly!$A$108+7,Summary!$A$2:$A$240,">="&IF(Dashboard!$B$3="",0,Dashboard!$B$3),Summary!$A$2:$A$240,"<"&IF(Dashboard!$B$4="",2958465,Dashboard!$B$4+1))) -> 0 | E29: =IF($A29="","",COUNTIFS(Summary!$E$2:$E$240,$A29,Summary!$A$2:$A$240,">="&Calc_Weekly!$A$109,Summary!$A$2:$A$240,"<"&Calc_Weekly!$A$109+7,Summary!$A$2:$A$240,">="&IF(Dashboard!$B$3="",0,Dashboard!$B$3),Summary!$A$2:$A$240,"<"&IF(Dashboard!$B$4="",2958465,Dashboard!$B$4+1))) -> 0 | F29: =IF($A29="","",COUNTIFS(Summary!$E$2:$E$240,$A29,Summary!$A$2:$A$240,">="&Calc_Weekly!$A$110,Summary!$A$2:$A$240,"<"&Calc_Weekly!$A$110+7,Summary!$A$2:$A$240,">="&IF(Dashboard!$B$3="",0,Dashboard!$B$3),Summary!$A$2:$A$240,"<"&IF(Dashboard!$B$4="",2958465,Dashboard!$B$4+1))) -> 0 | G29: =IF($A29="","",COUNTIFS(Summary!$E$2:$E$240,$A29,Summary!$A$2:$A$240,">="&Calc_Weekly!$A$111,Summary!$A$2:$A$240,"<"&Calc_Weekly!$A$111+7,Summary!$A$2:$A$240,">="&IF(Dashboard!$B$3="",0,Dashboard!$B$3),Summary!$A$2:$A$240,"<"&IF(Dashboard!$B$4="",2958465,Dashboard!$B$4+1))) -> 0 | H29: =IF($A29="","",COUNTIFS(Summary!$E$2:$E$240,$A29,Summary!$A$2:$A$240,">="&Calc_Weekly!$A$112,Summary!$A$2:$A$240,"<"&Calc_Weekly!$A$112+7,Summary!$A$2:$A$240,">="&IF(Dashboard!$B$3="",0,Dashboard!$B$3),Summary!$A$2:$A$240,"<"&IF(Dashboard!$B$4="",2958465,Dashboard!$B$4+1))) -> 0 | I29: =IF($A29="","",COUNTIFS(Summary!$E$2:$E$240,$A29,Summary!$A$2:$A$240,">="&Calc_Weekly!$A$113,Summary!$A$2:$A$240,"<"&Calc_Weekly!$A$113+7,Summary!$A$2:$A$240,">="&IF(Dashboard!$B$3="",0,Dashboard!$B$3),Summary!$A$2:$A$240,"<"&IF(Dashboard!$B$4="",2958465,Dashboard!$B$4+1))) -> 0 | J29: =IF($A29="","",COUNTIFS(Summary!$E$2:$E$240,$A29,Summary!$A$2:$A$240,">="&Calc_Weekly!$A$114,Summary!$A$2:$A$240,"<"&Calc_Weekly!$A$114+7,Summary!$A$2:$A$240,">="&IF(Dashboard!$B$3="",0,Dashboard!$B$3),Summary!$A$2:$A$240,"<"&IF(Dashboard!$B$4="",2958465,Dashboard!$B$4+1))) -> 0 | K29: =IF($A29="","",COUNTIFS(Summary!$E$2:$E$240,$A29,Summary!$A$2:$A$240,">="&Calc_Weekly!$A$115,Summary!$A$2:$A$240,"<"&Calc_Weekly!$A$115+7,Summary!$A$2:$A$240,">="&IF(Dashboard!$B$3="",0,Dashboard!$B$3),Summary!$A$2:$A$240,"<"&IF(Dashboard!$B$4="",2958465,Dashboard!$B$4+1))) -> 0 | L29: =IF($A29="","",COUNTIFS(Summary!$E$2:$E$240,$A29,Summary!$A$2:$A$240,">="&Calc_Weekly!$A$116,Summary!$A$2:$A$240,"<"&Calc_Weekly!$A$116+7,Summary!$A$2:$A$240,">="&IF(Dashboard!$B$3="",0,Dashboard!$B$3),Summary!$A$2:$A$240,"<"&IF(Dashboard!$B$4="",2958465,Dashboard!$B$4+1))) -> 0 | M29: =IF($A29="","",COUNTIFS(Summary!$E$2:$E$240,$A29,Summary!$A$2:$A$240,">="&Calc_Weekly!$A$117,Summary!$A$2:$A$240,"<"&Calc_Weekly!$A$117+7,Summary!$A$2:$A$240,">="&IF(Dashboard!$B$3="",0,Dashboard!$B$3),Summary!$A$2:$A$240,"<"&IF(Dashboard!$B$4="",2958465,Dashboard!$B$4+1))) -> 0 | N29: =IF($A29="","",COUNTIFS(Summary!$E$2:$E$240,$A29,Summary!$A$2:$A$240,">="&Calc_Weekly!$A$118,Summary!$A$2:$A$240,"<"&Calc_Weekly!$A$118+7,Summary!$A$2:$A$240,">="&IF(Dashboard!$B$3="",0,Dashboard!$B$3),Summary!$A$2:$A$240,"<"&IF(Dashboard!$B$4="",2958465,Dashboard!$B$4+1))) -> 0 | O29: =IF($A29="","",COUNTIFS(Summary!$E$2:$E$240,$A29,Summary!$A$2:$A$240,">="&Calc_Weekly!$A$119,Summary!$A$2:$A$240,"<"&Calc_Weekly!$A$119+7,Summary!$A$2:$A$240,">="&IF(Dashboard!$B$3="",0,Dashboard!$B$3),Summary!$A$2:$A$240,"<"&IF(Dashboard!$B$4="",2958465,Dashboard!$B$4+1))) -> 0 | P29: =IF($A29="","",COUNTIFS(Summary!$E$2:$E$240,$A29,Summary!$A$2:$A$240,">="&Calc_Weekly!$A$120,Summary!$A$2:$A$240,"<"&Calc_Weekly!$A$120+7,Summary!$A$2:$A$240,">="&IF(Dashboard!$B$3="",0,Dashboard!$B$3),Summary!$A$2:$A$240,"<"&IF(Dashboard!$B$4="",2958465,Dashboard!$B$4+1))) -> 0 | Q29: =IF($A29="","",COUNTIFS(Summary!$E$2:$E$240,$A29,Summary!$A$2:$A$240,">="&Calc_Weekly!$A$121,Summary!$A$2:$A$240,"<"&Calc_Weekly!$A$121+7,Summary!$A$2:$A$240,">="&IF(Dashboard!$B$3="",0,Dashboard!$B$3),Summary!$A$2:$A$240,"<"&IF(Dashboard!$B$4="",2958465,Dashboard!$B$4+1))) -> 0 | R29: =IF($A29="","",COUNTIFS(Summary!$E$2:$E$240,$A29,Summary!$A$2:$A$240,">="&Calc_Weekly!$A$122,Summary!$A$2:$A$240,"<"&Calc_Weekly!$A$122+7,Summary!$A$2:$A$240,">="&IF(Dashboard!$B$3="",0,Dashboard!$B$3),Summary!$A$2:$A$240,"<"&IF(Dashboard!$B$4="",2958465,Dashboard!$B$4+1))) -> 0 | S29: =IF($A29="","",COUNTIFS(Summary!$E$2:$E$240,$A29,Summary!$A$2:$A$240,">="&Calc_Weekly!$A$123,Summary!$A$2:$A$240,"<"&Calc_Weekly!$A$123+7,Summary!$A$2:$A$240,">="&IF(Dashboard!$B$3="",0,Dashboard!$B$3),Summary!$A$2:$A$240,"<"&IF(Dashboard!$B$4="",2958465,Dashboard!$B$4+1))) -> 0 | T29: =IF($A29="","",COUNTIFS(Summary!$E$2:$E$240,$A29,Summary!$A$2:$A$240,">="&Calc_Weekly!$A$124,Summary!$A$2:$A$240,"<"&Calc_Weekly!$A$124+7,Summary!$A$2:$A$240,">="&IF(Dashboard!$B$3="",0,Dashboard!$B$3),Summary!$A$2:$A$240,"<"&IF(Dashboard!$B$4="",2958465,Dashboard!$B$4+1))) -> 0
A30: =IF(Settings!A29="","",Settings!A29) -> Wrong program | B30: =IF($A30="","",COUNTIFS(Summary!$E$2:$E$240,$A30,Summary!$A$2:$A$240,">="&Calc_Weekly!$A$106,Summary!$A$2:$A$240,"<"&Calc_Weekly!$A$106+7,Summary!$A$2:$A$240,">="&IF(Dashboard!$B$3="",0,Dashboard!$B$3),Summary!$A$2:$A$240,"<"&IF(Dashboard!$B$4="",2958465,Dashboard!$B$4+1))) -> 0 | C30: =IF($A30="","",COUNTIFS(Summary!$E$2:$E$240,$A30,Summary!$A$2:$A$240,">="&Calc_Weekly!$A$107,Summary!$A$2:$A$240,"<"&Calc_Weekly!$A$107+7,Summary!$A$2:$A$240,">="&IF(Dashboard!$B$3="",0,Dashboard!$B$3),Summary!$A$2:$A$240,"<"&IF(Dashboard!$B$4="",2958465,Dashboard!$B$4+1))) -> 0 | D30: =IF($A30="","",COUNTIFS(Summary!$E$2:$E$240,$A30,Summary!$A$2:$A$240,">="&Calc_Weekly!$A$108,Summary!$A$2:$A$240,"<"&Calc_Weekly!$A$108+7,Summary!$A$2:$A$240,">="&IF(Dashboard!$B$3="",0,Dashboard!$B$3),Summary!$A$2:$A$240,"<"&IF(Dashboard!$B$4="",2958465,Dashboard!$B$4+1))) -> 0 | E30: =IF($A30="","",COUNTIFS(Summary!$E$2:$E$240,$A30,Summary!$A$2:$A$240,">="&Calc_Weekly!$A$109,Summary!$A$2:$A$240,"<"&Calc_Weekly!$A$109+7,Summary!$A$2:$A$240,">="&IF(Dashboard!$B$3="",0,Dashboard!$B$3),Summary!$A$2:$A$240,"<"&IF(Dashboard!$B$4="",2958465,Dashboard!$B$4+1))) -> 0 | F30: =IF($A30="","",COUNTIFS(Summary!$E$2:$E$240,$A30,Summary!$A$2:$A$240,">="&Calc_Weekly!$A$110,Summary!$A$2:$A$240,"<"&Calc_Weekly!$A$110+7,Summary!$A$2:$A$240,">="&IF(Dashboard!$B$3="",0,Dashboard!$B$3),Summary!$A$2:$A$240,"<"&IF(Dashboard!$B$4="",2958465,Dashboard!$B$4+1))) -> 0 | G30: =IF($A30="","",COUNTIFS(Summary!$E$2:$E$240,$A30,Summary!$A$2:$A$240,">="&Calc_Weekly!$A$111,Summary!$A$2:$A$240,"<"&Calc_Weekly!$A$111+7,Summary!$A$2:$A$240,">="&IF(Dashboard!$B$3="",0,Dashboard!$B$3),Summary!$A$2:$A$240,"<"&IF(Dashboard!$B$4="",2958465,Dashboard!$B$4+1))) -> 0 | H30: =IF($A30="","",COUNTIFS(Summary!$E$2:$E$240,$A30,Summary!$A$2:$A$240,">="&Calc_Weekly!$A$112,Summary!$A$2:$A$240,"<"&Calc_Weekly!$A$112+7,Summary!$A$2:$A$240,">="&IF(Dashboard!$B$3="",0,Dashboard!$B$3),Summary!$A$2:$A$240,"<"&IF(Dashboard!$B$4="",2958465,Dashboard!$B$4+1))) -> 0 | I30: =IF($A30="","",COUNTIFS(Summary!$E$2:$E$240,$A30,Summary!$A$2:$A$240,">="&Calc_Weekly!$A$113,Summary!$A$2:$A$240,"<"&Calc_Weekly!$A$113+7,Summary!$A$2:$A$240,">="&IF(Dashboard!$B$3="",0,Dashboard!$B$3),Summary!$A$2:$A$240,"<"&IF(Dashboard!$B$4="",2958465,Dashboard!$B$4+1))) -> 0 | J30: =IF($A30="","",COUNTIFS(Summary!$E$2:$E$240,$A30,Summary!$A$2:$A$240,">="&Calc_Weekly!$A$114,Summary!$A$2:$A$240,"<"&Calc_Weekly!$A$114+7,Summary!$A$2:$A$240,">="&IF(Dashboard!$B$3="",0,Dashboard!$B$3),Summary!$A$2:$A$240,"<"&IF(Dashboard!$B$4="",2958465,Dashboard!$B$4+1))) -> 0 | K30: =IF($A30="","",COUNTIFS(Summary!$E$2:$E$240,$A30,Summary!$A$2:$A$240,">="&Calc_Weekly!$A$115,Summary!$A$2:$A$240,"<"&Calc_Weekly!$A$115+7,Summary!$A$2:$A$240,">="&IF(Dashboard!$B$3="",0,Dashboard!$B$3),Summary!$A$2:$A$240,"<"&IF(Dashboard!$B$4="",2958465,Dashboard!$B$4+1))) -> 0 | L30: =IF($A30="","",COUNTIFS(Summary!$E$2:$E$240,$A30,Summary!$A$2:$A$240,">="&Calc_Weekly!$A$116,Summary!$A$2:$A$240,"<"&Calc_Weekly!$A$116+7,Summary!$A$2:$A$240,">="&IF(Dashboard!$B$3="",0,Dashboard!$B$3),Summary!$A$2:$A$240,"<"&IF(Dashboard!$B$4="",2958465,Dashboard!$B$4+1))) -> 0 | M30: =IF($A30="","",COUNTIFS(Summary!$E$2:$E$240,$A30,Summary!$A$2:$A$240,">="&Calc_Weekly!$A$117,Summary!$A$2:$A$240,"<"&Calc_Weekly!$A$117+7,Summary!$A$2:$A$240,">="&IF(Dashboard!$B$3="",0,Dashboard!$B$3),Summary!$A$2:$A$240,"<"&IF(Dashboard!$B$4="",2958465,Dashboard!$B$4+1))) -> 0 | N30: =IF($A30="","",COUNTIFS(Summary!$E$2:$E$240,$A30,Summary!$A$2:$A$240,">="&Calc_Weekly!$A$118,Summary!$A$2:$A$240,"<"&Calc_Weekly!$A$118+7,Summary!$A$2:$A$240,">="&IF(Dashboard!$B$3="",0,Dashboard!$B$3),Summary!$A$2:$A$240,"<"&IF(Dashboard!$B$4="",2958465,Dashboard!$B$4+1))) -> 0 | O30: =IF($A30="","",COUNTIFS(Summary!$E$2:$E$240,$A30,Summary!$A$2:$A$240,">="&Calc_Weekly!$A$119,Summary!$A$2:$A$240,"<"&Calc_Weekly!$A$119+7,Summary!$A$2:$A$240,">="&IF(Dashboard!$B$3="",0,Dashboard!$B$3),Summary!$A$2:$A$240,"<"&IF(Dashboard!$B$4="",2958465,Dashboard!$B$4+1))) -> 0 | P30: =IF($A30="","",COUNTIFS(Summary!$E$2:$E$240,$A30,Summary!$A$2:$A$240,">="&Calc_Weekly!$A$120,Summary!$A$2:$A$240,"<"&Calc_Weekly!$A$120+7,Summary!$A$2:$A$240,">="&IF(Dashboard!$B$3="",0,Dashboard!$B$3),Summary!$A$2:$A$240,"<"&IF(Dashboard!$B$4="",2958465,Dashboard!$B$4+1))) -> 0 | Q30: =IF($A30="","",COUNTIFS(Summary!$E$2:$E$240,$A30,Summary!$A$2:$A$240,">="&Calc_Weekly!$A$121,Summary!$A$2:$A$240,"<"&Calc_Weekly!$A$121+7,Summary!$A$2:$A$240,">="&IF(Dashboard!$B$3="",0,Dashboard!$B$3),Summary!$A$2:$A$240,"<"&IF(Dashboard!$B$4="",2958465,Dashboard!$B$4+1))) -> 0 | R30: =IF($A30="","",COUNTIFS(Summary!$E$2:$E$240,$A30,Summary!$A$2:$A$240,">="&Calc_Weekly!$A$122,Summary!$A$2:$A$240,"<"&Calc_Weekly!$A$122+7,Summary!$A$2:$A$240,">="&IF(Dashboard!$B$3="",0,Dashboard!$B$3),Summary!$A$2:$A$240,"<"&IF(Dashboard!$B$4="",2958465,Dashboard!$B$4+1))) -> 0 | S30: =IF($A30="","",COUNTIFS(Summary!$E$2:$E$240,$A30,Summary!$A$2:$A$240,">="&Calc_Weekly!$A$123,Summary!$A$2:$A$240,"<"&Calc_Weekly!$A$123+7,Summary!$A$2:$A$240,">="&IF(Dashboard!$B$3="",0,Dashboard!$B$3),Summary!$A$2:$A$240,"<"&IF(Dashboard!$B$4="",2958465,Dashboard!$B$4+1))) -> 1 | T30: =IF($A30="","",COUNTIFS(Summary!$E$2:$E$240,$A30,Summary!$A$2:$A$240,">="&Calc_Weekly!$A$124,Summary!$A$2:$A$240,"<"&Calc_Weekly!$A$124+7,Summary!$A$2:$A$240,">="&IF(Dashboard!$B$3="",0,Dashboard!$B$3),Summary!$A$2:$A$240,"<"&IF(Dashboard!$B$4="",2958465,Dashboard!$B$4+1))) -> 0
A40: Heatmap date basis | B40: Call date
A41: Heatmap first week | B41: =B42-WEEKDAY(B42,2)+1 -> 46174.419
A42: Heatmap first plotted date | B42: =IF(hm_basis="Call date",IFERROR(_xlfn.AGGREGATE(15,6,Summary!$A$2:$A$240/((Summary!$A$2:$A$240>=IF(Dashboard!$B$3="",0,Dashboard!$B$3))*(Summary!$A$2:$A$240<IF(Dashboard!$B$4="",2958465,Dashboard!$B$4+1))*(Summary!$A$2:$A$240>0)),1),IF(Dashboard!$B$3="",TODAY(),Dashboard!$B$3)),IFERROR(_xlfn.AGGREGATE(15,6,Summary!$D$2:$D$240/((Summary!$A$2:$A$240>=IF(Dashboard!$B$3="",0,Dashboard!$B$3))*(Summary!$A$2:$A$240<IF(Dashboard!$B$4="",2958465,Dashboard!$B$4+1))*(Summary!$D$2:$D$240>0)),1),IF(Dashboard!$B$3="",TODAY(),Dashboard!$B$3))) -> 46175.419

Sheet Interventions
A1: Intervention log - one row per clean point / fix action. Drives the clean-point lines chart. Settings' Clean-Point Date column still drives the after/before charts.
A3: Root Cause | B3: Date | C3: Label
A4: Ref. leak/ Low charge | B4: 46132 | C4: Clean point
A5: Door Torque | B5: 46178 | C5: Clean point
A6: Door Gasket | B6: 46178 | C6: Clean point
A7: Door frame heater | B7: 46178 | C7: Clean point
A8: Door Torsion rod | B8: 46178 | C8: Clean point
A9: Door not closed (Overnight) | B9: 46178 | C9: Clean point
A10: Door - general | B10: 46178 | C10: Clean point
A11: Drain tube blocked | B11: 46213 | C11: Clean point
A12: Wrong / Loose wiring | B12: 46108 | C12: Clean point
A13: Communication problem | B13: 46191 | C13: Clean point
A14: High Store RH | B14: 46171 | C14: Clean point
A15: Enclosure Seal | B15: 46135 | C15: Clean point
... A28: Program change - Hussmann | B28: 46171 | C28: Clean point

Sheet Timeline Calc
A1: Daily clean-point timeline source. Pickers live on Dashboard!B83:B84.
A2: Cause | B2: =tl_cause -> Communication problem
A3: Basis | B3: =tl_basis -> Commission date
B4: =Dashboard!B125&" - issues by "&Dashboard!B126&", with clean points ("&Dashboard!B5&")" -> Communication problem - issues by Commission date, with clean points (Jun 1 to Jul 15)
A7: Date | B7: Issues | C7: Clean Point 1 | D7: Clean Point 2 | E7: Clean Point 3 | F7: CP Date 1 | G7: CP Date 2 | H7: CP Date 3 | I7: CP Label 1 | J7: CP Label 2 | K7: CP Label 3 | L7: Ceiling | P7: Cause | Q7: Group | R7: CP date | U7: Pick list raw | V7: Pick list
A8: =MIN(IF(Dashboard!$B$3="",2958465,Dashboard!$B$3),IFERROR(IF(ISNUMBER(MATCH(tl_cause,Settings!$B$4:$B$83,0)),IF(tl_basis="Call date",_xlfn.AGGREGATE(15,6,Summary!$A$2:$A$240/((Summary!$K$2:$K$240=tl_cause)*(Summary!$A$2:$A$240>=IF(Dashboard!$B$3="",0,Dashboard!$B$3))*(Summary!$A$2:$A$240<IF(Dashboard!$B$4="",2958465,Dashboard!$B$4+1))*(Summary!$A$2:$A$240>0)),1),_xlfn.AGGREGATE(15,6,Summary!$D$2:$D$240/((Summary!$K$2:$K$240=tl_cause)*(Summary!$A$2:$A$240>=IF(Dashboard!$B$3="",0,Dashboard!$B$3))*(Summary!$A$2:$A$240<IF(Dashboard!$B$4="",2958465,Dashboard!$B$4+1))*(Summary!$D$2:$D$240>0)),1)),IF(tl_basis="Call date",_xlfn.AGGREGATE(15,6,Summary!$A$2:$A$240/((Summary!$E$2:$E$240=tl_cause)*(Summary!$A$2:$A$240>=IF(Dashboard!$B$3="",0,Dashboard!$B$3))*(Summary!$A$2:$A$240<IF(Dashboard!$B$4="",2958465,Dashboard!$B$4+1))*(Summary!$A$2:$A$240>0)),1),_xlfn.AGGREGATE(15,6,Summary!$D$2:$D$240/((Summary!$E$2:$E$240=tl_cause)*(Summary!$A$2:$A$240>=IF(Dashboard!$B$3="",0,Dashboard!$B$3))*(Summary!$A$2:$A$240<IF(Dashboard!$B$4="",2958465,Dashboard!$B$4+1))*(Summary!$D$2:$D$240>0)),1))),IF(Dashboard!$B$3="",2958465,Dashboard!$B$3)),IF($F$8>0,$F$8,IF(Dashboard!$B$3="",2958465,Dashboard!$B$3)),IF($G$8>0,$G$8,IF(Dashboard!$B$3="",2958465,Dashboard!$B$3)),IF($H$8>0,$H$8,IF(Dashboard!$B$3="",2958465,Dashboard!$B$3))) -> 46099 | B8: =IF(ISNUMBER(MATCH(tl_cause,Settings!$B$4:$B$83,0)),IF(tl_basis="Call date",COUNTIFS(Summary!$K$2:$K$240,tl_cause,Summary!$A$2:$A$240,">="&$A8,Summary!$A$2:$A$240,"<"&$A8+1,Summary!$A$2:$A$240,">="&IF(Dashboard!$B$3="",0,Dashboard!$B$3),Summary!$A$2:$A$240,"<"&IF(Dashboard!$B$4="",2958465,Dashboard!$B$4+1)),COUNTIFS(Summary!$K$2:$K$240,tl_cause,Summary!$D$2:$D$240,">="&$A8,Summary!$D$2:$D$240,"<"&$A8+1,Summary!$A$2:$A$240,">="&IF(Dashboard!$B$3="",0,Dashboard!$B$3),Summary!$A$2:$A$240,"<"&IF(Dashboard!$B$4="",2958465,Dashboard!$B$4+1))),IF(tl_basis="Call date",COUNTIFS(Summary!$E$2:$E$240,tl_cause,Summary!$A$2:$A$240,">="&$A8,Summary!$A$2:$A$240,"<"&$A8+1,Summary!$A$2:$A$240,">="&IF(Dashboard!$B$3="",0,Dashboard!$B$3),Summary!$A$2:$A$240,"<"&IF(Dashboard!$B$4="",2958465,Dashboard!$B$4+1)),COUNTIFS(Summary!$E$2:$E$240,tl_cause,Summary!$D$2:$D$240,">="&$A8,Summary!$D$2:$D$240,"<"&$A8+1,Summary!$A$2:$A$240,">="&IF(Dashboard!$B$3="",0,Dashboard!$B$3),Summary!$A$2:$A$240,"<"&IF(Dashboard!$B$4="",2958465,Dashboard!$B$4+1)))) -> 2 | C8: =IF(AND($F$8<>"",$A8=$F$8),1,NA()) -> #N/A | D8: =IF(AND($G$8<>"",$G$8>0,$A8=$G$8),1,NA()) -> #N/A | E8: =IF(AND($H$8<>"",$H$8>0,$A8=$H$8),1,NA()) -> #N/A | F8: {=MIN(IF((($P$8:$P$247=tl_cause)+($Q$8:$Q$247=tl_cause))*($R$8:$R$247>0),$R$8:$R$247))} -> 46191 | G8: {=MIN(IF((($P$8:$P$247=tl_cause)+($Q$8:$Q$247=tl_cause))*($R$8:$R$247>$F$8),$R$8:$R$247))} -> 0 | H8: {=MIN(IF((($P$8:$P$247=tl_cause)+($Q$8:$Q$247=tl_cause))*($R$8:$R$247>$G$8)*($G$8>0),$R$8:$R$247))} -> 0 | I8: =IF(OR(F8="",F8=0),"","Clean point 1 - "&TEXT(F8,"mmm d")) -> Clean point 1 - Jun 18 | J8: =IF(OR(G8="",G8=0),"","Clean point 2 - "&TEXT(G8,"mmm d")) | K8: =IF(OR(H8="",H8=0),"","Clean point 3 - "&TEXT(H8,"mmm d")) | L8: =MAX(1,MAX(B8:B191)+1) -> 3 | P8: =IF(Settings!A4="","",Settings!A4) -> Ref. leak/ Low charge | Q8: =IF(Settings!A4="","",Settings!B4) -> Ref. leak/ Low charge | R8: =IF(Settings!E4="",0,Settings!E4) -> 46132 | U8: =IF(Settings!A4="","",Settings!A4) -> Ref. leak/ Low charge | V8: {=IFERROR(INDEX($U$8:$U$167,SMALL(IF($U$8:$U$167<>"",ROW($U$8:$U$167)-7),ROW()-7)),"")} -> Ref. leak/ Low charge
A9: =A8+1 -> 46100 | B9: =IF(ISNUMBER(MATCH(tl_cause,Settings!$B$4:$B$83,0)),IF(tl_basis="Call date",COUNTIFS(Summary!$K$2:$K$240,tl_cause,Summary!$A$2:$A$240,">="&$A9,Summary!$A$2:$A$240,"<"&$A9+1,Summary!$A$2:$A$240,">="&IF(Dashboard!$B$3="",0,Dashboard!$B$3),Summary!$A$2:$A$240,"<"&IF(Dashboard!$B$4="",2958465,Dashboard!$B$4+1)),COUNTIFS(Summary!$K$2:$K$240,tl_cause,Summary!$D$2:$D$240,">="&$A9,Summary!$D$2:$D$240,"<"&$A9+1,Summary!$A$2:$A$240,">="&IF(Dashboard!$B$3="",0,Dashboard!$B$3),Summary!$A$2:$A$240,"<"&IF(Dashboard!$B$4="",2958465,Dashboard!$B$4+1))),IF(tl_basis="Call date",COUNTIFS(Summary!$E$2:$E$240,tl_cause,Summary!$A$2:$A$240,">="&$A9,Summary!$A$2:$A$240,"<"&$A9+1,Summary!$A$2:$A$240,">="&IF(Dashboard!$B$3="",0,Dashboard!$B$3),Summary!$A$2:$A$240,"<"&IF(Dashboard!$B$4="",2958465,Dashboard!$B$4+1)),COUNTIFS(Summary!$E$2:$E$240,tl_cause,Summary!$D$2:$D$240,">="&$A9,Summary!$D$2:$D$240,"<"&$A9+1,Summary!$A$2:$A$240,">="&IF(Dashboard!$B$3="",0,Dashboard!$B$3),Summary!$A$2:$A$240,"<"&IF(Dashboard!$B$4="",2958465,Dashboard!$B$4+1)))) -> 0 | C9: =IF(AND($F$8<>"",$A9=$F$8),1,NA()) -> #N/A | D9: =IF(AND($G$8<>"",$G$8>0,$A9=$G$8),1,NA()) -> #N/A | E9: =IF(AND($H$8<>"",$H$8>0,$A9=$H$8),1,NA()) -> #N/A | P9: =IF(Settings!A5="","",Settings!A5) -> Door Torque | Q9: =IF(Settings!A5="","",Settings!B5) -> Doors | R9: =IF(Settings!E5="",0,Settings!E5) -> 46178 | U9: =IF(Settings!A5="","",Settings!A5) -> Door Torque | V9: {=IFERROR(INDEX($U$8:$U$167,SMALL(IF($U$8:$U$167<>"",ROW($U$8:$U$167)-7),ROW()-7)),"")} -> Door Torque
A10: =A9+1 -> 46101 | B10: =IF(ISNUMBER(MATCH(tl_cause,Settings!$B$4:$B$83,0)),IF(tl_basis="Call date",COUNTIFS(Summary!$K$2:$K$240,tl_cause,Summary!$A$2:$A$240,">="&$A10,Summary!$A$2:$A$240,"<"&$A10+1,Summary!$A$2:$A$240,">="&IF(Dashboard!$B$3="",0,Dashboard!$B$3),Summary!$A$2:$A$240,"<"&IF(Dashboard!$B$4="",2958465,Dashboard!$B$4+1)),COUNTIFS(Summary!$K$2:$K$240,tl_cause,Summary!$D$2:$D$240,">="&$A10,Summary!$D$2:$D$240,"<"&$A10+1,Summary!$A$2:$A$240,">="&IF(Dashboard!$B$3="",0,Dashboard!$B$3),Summary!$A$2:$A$240,"<"&IF(Dashboard!$B$4="",2958465,Dashboard!$B$4+1))),IF(tl_basis="Call date",COUNTIFS(Summary!$E$2:$E$240,tl_cause,Summary!$A$2:$A$240,">="&$A10,Summary!$A$2:$A$240,"<"&$A10+1,Summary!$A$2:$A$240,">="&IF(Dashboard!$B$3="",0,Dashboard!$B$3),Summary!$A$2:$A$240,"<"&IF(Dashboard!$B$4="",2958465,Dashboard!$B$4+1)),COUNTIFS(Summary!$E$2:$E$240,tl_cause,Summary!$D$2:$D$240,">="&$A10,Summary!$D$2:$D$240,"<"&$A10+1,Summary!$A$2:$A$240,">="&IF(Dashboard!$B$3="",0,Dashboard!$B$3),Summary!$A$2:$A$240,"<"&IF(Dashboard!$B$4="",2958465,Dashboard!$B$4+1)))) -> 0 | C10: =IF(AND($F$8<>"",$A10=$F$8),1,NA()) -> #N/A | D10: =IF(AND($G$8<>"",$G$8>0,$A10=$G$8),1,NA()) -> #N/A | E10: =IF(AND($H$8<>"",$H$8>0,$A10=$H$8),1,NA()) -> #N/A | P10: =IF(Settings!A6="","",Settings!A6) -> Door Gasket | Q10: =IF(Settings!A6="","",Settings!B6) -> Doors | R10: =IF(Settings!E6="",0,Settings!E6) -> 46178 | U10: =IF(Settings!A6="","",Settings!A6) -> Door Gasket | V10: {=IFERROR(INDEX($U$8:$U$167,SMALL(IF($U$8:$U$167<>"",ROW($U$8:$U$167)-7),ROW()-7)),"")} -> Door Gasket
A11: =A10+1 -> 46102 | B11: =IF(ISNUMBER(MATCH(tl_cause,Settings!$B$4:$B$83,0)),IF(tl_basis="Call date",COUNTIFS(Summary!$K$2:$K$240,tl_cause,Summary!$A$2:$A$240,">="&$A11,Summary!$A$2:$A$240,"<"&$A11+1,Summary!$A$2:$A$240,">="&IF(Dashboard!$B$3="",0,Dashboard!$B$3),Summary!$A$2:$A$240,"<"&IF(Dashboard!$B$4="",2958465,Dashboard!$B$4+1)),COUNTIFS(Summary!$K$2:$K$240,tl_cause,Summary!$D$2:$D$240,">="&$A11,Summary!$D$2:$D$240,"<"&$A11+1,Summary!$A$2:$A$240,">="&IF(Dashboard!$B$3="",0,Dashboard!$B$3),Summary!$A$2:$A$240,"<"&IF(Dashboard!$B$4="",2958465,Dashboard!$B$4+1))),IF(tl_basis="Call date",COUNTIFS(Summary!$E$2:$E$240,tl_cause,Summary!$A$2:$A$240,">="&$A11,Summary!$A$2:$A$240,"<"&$A11+1,Summary!$A$2:$A$240,">="&IF(Dashboard!$B$3="",0,Dashboard!$B$3),Summary!$A$2:$A$240,"<"&IF(Dashboard!$B$4="",2958465,Dashboard!$B$4+1)),COUNTIFS(Summary!$E$2:$E$240,tl_cause,Summary!$D$2:$D$240,">="&$A11,Summary!$D$2:$D$240,"<"&$A11+1,Summary!$A$2:$A$240,">="&IF(Dashboard!$B$3="",0,Dashboard!$B$3),Summary!$A$2:$A$240,"<"&IF(Dashboard!$B$4="",2958465,Dashboard!$B$4+1)))) -> 0 | C11: =IF(AND($F$8<>"",$A11=$F$8),1,NA()) -> #N/A | D11: =IF(AND($G$8<>"",$G$8>0,$A11=$G$8),1,NA()) -> #N/A | E11: =IF(AND($H$8<>"",$H$8>0,$A11=$H$8),1,NA()) -> #N/A | P11: =IF(Settings!A7="","",Settings!A7) -> Door frame heater | Q11: =IF(Settings!A7="","",Settings!B7) -> Doors | R11: =IF(Settings!E7="",0,Settings!E7) -> 46178 | U11: =IF(Settings!A7="","",Settings!A7) -> Door frame heater | V11: {=IFERROR(INDEX($U$8:$U$167,SMALL(IF($U$8:$U$167<>"",ROW($U$8:$U$167)-7),ROW()-7)),"")} -> Door frame heater
A12: =A11+1 -> 46103 | B12: =IF(ISNUMBER(MATCH(tl_cause,Settings!$B$4:$B$83,0)),IF(tl_basis="Call date",COUNTIFS(Summary!$K$2:$K$240,tl_cause,Summary!$A$2:$A$240,">="&$A12,Summary!$A$2:$A$240,"<"&$A12+1,Summary!$A$2:$A$240,">="&IF(Dashboard!$B$3="",0,Dashboard!$B$3),Summary!$A$2:$A$240,"<"&IF(Dashboard!$B$4="",2958465,Dashboard!$B$4+1)),COUNTIFS(Summary!$K$2:$K$240,tl_cause,Summary!$D$2:$D$240,">="&$A12,Summary!$D$2:$D$240,"<"&$A12+1,Summary!$A$2:$A$240,">="&IF(Dashboard!$B$3="",0,Dashboard!$B$3),Summary!$A$2:$A$240,"<"&IF(Dashboard!$B$4="",2958465,Dashboard!$B$4+1))),IF(tl_basis="Call date",COUNTIFS(Summary!$E$2:$E$240,tl_cause,Summary!$A$2:$A$240,">="&$A12,Summary!$A$2:$A$240,"<"&$A12+1,Summary!$A$2:$A$240,">="&IF(Dashboard!$B$3="",0,Dashboard!$B$3),Summary!$A$2:$A$240,"<"&IF(Dashboard!$B$4="",2958465,Dashboard!$B$4+1)),COUNTIFS(Summary!$E$2:$E$240,tl_cause,Summary!$D$2:$D$240,">="&$A12,Summary!$D$2:$D$240,"<"&$A12+1,Summary!$A$2:$A$240,">="&IF(Dashboard!$B$3="",0,Dashboard!$B$3),Summary!$A$2:$A$240,"<"&IF(Dashboard!$B$4="",2958465,Dashboard!$B$4+1)))) -> 0 | C12: =IF(AND($F$8<>"",$A12=$F$8),1,NA()) -> #N/A | D12: =IF(AND($G$8<>"",$G$8>0,$A12=$G$8),1,NA()) -> #N/A | E12: =IF(AND($H$8<>"",$H$8>0,$A12=$H$8),1,NA()) -> #N/A | P12: =IF(Settings!A8="","",Settings!A8) -> Door Torsion rod | Q12: =IF(Settings!A8="","",Settings!B8) -> Doors | R12: =IF(Settings!E8="",0,Settings!E8) -> 46178 | U12: =IF(Settings!A8="","",Settings!A8) -> Door Torsion rod | V12: {=IFERROR(INDEX($U$8:$U$167,SMALL(IF($U$8:$U$167<>"",ROW($U$8:$U$167)-7),ROW()-7)),"")} -> Door Torsion rod
A13: =A12+1 -> 46104 | B13: =IF(ISNUMBER(MATCH(tl_cause,Settings!$B$4:$B$83,0)),IF(tl_basis="Call date",COUNTIFS(Summary!$K$2:$K$240,tl_cause,Summary!$A$2:$A$240,">="&$A13,Summary!$A$2:$A$240,"<"&$A13+1,Summary!$A$2:$A$240,">="&IF(Dashboard!$B$3="",0,Dashboard!$B$3),Summary!$A$2:$A$240,"<"&IF(Dashboard!$B$4="",2958465,Dashboard!$B$4+1)),COUNTIFS(Summary!$K$2:$K$240,tl_cause,Summary!$D$2:$D$240,">="&$A13,Summary!$D$2:$D$240,"<"&$A13+1,Summary!$A$2:$A$240,">="&IF(Dashboard!$B$3="",0,Dashboard!$B$3),Summary!$A$2:$A$240,"<"&IF(Dashboard!$B$4="",2958465,Dashboard!$B$4+1))),IF(tl_basis="Call date",COUNTIFS(Summary!$E$2:$E$240,tl_cause,Summary!$A$2:$A$240,">="&$A13,Summary!$A$2:$A$240,"<"&$A13+1,Summary!$A$2:$A$240,">="&IF(Dashboard!$B$3="",0,Dashboard!$B$3),Summary!$A$2:$A$240,"<"&IF(Dashboard!$B$4="",2958465,Dashboard!$B$4+1)),COUNTIFS(Summary!$E$2:$E$240,tl_cause,Summary!$D$2:$D$240,">="&$A13,Summary!$D$2:$D$240,"<"&$A13+1,Summary!$A$2:$A$240,">="&IF(Dashboard!$B$3="",0,Dashboard!$B$3),Summary!$A$2:$A$240,"<"&IF(Dashboard!$B$4="",2958465,Dashboard!$B$4+1)))) -> 0 | C13: =IF(AND($F$8<>"",$A13=$F$8),1,NA()) -> #N/A | D13: =IF(AND($G$8<>"",$G$8>0,$A13=$G$8),1,NA()) -> #N/A | E13: =IF(AND($H$8<>"",$H$8>0,$A13=$H$8),1,NA()) -> #N/A | P13: =IF(Settings!A9="","",Settings!A9) -> Door not closed (Overnight) | Q13: =IF(Settings!A9="","",Settings!B9) -> Doors | R13: =IF(Settings!E9="",0,Settings!E9) -> 46178 | U13: =IF(Settings!A9="","",Settings!A9) -> Door not closed (Overnight) | V13: {=IFERROR(INDEX($U$8:$U$167,SMALL(IF($U$8:$U$167<>"",ROW($U$8:$U$167)-7),ROW()-7)),"")} -> Door not closed (Overnight)
A14: =A13+1 -> 46105 | B14: =IF(ISNUMBER(MATCH(tl_cause,Settings!$B$4:$B$83,0)),IF(tl_basis="Call date",COUNTIFS(Summary!$K$2:$K$240,tl_cause,Summary!$A$2:$A$240,">="&$A14,Summary!$A$2:$A$240,"<"&$A14+1,Summary!$A$2:$A$240,">="&IF(Dashboard!$B$3="",0,Dashboard!$B$3),Summary!$A$2:$A$240,"<"&IF(Dashboard!$B$4="",2958465,Dashboard!$B$4+1)),COUNTIFS(Summary!$K$2:$K$240,tl_cause,Summary!$D$2:$D$240,">="&$A14,Summary!$D$2:$D$240,"<"&$A14+1,Summary!$A$2:$A$240,">="&IF(Dashboard!$B$3="",0,Dashboard!$B$3),Summary!$A$2:$A$240,"<"&IF(Dashboard!$B$4="",2958465,Dashboard!$B$4+1))),IF(tl_basis="Call date",COUNTIFS(Summary!$E$2:$E$240,tl_cause,Summary!$A$2:$A$240,">="&$A14,Summary!$A$2:$A$240,"<"&$A14+1,Summary!$A$2:$A$240,">="&IF(Dashboard!$B$3="",0,Dashboard!$B$3),Summary!$A$2:$A$240,"<"&IF(Dashboard!$B$4="",2958465,Dashboard!$B$4+1)),COUNTIFS(Summary!$E$2:$E$240,tl_cause,Summary!$D$2:$D$240,">="&$A14,Summary!$D$2:$D$240,"<"&$A14+1,Summary!$A$2:$A$240,">="&IF(Dashboard!$B$3="",0,Dashboard!$B$3),Summary!$A$2:$A$240,"<"&IF(Dashboard!$B$4="",2958465,Dashboard!$B$4+1)))) -> 0 | C14: =IF(AND($F$8<>"",$A14=$F$8),1,NA()) -> #N/A | D14: =IF(AND($G$8<>"",$G$8>0,$A14=$G$8),1,NA()) -> #N/A | E14: =IF(AND($H$8<>"",$H$8>0,$A14=$H$8),1,NA()) -> #N/A | P14: =IF(Settings!A10="","",Settings!A10) -> Door - general | Q14: =IF(Settings!A10="","",Settings!B10) -> Doors | R14: =IF(Settings!E10="",0,Settings!E10) -> 46178 | U14: =IF(Settings!A10="","",Settings!A10) -> Door - general | V14: {=IFERROR(INDEX($U$8:$U$167,SMALL(IF($U$8:$U$167<>"",ROW($U$8:$U$167)-7),ROW()-7)),"")} -> Door - general
A15: =A14+1 -> 46106 | B15: =IF(ISNUMBER(MATCH(tl_cause,Settings!$B$4:$B$83,0)),IF(tl_basis="Call date",COUNTIFS(Summary!$K$2:$K$240,tl_cause,Summary!$A$2:$A$240,">="&$A15,Summary!$A$2:$A$240,"<"&$A15+1,Summary!$A$2:$A$240,">="&IF(Dashboard!$B$3="",0,Dashboard!$B$3),Summary!$A$2:$A$240,"<"&IF(Dashboard!$B$4="",2958465,Dashboard!$B$4+1)),COUNTIFS(Summary!$K$2:$K$240,tl_cause,Summary!$D$2:$D$240,">="&$A15,Summary!$D$2:$D$240,"<"&$A15+1,Summary!$A$2:$A$240,">="&IF(Dashboard!$B$3="",0,Dashboard!$B$3),Summary!$A$2:$A$240,"<"&IF(Dashboard!$B$4="",2958465,Dashboard!$B$4+1))),IF(tl_basis="Call date",COUNTIFS(Summary!$E$2:$E$240,tl_cause,Summary!$A$2:$A$240,">="&$A15,Summary!$A$2:$A$240,"<"&$A15+1,Summary!$A$2:$A$240,">="&IF(Dashboard!$B$3="",0,Dashboard!$B$3),Summary!$A$2:$A$240,"<"&IF(Dashboard!$B$4="",2958465,Dashboard!$B$4+1)),COUNTIFS(Summary!$E$2:$E$240,tl_cause,Summary!$D$2:$D$240,">="&$A15,Summary!$D$2:$D$240,"<"&$A15+1,Summary!$A$2:$A$240,">="&IF(Dashboard!$B$3="",0,Dashboard!$B$3),Summary!$A$2:$A$240,"<"&IF(Dashboard!$B$4="",2958465,Dashboard!$B$4+1)))) -> 0 | C15: =IF(AND($F$8<>"",$A15=$F$8),1,NA()) -> #N/A | D15: =IF(AND($G$8<>"",$G$8>0,$A15=$G$8),1,NA()) -> #N/A | E15: =IF(AND($H$8<>"",$H$8>0,$A15=$H$8),1,NA()) -> #N/A | P15: =IF(Settings!A11="","",Settings!A11) -> Drain tube blocked | Q15: =IF(Settings!A11="","",Settings!B11) -> Drain tube blocked | R15: =IF(Settings!E11="",0,Settings!E11) -> 46213 | U15: =IF(Settings!A11="","",Settings!A11) -> Drain tube blocked | V15: {=IFERROR(INDEX($U$8:$U$167,SMALL(IF($U$8:$U$167<>"",ROW($U$8:$U$167)-7),ROW()-7)),"")} -> Drain tube blocked
A16: =A15+1 -> 46107 | B16: =IF(ISNUMBER(MATCH(tl_cause,Settings!$B$4:$B$83,0)),IF(tl_basis="Call date",COUNTIFS(Summary!$K$2:$K$240,tl_cause,Summary!$A$2:$A$240,">="&$A16,Summary!$A$2:$A$240,"<"&$A16+1,Summary!$A$2:$A$240,">="&IF(Dashboard!$B$3="",0,Dashboard!$B$3),Summary!$A$2:$A$240,"<"&IF(Dashboard!$B$4="",2958465,Dashboard!$B$4+1)),COUNTIFS(Summary!$K$2:$K$240,tl_cause,Summary!$D$2:$D$240,">="&$A16,Summary!$D$2:$D$240,"<"&$A16+1,Summary!$A$2:$A$240,">="&IF(Dashboard!$B$3="",0,Dashboard!$B$3),Summary!$A$2:$A$240,"<"&IF(Dashboard!$B$4="",2958465,Dashboard!$B$4+1))),IF(tl_basis="Call date",COUNTIFS(Summary!$E$2:$E$240,tl_cause,Summary!$A$2:$A$240,">="&$A16,Summary!$A$2:$A$240,"<"&$A16+1,Summary!$A$2:$A$240,">="&IF(Dashboard!$B$3="",0,Dashboard!$B$3),Summary!$A$2:$A$240,"<"&IF(Dashboard!$B$4="",2958465,Dashboard!$B$4+1)),COUNTIFS(Summary!$E$2:$E$240,tl_cause,Summary!$D$2:$D$240,">="&$A16,Summary!$D$2:$D$240,"<"&$A16+1,Summary!$A$2:$A$240,">="&IF(Dashboard!$B$3="",0,Dashboard!$B$3),Summary!$A$2:$A$240,"<"&IF(Dashboard!$B$4="",2958465,Dashboard!$B$4+1)))) -> 0 | C16: =IF(AND($F$8<>"",$A16=$F$8),1,NA()) -> #N/A | D16: =IF(AND($G$8<>"",$G$8>0,$A16=$G$8),1,NA()) -> #N/A | E16: =IF(AND($H$8<>"",$H$8>0,$A16=$H$8),1,NA()) -> #N/A | P16: =IF(Settings!A12="","",Settings!A12) -> Wrong / Loose wiring | Q16: =IF(Settings!A12="","",Settings!B12) -> Wrong / Loose wiring | R16: =IF(Settings!E12="",0,Settings!E12) -> 46108 | U16: =IF(Settings!A12="","",Settings!A12) -> Wrong / Loose wiring | V16: {=IFERROR(INDEX($U$8:$U$167,SMALL(IF($U$8:$U$167<>"",ROW($U$8:$U$167)-7),ROW()-7)),"")} -> Wrong / Loose wiring
A17: =A16+1 -> 46108 | B17: =IF(ISNUMBER(MATCH(tl_cause,Settings!$B$4:$B$83,0)),IF(tl_basis="Call date",COUNTIFS(Summary!$K$2:$K$240,tl_cause,Summary!$A$2:$A$240,">="&$A17,Summary!$A$2:$A$240,"<"&$A17+1,Summary!$A$2:$A$240,">="&IF(Dashboard!$B$3="",0,Dashboard!$B$3),Summary!$A$2:$A$240,"<"&IF(Dashboard!$B$4="",2958465,Dashboard!$B$4+1)),COUNTIFS(Summary!$K$2:$K$240,tl_cause,Summary!$D$2:$D$240,">="&$A17,Summary!$D$2:$D$240,"<"&$A17+1,Summary!$A$2:$A$240,">="&IF(Dashboard!$B$3="",0,Dashboard!$B$3),Summary!$A$2:$A$240,"<"&IF(Dashboard!$B$4="",2958465,Dashboard!$B$4+1))),IF(tl_basis="Call date",COUNTIFS(Summary!$E$2:$E$240,tl_cause,Summary!$A$2:$A$240,">="&$A17,Summary!$A$2:$A$240,"<"&$A17+1,Summary!$A$2:$A$240,">="&IF(Dashboard!$B$3="",0,Dashboard!$B$3),Summary!$A$2:$A$240,"<"&IF(Dashboard!$B$4="",2958465,Dashboard!$B$4+1)),COUNTIFS(Summary!$E$2:$E$240,tl_cause,Summary!$D$2:$D$240,">="&$A17,Summary!$D$2:$D$240,"<"&$A17+1,Summary!$A$2:$A$240,">="&IF(Dashboard!$B$3="",0,Dashboard!$B$3),Summary!$A$2:$A$240,"<"&IF(Dashboard!$B$4="",2958465,Dashboard!$B$4+1)))) -> 0 | C17: =IF(AND($F$8<>"",$A17=$F$8),1,NA()) -> #N/A | D17: =IF(AND($G$8<>"",$G$8>0,$A17=$G$8),1,NA()) -> #N/A | E17: =IF(AND($H$8<>"",$H$8>0,$A17=$H$8),1,NA()) -> #N/A | P17: =IF(Settings!A13="","",Settings!A13) -> Communication problem | Q17: =IF(Settings!A13="","",Settings!B13) -> Communication problem | R17: =IF(Settings!E13="",0,Settings!E13) -> 46191 | U17: =IF(Settings!A13="","",Settings!A13) -> Communication problem | V17: {=IFERROR(INDEX($U$8:$U$167,SMALL(IF($U$8:$U$167<>"",ROW($U$8:$U$167)-7),ROW()-7)),"")} -> Communication problem
A18: =A17+1 -> 46109 | B18: =IF(ISNUMBER(MATCH(tl_cause,Settings!$B$4:$B$83,0)),IF(tl_basis="Call date",COUNTIFS(Summary!$K$2:$K$240,tl_cause,Summary!$A$2:$A$240,">="&$A18,Summary!$A$2:$A$240,"<"&$A18+1,Summary!$A$2:$A$240,">="&IF(Dashboard!$B$3="",0,Dashboard!$B$3),Summary!$A$2:$A$240,"<"&IF(Dashboard!$B$4="",2958465,Dashboard!$B$4+1)),COUNTIFS(Summary!$K$2:$K$240,tl_cause,Summary!$D$2:$D$240,">="&$A18,Summary!$D$2:$D$240,"<"&$A18+1,Summary!$A$2:$A$240,">="&IF(Dashboard!$B$3="",0,Dashboard!$B$3),Summary!$A$2:$A$240,"<"&IF(Dashboard!$B$4="",2958465,Dashboard!$B$4+1))),IF(tl_basis="Call date",COUNTIFS(Summary!$E$2:$E$240,tl_cause,Summary!$A$2:$A$240,">="&$A18,Summary!$A$2:$A$240,"<"&$A18+1,Summary!$A$2:$A$240,">="&IF(Dashboard!$B$3="",0,Dashboard!$B$3),Summary!$A$2:$A$240,"<"&IF(Dashboard!$B$4="",2958465,Dashboard!$B$4+1)),COUNTIFS(Summary!$E$2:$E$240,tl_cause,Summary!$D$2:$D$240,">="&$A18,Summary!$D$2:$D$240,"<"&$A18+1,Summary!$A$2:$A$240,">="&IF(Dashboard!$B$3="",0,Dashboard!$B$3),Summary!$A$2:$A$240,"<"&IF(Dashboard!$B$4="",2958465,Dashboard!$B$4+1)))) -> 0 | C18: =IF(AND($F$8<>"",$A18=$F$8),1,NA()) -> #N/A | D18: =IF(AND($G$8<>"",$G$8>0,$A18=$G$8),1,NA()) -> #N/A | E18: =IF(AND($H$8<>"",$H$8>0,$A18=$H$8),1,NA()) -> #N/A | P18: =IF(Settings!A14="","",Settings!A14) -> High Store RH | Q18: =IF(Settings!A14="","",Settings!B14) -> High Store RH | R18: =IF(Settings!E14="",0,Settings!E14) -> 46171 | U18: =IF(Settings!A14="","",Settings!A14) -> High Store RH | V18: {=IFERROR(INDEX($U$8:$U$167,SMALL(IF($U$8:$U$167<>"",ROW($U$8:$U$167)-7),ROW()-7)),"")} -> High Store RH
A19: =A18+1 -> 46110 | B19: =IF(ISNUMBER(MATCH(tl_cause,Settings!$B$4:$B$83,0)),IF(tl_basis="Call date",COUNTIFS(Summary!$K$2:$K$240,tl_cause,Summary!$A$2:$A$240,">="&$A19,Summary!$A$2:$A$240,"<"&$A19+1,Summary!$A$2:$A$240,">="&IF(Dashboard!$B$3="",0,Dashboard!$B$3),Summary!$A$2:$A$240,"<"&IF(Dashboard!$B$4="",2958465,Dashboard!$B$4+1)),COUNTIFS(Summary!$K$2:$K$240,tl_cause,Summary!$D$2:$D$240,">="&$A19,Summary!$D$2:$D$240,"<"&$A19+1,Summary!$A$2:$A$240,">="&IF(Dashboard!$B$3="",0,Dashboard!$B$3),Summary!$A$2:$A$240,"<"&IF(Dashboard!$B$4="",2958465,Dashboard!$B$4+1))),IF(tl_basis="Call date",COUNTIFS(Summary!$E$2:$E$240,tl_cause,Summary!$A$2:$A$240,">="&$A19,Summary!$A$2:$A$240,"<"&$A19+1,Summary!$A$2:$A$240,">="&IF(Dashboard!$B$3="",0,Dashboard!$B$3),Summary!$A$2:$A$240,"<"&IF(Dashboard!$B$4="",2958465,Dashboard!$B$4+1)),COUNTIFS(Summary!$E$2:$E$240,tl_cause,Summary!$D$2:$D$240,">="&$A19,Summary!$D$2:$D$240,"<"&$A19+1,Summary!$A$2:$A$240,">="&IF(Dashboard!$B$3="",0,Dashboard!$B$3),Summary!$A$2:$A$240,"<"&IF(Dashboard!$B$4="",2958465,Dashboard!$B$4+1)))) -> 0 | C19: =IF(AND($F$8<>"",$A19=$F$8),1,NA()) -> #N/A | D19: =IF(AND($G$8<>"",$G$8>0,$A19=$G$8),1,NA()) -> #N/A | E19: =IF(AND($H$8<>"",$H$8>0,$A19=$H$8),1,NA()) -> #N/A | P19: =IF(Settings!A15="","",Settings!A15) -> Enclosure Seal | Q19: =IF(Settings!A15="","",Settings!B15) -> Enclosure Seal | R19: =IF(Settings!E15="",0,Settings!E15) -> 46135 | U19: =IF(Settings!A15="","",Settings!A15) -> Enclosure Seal | V19: {=IFERROR(INDEX($U$8:$U$167,SMALL(IF($U$8:$U$167<>"",ROW($U$8:$U$167)-7),ROW()-7)),"")} -> Enclosure Seal
A20: =A19+1 -> 46111 | B20: =IF(ISNUMBER(MATCH(tl_cause,Settings!$B$4:$B$83,0)),IF(tl_basis="Call date",COUNTIFS(Summary!$K$2:$K$240,tl_cause,Summary!$A$2:$A$240,">="&$A20,Summary!$A$2:$A$240,"<"&$A20+1,Summary!$A$2:$A$240,">="&IF(Dashboard!$B$3="",0,Dashboard!$B$3),Summary!$A$2:$A$240,"<"&IF(Dashboard!$B$4="",2958465,Dashboard!$B$4+1)),COUNTIFS(Summary!$K$2:$K$240,tl_cause,Summary!$D$2:$D$240,">="&$A20,Summary!$D$2:$D$240,"<"&$A20+1,Summary!$A$2:$A$240,">="&IF(Dashboard!$B$3="",0,Dashboard!$B$3),Summary!$A$2:$A$240,"<"&IF(Dashboard!$B$4="",2958465,Dashboard!$B$4+1))),IF(tl_basis="Call date",COUNTIFS(Summary!$E$2:$E$240,tl_cause,Summary!$A$2:$A$240,">="&$A20,Summary!$A$2:$A$240,"<"&$A20+1,Summary!$A$2:$A$240,">="&IF(Dashboard!$B$3="",0,Dashboard!$B$3),Summary!$A$2:$A$240,"<"&IF(Dashboard!$B$4="",2958465,Dashboard!$B$4+1)),COUNTIFS(Summary!$E$2:$E$240,tl_cause,Summary!$D$2:$D$240,">="&$A20,Summary!$D$2:$D$240,"<"&$A20+1,Summary!$A$2:$A$240,">="&IF(Dashboard!$B$3="",0,Dashboard!$B$3),Summary!$A$2:$A$240,"<"&IF(Dashboard!$B$4="",2958465,Dashboard!$B$4+1)))) -> 0 | C20: =IF(AND($F$8<>"",$A20=$F$8),1,NA()) -> #N/A | D20: =IF(AND($G$8<>"",$G$8>0,$A20=$G$8),1,NA()) -> #N/A | E20: =IF(AND($H$8<>"",$H$8>0,$A20=$H$8),1,NA()) -> #N/A | P20: =IF(Settings!A16="","",Settings!A16) -> Component Failure | Q20: =IF(Settings!A16="","",Settings!B16) -> Component Failure | R20: =IF(Settings!E16="",0,Settings!E16) -> 46082 | U20: =IF(Settings!A16="","",Settings!A16) -> Component Failure | V20: {=IFERROR(INDEX($U$8:$U$167,SMALL(IF($U$8:$U$167<>"",ROW($U$8:$U$167)-7),ROW()-7)),"")} -> Component Failure
... A87: =A86+1 -> 46178 | B87: =IF(ISNUMBER(MATCH(tl_cause,Settings!$B$4:$B$83,0)),IF(tl_basis="Call date",COUNTIFS(Summary!$K$2:$K$240,tl_cause,Summary!$A$2:$A$240,">="&$A87,Summary!$A$2:$A$240,"<"&$A87+1,Summary!$A$2:$A$240,">="&IF(Dashboard!$B$3="",0,Dashboard!$B$3),Summary!$A$2:$A$240,"<"&IF(Dashboard!$B$4="",2958465,Dashboard!$B$4+1)),COUNTIFS(Summary!$K$2:$K$240,tl_cause,Summary!$D$2:$D$240,">="&$A87,Summary!$D$2:$D$240,"<"&$A87+1,Summary!$A$2:$A$240,">="&IF(Dashboard!$B$3="",0,Dashboard!$B$3),Summary!$A$2:$A$240,"<"&IF(Dashboard!$B$4="",2958465,Dashboard!$B$4+1))),IF(tl_basis="Call date",COUNTIFS(Summary!$E$2:$E$240,tl_cause,Summary!$A$2:$A$240,">="&$A87,Summary!$A$2:$A$240,"<"&$A87+1,Summary!$A$2:$A$240,">="&IF(Dashboard!$B$3="",0,Dashboard!$B$3),Summary!$A$2:$A$240,"<"&IF(Dashboard!$B$4="",2958465,Dashboard!$B$4+1)),COUNTIFS(Summary!$E$2:$E$240,tl_cause,Summary!$D$2:$D$240,">="&$A87,Summary!$D$2:$D$240,"<"&$A87+1,Summary!$A$2:$A$240,">="&IF(Dashboard!$B$3="",0,Dashboard!$B$3),Summary!$A$2:$A$240,"<"&IF(Dashboard!$B$4="",2958465,Dashboard!$B$4+1)))) -> 0 | C87: =IF(AND($F$8<>"",$A87=$F$8),1,NA()) -> #N/A | D87: =IF(AND($G$8<>"",$G$8>0,$A87=$G$8),1,NA()) -> #N/A | E87: =IF(AND($H$8<>"",$H$8>0,$A87=$H$8),1,NA()) -> #N/A | P87: =IF(Settings!A83="","",Settings!A83) | Q87: =IF(Settings!A83="","",Settings!B83) | R87: =IF(Settings!E83="",0,Settings!E83) -> 0 | U87: =IF(Settings!A83="","",Settings!A83) | V87: {=IFERROR(INDEX($U$8:$U$167,SMALL(IF($U$8:$U$167<>"",ROW($U$8:$U$167)-7),ROW()-7)),"")}
A88: =A87+1 -> 46179 | B88: =IF(ISNUMBER(MATCH(tl_cause,Settings!$B$4:$B$83,0)),IF(tl_basis="Call date",COUNTIFS(Summary!$K$2:$K$240,tl_cause,Summary!$A$2:$A$240,">="&$A88,Summary!$A$2:$A$240,"<"&$A88+1,Summary!$A$2:$A$240,">="&IF(Dashboard!$B$3="",0,Dashboard!$B$3),Summary!$A$2:$A$240,"<"&IF(Dashboard!$B$4="",2958465,Dashboard!$B$4+1)),COUNTIFS(Summary!$K$2:$K$240,tl_cause,Summary!$D$2:$D$240,">="&$A88,Summary!$D$2:$D$240,"<"&$A88+1,Summary!$A$2:$A$240,">="&IF(Dashboard!$B$3="",0,Dashboard!$B$3),Summary!$A$2:$A$240,"<"&IF(Dashboard!$B$4="",2958465,Dashboard!$B$4+1))),IF(tl_basis="Call date",COUNTIFS(Summary!$E$2:$E$240,tl_cause,Summary!$A$2:$A$240,">="&$A88,Summary!$A$2:$A$240,"<"&$A88+1,Summary!$A$2:$A$240,">="&IF(Dashboard!$B$3="",0,Dashboard!$B$3),Summary!$A$2:$A$240,"<"&IF(Dashboard!$B$4="",2958465,Dashboard!$B$4+1)),COUNTIFS(Summary!$E$2:$E$240,tl_cause,Summary!$D$2:$D$240,">="&$A88,Summary!$D$2:$D$240,"<"&$A88+1,Summary!$A$2:$A$240,">="&IF(Dashboard!$B$3="",0,Dashboard!$B$3),Summary!$A$2:$A$240,"<"&IF(Dashboard!$B$4="",2958465,Dashboard!$B$4+1)))) -> 0 | C88: =IF(AND($F$8<>"",$A88=$F$8),1,NA()) -> #N/A | D88: =IF(AND($G$8<>"",$G$8>0,$A88=$G$8),1,NA()) -> #N/A | E88: =IF(AND($H$8<>"",$H$8>0,$A88=$H$8),1,NA()) -> #N/A | P88: =IF(Settings!A4="","",Settings!A4) -> Ref. leak/ Low charge | Q88: =IF(Settings!A4="","",Settings!B4) -> Ref. leak/ Low charge | R88: =IF(Settings!F4="",0,Settings!F4) -> 0 | U88: =IF(OR(Settings!B4="",COUNTIF(Settings!$A$4:$A$83,Settings!B4)>0,COUNTIF(Settings!$B$4:B4,Settings!B4)>1),"",Settings!B4) | V88: {=IFERROR(INDEX($U$8:$U$167,SMALL(IF($U$8:$U$167<>"",ROW($U$8:$U$167)-7),ROW()-7)),"")}
A89: =A88+1 -> 46180 | B89: =IF(ISNUMBER(MATCH(tl_cause,Settings!$B$4:$B$83,0)),IF(tl_basis="Call date",COUNTIFS(Summary!$K$2:$K$240,tl_cause,Summary!$A$2:$A$240,">="&$A89,Summary!$A$2:$A$240,"<"&$A89+1,Summary!$A$2:$A$240,">="&IF(Dashboard!$B$3="",0,Dashboard!$B$3),Summary!$A$2:$A$240,"<"&IF(Dashboard!$B$4="",2958465,Dashboard!$B$4+1)),COUNTIFS(Summary!$K$2:$K$240,tl_cause,Summary!$D$2:$D$240,">="&$A89,Summary!$D$2:$D$240,"<"&$A89+1,Summary!$A$2:$A$240,">="&IF(Dashboard!$B$3="",0,Dashboard!$B$3),Summary!$A$2:$A$240,"<"&IF(Dashboard!$B$4="",2958465,Dashboard!$B$4+1))),IF(tl_basis="Call date",COUNTIFS(Summary!$E$2:$E$240,tl_cause,Summary!$A$2:$A$240,">="&$A89,Summary!$A$2:$A$240,"<"&$A89+1,Summary!$A$2:$A$240,">="&IF(Dashboard!$B$3="",0,Dashboard!$B$3),Summary!$A$2:$A$240,"<"&IF(Dashboard!$B$4="",2958465,Dashboard!$B$4+1)),COUNTIFS(Summary!$E$2:$E$240,tl_cause,Summary!$D$2:$D$240,">="&$A89,Summary!$D$2:$D$240,"<"&$A89+1,Summary!$A$2:$A$240,">="&IF(Dashboard!$B$3="",0,Dashboard!$B$3),Summary!$A$2:$A$240,"<"&IF(Dashboard!$B$4="",2958465,Dashboard!$B$4+1)))) -> 0 | C89: =IF(AND($F$8<>"",$A89=$F$8),1,NA()) -> #N/A | D89: =IF(AND($G$8<>"",$G$8>0,$A89=$G$8),1,NA()) -> #N/A | E89: =IF(AND($H$8<>"",$H$8>0,$A89=$H$8),1,NA()) -> #N/A | P89: =IF(Settings!A5="","",Settings!A5) -> Door Torque | Q89: =IF(Settings!A5="","",Settings!B5) -> Doors | R89: =IF(Settings!F5="",0,Settings!F5) -> 0 | U89: =IF(OR(Settings!B5="",COUNTIF(Settings!$A$4:$A$83,Settings!B5)>0,COUNTIF(Settings!$B$4:B5,Settings!B5)>1),"",Settings!B5) -> Doors | V89: {=IFERROR(INDEX($U$8:$U$167,SMALL(IF($U$8:$U$167<>"",ROW($U$8:$U$167)-7),ROW()-7)),"")}
A90: =A89+1 -> 46181 | B90: =IF(ISNUMBER(MATCH(tl_cause,Settings!$B$4:$B$83,0)),IF(tl_basis="Call date",COUNTIFS(Summary!$K$2:$K$240,tl_cause,Summary!$A$2:$A$240,">="&$A90,Summary!$A$2:$A$240,"<"&$A90+1,Summary!$A$2:$A$240,">="&IF(Dashboard!$B$3="",0,Dashboard!$B$3),Summary!$A$2:$A$240,"<"&IF(Dashboard!$B$4="",2958465,Dashboard!$B$4+1)),COUNTIFS(Summary!$K$2:$K$240,tl_cause,Summary!$D$2:$D$240,">="&$A90,Summary!$D$2:$D$240,"<"&$A90+1,Summary!$A$2:$A$240,">="&IF(Dashboard!$B$3="",0,Dashboard!$B$3),Summary!$A$2:$A$240,"<"&IF(Dashboard!$B$4="",2958465,Dashboard!$B$4+1))),IF(tl_basis="Call date",COUNTIFS(Summary!$E$2:$E$240,tl_cause,Summary!$A$2:$A$240,">="&$A90,Summary!$A$2:$A$240,"<"&$A90+1,Summary!$A$2:$A$240,">="&IF(Dashboard!$B$3="",0,Dashboard!$B$3),Summary!$A$2:$A$240,"<"&IF(Dashboard!$B$4="",2958465,Dashboard!$B$4+1)),COUNTIFS(Summary!$E$2:$E$240,tl_cause,Summary!$D$2:$D$240,">="&$A90,Summary!$D$2:$D$240,"<"&$A90+1,Summary!$A$2:$A$240,">="&IF(Dashboard!$B$3="",0,Dashboard!$B$3),Summary!$A$2:$A$240,"<"&IF(Dashboard!$B$4="",2958465,Dashboard!$B$4+1)))) -> 0 | C90: =IF(AND($F$8<>"",$A90=$F$8),1,NA()) -> #N/A | D90: =IF(AND($G$8<>"",$G$8>0,$A90=$G$8),1,NA()) -> #N/A | E90: =IF(AND($H$8<>"",$H$8>0,$A90=$H$8),1,NA()) -> #N/A | P90: =IF(Settings!A6="","",Settings!A6) -> Door Gasket | Q90: =IF(Settings!A6="","",Settings!B6) -> Doors | R90: =IF(Settings!F6="",0,Settings!F6) -> 0 | U90: =IF(OR(Settings!B6="",COUNTIF(Settings!$A$4:$A$83,Settings!B6)>0,COUNTIF(Settings!$B$4:B6,Settings!B6)>1),"",Settings!B6) | V90: {=IFERROR(INDEX($U$8:$U$167,SMALL(IF($U$8:$U$167<>"",ROW($U$8:$U$167)-7),ROW()-7)),"")}
A91: =A90+1 -> 46182 | B91: =IF(ISNUMBER(MATCH(tl_cause,Settings!$B$4:$B$83,0)),IF(tl_basis="Call date",COUNTIFS(Summary!$K$2:$K$240,tl_cause,Summary!$A$2:$A$240,">="&$A91,Summary!$A$2:$A$240,"<"&$A91+1,Summary!$A$2:$A$240,">="&IF(Dashboard!$B$3="",0,Dashboard!$B$3),Summary!$A$2:$A$240,"<"&IF(Dashboard!$B$4="",2958465,Dashboard!$B$4+1)),COUNTIFS(Summary!$K$2:$K$240,tl_cause,Summary!$D$2:$D$240,">="&$A91,Summary!$D$2:$D$240,"<"&$A91+1,Summary!$A$2:$A$240,">="&IF(Dashboard!$B$3="",0,Dashboard!$B$3),Summary!$A$2:$A$240,"<"&IF(Dashboard!$B$4="",2958465,Dashboard!$B$4+1))),IF(tl_basis="Call date",COUNTIFS(Summary!$E$2:$E$240,tl_cause,Summary!$A$2:$A$240,">="&$A91,Summary!$A$2:$A$240,"<"&$A91+1,Summary!$A$2:$A$240,">="&IF(Dashboard!$B$3="",0,Dashboard!$B$3),Summary!$A$2:$A$240,"<"&IF(Dashboard!$B$4="",2958465,Dashboard!$B$4+1)),COUNTIFS(Summary!$E$2:$E$240,tl_cause,Summary!$D$2:$D$240,">="&$A91,Summary!$D$2:$D$240,"<"&$A91+1,Summary!$A$2:$A$240,">="&IF(Dashboard!$B$3="",0,Dashboard!$B$3),Summary!$A$2:$A$240,"<"&IF(Dashboard!$B$4="",2958465,Dashboard!$B$4+1)))) -> 0 | C91: =IF(AND($F$8<>"",$A91=$F$8),1,NA()) -> #N/A | D91: =IF(AND($G$8<>"",$G$8>0,$A91=$G$8),1,NA()) -> #N/A | E91: =IF(AND($H$8<>"",$H$8>0,$A91=$H$8),1,NA()) -> #N/A | P91: =IF(Settings!A7="","",Settings!A7) -> Door frame heater | Q91: =IF(Settings!A7="","",Settings!B7) -> Doors | R91: =IF(Settings!F7="",0,Settings!F7) -> 0 | U91: =IF(OR(Settings!B7="",COUNTIF(Settings!$A$4:$A$83,Settings!B7)>0,COUNTIF(Settings!$B$4:B7,Settings!B7)>1),"",Settings!B7) | V91: {=IFERROR(INDEX($U$8:$U$167,SMALL(IF($U$8:$U$167<>"",ROW($U$8:$U$167)-7),ROW()-7)),"")}
A92: =A91+1 -> 46183 | B92: =IF(ISNUMBER(MATCH(tl_cause,Settings!$B$4:$B$83,0)),IF(tl_basis="Call date",COUNTIFS(Summary!$K$2:$K$240,tl_cause,Summary!$A$2:$A$240,">="&$A92,Summary!$A$2:$A$240,"<"&$A92+1,Summary!$A$2:$A$240,">="&IF(Dashboard!$B$3="",0,Dashboard!$B$3),Summary!$A$2:$A$240,"<"&IF(Dashboard!$B$4="",2958465,Dashboard!$B$4+1)),COUNTIFS(Summary!$K$2:$K$240,tl_cause,Summary!$D$2:$D$240,">="&$A92,Summary!$D$2:$D$240,"<"&$A92+1,Summary!$A$2:$A$240,">="&IF(Dashboard!$B$3="",0,Dashboard!$B$3),Summary!$A$2:$A$240,"<"&IF(Dashboard!$B$4="",2958465,Dashboard!$B$4+1))),IF(tl_basis="Call date",COUNTIFS(Summary!$E$2:$E$240,tl_cause,Summary!$A$2:$A$240,">="&$A92,Summary!$A$2:$A$240,"<"&$A92+1,Summary!$A$2:$A$240,">="&IF(Dashboard!$B$3="",0,Dashboard!$B$3),Summary!$A$2:$A$240,"<"&IF(Dashboard!$B$4="",2958465,Dashboard!$B$4+1)),COUNTIFS(Summary!$E$2:$E$240,tl_cause,Summary!$D$2:$D$240,">="&$A92,Summary!$D$2:$D$240,"<"&$A92+1,Summary!$A$2:$A$240,">="&IF(Dashboard!$B$3="",0,Dashboard!$B$3),Summary!$A$2:$A$240,"<"&IF(Dashboard!$B$4="",2958465,Dashboard!$B$4+1)))) -> 0 | C92: =IF(AND($F$8<>"",$A92=$F$8),1,NA()) -> #N/A | D92: =IF(AND($G$8<>"",$G$8>0,$A92=$G$8),1,NA()) -> #N/A | E92: =IF(AND($H$8<>"",$H$8>0,$A92=$H$8),1,NA()) -> #N/A | P92: =IF(Settings!A8="","",Settings!A8) -> Door Torsion rod | Q92: =IF(Settings!A8="","",Settings!B8) -> Doors | R92: =IF(Settings!F8="",0,Settings!F8) -> 0 | U92: =IF(OR(Settings!B8="",COUNTIF(Settings!$A$4:$A$83,Settings!B8)>0,COUNTIF(Settings!$B$4:B8,Settings!B8)>1),"",Settings!B8) | V92: {=IFERROR(INDEX($U$8:$U$167,SMALL(IF($U$8:$U$167<>"",ROW($U$8:$U$167)-7),ROW()-7)),"")}
A93: =A92+1 -> 46184 | B93: =IF(ISNUMBER(MATCH(tl_cause,Settings!$B$4:$B$83,0)),IF(tl_basis="Call date",COUNTIFS(Summary!$K$2:$K$240,tl_cause,Summary!$A$2:$A$240,">="&$A93,Summary!$A$2:$A$240,"<"&$A93+1,Summary!$A$2:$A$240,">="&IF(Dashboard!$B$3="",0,Dashboard!$B$3),Summary!$A$2:$A$240,"<"&IF(Dashboard!$B$4="",2958465,Dashboard!$B$4+1)),COUNTIFS(Summary!$K$2:$K$240,tl_cause,Summary!$D$2:$D$240,">="&$A93,Summary!$D$2:$D$240,"<"&$A93+1,Summary!$A$2:$A$240,">="&IF(Dashboard!$B$3="",0,Dashboard!$B$3),Summary!$A$2:$A$240,"<"&IF(Dashboard!$B$4="",2958465,Dashboard!$B$4+1))),IF(tl_basis="Call date",COUNTIFS(Summary!$E$2:$E$240,tl_cause,Summary!$A$2:$A$240,">="&$A93,Summary!$A$2:$A$240,"<"&$A93+1,Summary!$A$2:$A$240,">="&IF(Dashboard!$B$3="",0,Dashboard!$B$3),Summary!$A$2:$A$240,"<"&IF(Dashboard!$B$4="",2958465,Dashboard!$B$4+1)),COUNTIFS(Summary!$E$2:$E$240,tl_cause,Summary!$D$2:$D$240,">="&$A93,Summary!$D$2:$D$240,"<"&$A93+1,Summary!$A$2:$A$240,">="&IF(Dashboard!$B$3="",0,Dashboard!$B$3),Summary!$A$2:$A$240,"<"&IF(Dashboard!$B$4="",2958465,Dashboard!$B$4+1)))) -> 0 | C93: =IF(AND($F$8<>"",$A93=$F$8),1,NA()) -> #N/A | D93: =IF(AND($G$8<>"",$G$8>0,$A93=$G$8),1,NA()) -> #N/A | E93: =IF(AND($H$8<>"",$H$8>0,$A93=$H$8),1,NA()) -> #N/A | P93: =IF(Settings!A9="","",Settings!A9) -> Door not closed (Overnight) | Q93: =IF(Settings!A9="","",Settings!B9) -> Doors | R93: =IF(Settings!F9="",0,Settings!F9) -> 0 | U93: =IF(OR(Settings!B9="",COUNTIF(Settings!$A$4:$A$83,Settings!B9)>0,COUNTIF(Settings!$B$4:B9,Settings!B9)>1),"",Settings!B9) | V93: {=IFERROR(INDEX($U$8:$U$167,SMALL(IF($U$8:$U$167<>"",ROW($U$8:$U$167)-7),ROW()-7)),"")}
A94: =A93+1 -> 46185 | B94: =IF(ISNUMBER(MATCH(tl_cause,Settings!$B$4:$B$83,0)),IF(tl_basis="Call date",COUNTIFS(Summary!$K$2:$K$240,tl_cause,Summary!$A$2:$A$240,">="&$A94,Summary!$A$2:$A$240,"<"&$A94+1,Summary!$A$2:$A$240,">="&IF(Dashboard!$B$3="",0,Dashboard!$B$3),Summary!$A$2:$A$240,"<"&IF(Dashboard!$B$4="",2958465,Dashboard!$B$4+1)),COUNTIFS(Summary!$K$2:$K$240,tl_cause,Summary!$D$2:$D$240,">="&$A94,Summary!$D$2:$D$240,"<"&$A94+1,Summary!$A$2:$A$240,">="&IF(Dashboard!$B$3="",0,Dashboard!$B$3),Summary!$A$2:$A$240,"<"&IF(Dashboard!$B$4="",2958465,Dashboard!$B$4+1))),IF(tl_basis="Call date",COUNTIFS(Summary!$E$2:$E$240,tl_cause,Summary!$A$2:$A$240,">="&$A94,Summary!$A$2:$A$240,"<"&$A94+1,Summary!$A$2:$A$240,">="&IF(Dashboard!$B$3="",0,Dashboard!$B$3),Summary!$A$2:$A$240,"<"&IF(Dashboard!$B$4="",2958465,Dashboard!$B$4+1)),COUNTIFS(Summary!$E$2:$E$240,tl_cause,Summary!$D$2:$D$240,">="&$A94,Summary!$D$2:$D$240,"<"&$A94+1,Summary!$A$2:$A$240,">="&IF(Dashboard!$B$3="",0,Dashboard!$B$3),Summary!$A$2:$A$240,"<"&IF(Dashboard!$B$4="",2958465,Dashboard!$B$4+1)))) -> 0 | C94: =IF(AND($F$8<>"",$A94=$F$8),1,NA()) -> #N/A | D94: =IF(AND($G$8<>"",$G$8>0,$A94=$G$8),1,NA()) -> #N/A | E94: =IF(AND($H$8<>"",$H$8>0,$A94=$H$8),1,NA()) -> #N/A | P94: =IF(Settings!A10="","",Settings!A10) -> Door - general | Q94: =IF(Settings!A10="","",Settings!B10) -> Doors | R94: =IF(Settings!F10="",0,Settings!F10) -> 0 | U94: =IF(OR(Settings!B10="",COUNTIF(Settings!$A$4:$A$83,Settings!B10)>0,COUNTIF(Settings!$B$4:B10,Settings!B10)>1),"",Settings!B10) | V94: {=IFERROR(INDEX($U$8:$U$167,SMALL(IF($U$8:$U$167<>"",ROW($U$8:$U$167)-7),ROW()-7)),"")}
A95: =A94+1 -> 46186 | B95: =IF(ISNUMBER(MATCH(tl_cause,Settings!$B$4:$B$83,0)),IF(tl_basis="Call date",COUNTIFS(Summary!$K$2:$K$240,tl_cause,Summary!$A$2:$A$240,">="&$A95,Summary!$A$2:$A$240,"<"&$A95+1,Summary!$A$2:$A$240,">="&IF(Dashboard!$B$3="",0,Dashboard!$B$3),Summary!$A$2:$A$240,"<"&IF(Dashboard!$B$4="",2958465,Dashboard!$B$4+1)),COUNTIFS(Summary!$K$2:$K$240,tl_cause,Summary!$D$2:$D$240,">="&$A95,Summary!$D$2:$D$240,"<"&$A95+1,Summary!$A$2:$A$240,">="&IF(Dashboard!$B$3="",0,Dashboard!$B$3),Summary!$A$2:$A$240,"<"&IF(Dashboard!$B$4="",2958465,Dashboard!$B$4+1))),IF(tl_basis="Call date",COUNTIFS(Summary!$E$2:$E$240,tl_cause,Summary!$A$2:$A$240,">="&$A95,Summary!$A$2:$A$240,"<"&$A95+1,Summary!$A$2:$A$240,">="&IF(Dashboard!$B$3="",0,Dashboard!$B$3),Summary!$A$2:$A$240,"<"&IF(Dashboard!$B$4="",2958465,Dashboard!$B$4+1)),COUNTIFS(Summary!$E$2:$E$240,tl_cause,Summary!$D$2:$D$240,">="&$A95,Summary!$D$2:$D$240,"<"&$A95+1,Summary!$A$2:$A$240,">="&IF(Dashboard!$B$3="",0,Dashboard!$B$3),Summary!$A$2:$A$240,"<"&IF(Dashboard!$B$4="",2958465,Dashboard!$B$4+1)))) -> 0 | C95: =IF(AND($F$8<>"",$A95=$F$8),1,NA()) -> #N/A | D95: =IF(AND($G$8<>"",$G$8>0,$A95=$G$8),1,NA()) -> #N/A | E95: =IF(AND($H$8<>"",$H$8>0,$A95=$H$8),1,NA()) -> #N/A | P95: =IF(Settings!A11="","",Settings!A11) -> Drain tube blocked | Q95: =IF(Settings!A11="","",Settings!B11) -> Drain tube blocked | R95: =IF(Settings!F11="",0,Settings!F11) -> 0 | U95: =IF(OR(Settings!B11="",COUNTIF(Settings!$A$4:$A$83,Settings!B11)>0,COUNTIF(Settings!$B$4:B11,Settings!B11)>1),"",Settings!B11) | V95: {=IFERROR(INDEX($U$8:$U$167,SMALL(IF($U$8:$U$167<>"",ROW($U$8:$U$167)-7),ROW()-7)),"")}
A96: =A95+1 -> 46187 | B96: =IF(ISNUMBER(MATCH(tl_cause,Settings!$B$4:$B$83,0)),IF(tl_basis="Call date",COUNTIFS(Summary!$K$2:$K$240,tl_cause,Summary!$A$2:$A$240,">="&$A96,Summary!$A$2:$A$240,"<"&$A96+1,Summary!$A$2:$A$240,">="&IF(Dashboard!$B$3="",0,Dashboard!$B$3),Summary!$A$2:$A$240,"<"&IF(Dashboard!$B$4="",2958465,Dashboard!$B$4+1)),COUNTIFS(Summary!$K$2:$K$240,tl_cause,Summary!$D$2:$D$240,">="&$A96,Summary!$D$2:$D$240,"<"&$A96+1,Summary!$A$2:$A$240,">="&IF(Dashboard!$B$3="",0,Dashboard!$B$3),Summary!$A$2:$A$240,"<"&IF(Dashboard!$B$4="",2958465,Dashboard!$B$4+1))),IF(tl_basis="Call date",COUNTIFS(Summary!$E$2:$E$240,tl_cause,Summary!$A$2:$A$240,">="&$A96,Summary!$A$2:$A$240,"<"&$A96+1,Summary!$A$2:$A$240,">="&IF(Dashboard!$B$3="",0,Dashboard!$B$3),Summary!$A$2:$A$240,"<"&IF(Dashboard!$B$4="",2958465,Dashboard!$B$4+1)),COUNTIFS(Summary!$E$2:$E$240,tl_cause,Summary!$D$2:$D$240,">="&$A96,Summary!$D$2:$D$240,"<"&$A96+1,Summary!$A$2:$A$240,">="&IF(Dashboard!$B$3="",0,Dashboard!$B$3),Summary!$A$2:$A$240,"<"&IF(Dashboard!$B$4="",2958465,Dashboard!$B$4+1)))) -> 0 | C96: =IF(AND($F$8<>"",$A96=$F$8),1,NA()) -> #N/A | D96: =IF(AND($G$8<>"",$G$8>0,$A96=$G$8),1,NA()) -> #N/A | E96: =IF(AND($H$8<>"",$H$8>0,$A96=$H$8),1,NA()) -> #N/A | P96: =IF(Settings!A12="","",Settings!A12) -> Wrong / Loose wiring | Q96: =IF(Settings!A12="","",Settings!B12) -> Wrong / Loose wiring | R96: =IF(Settings!F12="",0,Settings!F12) -> 0 | U96: =IF(OR(Settings!B12="",COUNTIF(Settings!$A$4:$A$83,Settings!B12)>0,COUNTIF(Settings!$B$4:B12,Settings!B12)>1),"",Settings!B12) | V96: {=IFERROR(INDEX($U$8:$U$167,SMALL(IF($U$8:$U$167<>"",ROW($U$8:$U$167)-7),ROW()-7)),"")}
A97: =A96+1 -> 46188 | B97: =IF(ISNUMBER(MATCH(tl_cause,Settings!$B$4:$B$83,0)),IF(tl_basis="Call date",COUNTIFS(Summary!$K$2:$K$240,tl_cause,Summary!$A$2:$A$240,">="&$A97,Summary!$A$2:$A$240,"<"&$A97+1,Summary!$A$2:$A$240,">="&IF(Dashboard!$B$3="",0,Dashboard!$B$3),Summary!$A$2:$A$240,"<"&IF(Dashboard!$B$4="",2958465,Dashboard!$B$4+1)),COUNTIFS(Summary!$K$2:$K$240,tl_cause,Summary!$D$2:$D$240,">="&$A97,Summary!$D$2:$D$240,"<"&$A97+1,Summary!$A$2:$A$240,">="&IF(Dashboard!$B$3="",0,Dashboard!$B$3),Summary!$A$2:$A$240,"<"&IF(Dashboard!$B$4="",2958465,Dashboard!$B$4+1))),IF(tl_basis="Call date",COUNTIFS(Summary!$E$2:$E$240,tl_cause,Summary!$A$2:$A$240,">="&$A97,Summary!$A$2:$A$240,"<"&$A97+1,Summary!$A$2:$A$240,">="&IF(Dashboard!$B$3="",0,Dashboard!$B$3),Summary!$A$2:$A$240,"<"&IF(Dashboard!$B$4="",2958465,Dashboard!$B$4+1)),COUNTIFS(Summary!$E$2:$E$240,tl_cause,Summary!$D$2:$D$240,">="&$A97,Summary!$D$2:$D$240,"<"&$A97+1,Summary!$A$2:$A$240,">="&IF(Dashboard!$B$3="",0,Dashboard!$B$3),Summary!$A$2:$A$240,"<"&IF(Dashboard!$B$4="",2958465,Dashboard!$B$4+1)))) -> 0 | C97: =IF(AND($F$8<>"",$A97=$F$8),1,NA()) -> #N/A | D97: =IF(AND($G$8<>"",$G$8>0,$A97=$G$8),1,NA()) -> #N/A | E97: =IF(AND($H$8<>"",$H$8>0,$A97=$H$8),1,NA()) -> #N/A | P97: =IF(Settings!A13="","",Settings!A13) -> Communication problem | Q97: =IF(Settings!A13="","",Settings!B13) -> Communication problem | R97: =IF(Settings!F13="",0,Settings!F13) -> 0 | U97: =IF(OR(Settings!B13="",COUNTIF(Settings!$A$4:$A$83,Settings!B13)>0,COUNTIF(Settings!$B$4:B13,Settings!B13)>1),"",Settings!B13) | V97: {=IFERROR(INDEX($U$8:$U$167,SMALL(IF($U$8:$U$167<>"",ROW($U$8:$U$167)-7),ROW()-7)),"")}
A98: =A97+1 -> 46189 | B98: =IF(ISNUMBER(MATCH(tl_cause,Settings!$B$4:$B$83,0)),IF(tl_basis="Call date",COUNTIFS(Summary!$K$2:$K$240,tl_cause,Summary!$A$2:$A$240,">="&$A98,Summary!$A$2:$A$240,"<"&$A98+1,Summary!$A$2:$A$240,">="&IF(Dashboard!$B$3="",0,Dashboard!$B$3),Summary!$A$2:$A$240,"<"&IF(Dashboard!$B$4="",2958465,Dashboard!$B$4+1)),COUNTIFS(Summary!$K$2:$K$240,tl_cause,Summary!$D$2:$D$240,">="&$A98,Summary!$D$2:$D$240,"<"&$A98+1,Summary!$A$2:$A$240,">="&IF(Dashboard!$B$3="",0,Dashboard!$B$3),Summary!$A$2:$A$240,"<"&IF(Dashboard!$B$4="",2958465,Dashboard!$B$4+1))),IF(tl_basis="Call date",COUNTIFS(Summary!$E$2:$E$240,tl_cause,Summary!$A$2:$A$240,">="&$A98,Summary!$A$2:$A$240,"<"&$A98+1,Summary!$A$2:$A$240,">="&IF(Dashboard!$B$3="",0,Dashboard!$B$3),Summary!$A$2:$A$240,"<"&IF(Dashboard!$B$4="",2958465,Dashboard!$B$4+1)),COUNTIFS(Summary!$E$2:$E$240,tl_cause,Summary!$D$2:$D$240,">="&$A98,Summary!$D$2:$D$240,"<"&$A98+1,Summary!$A$2:$A$240,">="&IF(Dashboard!$B$3="",0,Dashboard!$B$3),Summary!$A$2:$A$240,"<"&IF(Dashboard!$B$4="",2958465,Dashboard!$B$4+1)))) -> 0 | C98: =IF(AND($F$8<>"",$A98=$F$8),1,NA()) -> #N/A | D98: =IF(AND($G$8<>"",$G$8>0,$A98=$G$8),1,NA()) -> #N/A | E98: =IF(AND($H$8<>"",$H$8>0,$A98=$H$8),1,NA()) -> #N/A | P98: =IF(Settings!A14="","",Settings!A14) -> High Store RH | Q98: =IF(Settings!A14="","",Settings!B14) -> High Store RH | R98: =IF(Settings!F14="",0,Settings!F14) -> 0 | U98: =IF(OR(Settings!B14="",COUNTIF(Settings!$A$4:$A$83,Settings!B14)>0,COUNTIF(Settings!$B$4:B14,Settings!B14)>1),"",Settings!B14) | V98: {=IFERROR(INDEX($U$8:$U$167,SMALL(IF($U$8:$U$167<>"",ROW($U$8:$U$167)-7),ROW()-7)),"")}
A99: =A98+1 -> 46190 | B99: =IF(ISNUMBER(MATCH(tl_cause,Settings!$B$4:$B$83,0)),IF(tl_basis="Call date",COUNTIFS(Summary!$K$2:$K$240,tl_cause,Summary!$A$2:$A$240,">="&$A99,Summary!$A$2:$A$240,"<"&$A99+1,Summary!$A$2:$A$240,">="&IF(Dashboard!$B$3="",0,Dashboard!$B$3),Summary!$A$2:$A$240,"<"&IF(Dashboard!$B$4="",2958465,Dashboard!$B$4+1)),COUNTIFS(Summary!$K$2:$K$240,tl_cause,Summary!$D$2:$D$240,">="&$A99,Summary!$D$2:$D$240,"<"&$A99+1,Summary!$A$2:$A$240,">="&IF(Dashboard!$B$3="",0,Dashboard!$B$3),Summary!$A$2:$A$240,"<"&IF(Dashboard!$B$4="",2958465,Dashboard!$B$4+1))),IF(tl_basis="Call date",COUNTIFS(Summary!$E$2:$E$240,tl_cause,Summary!$A$2:$A$240,">="&$A99,Summary!$A$2:$A$240,"<"&$A99+1,Summary!$A$2:$A$240,">="&IF(Dashboard!$B$3="",0,Dashboard!$B$3),Summary!$A$2:$A$240,"<"&IF(Dashboard!$B$4="",2958465,Dashboard!$B$4+1)),COUNTIFS(Summary!$E$2:$E$240,tl_cause,Summary!$D$2:$D$240,">="&$A99,Summary!$D$2:$D$240,"<"&$A99+1,Summary!$A$2:$A$240,">="&IF(Dashboard!$B$3="",0,Dashboard!$B$3),Summary!$A$2:$A$240,"<"&IF(Dashboard!$B$4="",2958465,Dashboard!$B$4+1)))) -> 0 | C99: =IF(AND($F$8<>"",$A99=$F$8),1,NA()) -> #N/A | D99: =IF(AND($G$8<>"",$G$8>0,$A99=$G$8),1,NA()) -> #N/A | E99: =IF(AND($H$8<>"",$H$8>0,$A99=$H$8),1,NA()) -> #N/A | P99: =IF(Settings!A15="","",Settings!A15) -> Enclosure Seal | Q99: =IF(Settings!A15="","",Settings!B15) -> Enclosure Seal | R99: =IF(Settings!F15="",0,Settings!F15) -> 0 | U99: =IF(OR(Settings!B15="",COUNTIF(Settings!$A$4:$A$83,Settings!B15)>0,COUNTIF(Settings!$B$4:B15,Settings!B15)>1),"",Settings!B15) | V99: {=IFERROR(INDEX($U$8:$U$167,SMALL(IF($U$8:$U$167<>"",ROW($U$8:$U$167)-7),ROW()-7)),"")}
... A167: =A166+1 -> 46258 | B167: =IF(ISNUMBER(MATCH(tl_cause,Settings!$B$4:$B$83,0)),IF(tl_basis="Call date",COUNTIFS(Summary!$K$2:$K$240,tl_cause,Summary!$A$2:$A$240,">="&$A167,Summary!$A$2:$A$240,"<"&$A167+1,Summary!$A$2:$A$240,">="&IF(Dashboard!$B$3="",0,Dashboard!$B$3),Summary!$A$2:$A$240,"<"&IF(Dashboard!$B$4="",2958465,Dashboard!$B$4+1)),COUNTIFS(Summary!$K$2:$K$240,tl_cause,Summary!$D$2:$D$240,">="&$A167,Summary!$D$2:$D$240,"<"&$A167+1,Summary!$A$2:$A$240,">="&IF(Dashboard!$B$3="",0,Dashboard!$B$3),Summary!$A$2:$A$240,"<"&IF(Dashboard!$B$4="",2958465,Dashboard!$B$4+1))),IF(tl_basis="Call date",COUNTIFS(Summary!$E$2:$E$240,tl_cause,Summary!$A$2:$A$240,">="&$A167,Summary!$A$2:$A$240,"<"&$A167+1,Summary!$A$2:$A$240,">="&IF(Dashboard!$B$3="",0,Dashboard!$B$3),Summary!$A$2:$A$240,"<"&IF(Dashboard!$B$4="",2958465,Dashboard!$B$4+1)),COUNTIFS(Summary!$E$2:$E$240,tl_cause,Summary!$D$2:$D$240,">="&$A167,Summary!$D$2:$D$240,"<"&$A167+1,Summary!$A$2:$A$240,">="&IF(Dashboard!$B$3="",0,Dashboard!$B$3),Summary!$A$2:$A$240,"<"&IF(Dashboard!$B$4="",2958465,Dashboard!$B$4+1)))) -> 0 | C167: =IF(AND($F$8<>"",$A167=$F$8),1,NA()) -> #N/A | D167: =IF(AND($G$8<>"",$G$8>0,$A167=$G$8),1,NA()) -> #N/A | E167: =IF(AND($H$8<>"",$H$8>0,$A167=$H$8),1,NA()) -> #N/A | P167: =IF(Settings!A83="","",Settings!A83) | Q167: =IF(Settings!A83="","",Settings!B83) | R167: =IF(Settings!F83="",0,Settings!F83) -> 0 | U167: =IF(OR(Settings!B83="",COUNTIF(Settings!$A$4:$A$83,Settings!B83)>0,COUNTIF(Settings!$B$4:B83,Settings!B83)>1),"",Settings!B83) | V167: {=IFERROR(INDEX($U$8:$U$167,SMALL(IF($U$8:$U$167<>"",ROW($U$8:$U$167)-7),ROW()-7)),"")}
A168: =A167+1 -> 46259 | B168: =IF(ISNUMBER(MATCH(tl_cause,Settings!$B$4:$B$83,0)),IF(tl_basis="Call date",COUNTIFS(Summary!$K$2:$K$240,tl_cause,Summary!$A$2:$A$240,">="&$A168,Summary!$A$2:$A$240,"<"&$A168+1,Summary!$A$2:$A$240,">="&IF(Dashboard!$B$3="",0,Dashboard!$B$3),Summary!$A$2:$A$240,"<"&IF(Dashboard!$B$4="",2958465,Dashboard!$B$4+1)),COUNTIFS(Summary!$K$2:$K$240,tl_cause,Summary!$D$2:$D$240,">="&$A168,Summary!$D$2:$D$240,"<"&$A168+1,Summary!$A$2:$A$240,">="&IF(Dashboard!$B$3="",0,Dashboard!$B$3),Summary!$A$2:$A$240,"<"&IF(Dashboard!$B$4="",2958465,Dashboard!$B$4+1))),IF(tl_basis="Call date",COUNTIFS(Summary!$E$2:$E$240,tl_cause,Summary!$A$2:$A$240,">="&$A168,Summary!$A$2:$A$240,"<"&$A168+1,Summary!$A$2:$A$240,">="&IF(Dashboard!$B$3="",0,Dashboard!$B$3),Summary!$A$2:$A$240,"<"&IF(Dashboard!$B$4="",2958465,Dashboard!$B$4+1)),COUNTIFS(Summary!$E$2:$E$240,tl_cause,Summary!$D$2:$D$240,">="&$A168,Summary!$D$2:$D$240,"<"&$A168+1,Summary!$A$2:$A$240,">="&IF(Dashboard!$B$3="",0,Dashboard!$B$3),Summary!$A$2:$A$240,"<"&IF(Dashboard!$B$4="",2958465,Dashboard!$B$4+1)))) -> 0 | C168: =IF(AND($F$8<>"",$A168=$F$8),1,NA()) -> #N/A | D168: =IF(AND($G$8<>"",$G$8>0,$A168=$G$8),1,NA()) -> #N/A | E168: =IF(AND($H$8<>"",$H$8>0,$A168=$H$8),1,NA()) -> #N/A | P168: =IF(Settings!A4="","",Settings!A4) -> Ref. leak/ Low charge | Q168: =IF(Settings!A4="","",Settings!B4) -> Ref. leak/ Low charge | R168: =IF(Settings!G4="",0,Settings!G4) -> 0
A169: =A168+1 -> 46260 | B169: =IF(ISNUMBER(MATCH(tl_cause,Settings!$B$4:$B$83,0)),IF(tl_basis="Call date",COUNTIFS(Summary!$K$2:$K$240,tl_cause,Summary!$A$2:$A$240,">="&$A169,Summary!$A$2:$A$240,"<"&$A169+1,Summary!$A$2:$A$240,">="&IF(Dashboard!$B$3="",0,Dashboard!$B$3),Summary!$A$2:$A$240,"<"&IF(Dashboard!$B$4="",2958465,Dashboard!$B$4+1)),COUNTIFS(Summary!$K$2:$K$240,tl_cause,Summary!$D$2:$D$240,">="&$A169,Summary!$D$2:$D$240,"<"&$A169+1,Summary!$A$2:$A$240,">="&IF(Dashboard!$B$3="",0,Dashboard!$B$3),Summary!$A$2:$A$240,"<"&IF(Dashboard!$B$4="",2958465,Dashboard!$B$4+1))),IF(tl_basis="Call date",COUNTIFS(Summary!$E$2:$E$240,tl_cause,Summary!$A$2:$A$240,">="&$A169,Summary!$A$2:$A$240,"<"&$A169+1,Summary!$A$2:$A$240,">="&IF(Dashboard!$B$3="",0,Dashboard!$B$3),Summary!$A$2:$A$240,"<"&IF(Dashboard!$B$4="",2958465,Dashboard!$B$4+1)),COUNTIFS(Summary!$E$2:$E$240,tl_cause,Summary!$D$2:$D$240,">="&$A169,Summary!$D$2:$D$240,"<"&$A169+1,Summary!$A$2:$A$240,">="&IF(Dashboard!$B$3="",0,Dashboard!$B$3),Summary!$A$2:$A$240,"<"&IF(Dashboard!$B$4="",2958465,Dashboard!$B$4+1)))) -> 0 | C169: =IF(AND($F$8<>"",$A169=$F$8),1,NA()) -> #N/A | D169: =IF(AND($G$8<>"",$G$8>0,$A169=$G$8),1,NA()) -> #N/A | E169: =IF(AND($H$8<>"",$H$8>0,$A169=$H$8),1,NA()) -> #N/A | P169: =IF(Settings!A5="","",Settings!A5) -> Door Torque | Q169: =IF(Settings!A5="","",Settings!B5) -> Doors | R169: =IF(Settings!G5="",0,Settings!G5) -> 0
A170: =A169+1 -> 46261 | B170: =IF(ISNUMBER(MATCH(tl_cause,Settings!$B$4:$B$83,0)),IF(tl_basis="Call date",COUNTIFS(Summary!$K$2:$K$240,tl_cause,Summary!$A$2:$A$240,">="&$A170,Summary!$A$2:$A$240,"<"&$A170+1,Summary!$A$2:$A$240,">="&IF(Dashboard!$B$3="",0,Dashboard!$B$3),Summary!$A$2:$A$240,"<"&IF(Dashboard!$B$4="",2958465,Dashboard!$B$4+1)),COUNTIFS(Summary!$K$2:$K$240,tl_cause,Summary!$D$2:$D$240,">="&$A170,Summary!$D$2:$D$240,"<"&$A170+1,Summary!$A$2:$A$240,">="&IF(Dashboard!$B$3="",0,Dashboard!$B$3),Summary!$A$2:$A$240,"<"&IF(Dashboard!$B$4="",2958465,Dashboard!$B$4+1))),IF(tl_basis="Call date",COUNTIFS(Summary!$E$2:$E$240,tl_cause,Summary!$A$2:$A$240,">="&$A170,Summary!$A$2:$A$240,"<"&$A170+1,Summary!$A$2:$A$240,">="&IF(Dashboard!$B$3="",0,Dashboard!$B$3),Summary!$A$2:$A$240,"<"&IF(Dashboard!$B$4="",2958465,Dashboard!$B$4+1)),COUNTIFS(Summary!$E$2:$E$240,tl_cause,Summary!$D$2:$D$240,">="&$A170,Summary!$D$2:$D$240,"<"&$A170+1,Summary!$A$2:$A$240,">="&IF(Dashboard!$B$3="",0,Dashboard!$B$3),Summary!$A$2:$A$240,"<"&IF(Dashboard!$B$4="",2958465,Dashboard!$B$4+1)))) -> 0 | C170: =IF(AND($F$8<>"",$A170=$F$8),1,NA()) -> #N/A | D170: =IF(AND($G$8<>"",$G$8>0,$A170=$G$8),1,NA()) -> #N/A | E170: =IF(AND($H$8<>"",$H$8>0,$A170=$H$8),1,NA()) -> #N/A | P170: =IF(Settings!A6="","",Settings!A6) -> Door Gasket | Q170: =IF(Settings!A6="","",Settings!B6) -> Doors | R170: =IF(Settings!G6="",0,Settings!G6) -> 0
A171: =A170+1 -> 46262 | B171: =IF(ISNUMBER(MATCH(tl_cause,Settings!$B$4:$B$83,0)),IF(tl_basis="Call date",COUNTIFS(Summary!$K$2:$K$240,tl_cause,Summary!$A$2:$A$240,">="&$A171,Summary!$A$2:$A$240,"<"&$A171+1,Summary!$A$2:$A$240,">="&IF(Dashboard!$B$3="",0,Dashboard!$B$3),Summary!$A$2:$A$240,"<"&IF(Dashboard!$B$4="",2958465,Dashboard!$B$4+1)),COUNTIFS(Summary!$K$2:$K$240,tl_cause,Summary!$D$2:$D$240,">="&$A171,Summary!$D$2:$D$240,"<"&$A171+1,Summary!$A$2:$A$240,">="&IF(Dashboard!$B$3="",0,Dashboard!$B$3),Summary!$A$2:$A$240,"<"&IF(Dashboard!$B$4="",2958465,Dashboard!$B$4+1))),IF(tl_basis="Call date",COUNTIFS(Summary!$E$2:$E$240,tl_cause,Summary!$A$2:$A$240,">="&$A171,Summary!$A$2:$A$240,"<"&$A171+1,Summary!$A$2:$A$240,">="&IF(Dashboard!$B$3="",0,Dashboard!$B$3),Summary!$A$2:$A$240,"<"&IF(Dashboard!$B$4="",2958465,Dashboard!$B$4+1)),COUNTIFS(Summary!$E$2:$E$240,tl_cause,Summary!$D$2:$D$240,">="&$A171,Summary!$D$2:$D$240,"<"&$A171+1,Summary!$A$2:$A$240,">="&IF(Dashboard!$B$3="",0,Dashboard!$B$3),Summary!$A$2:$A$240,"<"&IF(Dashboard!$B$4="",2958465,Dashboard!$B$4+1)))) -> 0 | C171: =IF(AND($F$8<>"",$A171=$F$8),1,NA()) -> #N/A | D171: =IF(AND($G$8<>"",$G$8>0,$A171=$G$8),1,NA()) -> #N/A | E171: =IF(AND($H$8<>"",$H$8>0,$A171=$H$8),1,NA()) -> #N/A | P171: =IF(Settings!A7="","",Settings!A7) -> Door frame heater | Q171: =IF(Settings!A7="","",Settings!B7) -> Doors | R171: =IF(Settings!G7="",0,Settings!G7) -> 0
A172: =A171+1 -> 46263 | B172: =IF(ISNUMBER(MATCH(tl_cause,Settings!$B$4:$B$83,0)),IF(tl_basis="Call date",COUNTIFS(Summary!$K$2:$K$240,tl_cause,Summary!$A$2:$A$240,">="&$A172,Summary!$A$2:$A$240,"<"&$A172+1,Summary!$A$2:$A$240,">="&IF(Dashboard!$B$3="",0,Dashboard!$B$3),Summary!$A$2:$A$240,"<"&IF(Dashboard!$B$4="",2958465,Dashboard!$B$4+1)),COUNTIFS(Summary!$K$2:$K$240,tl_cause,Summary!$D$2:$D$240,">="&$A172,Summary!$D$2:$D$240,"<"&$A172+1,Summary!$A$2:$A$240,">="&IF(Dashboard!$B$3="",0,Dashboard!$B$3),Summary!$A$2:$A$240,"<"&IF(Dashboard!$B$4="",2958465,Dashboard!$B$4+1))),IF(tl_basis="Call date",COUNTIFS(Summary!$E$2:$E$240,tl_cause,Summary!$A$2:$A$240,">="&$A172,Summary!$A$2:$A$240,"<"&$A172+1,Summary!$A$2:$A$240,">="&IF(Dashboard!$B$3="",0,Dashboard!$B$3),Summary!$A$2:$A$240,"<"&IF(Dashboard!$B$4="",2958465,Dashboard!$B$4+1)),COUNTIFS(Summary!$E$2:$E$240,tl_cause,Summary!$D$2:$D$240,">="&$A172,Summary!$D$2:$D$240,"<"&$A172+1,Summary!$A$2:$A$240,">="&IF(Dashboard!$B$3="",0,Dashboard!$B$3),Summary!$A$2:$A$240,"<"&IF(Dashboard!$B$4="",2958465,Dashboard!$B$4+1)))) -> 0 | C172: =IF(AND($F$8<>"",$A172=$F$8),1,NA()) -> #N/A | D172: =IF(AND($G$8<>"",$G$8>0,$A172=$G$8),1,NA()) -> #N/A | E172: =IF(AND($H$8<>"",$H$8>0,$A172=$H$8),1,NA()) -> #N/A | P172: =IF(Settings!A8="","",Settings!A8) -> Door Torsion rod | Q172: =IF(Settings!A8="","",Settings!B8) -> Doors | R172: =IF(Settings!G8="",0,Settings!G8) -> 0
A173: =A172+1 -> 46264 | B173: =IF(ISNUMBER(MATCH(tl_cause,Settings!$B$4:$B$83,0)),IF(tl_basis="Call date",COUNTIFS(Summary!$K$2:$K$240,tl_cause,Summary!$A$2:$A$240,">="&$A173,Summary!$A$2:$A$240,"<"&$A173+1,Summary!$A$2:$A$240,">="&IF(Dashboard!$B$3="",0,Dashboard!$B$3),Summary!$A$2:$A$240,"<"&IF(Dashboard!$B$4="",2958465,Dashboard!$B$4+1)),COUNTIFS(Summary!$K$2:$K$240,tl_cause,Summary!$D$2:$D$240,">="&$A173,Summary!$D$2:$D$240,"<"&$A173+1,Summary!$A$2:$A$240,">="&IF(Dashboard!$B$3="",0,Dashboard!$B$3),Summary!$A$2:$A$240,"<"&IF(Dashboard!$B$4="",2958465,Dashboard!$B$4+1))),IF(tl_basis="Call date",COUNTIFS(Summary!$E$2:$E$240,tl_cause,Summary!$A$2:$A$240,">="&$A173,Summary!$A$2:$A$240,"<"&$A173+1,Summary!$A$2:$A$240,">="&IF(Dashboard!$B$3="",0,Dashboard!$B$3),Summary!$A$2:$A$240,"<"&IF(Dashboard!$B$4="",2958465,Dashboard!$B$4+1)),COUNTIFS(Summary!$E$2:$E$240,tl_cause,Summary!$D$2:$D$240,">="&$A173,Summary!$D$2:$D$240,"<"&$A173+1,Summary!$A$2:$A$240,">="&IF(Dashboard!$B$3="",0,Dashboard!$B$3),Summary!$A$2:$A$240,"<"&IF(Dashboard!$B$4="",2958465,Dashboard!$B$4+1)))) -> 0 | C173: =IF(AND($F$8<>"",$A173=$F$8),1,NA()) -> #N/A | D173: =IF(AND($G$8<>"",$G$8>0,$A173=$G$8),1,NA()) -> #N/A | E173: =IF(AND($H$8<>"",$H$8>0,$A173=$H$8),1,NA()) -> #N/A | P173: =IF(Settings!A9="","",Settings!A9) -> Door not closed (Overnight) | Q173: =IF(Settings!A9="","",Settings!B9) -> Doors | R173: =IF(Settings!G9="",0,Settings!G9) -> 0
A174: =A173+1 -> 46265 | B174: =IF(ISNUMBER(MATCH(tl_cause,Settings!$B$4:$B$83,0)),IF(tl_basis="Call date",COUNTIFS(Summary!$K$2:$K$240,tl_cause,Summary!$A$2:$A$240,">="&$A174,Summary!$A$2:$A$240,"<"&$A174+1,Summary!$A$2:$A$240,">="&IF(Dashboard!$B$3="",0,Dashboard!$B$3),Summary!$A$2:$A$240,"<"&IF(Dashboard!$B$4="",2958465,Dashboard!$B$4+1)),COUNTIFS(Summary!$K$2:$K$240,tl_cause,Summary!$D$2:$D$240,">="&$A174,Summary!$D$2:$D$240,"<"&$A174+1,Summary!$A$2:$A$240,">="&IF(Dashboard!$B$3="",0,Dashboard!$B$3),Summary!$A$2:$A$240,"<"&IF(Dashboard!$B$4="",2958465,Dashboard!$B$4+1))),IF(tl_basis="Call date",COUNTIFS(Summary!$E$2:$E$240,tl_cause,Summary!$A$2:$A$240,">="&$A174,Summary!$A$2:$A$240,"<"&$A174+1,Summary!$A$2:$A$240,">="&IF(Dashboard!$B$3="",0,Dashboard!$B$3),Summary!$A$2:$A$240,"<"&IF(Dashboard!$B$4="",2958465,Dashboard!$B$4+1)),COUNTIFS(Summary!$E$2:$E$240,tl_cause,Summary!$D$2:$D$240,">="&$A174,Summary!$D$2:$D$240,"<"&$A174+1,Summary!$A$2:$A$240,">="&IF(Dashboard!$B$3="",0,Dashboard!$B$3),Summary!$A$2:$A$240,"<"&IF(Dashboard!$B$4="",2958465,Dashboard!$B$4+1)))) -> 0 | C174: =IF(AND($F$8<>"",$A174=$F$8),1,NA()) -> #N/A | D174: =IF(AND($G$8<>"",$G$8>0,$A174=$G$8),1,NA()) -> #N/A | E174: =IF(AND($H$8<>"",$H$8>0,$A174=$H$8),1,NA()) -> #N/A | P174: =IF(Settings!A10="","",Settings!A10) -> Door - general | Q174: =IF(Settings!A10="","",Settings!B10) -> Doors | R174: =IF(Settings!G10="",0,Settings!G10) -> 0
A175: =A174+1 -> 46266 | B175: =IF(ISNUMBER(MATCH(tl_cause,Settings!$B$4:$B$83,0)),IF(tl_basis="Call date",COUNTIFS(Summary!$K$2:$K$240,tl_cause,Summary!$A$2:$A$240,">="&$A175,Summary!$A$2:$A$240,"<"&$A175+1,Summary!$A$2:$A$240,">="&IF(Dashboard!$B$3="",0,Dashboard!$B$3),Summary!$A$2:$A$240,"<"&IF(Dashboard!$B$4="",2958465,Dashboard!$B$4+1)),COUNTIFS(Summary!$K$2:$K$240,tl_cause,Summary!$D$2:$D$240,">="&$A175,Summary!$D$2:$D$240,"<"&$A175+1,Summary!$A$2:$A$240,">="&IF(Dashboard!$B$3="",0,Dashboard!$B$3),Summary!$A$2:$A$240,"<"&IF(Dashboard!$B$4="",2958465,Dashboard!$B$4+1))),IF(tl_basis="Call date",COUNTIFS(Summary!$E$2:$E$240,tl_cause,Summary!$A$2:$A$240,">="&$A175,Summary!$A$2:$A$240,"<"&$A175+1,Summary!$A$2:$A$240,">="&IF(Dashboard!$B$3="",0,Dashboard!$B$3),Summary!$A$2:$A$240,"<"&IF(Dashboard!$B$4="",2958465,Dashboard!$B$4+1)),COUNTIFS(Summary!$E$2:$E$240,tl_cause,Summary!$D$2:$D$240,">="&$A175,Summary!$D$2:$D$240,"<"&$A175+1,Summary!$A$2:$A$240,">="&IF(Dashboard!$B$3="",0,Dashboard!$B$3),Summary!$A$2:$A$240,"<"&IF(Dashboard!$B$4="",2958465,Dashboard!$B$4+1)))) -> 0 | C175: =IF(AND($F$8<>"",$A175=$F$8),1,NA()) -> #N/A | D175: =IF(AND($G$8<>"",$G$8>0,$A175=$G$8),1,NA()) -> #N/A | E175: =IF(AND($H$8<>"",$H$8>0,$A175=$H$8),1,NA()) -> #N/A | P175: =IF(Settings!A11="","",Settings!A11) -> Drain tube blocked | Q175: =IF(Settings!A11="","",Settings!B11) -> Drain tube blocked | R175: =IF(Settings!G11="",0,Settings!G11) -> 0
A176: =A175+1 -> 46267 | B176: =IF(ISNUMBER(MATCH(tl_cause,Settings!$B$4:$B$83,0)),IF(tl_basis="Call date",COUNTIFS(Summary!$K$2:$K$240,tl_cause,Summary!$A$2:$A$240,">="&$A176,Summary!$A$2:$A$240,"<"&$A176+1,Summary!$A$2:$A$240,">="&IF(Dashboard!$B$3="",0,Dashboard!$B$3),Summary!$A$2:$A$240,"<"&IF(Dashboard!$B$4="",2958465,Dashboard!$B$4+1)),COUNTIFS(Summary!$K$2:$K$240,tl_cause,Summary!$D$2:$D$240,">="&$A176,Summary!$D$2:$D$240,"<"&$A176+1,Summary!$A$2:$A$240,">="&IF(Dashboard!$B$3="",0,Dashboard!$B$3),Summary!$A$2:$A$240,"<"&IF(Dashboard!$B$4="",2958465,Dashboard!$B$4+1))),IF(tl_basis="Call date",COUNTIFS(Summary!$E$2:$E$240,tl_cause,Summary!$A$2:$A$240,">="&$A176,Summary!$A$2:$A$240,"<"&$A176+1,Summary!$A$2:$A$240,">="&IF(Dashboard!$B$3="",0,Dashboard!$B$3),Summary!$A$2:$A$240,"<"&IF(Dashboard!$B$4="",2958465,Dashboard!$B$4+1)),COUNTIFS(Summary!$E$2:$E$240,tl_cause,Summary!$D$2:$D$240,">="&$A176,Summary!$D$2:$D$240,"<"&$A176+1,Summary!$A$2:$A$240,">="&IF(Dashboard!$B$3="",0,Dashboard!$B$3),Summary!$A$2:$A$240,"<"&IF(Dashboard!$B$4="",2958465,Dashboard!$B$4+1)))) -> 0 | C176: =IF(AND($F$8<>"",$A176=$F$8),1,NA()) -> #N/A | D176: =IF(AND($G$8<>"",$G$8>0,$A176=$G$8),1,NA()) -> #N/A | E176: =IF(AND($H$8<>"",$H$8>0,$A176=$H$8),1,NA()) -> #N/A | P176: =IF(Settings!A12="","",Settings!A12) -> Wrong / Loose wiring | Q176: =IF(Settings!A12="","",Settings!B12) -> Wrong / Loose wiring | R176: =IF(Settings!G12="",0,Settings!G12) -> 0
A177: =A176+1 -> 46268 | B177: =IF(ISNUMBER(MATCH(tl_cause,Settings!$B$4:$B$83,0)),IF(tl_basis="Call date",COUNTIFS(Summary!$K$2:$K$240,tl_cause,Summary!$A$2:$A$240,">="&$A177,Summary!$A$2:$A$240,"<"&$A177+1,Summary!$A$2:$A$240,">="&IF(Dashboard!$B$3="",0,Dashboard!$B$3),Summary!$A$2:$A$240,"<"&IF(Dashboard!$B$4="",2958465,Dashboard!$B$4+1)),COUNTIFS(Summary!$K$2:$K$240,tl_cause,Summary!$D$2:$D$240,">="&$A177,Summary!$D$2:$D$240,"<"&$A177+1,Summary!$A$2:$A$240,">="&IF(Dashboard!$B$3="",0,Dashboard!$B$3),Summary!$A$2:$A$240,"<"&IF(Dashboard!$B$4="",2958465,Dashboard!$B$4+1))),IF(tl_basis="Call date",COUNTIFS(Summary!$E$2:$E$240,tl_cause,Summary!$A$2:$A$240,">="&$A177,Summary!$A$2:$A$240,"<"&$A177+1,Summary!$A$2:$A$240,">="&IF(Dashboard!$B$3="",0,Dashboard!$B$3),Summary!$A$2:$A$240,"<"&IF(Dashboard!$B$4="",2958465,Dashboard!$B$4+1)),COUNTIFS(Summary!$E$2:$E$240,tl_cause,Summary!$D$2:$D$240,">="&$A177,Summary!$D$2:$D$240,"<"&$A177+1,Summary!$A$2:$A$240,">="&IF(Dashboard!$B$3="",0,Dashboard!$B$3),Summary!$A$2:$A$240,"<"&IF(Dashboard!$B$4="",2958465,Dashboard!$B$4+1)))) -> 0 | C177: =IF(AND($F$8<>"",$A177=$F$8),1,NA()) -> #N/A | D177: =IF(AND($G$8<>"",$G$8>0,$A177=$G$8),1,NA()) -> #N/A | E177: =IF(AND($H$8<>"",$H$8>0,$A177=$H$8),1,NA()) -> #N/A | P177: =IF(Settings!A13="","",Settings!A13) -> Communication problem | Q177: =IF(Settings!A13="","",Settings!B13) -> Communication problem | R177: =IF(Settings!G13="",0,Settings!G13) -> 0
A178: =A177+1 -> 46269 | B178: =IF(ISNUMBER(MATCH(tl_cause,Settings!$B$4:$B$83,0)),IF(tl_basis="Call date",COUNTIFS(Summary!$K$2:$K$240,tl_cause,Summary!$A$2:$A$240,">="&$A178,Summary!$A$2:$A$240,"<"&$A178+1,Summary!$A$2:$A$240,">="&IF(Dashboard!$B$3="",0,Dashboard!$B$3),Summary!$A$2:$A$240,"<"&IF(Dashboard!$B$4="",2958465,Dashboard!$B$4+1)),COUNTIFS(Summary!$K$2:$K$240,tl_cause,Summary!$D$2:$D$240,">="&$A178,Summary!$D$2:$D$240,"<"&$A178+1,Summary!$A$2:$A$240,">="&IF(Dashboard!$B$3="",0,Dashboard!$B$3),Summary!$A$2:$A$240,"<"&IF(Dashboard!$B$4="",2958465,Dashboard!$B$4+1))),IF(tl_basis="Call date",COUNTIFS(Summary!$E$2:$E$240,tl_cause,Summary!$A$2:$A$240,">="&$A178,Summary!$A$2:$A$240,"<"&$A178+1,Summary!$A$2:$A$240,">="&IF(Dashboard!$B$3="",0,Dashboard!$B$3),Summary!$A$2:$A$240,"<"&IF(Dashboard!$B$4="",2958465,Dashboard!$B$4+1)),COUNTIFS(Summary!$E$2:$E$240,tl_cause,Summary!$D$2:$D$240,">="&$A178,Summary!$D$2:$D$240,"<"&$A178+1,Summary!$A$2:$A$240,">="&IF(Dashboard!$B$3="",0,Dashboard!$B$3),Summary!$A$2:$A$240,"<"&IF(Dashboard!$B$4="",2958465,Dashboard!$B$4+1)))) -> 0 | C178: =IF(AND($F$8<>"",$A178=$F$8),1,NA()) -> #N/A | D178: =IF(AND($G$8<>"",$G$8>0,$A178=$G$8),1,NA()) -> #N/A | E178: =IF(AND($H$8<>"",$H$8>0,$A178=$H$8),1,NA()) -> #N/A | P178: =IF(Settings!A14="","",Settings!A14) -> High Store RH | Q178: =IF(Settings!A14="","",Settings!B14) -> High Store RH | R178: =IF(Settings!G14="",0,Settings!G14) -> 0
