Workbook
Name ch1_cats: OFFSET(Calc_Charts!$A$66,0,0,MAX(1,COUNTIF(Calc_Charts!$B$66:$B$90,">0")),1)
Name ch1_vals: OFFSET(Calc_Charts!$B$66,0,0,MAX(1,COUNTIF(Calc_Charts!$B$66:$B$90,">0")),1)
Name ch3_cats: OFFSET(Calc_Charts!$A$96,0,0,MAX(1,COUNTIF(Calc_Charts!$B$96:$B$120,">0")),1)
Name ch3_vals: OFFSET(Calc_Charts!$B$96,0,0,MAX(1,COUNTIF(Calc_Charts!$B$96:$B$120,">0")),1)
Name ch5_after: OFFSET(Calc_Charts!$B$126,0,0,MAX(1,COUNTIF(Calc_Charts!$D$126:$D$150,">0")),1)
Name ch5_before: OFFSET(Calc_Charts!$C$126,0,0,MAX(1,COUNTIF(Calc_Charts!$D$126:$D$150,">0")),1)
Name ch5_cats: OFFSET(Calc_Charts!$A$126,0,0,MAX(1,COUNTIF(Calc_Charts!$D$126:$D$150,">0")),1)
Name ch5_seg01: OFFSET(Calc_Charts!$B$156,0,0,MAX(1,COUNTIF(Calc_Charts!$D$126:$D$150,">0")),1)
Name ch5_seg02: OFFSET(Calc_Charts!$C$156,0,0,MAX(1,COUNTIF(Calc_Charts!$D$126:$D$150,">0")),1)
Name ch5_seg03: OFFSET(Calc_Charts!$D$156,0,0,MAX(1,COUNTIF(Calc_Charts!$D$126:$D$150,">0")),1)
Name ch5_seg04: OFFSET(Calc_Charts!$E$156,0,0,MAX(1,COUNTIF(Calc_Charts!$D$126:$D$150,">0")),1)
Name ch5_seg05: OFFSET(Calc_Charts!$F$156,0,0,MAX(1,COUNTIF(Calc_Charts!$D$126:$D$150,">0")),1)
Name ch5_seg06: OFFSET(Calc_Charts!$G$156,0,0,MAX(1,COUNTIF(Calc_Charts!$D$126:$D$150,">0")),1)
Name ch5_seg07: OFFSET(Calc_Charts!$H$156,0,0,MAX(1,COUNTIF(Calc_Charts!$D$126:$D$150,">0")),1)
Name ch5_seg08: OFFSET(Calc_Charts!$I$156,0,0,MAX(1,COUNTIF(Calc_Charts!$D$126:$D$150,">0")),1)
Name ch5_seg09: OFFSET(Calc_Charts!$J$156,0,0,MAX(1,COUNTIF(Calc_Charts!$D$126:$D$150,">0")),1)
Name ch5_seg10: OFFSET(Calc_Charts!$K$156,0,0,MAX(1,COUNTIF(Calc_Charts!$D$126:$D$150,">0")),1)
Name ch5_seg11: OFFSET(Calc_Charts!$L$156,0,0,MAX(1,COUNTIF(Calc_Charts!$D$126:$D$150,">0")),1)
Name ch5_seg12: OFFSET(Calc_Charts!$M$156,0,0,MAX(1,COUNTIF(Calc_Charts!$D$126:$D$150,">0")),1)
Name ch5_seg13: OFFSET(Calc_Charts!$N$156,0,0,MAX(1,COUNTIF(Calc_Charts!$D$126:$D$150,">0")),1)
Name ch5_seg14: OFFSET(Calc_Charts!$O$156,0,0,MAX(1,COUNTIF(Calc_Charts!$D$126:$D$150,">0")),1)
Name ch5_seg15: OFFSET(Calc_Charts!$P$156,0,0,MAX(1,COUNTIF(Calc_Charts!$D$126:$D$150,">0")),1)
Name ch5_seg16: OFFSET(Calc_Charts!$Q$156,0,0,MAX(1,COUNTIF(Calc_Charts!$D$126:$D$150,">0")),1)
Name ch5_seg17: OFFSET(Calc_Charts!$R$156,0,0,MAX(1,COUNTIF(Calc_Charts!$D$126:$D$150,">0")),1)
Name ch5_seg18: OFFSET(Calc_Charts!$S$156,0,0,MAX(1,COUNTIF(Calc_Charts!$D$126:$D$150,">0")),1)
Name ch5_seg19: OFFSET(Calc_Charts!$T$156,0,0,MAX(1,COUNTIF(Calc_Charts!$D$126:$D$150,">0")),1)
Name ch5_seg20: OFFSET(Calc_Charts!$U$156,0,0,MAX(1,COUNTIF(Calc_Charts!$D$126:$D$150,">0")),1)
Name ch5_seg21: OFFSET(Calc_Charts!$V$156,0,0,MAX(1,COUNTIF(Calc_Charts!$D$126:$D$150,">0")),1)
Name ch5_seg22: OFFSET(Calc_Charts!$W$156,0,0,MAX(1,COUNTIF(Calc_Charts!$D$126:$D$150,">0")),1)
Name ch5_seg23: OFFSET(Calc_Charts!$X$156,0,0,MAX(1,COUNTIF(Calc_Charts!$D$126:$D$150,">0")),1)
Name ch5_seg24: OFFSET(Calc_Charts!$Y$156,0,0,MAX(1,COUNTIF(Calc_Charts!$D$126:$D$150,">0")),1)
Name ch5_seg25: OFFSET(Calc_Charts!$Z$156,0,0,MAX(1,COUNTIF(Calc_Charts!$D$126:$D$150,">0")),1)
Name ch5_total: OFFSET(Calc_Charts!$D$126,0,0,MAX(1,COUNTIF(Calc_Charts!$D$126:$D$150,">0")),1)
Name ch6_cats: Calc_Charts!$A$244:$A$249
Name ch6_vals: Calc_Charts!$B$244:$B$249
Name ch7_after: OFFSET(Calc_Charts!$B$359,0,0,MAX(1,COUNTIF(Calc_Charts!$D$359:$D$383,">0")),1)
Name ch7_before: OFFSET(Calc_Charts!$C$359,0,0,MAX(1,COUNTIF(Calc_Charts!$D$359:$D$383,">0")),1)
Name ch7_cats: OFFSET(Calc_Charts!$A$359,0,0,MAX(1,COUNTIF(Calc_Charts!$D$359:$D$383,">0")),1)
Name ch7_prefix: Calc_Charts!$B$269
Name ch7_seg01: OFFSET(Calc_Charts!$B$387,0,0,MAX(1,COUNTIF(Calc_Charts!$D$359:$D$383,">0")),1)
Name ch7_seg02: OFFSET(Calc_Charts!$C$387,0,0,MAX(1,COUNTIF(Calc_Charts!$D$359:$D$383,">0")),1)
Name ch7_seg03: OFFSET(Calc_Charts!$D$387,0,0,MAX(1,COUNTIF(Calc_Charts!$D$359:$D$383,">0")),1)
Name ch7_seg04: OFFSET(Calc_Charts!$E$387,0,0,MAX(1,COUNTIF(Calc_Charts!$D$359:$D$383,">0")),1)
Name ch7_seg05: OFFSET(Calc_Charts!$F$387,0,0,MAX(1,COUNTIF(Calc_Charts!$D$359:$D$383,">0")),1)
Name ch7_seg06: OFFSET(Calc_Charts!$G$387,0,0,MAX(1,COUNTIF(Calc_Charts!$D$359:$D$383,">0")),1)
Name ch7_seg07: OFFSET(Calc_Charts!$H$387,0,0,MAX(1,COUNTIF(Calc_Charts!$D$359:$D$383,">0")),1)
Name ch7_seg08: OFFSET(Calc_Charts!$I$387,0,0,MAX(1,COUNTIF(Calc_Charts!$D$359:$D$383,">0")),1)
Name ch7_seg09: OFFSET(Calc_Charts!$J$387,0,0,MAX(1,COUNTIF(Calc_Charts!$D$359:$D$383,">0")),1)
Name ch7_seg10: OFFSET(Calc_Charts!$K$387,0,0,MAX(1,COUNTIF(Calc_Charts!$D$359:$D$383,">0")),1)
Name ch7_seg11: OFFSET(Calc_Charts!$L$387,0,0,MAX(1,COUNTIF(Calc_Charts!$D$359:$D$383,">0")),1)
Name ch7_seg12: OFFSET(Calc_Charts!$M$387,0,0,MAX(1,COUNTIF(Calc_Charts!$D$359:$D$383,">0")),1)
Name ch7_seg13: OFFSET(Calc_Charts!$N$387,0,0,MAX(1,COUNTIF(Calc_Charts!$D$359:$D$383,">0")),1)
Name ch7_seg14: OFFSET(Calc_Charts!$O$387,0,0,MAX(1,COUNTIF(Calc_Charts!$D$359:$D$383,">0")),1)
Name ch7_seg15: OFFSET(Calc_Charts!$P$387,0,0,MAX(1,COUNTIF(Calc_Charts!$D$359:$D$383,">0")),1)
Name ch7_seg16: OFFSET(Calc_Charts!$Q$387,0,0,MAX(1,COUNTIF(Calc_Charts!$D$359:$D$383,">0")),1)
Name ch7_seg17: OFFSET(Calc_Charts!$R$387,0,0,MAX(1,COUNTIF(Calc_Charts!$D$359:$D$383,">0")),1)
Name ch7_seg18: OFFSET(Calc_Charts!$S$387,0,0,MAX(1,COUNTIF(Calc_Charts!$D$359:$D$383,">0")),1)
Name ch7_seg19: OFFSET(Calc_Charts!$T$387,0,0,MAX(1,COUNTIF(Calc_Charts!$D$359:$D$383,">0")),1)
Name ch7_seg20: OFFSET(Calc_Charts!$U$387,0,0,MAX(1,COUNTIF(Calc_Charts!$D$359:$D$383,">0")),1)
Name ch7_seg21: OFFSET(Calc_Charts!$V$387,0,0,MAX(1,COUNTIF(Calc_Charts!$D$359:$D$383,">0")),1)

Sheet README
A1: DG-template workbook guide
A3: Purpose | B3: Tracks service-call root causes and feeds six dashboard charts with timeline filtering, zero-bar hiding, sorted rankings, and stable chart colors.
A5: Weekly update workflow | B5: Paste CRM rows into Raw Data, classify lines in Summary, review Data Checks, then use Dashboard. From/To blanks mean all data.
A7: Color legend | B7: Blue text = user input; black = formula; gray fill = helper/sort columns; yellow fill = dashboard timeline inputs.
A9: Limit | B9: Value | C9: Settings name
A10: Max Summary rows | B10: =Settings!B65 -> 240 | C10: set_maxSummaryRow
A11: Max Raw rows | B11: =Settings!B66 -> 400 | C11: set_maxRawRow
A12: Max causes | B12: =Settings!B67 -> 80 | C12: set_maxCauses
A13: Weeks shown | B13: =Settings!B68 -> 20 | C13: set_weeksShown
A14: Tiebreak divisor | B14: =Settings!B69 -> 100000 | C14: set_tiebreakDivisor
A17: Calc table | B17: Description
A18: T1 | B18: Cause totals filtered by Dashboard date window.
A19: T2 | B19: Unique group totals with dedup helper and sort helpers.
A20: T3 | B20: Ranked groups by total; feeds Chart 1 names.
A21: T4 | B21: Ranked groups by after-clean count; feeds Chart 3 names.
A22: T5 | B22: Chart 5 stacked after/before feed.
A23: T6 | B23: Chart 5 diagonal matrix for stable rank colors.
A24: T7 | B24: Formula-driven week labels and total-label series.
A25: T8 | B25: Counts rollup by group.
A26: T9 | B26: Case serial-prefix counts for Chart 6.
A27: T10 | B27: Dynamic chart title cells.
A29: Phase 3 charts
A30: Charts 7-9 | B30: Per-nomenclature after-vs-before clean point charts for RLN3MA, RLN2MA, and RMN4MA. Add another prefix by copying one T-block, cloning the chN_* names, and cloning Chart 5.
A31: Prefix correction | B31: Settings T-S3 corrected RMN2MA to RMN4MA after confirming RMN2MA has no serial matches and RMN4MA has matches.

Sheet Dashboard
A1: DG Service-Call Dashboard
A3: From | B3: 46174
A4: To | B4: 46218
A5: Period | B5: =Calc_Charts!$B$262 -> Jun 1 to Jul 15
A6: Checks needing review | B6: =COUNTIF('Data Checks'!$C:$C,"Review") -> 1

Sheet Summary
A1: Edit blue-input columns only: Work Order, Root Cause, and Notes. Formula columns classify/store/date/after-clean status.
A2: Summary - one line per root-cause pick
A3: Visible classified lines: | C3: =SUBTOTAL(103,$E$5:$E$241) -> 38 | E3: Filter Root Cause to read this count.
A4: Call Date | B4: Work Order | C4: Store | D4: Commission Date | E4: Root Cause | F4: Notes | G4: After Clean Point | H4: Case Serial (from Raw) | I4: Column1
A5: =IFERROR(INDEX('Raw Data'!$D$5:$D$400,MATCH($B5,'Raw Data'!$H$5:$H$400,0)),"") -> 46094.393 | B5: WO-0532764 | C5: =IFERROR(TRIM(INDEX('Raw Data'!$J$5:$J$400,MATCH($B5,'Raw Data'!$H$5:$H$400,0))),"") -> Dollar General #22515 | D5: =IFERROR(INDEX('Store List'!$B$4:$B$300,MATCH($C5,'Store List'!$A$4:$A$300,0)),"") -> 46090 | E5: Door Torque | F5: Tech found door torque issue and adjusted it | G5: =IF($E5="","",IFERROR(IF(OR(NOT(ISNUMBER($D5)),NOT(ISNUMBER(INDEX(Settings!$E$4:$E$80,MATCH($E5,Settings!$A$4:$A$80,0))))),"No",IF($D5>INDEX(Settings!$E$4:$E$80,MATCH($E5,Settings!$A$4:$A$80,0)),"Yes","No")),"")) -> No | H5: =IFERROR(TRIM(INDEX('Raw Data'!$S$5:$S$400,MATCH($B5,'Raw Data'!$H$5:$H$400,0))),"") -> RMN5MA/MY26B013859
A6: =IFERROR(INDEX('Raw Data'!$D$5:$D$400,MATCH($B6,'Raw Data'!$H$5:$H$400,0)),"") -> 46094.393 | B6: WO-0532764 | C6: =IFERROR(TRIM(INDEX('Raw Data'!$J$5:$J$400,MATCH($B6,'Raw Data'!$H$5:$H$400,0))),"") -> Dollar General #22515 | D6: =IFERROR(INDEX('Store List'!$B$4:$B$300,MATCH($C6,'Store List'!$A$4:$A$300,0)),"") -> 46090 | E6: Drain tube blocked | G6: =IF($E6="","",IFERROR(IF(OR(NOT(ISNUMBER($D6)),NOT(ISNUMBER(INDEX(Settings!$E$4:$E$80,MATCH($E6,Settings!$A$4:$A$80,0))))),"No",IF($D6>INDEX(Settings!$E$4:$E$80,MATCH($E6,Settings!$A$4:$A$80,0)),"Yes","No")),"")) -> No | H6: =IFERROR(TRIM(INDEX('Raw Data'!$S$5:$S$400,MATCH($B6,'Raw Data'!$H$5:$H$400,0))),"") -> RMN5MA/MY26B013859
A7: =IFERROR(INDEX('Raw Data'!$D$5:$D$400,MATCH($B7,'Raw Data'!$H$5:$H$400,0)),"") -> 46092.344 | B7: WO-0531272 | C7: =IFERROR(TRIM(INDEX('Raw Data'!$J$5:$J$400,MATCH($B7,'Raw Data'!$H$5:$H$400,0))),"") -> Dollar General #21606 | D7: =IFERROR(INDEX('Store List'!$B$4:$B$300,MATCH($C7,'Store List'!$A$4:$A$300,0)),"") -> 46084 | E7: Drain tube blocked | G7: =IF($E7="","",IFERROR(IF(OR(NOT(ISNUMBER($D7)),NOT(ISNUMBER(INDEX(Settings!$E$4:$E$80,MATCH($E7,Settings!$A$4:$A$80,0))))),"No",IF($D7>INDEX(Settings!$E$4:$E$80,MATCH($E7,Settings!$A$4:$A$80,0)),"Yes","No")),"")) -> No | H7: =IFERROR(TRIM(INDEX('Raw Data'!$S$5:$S$400,MATCH($B7,'Raw Data'!$H$5:$H$400,0))),"") -> RMN5MA/MY26B013853
A8: =IFERROR(INDEX('Raw Data'!$D$5:$D$400,MATCH($B8,'Raw Data'!$H$5:$H$400,0)),"") -> 46092.344 | B8: WO-0531272 | C8: =IFERROR(TRIM(INDEX('Raw Data'!$J$5:$J$400,MATCH($B8,'Raw Data'!$H$5:$H$400,0))),"") -> Dollar General #21606 | D8: =IFERROR(INDEX('Store List'!$B$4:$B$300,MATCH($C8,'Store List'!$A$4:$A$300,0)),"") -> 46084 | E8: High Store RH | G8: =IF($E8="","",IFERROR(IF(OR(NOT(ISNUMBER($D8)),NOT(ISNUMBER(INDEX(Settings!$E$4:$E$80,MATCH($E8,Settings!$A$4:$A$80,0))))),"No",IF($D8>INDEX(Settings!$E$4:$E$80,MATCH($E8,Settings!$A$4:$A$80,0)),"Yes","No")),"")) -> No | H8: =IFERROR(TRIM(INDEX('Raw Data'!$S$5:$S$400,MATCH($B8,'Raw Data'!$H$5:$H$400,0))),"") -> RMN5MA/MY26B013853
A9: =IFERROR(INDEX('Raw Data'!$D$5:$D$400,MATCH($B9,'Raw Data'!$H$5:$H$400,0)),"") -> 46102.389 | B9: WO-0536941 | C9: =IFERROR(TRIM(INDEX('Raw Data'!$J$5:$J$400,MATCH($B9,'Raw Data'!$H$5:$H$400,0))),"") -> Dollar General #20582 | D9: =IFERROR(INDEX('Store List'!$B$4:$B$300,MATCH($C9,'Store List'!$A$4:$A$300,0)),"") -> 46098 | E9: Ref. leak/ Low charge | G9: =IF($E9="","",IFERROR(IF(OR(NOT(ISNUMBER($D9)),NOT(ISNUMBER(INDEX(Settings!$E$4:$E$80,MATCH($E9,Settings!$A$4:$A$80,0))))),"No",IF($D9>INDEX(Settings!$E$4:$E$80,MATCH($E9,Settings!$A$4:$A$80,0)),"Yes","No")),"")) -> No | H9: =IFERROR(TRIM(INDEX('Raw Data'!$S$5:$S$400,MATCH($B9,'Raw Data'!$H$5:$H$400,0))),"") -> RLN3MA/MY26B014956, LEFT ~ RLN2MA/ MY26B016476, LEFT
A10: =IFERROR(INDEX('Raw Data'!$D$5:$D$400,MATCH($B10,'Raw Data'!$H$5:$H$400,0)),"") -> 46102.389 | B10: WO-0536941 | C10: =IFERROR(TRIM(INDEX('Raw Data'!$J$5:$J$400,MATCH($B10,'Raw Data'!$H$5:$H$400,0))),"") -> Dollar General #20582 | D10: =IFERROR(INDEX('Store List'!$B$4:$B$300,MATCH($C10,'Store List'!$A$4:$A$300,0)),"") -> 46098 | E10: Enclosure Seal | G10: =IF($E10="","",IFERROR(IF(OR(NOT(ISNUMBER($D10)),NOT(ISNUMBER(INDEX(Settings!$E$4:$E$80,MATCH($E10,Settings!$A$4:$A$80,0))))),"No",IF($D10>INDEX(Settings!$E$4:$E$80,MATCH($E10,Settings!$A$4:$A$80,0)),"Yes","No")),"")) -> No | H10: =IFERROR(TRIM(INDEX('Raw Data'!$S$5:$S$400,MATCH($B10,'Raw Data'!$H$5:$H$400,0))),"") -> RLN3MA/MY26B014956, LEFT ~ RLN2MA/ MY26B016476, LEFT
A11: =IFERROR(INDEX('Raw Data'!$D$5:$D$400,MATCH($B11,'Raw Data'!$H$5:$H$400,0)),"") -> 46100.539 | B11: WO-0536090 | C11: =IFERROR(TRIM(INDEX('Raw Data'!$J$5:$J$400,MATCH($B11,'Raw Data'!$H$5:$H$400,0))),"") -> Dollar General #04117 | D11: =IFERROR(INDEX('Store List'!$B$4:$B$300,MATCH($C11,'Store List'!$A$4:$A$300,0)),"") -> 46098 | E11: Communication problem | F11: Microblock | G11: =IF($E11="","",IFERROR(IF(OR(NOT(ISNUMBER($D11)),NOT(ISNUMBER(INDEX(Settings!$E$4:$E$80,MATCH($E11,Settings!$A$4:$A$80,0))))),"No",IF($D11>INDEX(Settings!$E$4:$E$80,MATCH($E11,Settings!$A$4:$A$80,0)),"Yes","No")),"")) -> No | H11: =IFERROR(TRIM(INDEX('Raw Data'!$S$5:$S$400,MATCH($B11,'Raw Data'!$H$5:$H$400,0))),"")
A12: =IFERROR(INDEX('Raw Data'!$D$5:$D$400,MATCH($B12,'Raw Data'!$H$5:$H$400,0)),"") -> 46111.269 | B12: WO-0541495 | C12: =IFERROR(TRIM(INDEX('Raw Data'!$J$5:$J$400,MATCH($B12,'Raw Data'!$H$5:$H$400,0))),"") -> Dollar General #22149 | D12: =IFERROR(INDEX('Store List'!$B$4:$B$300,MATCH($C12,'Store List'!$A$4:$A$300,0)),"") -> 46092 | E12: Component Failure | G12: =IF($E12="","",IFERROR(IF(OR(NOT(ISNUMBER($D12)),NOT(ISNUMBER(INDEX(Settings!$E$4:$E$80,MATCH($E12,Settings!$A$4:$A$80,0))))),"No",IF($D12>INDEX(Settings!$E$4:$E$80,MATCH($E12,Settings!$A$4:$A$80,0)),"Yes","No")),"")) -> No | H12: =IFERROR(TRIM(INDEX('Raw Data'!$S$5:$S$400,MATCH($B12,'Raw Data'!$H$5:$H$400,0))),"") -> RMN5MA/MY26B013852 RLN3MA/MY26B013833 ~ RLN2MA/MY26B013807 ~ RFMN4/MY21G066701
A13: =IFERROR(INDEX('Raw Data'!$D$5:$D$400,MATCH($B13,'Raw Data'!$H$5:$H$400,0)),"") -> 46111.266 | B13: WO-0541490 | C13: =IFERROR(TRIM(INDEX('Raw Data'!$J$5:$J$400,MATCH($B13,'Raw Data'!$H$5:$H$400,0))),"") -> Dollar General #6099 | D13: =IFERROR(INDEX('Store List'!$B$4:$B$300,MATCH($C13,'Store List'!$A$4:$A$300,0)),"") -> 46098 | E13: Communication problem | F13: Microblock | G13: =IF($E13="","",IFERROR(IF(OR(NOT(ISNUMBER($D13)),NOT(ISNUMBER(INDEX(Settings!$E$4:$E$80,MATCH($E13,Settings!$A$4:$A$80,0))))),"No",IF($D13>INDEX(Settings!$E$4:$E$80,MATCH($E13,Settings!$A$4:$A$80,0)),"Yes","No")),"")) -> No | H13: =IFERROR(TRIM(INDEX('Raw Data'!$S$5:$S$400,MATCH($B13,'Raw Data'!$H$5:$H$400,0))),"") -> N/A
A14: =IFERROR(INDEX('Raw Data'!$D$5:$D$400,MATCH($B14,'Raw Data'!$H$5:$H$400,0)),"") -> 46111.32 | B14: WO-0541572 | C14: =IFERROR(TRIM(INDEX('Raw Data'!$J$5:$J$400,MATCH($B14,'Raw Data'!$H$5:$H$400,0))),"") -> Dollar General 22799 | D14: =IFERROR(INDEX('Store List'!$B$4:$B$300,MATCH($C14,'Store List'!$A$4:$A$300,0)),"") -> 46099 | E14: Wrong program | G14: =IF($E14="","",IFERROR(IF(OR(NOT(ISNUMBER($D14)),NOT(ISNUMBER(INDEX(Settings!$E$4:$E$80,MATCH($E14,Settings!$A$4:$A$80,0))))),"No",IF($D14>INDEX(Settings!$E$4:$E$80,MATCH($E14,Settings!$A$4:$A$80,0)),"Yes","No")),"")) -> No | H14: =IFERROR(TRIM(INDEX('Raw Data'!$S$5:$S$400,MATCH($B14,'Raw Data'!$H$5:$H$400,0))),"") -> RLN2MA/MY26B014943
A15: =IFERROR(INDEX('Raw Data'!$D$5:$D$400,MATCH($B15,'Raw Data'!$H$5:$H$400,0)),"") -> 46111.378 | B15: WO-0541656 | C15: =IFERROR(TRIM(INDEX('Raw Data'!$J$5:$J$400,MATCH($B15,'Raw Data'!$H$5:$H$400,0))),"") -> DOLLAR GENERAL #10369 | D15: =IFERROR(INDEX('Store List'!$B$4:$B$300,MATCH($C15,'Store List'!$A$4:$A$300,0)),"") -> 46106 | E15: Wrong / Loose wiring | G15: =IF($E15="","",IFERROR(IF(OR(NOT(ISNUMBER($D15)),NOT(ISNUMBER(INDEX(Settings!$E$4:$E$80,MATCH($E15,Settings!$A$4:$A$80,0))))),"No",IF($D15>INDEX(Settings!$E$4:$E$80,MATCH($E15,Settings!$A$4:$A$80,0)),"Yes","No")),"")) -> No | H15: =IFERROR(TRIM(INDEX('Raw Data'!$S$5:$S$400,MATCH($B15,'Raw Data'!$H$5:$H$400,0))),"") -> RMN5MA/MY26B016046, LEFT
A16: =IFERROR(INDEX('Raw Data'!$D$5:$D$400,MATCH($B16,'Raw Data'!$H$5:$H$400,0)),"") -> 46114.614 | B16: WO-0545426 | C16: =IFERROR(TRIM(INDEX('Raw Data'!$J$5:$J$400,MATCH($B16,'Raw Data'!$H$5:$H$400,0))),"") -> Dollar General #12879 | D16: =IFERROR(INDEX('Store List'!$B$4:$B$300,MATCH($C16,'Store List'!$A$4:$A$300,0)),"") -> 46106 | E16: Wrong / Loose wiring | G16: =IF($E16="","",IFERROR(IF(OR(NOT(ISNUMBER($D16)),NOT(ISNUMBER(INDEX(Settings!$E$4:$E$80,MATCH($E16,Settings!$A$4:$A$80,0))))),"No",IF($D16>INDEX(Settings!$E$4:$E$80,MATCH($E16,Settings!$A$4:$A$80,0)),"Yes","No")),"")) -> No | H16: =IFERROR(TRIM(INDEX('Raw Data'!$S$5:$S$400,MATCH($B16,'Raw Data'!$H$5:$H$400,0))),"") -> RMN5MA/MY26B016549, LEFT
A17: =IFERROR(INDEX('Raw Data'!$D$5:$D$400,MATCH($B17,'Raw Data'!$H$5:$H$400,0)),"") -> 46114.637 | B17: WO-0545463 | C17: =IFERROR(TRIM(INDEX('Raw Data'!$J$5:$J$400,MATCH($B17,'Raw Data'!$H$5:$H$400,0))),"") -> DOLLAR GENERAL #10369 | D17: =IFERROR(INDEX('Store List'!$B$4:$B$300,MATCH($C17,'Store List'!$A$4:$A$300,0)),"") -> 46106 | E17: Wrong / Loose wiring | G17: =IF($E17="","",IFERROR(IF(OR(NOT(ISNUMBER($D17)),NOT(ISNUMBER(INDEX(Settings!$E$4:$E$80,MATCH($E17,Settings!$A$4:$A$80,0))))),"No",IF($D17>INDEX(Settings!$E$4:$E$80,MATCH($E17,Settings!$A$4:$A$80,0)),"Yes","No")),"")) -> No | H17: =IFERROR(TRIM(INDEX('Raw Data'!$S$5:$S$400,MATCH($B17,'Raw Data'!$H$5:$H$400,0))),"") -> RMN4MA/MY26B016036, LEFT
A18: =IFERROR(INDEX('Raw Data'!$D$5:$D$400,MATCH($B18,'Raw Data'!$H$5:$H$400,0)),"") -> 46116.77 | B18: WO-0546538 | C18: =IFERROR(TRIM(INDEX('Raw Data'!$J$5:$J$400,MATCH($B18,'Raw Data'!$H$5:$H$400,0))),"") -> Dollar General #20876 | D18: =IFERROR(INDEX('Store List'!$B$4:$B$300,MATCH($C18,'Store List'!$A$4:$A$300,0)),"") -> 46112 | E18: High Store RH | G18: =IF($E18="","",IFERROR(IF(OR(NOT(ISNUMBER($D18)),NOT(ISNUMBER(INDEX(Settings!$E$4:$E$80,MATCH($E18,Settings!$A$4:$A$80,0))))),"No",IF($D18>INDEX(Settings!$E$4:$E$80,MATCH($E18,Settings!$A$4:$A$80,0)),"Yes","No")),"")) -> No | H18: =IFERROR(TRIM(INDEX('Raw Data'!$S$5:$S$400,MATCH($B18,'Raw Data'!$H$5:$H$400,0))),"") -> RLN2MA/MY26B013812
A19: =IFERROR(INDEX('Raw Data'!$D$5:$D$400,MATCH($B19,'Raw Data'!$H$5:$H$400,0)),"") -> 46118.548 | B19: WO-0547346 | C19: =IFERROR(TRIM(INDEX('Raw Data'!$J$5:$J$400,MATCH($B19,'Raw Data'!$H$5:$H$400,0))),"") -> Dollar General #6827 | D19: =IFERROR(INDEX('Store List'!$B$4:$B$300,MATCH($C19,'Store List'!$A$4:$A$300,0)),"") -> 46086 | E19: False Alarm | G19: =IF($E19="","",IFERROR(IF(OR(NOT(ISNUMBER($D19)),NOT(ISNUMBER(INDEX(Settings!$E$4:$E$80,MATCH($E19,Settings!$A$4:$A$80,0))))),"No",IF($D19>INDEX(Settings!$E$4:$E$80,MATCH($E19,Settings!$A$4:$A$80,0)),"Yes","No")),"")) -> No | H19: =IFERROR(TRIM(INDEX('Raw Data'!$S$5:$S$400,MATCH($B19,'Raw Data'!$H$5:$H$400,0))),"") -> RLN2MA/MY26b013811 ~ RLN3MA/MY26B013832
A20: =IFERROR(INDEX('Raw Data'!$D$5:$D$400,MATCH($B20,'Raw Data'!$H$5:$H$400,0)),"") -> 46120.392 | B20: WO-0548436 | C20: =IFERROR(TRIM(INDEX('Raw Data'!$J$5:$J$400,MATCH($B20,'Raw Data'!$H$5:$H$400,0))),"") -> Dollar General #3270 | D20: =IFERROR(INDEX('Store List'!$B$4:$B$300,MATCH($C20,'Store List'!$A$4:$A$300,0)),"") -> 46120 | E20: Component Failure | G20: =IF($E20="","",IFERROR(IF(OR(NOT(ISNUMBER($D20)),NOT(ISNUMBER(INDEX(Settings!$E$4:$E$80,MATCH($E20,Settings!$A$4:$A$80,0))))),"No",IF($D20>INDEX(Settings!$E$4:$E$80,MATCH($E20,Settings!$A$4:$A$80,0)),"Yes","No")),"")) -> No | H20: =IFERROR(TRIM(INDEX('Raw Data'!$S$5:$S$400,MATCH($B20,'Raw Data'!$H$5:$H$400,0))),"") -> MY26B016515
A21: =IFERROR(INDEX('Raw Data'!$D$5:$D$400,MATCH($B21,'Raw Data'!$H$5:$H$400,0)),"") -> 46119.611 | B21: WO-0548123 | C21: =IFERROR(TRIM(INDEX('Raw Data'!$J$5:$J$400,MATCH($B21,'Raw Data'!$H$5:$H$400,0))),"") -> Dollar General #14858 | D21: =IFERROR(INDEX('Store List'!$B$4:$B$300,MATCH($C21,'Store List'!$A$4:$A$300,0)),"") -> 46097 | E21: Door Torque | F21: Tech found door torque issue and adjusted it | G21: =IF($E21="","",IFERROR(IF(OR(NOT(ISNUMBER($D21)),NOT(ISNUMBER(INDEX(Settings!$E$4:$E$80,MATCH($E21,Settings!$A$4:$A$80,0))))),"No",IF($D21>INDEX(Settings!$E$4:$E$80,MATCH($E21,Settings!$A$4:$A$80,0)),"Yes","No")),"")) -> No | H21: =IFERROR(TRIM(INDEX('Raw Data'!$S$5:$S$400,MATCH($B21,'Raw Data'!$H$5:$H$400,0))),"") -> RMN5MA/MY26B016546, LEFT
A22: =IFERROR(INDEX('Raw Data'!$D$5:$D$400,MATCH($B22,'Raw Data'!$H$5:$H$400,0)),"") -> 46119.611 | B22: WO-0548123 | C22: =IFERROR(TRIM(INDEX('Raw Data'!$J$5:$J$400,MATCH($B22,'Raw Data'!$H$5:$H$400,0))),"") -> Dollar General #14858 | D22: =IFERROR(INDEX('Store List'!$B$4:$B$300,MATCH($C22,'Store List'!$A$4:$A$300,0)),"") -> 46097 | E22: Wrong / Loose wiring | G22: =IF($E22="","",IFERROR(IF(OR(NOT(ISNUMBER($D22)),NOT(ISNUMBER(INDEX(Settings!$E$4:$E$80,MATCH($E22,Settings!$A$4:$A$80,0))))),"No",IF($D22>INDEX(Settings!$E$4:$E$80,MATCH($E22,Settings!$A$4:$A$80,0)),"Yes","No")),"")) -> No | H22: =IFERROR(TRIM(INDEX('Raw Data'!$S$5:$S$400,MATCH($B22,'Raw Data'!$H$5:$H$400,0))),"") -> RMN5MA/MY26B016546, LEFT
A23: =IFERROR(INDEX('Raw Data'!$D$5:$D$400,MATCH($B23,'Raw Data'!$H$5:$H$400,0)),"") -> 46121.515 | B23: WO-0549298 | C23: =IFERROR(TRIM(INDEX('Raw Data'!$J$5:$J$400,MATCH($B23,'Raw Data'!$H$5:$H$400,0))),"") -> Dollar General #21016 | D23: =IFERROR(INDEX('Store List'!$B$4:$B$300,MATCH($C23,'Store List'!$A$4:$A$300,0)),"") -> 46119 | E23: Communication problem | G23: =IF($E23="","",IFERROR(IF(OR(NOT(ISNUMBER($D23)),NOT(ISNUMBER(INDEX(Settings!$E$4:$E$80,MATCH($E23,Settings!$A$4:$A$80,0))))),"No",IF($D23>INDEX(Settings!$E$4:$E$80,MATCH($E23,Settings!$A$4:$A$80,0)),"Yes","No")),"")) -> No | H23: =IFERROR(TRIM(INDEX('Raw Data'!$S$5:$S$400,MATCH($B23,'Raw Data'!$H$5:$H$400,0))),"") -> RLN2MA/MY26B015995
A24: =IFERROR(INDEX('Raw Data'!$D$5:$D$400,MATCH($B24,'Raw Data'!$H$5:$H$400,0)),"") -> 46122.574 | B24: WO-0549951 | C24: =IFERROR(TRIM(INDEX('Raw Data'!$J$5:$J$400,MATCH($B24,'Raw Data'!$H$5:$H$400,0))),"") -> Dollar General #21223 | D24: =IFERROR(INDEX('Store List'!$B$4:$B$300,MATCH($C24,'Store List'!$A$4:$A$300,0)),"") -> 46120 | E24: Ref. leak/ Low charge | F24: Microblock | G24: =IF($E24="","",IFERROR(IF(OR(NOT(ISNUMBER($D24)),NOT(ISNUMBER(INDEX(Settings!$E$4:$E$80,MATCH($E24,Settings!$A$4:$A$80,0))))),"No",IF($D24>INDEX(Settings!$E$4:$E$80,MATCH($E24,Settings!$A$4:$A$80,0)),"Yes","No")),"")) -> No | H24: =IFERROR(TRIM(INDEX('Raw Data'!$S$5:$S$400,MATCH($B24,'Raw Data'!$H$5:$H$400,0))),"")
A25: =IFERROR(INDEX('Raw Data'!$D$5:$D$400,MATCH($B25,'Raw Data'!$H$5:$H$400,0)),"") -> 46120.636 | B25: WO-0548822 | C25: =IFERROR(TRIM(INDEX('Raw Data'!$J$5:$J$400,MATCH($B25,'Raw Data'!$H$5:$H$400,0))),"") -> Dollar General #13338 | D25: =IFERROR(INDEX('Store List'!$B$4:$B$300,MATCH($C25,'Store List'!$A$4:$A$300,0)),"") -> 46092 | E25: Component Failure | G25: =IF($E25="","",IFERROR(IF(OR(NOT(ISNUMBER($D25)),NOT(ISNUMBER(INDEX(Settings!$E$4:$E$80,MATCH($E25,Settings!$A$4:$A$80,0))))),"No",IF($D25>INDEX(Settings!$E$4:$E$80,MATCH($E25,Settings!$A$4:$A$80,0)),"Yes","No")),"")) -> No | H25: =IFERROR(TRIM(INDEX('Raw Data'!$S$5:$S$400,MATCH($B25,'Raw Data'!$H$5:$H$400,0))),"") -> RLN2MA/MY26B013807, RLN3MA/MY26B013833, RMN5MA/MY26B013852
A26: =IFERROR(INDEX('Raw Data'!$D$5:$D$400,MATCH($B26,'Raw Data'!$H$5:$H$400,0)),"") -> 46121.501 | B26: WO-0549280 | C26: =IFERROR(TRIM(INDEX('Raw Data'!$J$5:$J$400,MATCH($B26,'Raw Data'!$H$5:$H$400,0))),"") -> Dollar General #20407 | D26: =IFERROR(INDEX('Store List'!$B$4:$B$300,MATCH($C26,'Store List'!$A$4:$A$300,0)),"") -> 46119 | E26: Ref. leak/ Low charge | G26: =IF($E26="","",IFERROR(IF(OR(NOT(ISNUMBER($D26)),NOT(ISNUMBER(INDEX(Settings!$E$4:$E$80,MATCH($E26,Settings!$A$4:$A$80,0))))),"No",IF($D26>INDEX(Settings!$E$4:$E$80,MATCH($E26,Settings!$A$4:$A$80,0)),"Yes","No")),"")) -> No | H26: =IFERROR(TRIM(INDEX('Raw Data'!$S$5:$S$400,MATCH($B26,'Raw Data'!$H$5:$H$400,0))),"") -> RLN3MA/MY26B016017, RIGHT
A27: =IFERROR(INDEX('Raw Data'!$D$5:$D$400,MATCH($B27,'Raw Data'!$H$5:$H$400,0)),"") -> 46121.501 | B27: WO-0549280 | C27: =IFERROR(TRIM(INDEX('Raw Data'!$J$5:$J$400,MATCH($B27,'Raw Data'!$H$5:$H$400,0))),"") -> Dollar General #20407 | D27: =IFERROR(INDEX('Store List'!$B$4:$B$300,MATCH($C27,'Store List'!$A$4:$A$300,0)),"") -> 46119 | E27: Defrost Sync | G27: =IF($E27="","",IFERROR(IF(OR(NOT(ISNUMBER($D27)),NOT(ISNUMBER(INDEX(Settings!$E$4:$E$80,MATCH($E27,Settings!$A$4:$A$80,0))))),"No",IF($D27>INDEX(Settings!$E$4:$E$80,MATCH($E27,Settings!$A$4:$A$80,0)),"Yes","No")),"")) -> No | H27: =IFERROR(TRIM(INDEX('Raw Data'!$S$5:$S$400,MATCH($B27,'Raw Data'!$H$5:$H$400,0))),"") -> RLN3MA/MY26B016017, RIGHT
A28: =IFERROR(INDEX('Raw Data'!$D$5:$D$400,MATCH($B28,'Raw Data'!$H$5:$H$400,0)),"") -> 46125.433 | B28: WO-0551078 | C28: =IFERROR(TRIM(INDEX('Raw Data'!$J$5:$J$400,MATCH($B28,'Raw Data'!$H$5:$H$400,0))),"") -> Dollar General #14858 | D28: =IFERROR(INDEX('Store List'!$B$4:$B$300,MATCH($C28,'Store List'!$A$4:$A$300,0)),"") -> 46097 | E28: Return Air blocked | G28: =IF($E28="","",IFERROR(IF(OR(NOT(ISNUMBER($D28)),NOT(ISNUMBER(INDEX(Settings!$E$4:$E$80,MATCH($E28,Settings!$A$4:$A$80,0))))),"No",IF($D28>INDEX(Settings!$E$4:$E$80,MATCH($E28,Settings!$A$4:$A$80,0)),"Yes","No")),"")) -> No | H28: =IFERROR(TRIM(INDEX('Raw Data'!$S$5:$S$400,MATCH($B28,'Raw Data'!$H$5:$H$400,0))),"") -> RLN2MA/MY26B016475, LEFT
A29: =IFERROR(INDEX('Raw Data'!$D$5:$D$400,MATCH($B29,'Raw Data'!$H$5:$H$400,0)),"") -> 46126.384 | B29: WO-0551833 | C29: =IFERROR(TRIM(INDEX('Raw Data'!$J$5:$J$400,MATCH($B29,'Raw Data'!$H$5:$H$400,0))),"") -> Dollar General #21016 | D29: =IFERROR(INDEX('Store List'!$B$4:$B$300,MATCH($C29,'Store List'!$A$4:$A$300,0)),"") -> 46119 | E29: Unknown | G29: =IF($E29="","",IFERROR(IF(OR(NOT(ISNUMBER($D29)),NOT(ISNUMBER(INDEX(Settings!$E$4:$E$80,MATCH($E29,Settings!$A$4:$A$80,0))))),"No",IF($D29>INDEX(Settings!$E$4:$E$80,MATCH($E29,Settings!$A$4:$A$80,0)),"Yes","No")),"")) -> No | H29: =IFERROR(TRIM(INDEX('Raw Data'!$S$5:$S$400,MATCH($B29,'Raw Data'!$H$5:$H$400,0))),"") -> RMN3MA/MY26B016499
A30: =IFERROR(INDEX('Raw Data'!$D$5:$D$400,MATCH($B30,'Raw Data'!$H$5:$H$400,0)),"") -> 46126.512 | B30: WO-0552039 | C30: =IFERROR(TRIM(INDEX('Raw Data'!$J$5:$J$400,MATCH($B30,'Raw Data'!$H$5:$H$400,0))),"") -> Dollar General #14104 | D30: =IFERROR(INDEX('Store List'!$B$4:$B$300,MATCH($C30,'Store List'!$A$4:$A$300,0)),"") -> 46105 | E30: Freedom | G30: =IF($E30="","",IFERROR(IF(OR(NOT(ISNUMBER($D30)),NOT(ISNUMBER(INDEX(Settings!$E$4:$E$80,MATCH($E30,Settings!$A$4:$A$80,0))))),"No",IF($D30>INDEX(Settings!$E$4:$E$80,MATCH($E30,Settings!$A$4:$A$80,0)),"Yes","No")),"")) -> No | H30: =IFERROR(TRIM(INDEX('Raw Data'!$S$5:$S$400,MATCH($B30,'Raw Data'!$H$5:$H$400,0))),"") -> RLN2MA/MY26B015990 Left
A31: =IFERROR(INDEX('Raw Data'!$D$5:$D$400,MATCH($B31,'Raw Data'!$H$5:$H$400,0)),"") -> 46126.52 | B31: WO-0552056 | C31: =IFERROR(TRIM(INDEX('Raw Data'!$J$5:$J$400,MATCH($B31,'Raw Data'!$H$5:$H$400,0))),"") -> Dollar General #22286 | D31: =IFERROR(INDEX('Store List'!$B$4:$B$300,MATCH($C31,'Store List'!$A$4:$A$300,0)),"") -> 46099 | E31: False Alarm | G31: =IF($E31="","",IFERROR(IF(OR(NOT(ISNUMBER($D31)),NOT(ISNUMBER(INDEX(Settings!$E$4:$E$80,MATCH($E31,Settings!$A$4:$A$80,0))))),"No",IF($D31>INDEX(Settings!$E$4:$E$80,MATCH($E31,Settings!$A$4:$A$80,0)),"Yes","No")),"")) -> No | H31: =IFERROR(TRIM(INDEX('Raw Data'!$S$5:$S$400,MATCH($B31,'Raw Data'!$H$5:$H$400,0))),"") -> RLN2MA/MY26B014938, LEFT
A32: =IFERROR(INDEX('Raw Data'!$D$5:$D$400,MATCH($B32,'Raw Data'!$H$5:$H$400,0)),"") -> 46126.525 | B32: WO-0552063 | C32: =IFERROR(TRIM(INDEX('Raw Data'!$J$5:$J$400,MATCH($B32,'Raw Data'!$H$5:$H$400,0))),"") -> Dollar General #20876 | D32: =IFERROR(INDEX('Store List'!$B$4:$B$300,MATCH($C32,'Store List'!$A$4:$A$300,0)),"") -> 46112 | E32: High Store RH | G32: =IF($E32="","",IFERROR(IF(OR(NOT(ISNUMBER($D32)),NOT(ISNUMBER(INDEX(Settings!$E$4:$E$80,MATCH($E32,Settings!$A$4:$A$80,0))))),"No",IF($D32>INDEX(Settings!$E$4:$E$80,MATCH($E32,Settings!$A$4:$A$80,0)),"Yes","No")),"")) -> No | H32: =IFERROR(TRIM(INDEX('Raw Data'!$S$5:$S$400,MATCH($B32,'Raw Data'!$H$5:$H$400,0))),"") -> RLN2MA/MY26B013812
A33: =IFERROR(INDEX('Raw Data'!$D$5:$D$400,MATCH($B33,'Raw Data'!$H$5:$H$400,0)),"") -> 46126.535 | B33: WO-0552080 | C33: =IFERROR(TRIM(INDEX('Raw Data'!$J$5:$J$400,MATCH($B33,'Raw Data'!$H$5:$H$400,0))),"") -> Dollar General #22281 | D33: =IFERROR(INDEX('Store List'!$B$4:$B$300,MATCH($C33,'Store List'!$A$4:$A$300,0)),"") -> 46118 | E33: Defrost Sync | G33: =IF($E33="","",IFERROR(IF(OR(NOT(ISNUMBER($D33)),NOT(ISNUMBER(INDEX(Settings!$E$4:$E$80,MATCH($E33,Settings!$A$4:$A$80,0))))),"No",IF($D33>INDEX(Settings!$E$4:$E$80,MATCH($E33,Settings!$A$4:$A$80,0)),"Yes","No")),"")) -> No | H33: =IFERROR(TRIM(INDEX('Raw Data'!$S$5:$S$400,MATCH($B33,'Raw Data'!$H$5:$H$400,0))),"") -> RLN3MA/MY26B016019, RIGHT
A34: =IFERROR(INDEX('Raw Data'!$D$5:$D$400,MATCH($B34,'Raw Data'!$H$5:$H$400,0)),"") -> 46126.535 | B34: WO-0552080 | C34: =IFERROR(TRIM(INDEX('Raw Data'!$J$5:$J$400,MATCH($B34,'Raw Data'!$H$5:$H$400,0))),"") -> Dollar General #22281 | D34: =IFERROR(INDEX('Store List'!$B$4:$B$300,MATCH($C34,'Store List'!$A$4:$A$300,0)),"") -> 46118 | E34: False Alarm | G34: =IF($E34="","",IFERROR(IF(OR(NOT(ISNUMBER($D34)),NOT(ISNUMBER(INDEX(Settings!$E$4:$E$80,MATCH($E34,Settings!$A$4:$A$80,0))))),"No",IF($D34>INDEX(Settings!$E$4:$E$80,MATCH($E34,Settings!$A$4:$A$80,0)),"Yes","No")),"")) -> No | H34: =IFERROR(TRIM(INDEX('Raw Data'!$S$5:$S$400,MATCH($B34,'Raw Data'!$H$5:$H$400,0))),"") -> RLN3MA/MY26B016019, RIGHT
A35: =IFERROR(INDEX('Raw Data'!$D$5:$D$400,MATCH($B35,'Raw Data'!$H$5:$H$400,0)),"") -> 46126.541 | B35: WO-0552093 | C35: =IFERROR(TRIM(INDEX('Raw Data'!$J$5:$J$400,MATCH($B35,'Raw Data'!$H$5:$H$400,0))),"") -> Dollar General #3270 | D35: =IFERROR(INDEX('Store List'!$B$4:$B$300,MATCH($C35,'Store List'!$A$4:$A$300,0)),"") -> 46120 | E35: Ref. leak/ Low charge | G35: =IF($E35="","",IFERROR(IF(OR(NOT(ISNUMBER($D35)),NOT(ISNUMBER(INDEX(Settings!$E$4:$E$80,MATCH($E35,Settings!$A$4:$A$80,0))))),"No",IF($D35>INDEX(Settings!$E$4:$E$80,MATCH($E35,Settings!$A$4:$A$80,0)),"Yes","No")),"")) -> No | H35: =IFERROR(TRIM(INDEX('Raw Data'!$S$5:$S$400,MATCH($B35,'Raw Data'!$H$5:$H$400,0))),"") -> RLN3MA/MY26B016488, RIGHT
A36: =IFERROR(INDEX('Raw Data'!$D$5:$D$400,MATCH($B36,'Raw Data'!$H$5:$H$400,0)),"") -> 46126.559 | B36: WO-0552123 | C36: =IFERROR(TRIM(INDEX('Raw Data'!$J$5:$J$400,MATCH($B36,'Raw Data'!$H$5:$H$400,0))),"") -> Dollar General #22613 | D36: =IFERROR(INDEX('Store List'!$B$4:$B$300,MATCH($C36,'Store List'!$A$4:$A$300,0)),"") -> 46099 | E36: Wrong / Loose wiring | G36: =IF($E36="","",IFERROR(IF(OR(NOT(ISNUMBER($D36)),NOT(ISNUMBER(INDEX(Settings!$E$4:$E$80,MATCH($E36,Settings!$A$4:$A$80,0))))),"No",IF($D36>INDEX(Settings!$E$4:$E$80,MATCH($E36,Settings!$A$4:$A$80,0)),"Yes","No")),"")) -> No | H36: =IFERROR(TRIM(INDEX('Raw Data'!$S$5:$S$400,MATCH($B36,'Raw Data'!$H$5:$H$400,0))),"") -> RLN2MA/MY26B014941
... A40: =IFERROR(INDEX('Raw Data'!$D$5:$D$400,MATCH($B40,'Raw Data'!$H$5:$H$400,0)),"") -> 46127.322 | B40: WO-0552572 | C40: =IFERROR(TRIM(INDEX('Raw Data'!$J$5:$J$400,MATCH($B40,'Raw Data'!$H$5:$H$400,0))),"") -> Dollar General #21377 | D40: =IFERROR(INDEX('Store List'!$B$4:$B$300,MATCH($C40,'Store List'!$A$4:$A$300,0)),"") -> 46093 | E40: Door - general | G40: =IF($E40="","",IFERROR(IF(OR(NOT(ISNUMBER($D40)),NOT(ISNUMBER(INDEX(Settings!$E$4:$E$80,MATCH($E40,Settings!$A$4:$A$80,0))))),"No",IF($D40>INDEX(Settings!$E$4:$E$80,MATCH($E40,Settings!$A$4:$A$80,0)),"Yes","No")),"")) -> No | H40: =IFERROR(TRIM(INDEX('Raw Data'!$S$5:$S$400,MATCH($B40,'Raw Data'!$H$5:$H$400,0))),"") -> RLN2MA/MY26B013804, LEFT
A41: =IFERROR(INDEX('Raw Data'!$D$5:$D$400,MATCH($B41,'Raw Data'!$H$5:$H$400,0)),"") -> 46128.455 | B41: WO-0553537 | C41: =IFERROR(TRIM(INDEX('Raw Data'!$J$5:$J$400,MATCH($B41,'Raw Data'!$H$5:$H$400,0))),"") -> Dollar General #21135 | D41: =IFERROR(INDEX('Store List'!$B$4:$B$300,MATCH($C41,'Store List'!$A$4:$A$300,0)),"") -> 46106 | E41: Door Torque | F41: No comments from tech. but looking at the data, this is a door not closing issue which is most likely because of door torque | G41: =IF($E41="","",IFERROR(IF(OR(NOT(ISNUMBER($D41)),NOT(ISNUMBER(INDEX(Settings!$E$4:$E$80,MATCH($E41,Settings!$A$4:$A$80,0))))),"No",IF($D41>INDEX(Settings!$E$4:$E$80,MATCH($E41,Settings!$A$4:$A$80,0)),"Yes","No")),"")) -> No | H41: =IFERROR(TRIM(INDEX('Raw Data'!$S$5:$S$400,MATCH($B41,'Raw Data'!$H$5:$H$400,0))),"") -> RMN3MA/MY26b016480
A42: =IFERROR(INDEX('Raw Data'!$D$5:$D$400,MATCH($B42,'Raw Data'!$H$5:$H$400,0)),"") -> 46128.455 | B42: WO-0553537 | C42: =IFERROR(TRIM(INDEX('Raw Data'!$J$5:$J$400,MATCH($B42,'Raw Data'!$H$5:$H$400,0))),"") -> Dollar General #21135 | D42: =IFERROR(INDEX('Store List'!$B$4:$B$300,MATCH($C42,'Store List'!$A$4:$A$300,0)),"") -> 46106 | E42: Drain tube blocked | G42: =IF($E42="","",IFERROR(IF(OR(NOT(ISNUMBER($D42)),NOT(ISNUMBER(INDEX(Settings!$E$4:$E$80,MATCH($E42,Settings!$A$4:$A$80,0))))),"No",IF($D42>INDEX(Settings!$E$4:$E$80,MATCH($E42,Settings!$A$4:$A$80,0)),"Yes","No")),"")) -> No | H42: =IFERROR(TRIM(INDEX('Raw Data'!$S$5:$S$400,MATCH($B42,'Raw Data'!$H$5:$H$400,0))),"") -> RMN3MA/MY26b016480
A43: =IFERROR(INDEX('Raw Data'!$D$5:$D$400,MATCH($B43,'Raw Data'!$H$5:$H$400,0)),"") -> 46130.378 | B43: WO-0554820 | C43: =IFERROR(TRIM(INDEX('Raw Data'!$J$5:$J$400,MATCH($B43,'Raw Data'!$H$5:$H$400,0))),"") -> Dollar General #22982 | D43: =IFERROR(INDEX('Store List'!$B$4:$B$300,MATCH($C43,'Store List'!$A$4:$A$300,0)),"") -> 46126 | E43: Door - general | G43: =IF($E43="","",IFERROR(IF(OR(NOT(ISNUMBER($D43)),NOT(ISNUMBER(INDEX(Settings!$E$4:$E$80,MATCH($E43,Settings!$A$4:$A$80,0))))),"No",IF($D43>INDEX(Settings!$E$4:$E$80,MATCH($E43,Settings!$A$4:$A$80,0)),"Yes","No")),"")) -> No | H43: =IFERROR(TRIM(INDEX('Raw Data'!$S$5:$S$400,MATCH($B43,'Raw Data'!$H$5:$H$400,0))),"") -> RLN4MA/MY26B014967, LEFT
A44: =IFERROR(INDEX('Raw Data'!$D$5:$D$400,MATCH($B44,'Raw Data'!$H$5:$H$400,0)),"") -> 46133.411 | B44: WO-0556537 | C44: =IFERROR(TRIM(INDEX('Raw Data'!$J$5:$J$400,MATCH($B44,'Raw Data'!$H$5:$H$400,0))),"") -> Dollar General #22930 | D44: =IFERROR(INDEX('Store List'!$B$4:$B$300,MATCH($C44,'Store List'!$A$4:$A$300,0)),"") -> 46128 | E44: Enclosure Seal | G44: =IF($E44="","",IFERROR(IF(OR(NOT(ISNUMBER($D44)),NOT(ISNUMBER(INDEX(Settings!$E$4:$E$80,MATCH($E44,Settings!$A$4:$A$80,0))))),"No",IF($D44>INDEX(Settings!$E$4:$E$80,MATCH($E44,Settings!$A$4:$A$80,0)),"Yes","No")),"")) -> No | H44: =IFERROR(TRIM(INDEX('Raw Data'!$S$5:$S$400,MATCH($B44,'Raw Data'!$H$5:$H$400,0))),"") -> RLN4MA/MY26B014974
A45: =IFERROR(INDEX('Raw Data'!$D$5:$D$400,MATCH($B45,'Raw Data'!$H$5:$H$400,0)),"") -> 46133.411 | B45: WO-0556537 | C45: =IFERROR(TRIM(INDEX('Raw Data'!$J$5:$J$400,MATCH($B45,'Raw Data'!$H$5:$H$400,0))),"") -> Dollar General #22930 | D45: =IFERROR(INDEX('Store List'!$B$4:$B$300,MATCH($C45,'Store List'!$A$4:$A$300,0)),"") -> 46128 | E45: Component Failure | G45: =IF($E45="","",IFERROR(IF(OR(NOT(ISNUMBER($D45)),NOT(ISNUMBER(INDEX(Settings!$E$4:$E$80,MATCH($E45,Settings!$A$4:$A$80,0))))),"No",IF($D45>INDEX(Settings!$E$4:$E$80,MATCH($E45,Settings!$A$4:$A$80,0)),"Yes","No")),"")) -> No | H45: =IFERROR(TRIM(INDEX('Raw Data'!$S$5:$S$400,MATCH($B45,'Raw Data'!$H$5:$H$400,0))),"") -> RLN4MA/MY26B014974
A46: =IFERROR(INDEX('Raw Data'!$D$5:$D$400,MATCH($B46,'Raw Data'!$H$5:$H$400,0)),"") -> 46135.266 | B46: WO-0557805 | C46: =IFERROR(TRIM(INDEX('Raw Data'!$J$5:$J$400,MATCH($B46,'Raw Data'!$H$5:$H$400,0))),"") -> Dollar General #21130 | D46: =IFERROR(INDEX('Store List'!$B$4:$B$300,MATCH($C46,'Store List'!$A$4:$A$300,0)),"") -> 46125 | E46: DG Installation issue | G46: =IF($E46="","",IFERROR(IF(OR(NOT(ISNUMBER($D46)),NOT(ISNUMBER(INDEX(Settings!$E$4:$E$80,MATCH($E46,Settings!$A$4:$A$80,0))))),"No",IF($D46>INDEX(Settings!$E$4:$E$80,MATCH($E46,Settings!$A$4:$A$80,0)),"Yes","No")),"")) -> No | H46: =IFERROR(TRIM(INDEX('Raw Data'!$S$5:$S$400,MATCH($B46,'Raw Data'!$H$5:$H$400,0))),"") -> RLN3MA/MY26C019887
A47: =IFERROR(INDEX('Raw Data'!$D$5:$D$400,MATCH($B47,'Raw Data'!$H$5:$H$400,0)),"") -> 46134.245 | B47: WO-0557035 | C47: =IFERROR(TRIM(INDEX('Raw Data'!$J$5:$J$400,MATCH($B47,'Raw Data'!$H$5:$H$400,0))),"") -> Dollar General #20876 | D47: =IFERROR(INDEX('Store List'!$B$4:$B$300,MATCH($C47,'Store List'!$A$4:$A$300,0)),"") -> 46112 | E47: Communication problem | G47: =IF($E47="","",IFERROR(IF(OR(NOT(ISNUMBER($D47)),NOT(ISNUMBER(INDEX(Settings!$E$4:$E$80,MATCH($E47,Settings!$A$4:$A$80,0))))),"No",IF($D47>INDEX(Settings!$E$4:$E$80,MATCH($E47,Settings!$A$4:$A$80,0)),"Yes","No")),"")) -> No | H47: =IFERROR(TRIM(INDEX('Raw Data'!$S$5:$S$400,MATCH($B47,'Raw Data'!$H$5:$H$400,0))),"") -> RMN4MA/MY26B013850, RLN3MA/MY26B013819, RNL2MA/MY26B013812, RMN3MA/MY26B013772, RMN3MA/MY26B013770, RFMN5/MY19M090256, RFMN5/MY19M090255, RFLN4/MY19M090238, RFLN4/MY19M090237, RFLN3/MY19M090226
A48: =IFERROR(INDEX('Raw Data'!$D$5:$D$400,MATCH($B48,'Raw Data'!$H$5:$H$400,0)),"") -> 46134.245 | B48: WO-0557035 | C48: =IFERROR(TRIM(INDEX('Raw Data'!$J$5:$J$400,MATCH($B48,'Raw Data'!$H$5:$H$400,0))),"") -> Dollar General #20876 | D48: =IFERROR(INDEX('Store List'!$B$4:$B$300,MATCH($C48,'Store List'!$A$4:$A$300,0)),"") -> 46112 | E48: High Store RH | G48: =IF($E48="","",IFERROR(IF(OR(NOT(ISNUMBER($D48)),NOT(ISNUMBER(INDEX(Settings!$E$4:$E$80,MATCH($E48,Settings!$A$4:$A$80,0))))),"No",IF($D48>INDEX(Settings!$E$4:$E$80,MATCH($E48,Settings!$A$4:$A$80,0)),"Yes","No")),"")) -> No | H48: =IFERROR(TRIM(INDEX('Raw Data'!$S$5:$S$400,MATCH($B48,'Raw Data'!$H$5:$H$400,0))),"") -> RMN4MA/MY26B013850, RLN3MA/MY26B013819, RNL2MA/MY26B013812, RMN3MA/MY26B013772, RMN3MA/MY26B013770, RFMN5/MY19M090256, RFMN5/MY19M090255, RFLN4/MY19M090238, RFLN4/MY19M090237, RFLN3/MY19M090226
A49: =IFERROR(INDEX('Raw Data'!$D$5:$D$400,MATCH($B49,'Raw Data'!$H$5:$H$400,0)),"") -> 46139.225 | B49: WO-0559894 | C49: =IFERROR(TRIM(INDEX('Raw Data'!$J$5:$J$400,MATCH($B49,'Raw Data'!$H$5:$H$400,0))),"") -> Dollar General #21342 | D49: =IFERROR(INDEX('Store List'!$B$4:$B$300,MATCH($C49,'Store List'!$A$4:$A$300,0)),"") -> 46122 | E49: Ref. leak/ Low charge | G49: =IF($E49="","",IFERROR(IF(OR(NOT(ISNUMBER($D49)),NOT(ISNUMBER(INDEX(Settings!$E$4:$E$80,MATCH($E49,Settings!$A$4:$A$80,0))))),"No",IF($D49>INDEX(Settings!$E$4:$E$80,MATCH($E49,Settings!$A$4:$A$80,0)),"Yes","No")),"")) -> No | H49: =IFERROR(TRIM(INDEX('Raw Data'!$S$5:$S$400,MATCH($B49,'Raw Data'!$H$5:$H$400,0))),"") -> RLN3MA/MY26B016018, LEFT
A50: =IFERROR(INDEX('Raw Data'!$D$5:$D$400,MATCH($B50,'Raw Data'!$H$5:$H$400,0)),"") -> 46139.317 | B50: WO-0560039 | C50: =IFERROR(TRIM(INDEX('Raw Data'!$J$5:$J$400,MATCH($B50,'Raw Data'!$H$5:$H$400,0))),"") -> Dollar General #20582 | D50: =IFERROR(INDEX('Store List'!$B$4:$B$300,MATCH($C50,'Store List'!$A$4:$A$300,0)),"") -> 46098 | E50: Enclosure Seal | G50: =IF($E50="","",IFERROR(IF(OR(NOT(ISNUMBER($D50)),NOT(ISNUMBER(INDEX(Settings!$E$4:$E$80,MATCH($E50,Settings!$A$4:$A$80,0))))),"No",IF($D50>INDEX(Settings!$E$4:$E$80,MATCH($E50,Settings!$A$4:$A$80,0)),"Yes","No")),"")) -> No | H50: =IFERROR(TRIM(INDEX('Raw Data'!$S$5:$S$400,MATCH($B50,'Raw Data'!$H$5:$H$400,0))),"") -> RLN2MA/MY26B016475
A51: =IFERROR(INDEX('Raw Data'!$D$5:$D$400,MATCH($B51,'Raw Data'!$H$5:$H$400,0)),"") -> 46139.317 | B51: WO-0560039 | C51: =IFERROR(TRIM(INDEX('Raw Data'!$J$5:$J$400,MATCH($B51,'Raw Data'!$H$5:$H$400,0))),"") -> Dollar General #20582 | D51: =IFERROR(INDEX('Store List'!$B$4:$B$300,MATCH($C51,'Store List'!$A$4:$A$300,0)),"") -> 46098 | E51: Case End Seal | G51: =IF($E51="","",IFERROR(IF(OR(NOT(ISNUMBER($D51)),NOT(ISNUMBER(INDEX(Settings!$E$4:$E$80,MATCH($E51,Settings!$A$4:$A$80,0))))),"No",IF($D51>INDEX(Settings!$E$4:$E$80,MATCH($E51,Settings!$A$4:$A$80,0)),"Yes","No")),"")) -> No | H51: =IFERROR(TRIM(INDEX('Raw Data'!$S$5:$S$400,MATCH($B51,'Raw Data'!$H$5:$H$400,0))),"") -> RLN2MA/MY26B016475
A52: =IFERROR(INDEX('Raw Data'!$D$5:$D$400,MATCH($B52,'Raw Data'!$H$5:$H$400,0)),"") -> 46144.319 | B52: WO-0563528 | C52: =IFERROR(TRIM(INDEX('Raw Data'!$J$5:$J$400,MATCH($B52,'Raw Data'!$H$5:$H$400,0))),"") -> Dollar General #13396 | D52: =IFERROR(INDEX('Store List'!$B$4:$B$300,MATCH($C52,'Store List'!$A$4:$A$300,0)),"") -> 46141 | E52: Communication problem | G52: =IF($E52="","",IFERROR(IF(OR(NOT(ISNUMBER($D52)),NOT(ISNUMBER(INDEX(Settings!$E$4:$E$80,MATCH($E52,Settings!$A$4:$A$80,0))))),"No",IF($D52>INDEX(Settings!$E$4:$E$80,MATCH($E52,Settings!$A$4:$A$80,0)),"Yes","No")),"")) -> No | H52: =IFERROR(TRIM(INDEX('Raw Data'!$S$5:$S$400,MATCH($B52,'Raw Data'!$H$5:$H$400,0))),"") -> RLN2MA MY26B016003
A53: =IFERROR(INDEX('Raw Data'!$D$5:$D$400,MATCH($B53,'Raw Data'!$H$5:$H$400,0)),"") -> 46147 | B53: WO-0564924 | C53: =IFERROR(TRIM(INDEX('Raw Data'!$J$5:$J$400,MATCH($B53,'Raw Data'!$H$5:$H$400,0))),"") -> Dollar General #13631 | D53: =IFERROR(INDEX('Store List'!$B$4:$B$300,MATCH($C53,'Store List'!$A$4:$A$300,0)),"") -> 46147 | E53: False Alarm | G53: =IF($E53="","",IFERROR(IF(OR(NOT(ISNUMBER($D53)),NOT(ISNUMBER(INDEX(Settings!$E$4:$E$80,MATCH($E53,Settings!$A$4:$A$80,0))))),"No",IF($D53>INDEX(Settings!$E$4:$E$80,MATCH($E53,Settings!$A$4:$A$80,0)),"Yes","No")),"")) -> No | H53: =IFERROR(TRIM(INDEX('Raw Data'!$S$5:$S$400,MATCH($B53,'Raw Data'!$H$5:$H$400,0))),"") -> RMN4MA/MY26D028116
... A56: =IFERROR(INDEX('Raw Data'!$D$5:$D$400,MATCH($B56,'Raw Data'!$H$5:$H$400,0)),"") -> 46147.452 | B56: WO-0564555 | C56: =IFERROR(TRIM(INDEX('Raw Data'!$J$5:$J$400,MATCH($B56,'Raw Data'!$H$5:$H$400,0))),"") -> Dollar General #10339 | D56: =IFERROR(INDEX('Store List'!$B$4:$B$300,MATCH($C56,'Store List'!$A$4:$A$300,0)),"") -> 46141 | E56: Overstocking | G56: =IF($E56="","",IFERROR(IF(OR(NOT(ISNUMBER($D56)),NOT(ISNUMBER(INDEX(Settings!$E$4:$E$80,MATCH($E56,Settings!$A$4:$A$80,0))))),"No",IF($D56>INDEX(Settings!$E$4:$E$80,MATCH($E56,Settings!$A$4:$A$80,0)),"Yes","No")),"")) -> No | H56: =IFERROR(TRIM(INDEX('Raw Data'!$S$5:$S$400,MATCH($B56,'Raw Data'!$H$5:$H$400,0))),"") -> RLN2MA MY26B016459
A57: =IFERROR(INDEX('Raw Data'!$D$5:$D$400,MATCH($B57,'Raw Data'!$H$5:$H$400,0)),"") -> 46150.383 | B57: WO-0566374 | C57: =IFERROR(TRIM(INDEX('Raw Data'!$J$5:$J$400,MATCH($B57,'Raw Data'!$H$5:$H$400,0))),"") -> Dollar General #20639 | D57: =IFERROR(INDEX('Store List'!$B$4:$B$300,MATCH($C57,'Store List'!$A$4:$A$300,0)),"") -> 46125 | E57: Door Torque | F57: Tech found door torque issue and adjusted it | G57: =IF($E57="","",IFERROR(IF(OR(NOT(ISNUMBER($D57)),NOT(ISNUMBER(INDEX(Settings!$E$4:$E$80,MATCH($E57,Settings!$A$4:$A$80,0))))),"No",IF($D57>INDEX(Settings!$E$4:$E$80,MATCH($E57,Settings!$A$4:$A$80,0)),"Yes","No")),"")) -> No | H57: =IFERROR(TRIM(INDEX('Raw Data'!$S$5:$S$400,MATCH($B57,'Raw Data'!$H$5:$H$400,0))),"") -> RLN3MA/MY26B016016
A58: =IFERROR(INDEX('Raw Data'!$D$5:$D$400,MATCH($B58,'Raw Data'!$H$5:$H$400,0)),"") -> 46152.156 | B58: WO-0567300 | C58: =IFERROR(TRIM(INDEX('Raw Data'!$J$5:$J$400,MATCH($B58,'Raw Data'!$H$5:$H$400,0))),"") -> Dollar General #22864 | D58: =IFERROR(INDEX('Store List'!$B$4:$B$300,MATCH($C58,'Store List'!$A$4:$A$300,0)),"") -> 46105 | E58: Wrong program | G58: =IF($E58="","",IFERROR(IF(OR(NOT(ISNUMBER($D58)),NOT(ISNUMBER(INDEX(Settings!$E$4:$E$80,MATCH($E58,Settings!$A$4:$A$80,0))))),"No",IF($D58>INDEX(Settings!$E$4:$E$80,MATCH($E58,Settings!$A$4:$A$80,0)),"Yes","No")),"")) -> No | H58: =IFERROR(TRIM(INDEX('Raw Data'!$S$5:$S$400,MATCH($B58,'Raw Data'!$H$5:$H$400,0))),"") -> RLN3MA/MY26B014958
A59: =IFERROR(INDEX('Raw Data'!$D$5:$D$400,MATCH($B59,'Raw Data'!$H$5:$H$400,0)),"") -> 46154.49 | B59: WO-0568428 | C59: =IFERROR(TRIM(INDEX('Raw Data'!$J$5:$J$400,MATCH($B59,'Raw Data'!$H$5:$H$400,0))),"") -> Dollar General #22613 | D59: =IFERROR(INDEX('Store List'!$B$4:$B$300,MATCH($C59,'Store List'!$A$4:$A$300,0)),"") -> 46099 | E59: Ref. leak/ Low charge | G59: =IF($E59="","",IFERROR(IF(OR(NOT(ISNUMBER($D59)),NOT(ISNUMBER(INDEX(Settings!$E$4:$E$80,MATCH($E59,Settings!$A$4:$A$80,0))))),"No",IF($D59>INDEX(Settings!$E$4:$E$80,MATCH($E59,Settings!$A$4:$A$80,0)),"Yes","No")),"")) -> No | H59: =IFERROR(TRIM(INDEX('Raw Data'!$S$5:$S$400,MATCH($B59,'Raw Data'!$H$5:$H$400,0))),"") -> RLN2MA/MY26B014941
A60: =IFERROR(INDEX('Raw Data'!$D$5:$D$400,MATCH($B60,'Raw Data'!$H$5:$H$400,0)),"") -> 46154.492 | B60: WO-0568430 | C60: =IFERROR(TRIM(INDEX('Raw Data'!$J$5:$J$400,MATCH($B60,'Raw Data'!$H$5:$H$400,0))),"") -> Dollar General #14858 | D60: =IFERROR(INDEX('Store List'!$B$4:$B$300,MATCH($C60,'Store List'!$A$4:$A$300,0)),"") -> 46097 | E60: Ref. leak/ Low charge | G60: =IF($E60="","",IFERROR(IF(OR(NOT(ISNUMBER($D60)),NOT(ISNUMBER(INDEX(Settings!$E$4:$E$80,MATCH($E60,Settings!$A$4:$A$80,0))))),"No",IF($D60>INDEX(Settings!$E$4:$E$80,MATCH($E60,Settings!$A$4:$A$80,0)),"Yes","No")),"")) -> No | H60: =IFERROR(TRIM(INDEX('Raw Data'!$S$5:$S$400,MATCH($B60,'Raw Data'!$H$5:$H$400,0))),"") -> RLN3MA/MY26B016004
A61: =IFERROR(INDEX('Raw Data'!$D$5:$D$400,MATCH($B61,'Raw Data'!$H$5:$H$400,0)),"") -> 46154.177 | B61: WO-0568634 | C61: =IFERROR(TRIM(INDEX('Raw Data'!$J$5:$J$400,MATCH($B61,'Raw Data'!$H$5:$H$400,0))),"") -> Dollar General #3270 | D61: =IFERROR(INDEX('Store List'!$B$4:$B$300,MATCH($C61,'Store List'!$A$4:$A$300,0)),"") -> 46120 | E61: Ref. leak/ Low charge | G61: =IF($E61="","",IFERROR(IF(OR(NOT(ISNUMBER($D61)),NOT(ISNUMBER(INDEX(Settings!$E$4:$E$80,MATCH($E61,Settings!$A$4:$A$80,0))))),"No",IF($D61>INDEX(Settings!$E$4:$E$80,MATCH($E61,Settings!$A$4:$A$80,0)),"Yes","No")),"")) -> No | H61: =IFERROR(TRIM(INDEX('Raw Data'!$S$5:$S$400,MATCH($B61,'Raw Data'!$H$5:$H$400,0))),"") -> RLN3MA/ MY26B016488, CENTER/RIGHT
A62: =IFERROR(INDEX('Raw Data'!$D$5:$D$400,MATCH($B62,'Raw Data'!$H$5:$H$400,0)),"") -> 46154.485 | B62: WO-0568415 | C62: =IFERROR(TRIM(INDEX('Raw Data'!$J$5:$J$400,MATCH($B62,'Raw Data'!$H$5:$H$400,0))),"") -> Dollar General #14104 | D62: =IFERROR(INDEX('Store List'!$B$4:$B$300,MATCH($C62,'Store List'!$A$4:$A$300,0)),"") -> 46105 | E62: Unidentified air leak | G62: =IF($E62="","",IFERROR(IF(OR(NOT(ISNUMBER($D62)),NOT(ISNUMBER(INDEX(Settings!$E$4:$E$80,MATCH($E62,Settings!$A$4:$A$80,0))))),"No",IF($D62>INDEX(Settings!$E$4:$E$80,MATCH($E62,Settings!$A$4:$A$80,0)),"Yes","No")),"")) -> No | H62: =IFERROR(TRIM(INDEX('Raw Data'!$S$5:$S$400,MATCH($B62,'Raw Data'!$H$5:$H$400,0))),"") -> RLN2MA/MY26B015990
A63: =IFERROR(INDEX('Raw Data'!$D$5:$D$400,MATCH($B63,'Raw Data'!$H$5:$H$400,0)),"") -> 46154.485 | B63: WO-0568415 | C63: =IFERROR(TRIM(INDEX('Raw Data'!$J$5:$J$400,MATCH($B63,'Raw Data'!$H$5:$H$400,0))),"") -> Dollar General #14104 | D63: =IFERROR(INDEX('Store List'!$B$4:$B$300,MATCH($C63,'Store List'!$A$4:$A$300,0)),"") -> 46105 | E63: Heavy case load | G63: =IF($E63="","",IFERROR(IF(OR(NOT(ISNUMBER($D63)),NOT(ISNUMBER(INDEX(Settings!$E$4:$E$80,MATCH($E63,Settings!$A$4:$A$80,0))))),"No",IF($D63>INDEX(Settings!$E$4:$E$80,MATCH($E63,Settings!$A$4:$A$80,0)),"Yes","No")),"")) -> No | H63: =IFERROR(TRIM(INDEX('Raw Data'!$S$5:$S$400,MATCH($B63,'Raw Data'!$H$5:$H$400,0))),"") -> RLN2MA/MY26B015990
A64: =IFERROR(INDEX('Raw Data'!$D$5:$D$400,MATCH($B64,'Raw Data'!$H$5:$H$400,0)),"") -> 46154.495 | B64: WO-0568437 | C64: =IFERROR(TRIM(INDEX('Raw Data'!$J$5:$J$400,MATCH($B64,'Raw Data'!$H$5:$H$400,0))),"") -> Dollar General #22286 | D64: =IFERROR(INDEX('Store List'!$B$4:$B$300,MATCH($C64,'Store List'!$A$4:$A$300,0)),"") -> 46099 | E64: Unidentified air leak | G64: =IF($E64="","",IFERROR(IF(OR(NOT(ISNUMBER($D64)),NOT(ISNUMBER(INDEX(Settings!$E$4:$E$80,MATCH($E64,Settings!$A$4:$A$80,0))))),"No",IF($D64>INDEX(Settings!$E$4:$E$80,MATCH($E64,Settings!$A$4:$A$80,0)),"Yes","No")),"")) -> No | H64: =IFERROR(TRIM(INDEX('Raw Data'!$S$5:$S$400,MATCH($B64,'Raw Data'!$H$5:$H$400,0))),"") -> RLN2MA/MY26B014938
A65: =IFERROR(INDEX('Raw Data'!$D$5:$D$400,MATCH($B65,'Raw Data'!$H$5:$H$400,0)),"") -> 46155.342 | B65: WO-0568891 | C65: =IFERROR(TRIM(INDEX('Raw Data'!$J$5:$J$400,MATCH($B65,'Raw Data'!$H$5:$H$400,0))),"") -> Dollar General #21375 | D65: =IFERROR(INDEX('Store List'!$B$4:$B$300,MATCH($C65,'Store List'!$A$4:$A$300,0)),"") -> 46091 | E65: Wrong program | G65: =IF($E65="","",IFERROR(IF(OR(NOT(ISNUMBER($D65)),NOT(ISNUMBER(INDEX(Settings!$E$4:$E$80,MATCH($E65,Settings!$A$4:$A$80,0))))),"No",IF($D65>INDEX(Settings!$E$4:$E$80,MATCH($E65,Settings!$A$4:$A$80,0)),"Yes","No")),"")) -> No | H65: =IFERROR(TRIM(INDEX('Raw Data'!$S$5:$S$400,MATCH($B65,'Raw Data'!$H$5:$H$400,0))),"") -> RLN3MA/MY26B013828
A66: =IFERROR(INDEX('Raw Data'!$D$5:$D$400,MATCH($B66,'Raw Data'!$H$5:$H$400,0)),"") -> 46155.36 | B66: WO-0569146 | C66: =IFERROR(TRIM(INDEX('Raw Data'!$J$5:$J$400,MATCH($B66,'Raw Data'!$H$5:$H$400,0))),"") -> Dollar General #21130 | D66: =IFERROR(INDEX('Store List'!$B$4:$B$300,MATCH($C66,'Store List'!$A$4:$A$300,0)),"") -> 46125 | E66: Drain tube blocked | G66: =IF($E66="","",IFERROR(IF(OR(NOT(ISNUMBER($D66)),NOT(ISNUMBER(INDEX(Settings!$E$4:$E$80,MATCH($E66,Settings!$A$4:$A$80,0))))),"No",IF($D66>INDEX(Settings!$E$4:$E$80,MATCH($E66,Settings!$A$4:$A$80,0)),"Yes","No")),"")) -> No | H66: =IFERROR(TRIM(INDEX('Raw Data'!$S$5:$S$400,MATCH($B66,'Raw Data'!$H$5:$H$400,0))),"") -> RLN3MA/MY26C019887
A67: =IFERROR(INDEX('Raw Data'!$D$5:$D$400,MATCH($B67,'Raw Data'!$H$5:$H$400,0)),"") -> 46159.354 | B67: WO-0571130 | C67: =IFERROR(TRIM(INDEX('Raw Data'!$J$5:$J$400,MATCH($B67,'Raw Data'!$H$5:$H$400,0))),"") -> Dollar General #20597 | D67: =IFERROR(INDEX('Store List'!$B$4:$B$300,MATCH($C67,'Store List'!$A$4:$A$300,0)),"") -> 46134 | E67: Door frame heater | G67: =IF($E67="","",IFERROR(IF(OR(NOT(ISNUMBER($D67)),NOT(ISNUMBER(INDEX(Settings!$E$4:$E$80,MATCH($E67,Settings!$A$4:$A$80,0))))),"No",IF($D67>INDEX(Settings!$E$4:$E$80,MATCH($E67,Settings!$A$4:$A$80,0)),"Yes","No")),"")) -> No | H67: =IFERROR(TRIM(INDEX('Raw Data'!$S$5:$S$400,MATCH($B67,'Raw Data'!$H$5:$H$400,0))),"") -> RLN3MA/MY26B016493
A68: =IFERROR(INDEX('Raw Data'!$D$5:$D$400,MATCH($B68,'Raw Data'!$H$5:$H$400,0)),"") -> 46158.421 | B68: WO-0570321 | C68: =IFERROR(TRIM(INDEX('Raw Data'!$J$5:$J$400,MATCH($B68,'Raw Data'!$H$5:$H$400,0))),"") -> Dollar General #21778 | D68: =IFERROR(INDEX('Store List'!$B$4:$B$300,MATCH($C68,'Store List'!$A$4:$A$300,0)),"") -> 46148 | E68: Drain tube blocked | G68: =IF($E68="","",IFERROR(IF(OR(NOT(ISNUMBER($D68)),NOT(ISNUMBER(INDEX(Settings!$E$4:$E$80,MATCH($E68,Settings!$A$4:$A$80,0))))),"No",IF($D68>INDEX(Settings!$E$4:$E$80,MATCH($E68,Settings!$A$4:$A$80,0)),"Yes","No")),"")) -> No | H68: =IFERROR(TRIM(INDEX('Raw Data'!$S$5:$S$400,MATCH($B68,'Raw Data'!$H$5:$H$400,0))),"") -> RLN3MA/MY26D028107
A69: =IFERROR(INDEX('Raw Data'!$D$5:$D$400,MATCH($B69,'Raw Data'!$H$5:$H$400,0)),"") -> 46157.117 | B69: WO-0570508 | C69: =IFERROR(TRIM(INDEX('Raw Data'!$J$5:$J$400,MATCH($B69,'Raw Data'!$H$5:$H$400,0))),"") -> Dollar General #14928 | D69: =IFERROR(INDEX('Store List'!$B$4:$B$300,MATCH($C69,'Store List'!$A$4:$A$300,0)),"") -> 46154 | E69: Door - general | G69: =IF($E69="","",IFERROR(IF(OR(NOT(ISNUMBER($D69)),NOT(ISNUMBER(INDEX(Settings!$E$4:$E$80,MATCH($E69,Settings!$A$4:$A$80,0))))),"No",IF($D69>INDEX(Settings!$E$4:$E$80,MATCH($E69,Settings!$A$4:$A$80,0)),"Yes","No")),"")) -> No | H69: =IFERROR(TRIM(INDEX('Raw Data'!$S$5:$S$400,MATCH($B69,'Raw Data'!$H$5:$H$400,0))),"") -> RLN2MA/MY26D02809, RLN3MA/MY26D03141
A70: =IFERROR(INDEX('Raw Data'!$D$5:$D$400,MATCH($B70,'Raw Data'!$H$5:$H$400,0)),"") -> 46168.522 | B70: WO-0578039 | C70: =IFERROR(TRIM(INDEX('Raw Data'!$J$5:$J$400,MATCH($B70,'Raw Data'!$H$5:$H$400,0))),"") -> Dollar General #12799 | D70: =IFERROR(INDEX('Store List'!$B$4:$B$300,MATCH($C70,'Store List'!$A$4:$A$300,0)),"") | E70: DG Installation issue | F70: Disaster - move cases | G70: =IF($E70="","",IFERROR(IF(OR(NOT(ISNUMBER($D70)),NOT(ISNUMBER(INDEX(Settings!$E$4:$E$80,MATCH($E70,Settings!$A$4:$A$80,0))))),"No",IF($D70>INDEX(Settings!$E$4:$E$80,MATCH($E70,Settings!$A$4:$A$80,0)),"Yes","No")),"")) -> No | H70: =IFERROR(TRIM(INDEX('Raw Data'!$S$5:$S$400,MATCH($B70,'Raw Data'!$H$5:$H$400,0))),"")
A71: =IFERROR(INDEX('Raw Data'!$D$5:$D$400,MATCH($B71,'Raw Data'!$H$5:$H$400,0)),"") -> 46164.331 | B71: WO-0575409 | C71: =IFERROR(TRIM(INDEX('Raw Data'!$J$5:$J$400,MATCH($B71,'Raw Data'!$H$5:$H$400,0))),"") -> Dollar General #10339 | D71: =IFERROR(INDEX('Store List'!$B$4:$B$300,MATCH($C71,'Store List'!$A$4:$A$300,0)),"") -> 46141 | E71: Drain tube blocked | G71: =IF($E71="","",IFERROR(IF(OR(NOT(ISNUMBER($D71)),NOT(ISNUMBER(INDEX(Settings!$E$4:$E$80,MATCH($E71,Settings!$A$4:$A$80,0))))),"No",IF($D71>INDEX(Settings!$E$4:$E$80,MATCH($E71,Settings!$A$4:$A$80,0)),"Yes","No")),"")) -> No | H71: =IFERROR(TRIM(INDEX('Raw Data'!$S$5:$S$400,MATCH($B71,'Raw Data'!$H$5:$H$400,0))),"") -> RLN2MA/MY26B016459 (same case from 5/5)
A72: =IFERROR(INDEX('Raw Data'!$D$5:$D$400,MATCH($B72,'Raw Data'!$H$5:$H$400,0)),"") -> 46164.252 | B72: WO-0575297 | C72: =IFERROR(TRIM(INDEX('Raw Data'!$J$5:$J$400,MATCH($B72,'Raw Data'!$H$5:$H$400,0))),"") -> Dollar General #19997 | D72: =IFERROR(INDEX('Store List'!$B$4:$B$300,MATCH($C72,'Store List'!$A$4:$A$300,0)),"") -> 46142 | E72: Door Torque | F72: Tech found door torque issue and adjusted it | G72: =IF($E72="","",IFERROR(IF(OR(NOT(ISNUMBER($D72)),NOT(ISNUMBER(INDEX(Settings!$E$4:$E$80,MATCH($E72,Settings!$A$4:$A$80,0))))),"No",IF($D72>INDEX(Settings!$E$4:$E$80,MATCH($E72,Settings!$A$4:$A$80,0)),"Yes","No")),"")) -> No | H72: =IFERROR(TRIM(INDEX('Raw Data'!$S$5:$S$400,MATCH($B72,'Raw Data'!$H$5:$H$400,0))),"") -> RMN4MA/MY26B016517
A73: =IFERROR(INDEX('Raw Data'!$D$5:$D$400,MATCH($B73,'Raw Data'!$H$5:$H$400,0)),"") -> 46162.528 | B73: WO-0573996 | C73: =IFERROR(TRIM(INDEX('Raw Data'!$J$5:$J$400,MATCH($B73,'Raw Data'!$H$5:$H$400,0))),"") -> Dollar General #20107 | D73: =IFERROR(INDEX('Store List'!$B$4:$B$300,MATCH($C73,'Store List'!$A$4:$A$300,0)),"") -> 46148 | E73: Program change - Hussmann | G73: =IF($E73="","",IFERROR(IF(OR(NOT(ISNUMBER($D73)),NOT(ISNUMBER(INDEX(Settings!$E$4:$E$80,MATCH($E73,Settings!$A$4:$A$80,0))))),"No",IF($D73>INDEX(Settings!$E$4:$E$80,MATCH($E73,Settings!$A$4:$A$80,0)),"Yes","No")),"")) -> No | H73: =IFERROR(TRIM(INDEX('Raw Data'!$S$5:$S$400,MATCH($B73,'Raw Data'!$H$5:$H$400,0))),"") -> RLN2MA/MY26B015992 (not pulling up in PP)
A74: =IFERROR(INDEX('Raw Data'!$D$5:$D$400,MATCH($B74,'Raw Data'!$H$5:$H$400,0)),"") -> 46162.097 | B74: WO-0574005 | C74: =IFERROR(TRIM(INDEX('Raw Data'!$J$5:$J$400,MATCH($B74,'Raw Data'!$H$5:$H$400,0))),"") -> Dollar General #21223 | D74: =IFERROR(INDEX('Store List'!$B$4:$B$300,MATCH($C74,'Store List'!$A$4:$A$300,0)),"") -> 46120 | E74: DG Installation issue | G74: =IF($E74="","",IFERROR(IF(OR(NOT(ISNUMBER($D74)),NOT(ISNUMBER(INDEX(Settings!$E$4:$E$80,MATCH($E74,Settings!$A$4:$A$80,0))))),"No",IF($D74>INDEX(Settings!$E$4:$E$80,MATCH($E74,Settings!$A$4:$A$80,0)),"Yes","No")),"")) -> No | H74: =IFERROR(TRIM(INDEX('Raw Data'!$S$5:$S$400,MATCH($B74,'Raw Data'!$H$5:$H$400,0))),"") -> RLN2MA MY26B014946
A75: =IFERROR(INDEX('Raw Data'!$D$5:$D$400,MATCH($B75,'Raw Data'!$H$5:$H$400,0)),"") -> 46160.247 | B75: WO-0572389 | C75: =IFERROR(TRIM(INDEX('Raw Data'!$J$5:$J$400,MATCH($B75,'Raw Data'!$H$5:$H$400,0))),"") -> Dollar General #7231 | D75: =IFERROR(INDEX('Store List'!$B$4:$B$300,MATCH($C75,'Store List'!$A$4:$A$300,0)),"") | E75: Freedom | G75: =IF($E75="","",IFERROR(IF(OR(NOT(ISNUMBER($D75)),NOT(ISNUMBER(INDEX(Settings!$E$4:$E$80,MATCH($E75,Settings!$A$4:$A$80,0))))),"No",IF($D75>INDEX(Settings!$E$4:$E$80,MATCH($E75,Settings!$A$4:$A$80,0)),"Yes","No")),"")) -> No | H75: =IFERROR(TRIM(INDEX('Raw Data'!$S$5:$S$400,MATCH($B75,'Raw Data'!$H$5:$H$400,0))),"")
A76: =IFERROR(INDEX('Raw Data'!$D$5:$D$400,MATCH($B76,'Raw Data'!$H$5:$H$400,0)),"") -> 46171.399 | B76: WO-0580073 | C76: =IFERROR(TRIM(INDEX('Raw Data'!$J$5:$J$400,MATCH($B76,'Raw Data'!$H$5:$H$400,0))),"") -> Dollar General #20582 | D76: =IFERROR(INDEX('Store List'!$B$4:$B$300,MATCH($C76,'Store List'!$A$4:$A$300,0)),"") -> 46098 | E76: Door Torque | F76: Tech found door torque issue and adjusted it | G76: =IF($E76="","",IFERROR(IF(OR(NOT(ISNUMBER($D76)),NOT(ISNUMBER(INDEX(Settings!$E$4:$E$80,MATCH($E76,Settings!$A$4:$A$80,0))))),"No",IF($D76>INDEX(Settings!$E$4:$E$80,MATCH($E76,Settings!$A$4:$A$80,0)),"Yes","No")),"")) -> No | H76: =IFERROR(TRIM(INDEX('Raw Data'!$S$5:$S$400,MATCH($B76,'Raw Data'!$H$5:$H$400,0))),"") -> RLN3MA/MY26B014956
A77: =IFERROR(INDEX('Raw Data'!$D$5:$D$400,MATCH($B77,'Raw Data'!$H$5:$H$400,0)),"") -> 46172.206 | B77: WO-0580974 | C77: =IFERROR(TRIM(INDEX('Raw Data'!$J$5:$J$400,MATCH($B77,'Raw Data'!$H$5:$H$400,0))),"") -> Dollar General #21415 | D77: =IFERROR(INDEX('Store List'!$B$4:$B$300,MATCH($C77,'Store List'!$A$4:$A$300,0)),"") -> 46170 | E77: Freedom | F77: NA | G77: =IF($E77="","",IFERROR(IF(OR(NOT(ISNUMBER($D77)),NOT(ISNUMBER(INDEX(Settings!$E$4:$E$80,MATCH($E77,Settings!$A$4:$A$80,0))))),"No",IF($D77>INDEX(Settings!$E$4:$E$80,MATCH($E77,Settings!$A$4:$A$80,0)),"Yes","No")),"")) -> No | H77: =IFERROR(TRIM(INDEX('Raw Data'!$S$5:$S$400,MATCH($B77,'Raw Data'!$H$5:$H$400,0))),"")
A78: =IFERROR(INDEX('Raw Data'!$D$5:$D$400,MATCH($B78,'Raw Data'!$H$5:$H$400,0)),"") -> 46172.146 | B78: WO-0580946 | C78: =IFERROR(TRIM(INDEX('Raw Data'!$J$5:$J$400,MATCH($B78,'Raw Data'!$H$5:$H$400,0))),"") -> Dollar General #6372 | D78: =IFERROR(INDEX('Store List'!$B$4:$B$300,MATCH($C78,'Store List'!$A$4:$A$300,0)),"") -> 46126 | E78: Unknown | F78: All MB cases in one store | G78: =IF($E78="","",IFERROR(IF(OR(NOT(ISNUMBER($D78)),NOT(ISNUMBER(INDEX(Settings!$E$4:$E$80,MATCH($E78,Settings!$A$4:$A$80,0))))),"No",IF($D78>INDEX(Settings!$E$4:$E$80,MATCH($E78,Settings!$A$4:$A$80,0)),"Yes","No")),"")) -> No | H78: =IFERROR(TRIM(INDEX('Raw Data'!$S$5:$S$400,MATCH($B78,'Raw Data'!$H$5:$H$400,0))),"") -> RLN3MA/MY26C019883, RMN4MA/MY26B016031
A79: =IFERROR(INDEX('Raw Data'!$D$5:$D$400,MATCH($B79,'Raw Data'!$H$5:$H$400,0)),"") -> 46171.192 | B79: WO-0580512 | C79: =IFERROR(TRIM(INDEX('Raw Data'!$J$5:$J$400,MATCH($B79,'Raw Data'!$H$5:$H$400,0))),"") -> Dollar General #14347 | D79: =IFERROR(INDEX('Store List'!$B$4:$B$300,MATCH($C79,'Store List'!$A$4:$A$300,0)),"") -> 46134 | E79: Drain tube blocked | F79: No case noms. But before clean point | G79: =IF($E79="","",IFERROR(IF(OR(NOT(ISNUMBER($D79)),NOT(ISNUMBER(INDEX(Settings!$E$4:$E$80,MATCH($E79,Settings!$A$4:$A$80,0))))),"No",IF($D79>INDEX(Settings!$E$4:$E$80,MATCH($E79,Settings!$A$4:$A$80,0)),"Yes","No")),"")) -> No | H79: =IFERROR(TRIM(INDEX('Raw Data'!$S$5:$S$400,MATCH($B79,'Raw Data'!$H$5:$H$400,0))),"")
A80: =IFERROR(INDEX('Raw Data'!$D$5:$D$400,MATCH($B80,'Raw Data'!$H$5:$H$400,0)),"") -> 46171.192 | B80: WO-0580512 | C80: =IFERROR(TRIM(INDEX('Raw Data'!$J$5:$J$400,MATCH($B80,'Raw Data'!$H$5:$H$400,0))),"") -> Dollar General #14347 | D80: =IFERROR(INDEX('Store List'!$B$4:$B$300,MATCH($C80,'Store List'!$A$4:$A$300,0)),"") -> 46134 | E80: Freedom | F80: NA | G80: =IF($E80="","",IFERROR(IF(OR(NOT(ISNUMBER($D80)),NOT(ISNUMBER(INDEX(Settings!$E$4:$E$80,MATCH($E80,Settings!$A$4:$A$80,0))))),"No",IF($D80>INDEX(Settings!$E$4:$E$80,MATCH($E80,Settings!$A$4:$A$80,0)),"Yes","No")),"")) -> No | H80: =IFERROR(TRIM(INDEX('Raw Data'!$S$5:$S$400,MATCH($B80,'Raw Data'!$H$5:$H$400,0))),"")
A81: =IFERROR(INDEX('Raw Data'!$D$5:$D$400,MATCH($B81,'Raw Data'!$H$5:$H$400,0)),"") -> 46181.537 | B81: WO-0586550 | C81: =IFERROR(TRIM(INDEX('Raw Data'!$J$5:$J$400,MATCH($B81,'Raw Data'!$H$5:$H$400,0))),"") -> Dollar General #2600 | D81: =IFERROR(INDEX('Store List'!$B$4:$B$300,MATCH($C81,'Store List'!$A$4:$A$300,0)),"") -> 46169 | E81: Setpoint change | F81: One unit was set 5 degress higher than the other. | G81: =IF($E81="","",IFERROR(IF(OR(NOT(ISNUMBER($D81)),NOT(ISNUMBER(INDEX(Settings!$E$4:$E$80,MATCH($E81,Settings!$A$4:$A$80,0))))),"No",IF($D81>INDEX(Settings!$E$4:$E$80,MATCH($E81,Settings!$A$4:$A$80,0)),"Yes","No")),"")) -> Yes | H81: =IFERROR(TRIM(INDEX('Raw Data'!$S$5:$S$400,MATCH($B81,'Raw Data'!$H$5:$H$400,0))),"") -> RMN3MA/MY26D026820
A82: =IFERROR(INDEX('Raw Data'!$D$5:$D$400,MATCH($B82,'Raw Data'!$H$5:$H$400,0)),"") -> 46180.356 | B82: WO-0585699 | C82: =IFERROR(TRIM(INDEX('Raw Data'!$J$5:$J$400,MATCH($B82,'Raw Data'!$H$5:$H$400,0))),"") -> Dollar General #3277 | D82: =IFERROR(INDEX('Store List'!$B$4:$B$300,MATCH($C82,'Store List'!$A$4:$A$300,0)),"") -> 46149 | E82: Door not closed (Overnight) | F82: Per data the door was open. But tech has cleaned the evaporator to deiced | G82: =IF($E82="","",IFERROR(IF(OR(NOT(ISNUMBER($D82)),NOT(ISNUMBER(INDEX(Settings!$E$4:$E$80,MATCH($E82,Settings!$A$4:$A$80,0))))),"No",IF($D82>INDEX(Settings!$E$4:$E$80,MATCH($E82,Settings!$A$4:$A$80,0)),"Yes","No")),"")) -> No | H82: =IFERROR(TRIM(INDEX('Raw Data'!$S$5:$S$400,MATCH($B82,'Raw Data'!$H$5:$H$400,0))),"") -> RLN3MA/MY26D028108
A83: =IFERROR(INDEX('Raw Data'!$D$5:$D$400,MATCH($B83,'Raw Data'!$H$5:$H$400,0)),"") -> 46178.185 | B83: WO-0584971 | C83: =IFERROR(TRIM(INDEX('Raw Data'!$J$5:$J$400,MATCH($B83,'Raw Data'!$H$5:$H$400,0))),"") -> Dollar General #1247 | D83: =IFERROR(INDEX('Store List'!$B$4:$B$300,MATCH($C83,'Store List'!$A$4:$A$300,0)),"") -> 46174 | E83: Ref. leak/ Low charge | F83: Cassettes were replaced. Tech pierced cassettes and figured they are low on refrigerant | G83: =IF($E83="","",IFERROR(IF(OR(NOT(ISNUMBER($D83)),NOT(ISNUMBER(INDEX(Settings!$E$4:$E$80,MATCH($E83,Settings!$A$4:$A$80,0))))),"No",IF($D83>INDEX(Settings!$E$4:$E$80,MATCH($E83,Settings!$A$4:$A$80,0)),"Yes","No")),"")) -> Yes | H83: =IFERROR(TRIM(INDEX('Raw Data'!$S$5:$S$400,MATCH($B83,'Raw Data'!$H$5:$H$400,0))),"") -> RLN4MA/MY26C019909
A84: =IFERROR(INDEX('Raw Data'!$D$5:$D$400,MATCH($B84,'Raw Data'!$H$5:$H$400,0)),"") -> 46177.438 | B84: WO-0583967 | C84: =IFERROR(TRIM(INDEX('Raw Data'!$J$5:$J$400,MATCH($B84,'Raw Data'!$H$5:$H$400,0))),"") -> Dollar General #21342 | D84: =IFERROR(INDEX('Store List'!$B$4:$B$300,MATCH($C84,'Store List'!$A$4:$A$300,0)),"") -> 46122 | E84: Freedom | F84: Found issue with pumps on freedom cases | G84: =IF($E84="","",IFERROR(IF(OR(NOT(ISNUMBER($D84)),NOT(ISNUMBER(INDEX(Settings!$E$4:$E$80,MATCH($E84,Settings!$A$4:$A$80,0))))),"No",IF($D84>INDEX(Settings!$E$4:$E$80,MATCH($E84,Settings!$A$4:$A$80,0)),"Yes","No")),"")) -> No | H84: =IFERROR(TRIM(INDEX('Raw Data'!$S$5:$S$400,MATCH($B84,'Raw Data'!$H$5:$H$400,0))),"") -> RLN2MA/MY26C019880
A85: =IFERROR(INDEX('Raw Data'!$D$5:$D$400,MATCH($B85,'Raw Data'!$H$5:$H$400,0)),"") -> 46176.926 | B85: WO-0583750 | C85: =IFERROR(TRIM(INDEX('Raw Data'!$J$5:$J$400,MATCH($B85,'Raw Data'!$H$5:$H$400,0))),"") -> Dollar General #1247 | D85: =IFERROR(INDEX('Store List'!$B$4:$B$300,MATCH($C85,'Store List'!$A$4:$A$300,0)),"") -> 46174 | E85: Ref. leak/ Low charge | F85: Tech notes about cassette replacement. No more details. | G85: =IF($E85="","",IFERROR(IF(OR(NOT(ISNUMBER($D85)),NOT(ISNUMBER(INDEX(Settings!$E$4:$E$80,MATCH($E85,Settings!$A$4:$A$80,0))))),"No",IF($D85>INDEX(Settings!$E$4:$E$80,MATCH($E85,Settings!$A$4:$A$80,0)),"Yes","No")),"")) -> Yes | H85: =IFERROR(TRIM(INDEX('Raw Data'!$S$5:$S$400,MATCH($B85,'Raw Data'!$H$5:$H$400,0))),"") -> RMN4MA/MY26B016036
A86: =IFERROR(INDEX('Raw Data'!$D$5:$D$400,MATCH($B86,'Raw Data'!$H$5:$H$400,0)),"") -> 46176.403 | B86: WO-0583216 | C86: =IFERROR(TRIM(INDEX('Raw Data'!$J$5:$J$400,MATCH($B86,'Raw Data'!$H$5:$H$400,0))),"") -> Dollar General #20336 | D86: =IFERROR(INDEX('Store List'!$B$4:$B$300,MATCH($C86,'Store List'!$A$4:$A$300,0)),"") -> 46126 | E86: False Alarm | F86: Case data seems good. Tech's comments say he cant find anything wrong with the case | G86: =IF($E86="","",IFERROR(IF(OR(NOT(ISNUMBER($D86)),NOT(ISNUMBER(INDEX(Settings!$E$4:$E$80,MATCH($E86,Settings!$A$4:$A$80,0))))),"No",IF($D86>INDEX(Settings!$E$4:$E$80,MATCH($E86,Settings!$A$4:$A$80,0)),"Yes","No")),"")) -> No | H86: =IFERROR(TRIM(INDEX('Raw Data'!$S$5:$S$400,MATCH($B86,'Raw Data'!$H$5:$H$400,0))),"") -> RLN2MA/MY26B015996 | I86: fexa
A87: =IFERROR(INDEX('Raw Data'!$D$5:$D$400,MATCH($B87,'Raw Data'!$H$5:$H$400,0)),"") -> 46175.419 | B87: WO-0583040 | C87: =IFERROR(TRIM(INDEX('Raw Data'!$J$5:$J$400,MATCH($B87,'Raw Data'!$H$5:$H$400,0))),"") -> Dollar General #20440 | D87: =IFERROR(INDEX('Store List'!$B$4:$B$300,MATCH($C87,'Store List'!$A$4:$A$300,0)),"") -> 46161 | E87: Door frame heater | F87: Door heater plug was not fully plugged in | G87: =IF($E87="","",IFERROR(IF(OR(NOT(ISNUMBER($D87)),NOT(ISNUMBER(INDEX(Settings!$E$4:$E$80,MATCH($E87,Settings!$A$4:$A$80,0))))),"No",IF($D87>INDEX(Settings!$E$4:$E$80,MATCH($E87,Settings!$A$4:$A$80,0)),"Yes","No")),"")) -> No | H87: =IFERROR(TRIM(INDEX('Raw Data'!$S$5:$S$400,MATCH($B87,'Raw Data'!$H$5:$H$400,0))),"") -> RLN3MA/MY26B016036
A88: =IFERROR(INDEX('Raw Data'!$D$5:$D$400,MATCH($B88,'Raw Data'!$H$5:$H$400,0)),"") -> 46175.419 | B88: WO-0583039 | C88: =IFERROR(TRIM(INDEX('Raw Data'!$J$5:$J$400,MATCH($B88,'Raw Data'!$H$5:$H$400,0))),"") -> Dollar General #21709 | D88: =IFERROR(INDEX('Store List'!$B$4:$B$300,MATCH($C88,'Store List'!$A$4:$A$300,0)),"") -> 46169 | E88: False Alarm | F88: Store connect cancelled this dispatch | G88: =IF($E88="","",IFERROR(IF(OR(NOT(ISNUMBER($D88)),NOT(ISNUMBER(INDEX(Settings!$E$4:$E$80,MATCH($E88,Settings!$A$4:$A$80,0))))),"No",IF($D88>INDEX(Settings!$E$4:$E$80,MATCH($E88,Settings!$A$4:$A$80,0)),"Yes","No")),"")) -> Yes | H88: =IFERROR(TRIM(INDEX('Raw Data'!$S$5:$S$400,MATCH($B88,'Raw Data'!$H$5:$H$400,0))),"") -> RLN2MA/MY26B016465
A89: =IFERROR(INDEX('Raw Data'!$D$5:$D$400,MATCH($B89,'Raw Data'!$H$5:$H$400,0)),"") -> 46183 | B89: WO-0588157 | C89: =IFERROR(TRIM(INDEX('Raw Data'!$J$5:$J$400,MATCH($B89,'Raw Data'!$H$5:$H$400,0))),"") -> Dollar General # 13069 | D89: =IFERROR(INDEX('Store List'!$B$4:$B$300,MATCH($C89,'Store List'!$A$4:$A$300,0)),"") -> 46127 | E89: Door not closed (Overnight) | F89: Worked perfectly fine until the door never got closed on Jun 9th. Door Closed on jun 10th and its working fine after that | G89: =IF($E89="","",IFERROR(IF(OR(NOT(ISNUMBER($D89)),NOT(ISNUMBER(INDEX(Settings!$E$4:$E$80,MATCH($E89,Settings!$A$4:$A$80,0))))),"No",IF($D89>INDEX(Settings!$E$4:$E$80,MATCH($E89,Settings!$A$4:$A$80,0)),"Yes","No")),"")) -> No | H89: =IFERROR(TRIM(INDEX('Raw Data'!$S$5:$S$400,MATCH($B89,'Raw Data'!$H$5:$H$400,0))),"") -> RMN4MA/MY26B014985
A90: =IFERROR(INDEX('Raw Data'!$D$5:$D$400,MATCH($B90,'Raw Data'!$H$5:$H$400,0)),"") -> 46182.395 | B90: WO-0587865 | C90: =IFERROR(TRIM(INDEX('Raw Data'!$J$5:$J$400,MATCH($B90,'Raw Data'!$H$5:$H$400,0))),"") -> Dollar General #14341 | D90: =IFERROR(INDEX('Store List'!$B$4:$B$300,MATCH($C90,'Store List'!$A$4:$A$300,0)),"") -> 46132 | E90: Wrong / Loose wiring | F90: No power to hot gas defrost solenoid. Tech fixed it and everything worked fine | G90: =IF($E90="","",IFERROR(IF(OR(NOT(ISNUMBER($D90)),NOT(ISNUMBER(INDEX(Settings!$E$4:$E$80,MATCH($E90,Settings!$A$4:$A$80,0))))),"No",IF($D90>INDEX(Settings!$E$4:$E$80,MATCH($E90,Settings!$A$4:$A$80,0)),"Yes","No")),"")) -> Yes | H90: =IFERROR(TRIM(INDEX('Raw Data'!$S$5:$S$400,MATCH($B90,'Raw Data'!$H$5:$H$400,0))),"") -> RLN3MA/MY26B016495
A91: =IFERROR(INDEX('Raw Data'!$D$5:$D$400,MATCH($B91,'Raw Data'!$H$5:$H$400,0)),"") -> 46182.188 | B91: WO-0587673 | C91: =IFERROR(TRIM(INDEX('Raw Data'!$J$5:$J$400,MATCH($B91,'Raw Data'!$H$5:$H$400,0))),"") -> Dollar General #22799 | D91: =IFERROR(INDEX('Store List'!$B$4:$B$300,MATCH($C91,'Store List'!$A$4:$A$300,0)),"") -> 46099 | E91: Door frame heater | F91: Tech notes: Found case lights wired into the door heater controller fixed wiring and got lights on and door hearts wired correctly | G91: =IF($E91="","",IFERROR(IF(OR(NOT(ISNUMBER($D91)),NOT(ISNUMBER(INDEX(Settings!$E$4:$E$80,MATCH($E91,Settings!$A$4:$A$80,0))))),"No",IF($D91>INDEX(Settings!$E$4:$E$80,MATCH($E91,Settings!$A$4:$A$80,0)),"Yes","No")),"")) -> No | H91: =IFERROR(TRIM(INDEX('Raw Data'!$S$5:$S$400,MATCH($B91,'Raw Data'!$H$5:$H$400,0))),"") -> RLN3MA/MY26B016006
G92: =IF($E92="","",IFERROR(IF(OR(NOT(ISNUMBER($D92)),NOT(ISNUMBER(INDEX(Settings!$E$4:$E$80,MATCH($E92,Settings!$A$4:$A$80,0))))),"No",IF($D92>INDEX(Settings!$E$4:$E$80,MATCH($E92,Settings!$A$4:$A$80,0)),"Yes","No")),""))
A93: =IFERROR(INDEX('Raw Data'!$D$5:$D$400,MATCH($B93,'Raw Data'!$H$5:$H$400,0)),"") -> 46181.424 | B93: WO-0586308 | C93: =IFERROR(TRIM(INDEX('Raw Data'!$J$5:$J$400,MATCH($B93,'Raw Data'!$H$5:$H$400,0))),"") -> Dollar General #20654 | D93: =IFERROR(INDEX('Store List'!$B$4:$B$300,MATCH($C93,'Store List'!$A$4:$A$300,0)),"") -> 46106 | E93: Door Gasket | F93: Notes mentioned a new gasket is needed. | G93: =IF($E93="","",IFERROR(IF(OR(NOT(ISNUMBER($D93)),NOT(ISNUMBER(INDEX(Settings!$E$4:$E$80,MATCH($E93,Settings!$A$4:$A$80,0))))),"No",IF($D93>INDEX(Settings!$E$4:$E$80,MATCH($E93,Settings!$A$4:$A$80,0)),"Yes","No")),"")) -> No | H93: =IFERROR(TRIM(INDEX('Raw Data'!$S$5:$S$400,MATCH($B93,'Raw Data'!$H$5:$H$400,0))),"") -> RLN2MA/MY26B016474
A94: =IFERROR(INDEX('Raw Data'!$D$5:$D$400,MATCH($B94,'Raw Data'!$H$5:$H$400,0)),"") -> 46181.335 | B94: WO-0586957 | C94: =IFERROR(TRIM(INDEX('Raw Data'!$J$5:$J$400,MATCH($B94,'Raw Data'!$H$5:$H$400,0))),"") -> Dollar General #20761 | D94: =IFERROR(INDEX('Store List'!$B$4:$B$300,MATCH($C94,'Store List'!$A$4:$A$300,0)),"") -> 46106 | E94: False Alarm | F94: Tech says he observed low ref. operation condition. But this MT case has been pulling down to temp before tech got there and the compressor is also cycling. | G94: =IF($E94="","",IFERROR(IF(OR(NOT(ISNUMBER($D94)),NOT(ISNUMBER(INDEX(Settings!$E$4:$E$80,MATCH($E94,Settings!$A$4:$A$80,0))))),"No",IF($D94>INDEX(Settings!$E$4:$E$80,MATCH($E94,Settings!$A$4:$A$80,0)),"Yes","No")),"")) -> No | H94: =IFERROR(TRIM(INDEX('Raw Data'!$S$5:$S$400,MATCH($B94,'Raw Data'!$H$5:$H$400,0))),"") -> RMN4MA/MY26B016036 | I94: fexa
A95: =IFERROR(INDEX('Raw Data'!$D$5:$D$400,MATCH($B95,'Raw Data'!$H$5:$H$400,0)),"") -> 46186.342 | B95: WO-0590801 | C95: =IFERROR(TRIM(INDEX('Raw Data'!$J$5:$J$400,MATCH($B95,'Raw Data'!$H$5:$H$400,0))),"") -> Dollar General #13396 | D95: =IFERROR(INDEX('Store List'!$B$4:$B$300,MATCH($C95,'Store List'!$A$4:$A$300,0)),"") -> 46141 | E95: High Store RH | F95: Store connect dispatched this. Store was running high ambient then. No more such dispatches will happen until store ambient is fixed. | G95: =IF($E95="","",IFERROR(IF(OR(NOT(ISNUMBER($D95)),NOT(ISNUMBER(INDEX(Settings!$E$4:$E$80,MATCH($E95,Settings!$A$4:$A$80,0))))),"No",IF($D95>INDEX(Settings!$E$4:$E$80,MATCH($E95,Settings!$A$4:$A$80,0)),"Yes","No")),"")) -> No | H95: =IFERROR(TRIM(INDEX('Raw Data'!$S$5:$S$400,MATCH($B95,'Raw Data'!$H$5:$H$400,0))),"") -> RLN2MA/MY26B016003
A96: =IFERROR(INDEX('Raw Data'!$D$5:$D$400,MATCH($B96,'Raw Data'!$H$5:$H$400,0)),"") -> 46185.452 | B96: WO-0590856 | C96: =IFERROR(TRIM(INDEX('Raw Data'!$J$5:$J$400,MATCH($B96,'Raw Data'!$H$5:$H$400,0))),"") -> Dollar General #22286 | D96: =IFERROR(INDEX('Store List'!$B$4:$B$300,MATCH($C96,'Store List'!$A$4:$A$300,0)),"") -> 46099 | E96: False Alarm | F96: Cant see any issue with this. Defrost seems fine, case seems to be pulling down. All tech did was force a defrost and left. Everything running exactly how it did before. | G96: =IF($E96="","",IFERROR(IF(OR(NOT(ISNUMBER($D96)),NOT(ISNUMBER(INDEX(Settings!$E$4:$E$80,MATCH($E96,Settings!$A$4:$A$80,0))))),"No",IF($D96>INDEX(Settings!$E$4:$E$80,MATCH($E96,Settings!$A$4:$A$80,0)),"Yes","No")),"")) -> No | H96: =IFERROR(TRIM(INDEX('Raw Data'!$S$5:$S$400,MATCH($B96,'Raw Data'!$H$5:$H$400,0))),"") -> RMN4MA/MY26B016036 | I96: fexa
A97: =IFERROR(INDEX('Raw Data'!$D$5:$D$400,MATCH($B97,'Raw Data'!$H$5:$H$400,0)),"") -> 46185.39 | B97: WO-0589971 | C97: =IFERROR(TRIM(INDEX('Raw Data'!$J$5:$J$400,MATCH($B97,'Raw Data'!$H$5:$H$400,0))),"") -> Dollar General #11509 | D97: =IFERROR(INDEX('Store List'!$B$4:$B$300,MATCH($C97,'Store List'!$A$4:$A$300,0)),"") -> 46161 | E97: DG Installation issue | F97: All cases freedom and MD lost communication from Jun 10 4pm to jun 13 1pm | G97: =IF($E97="","",IFERROR(IF(OR(NOT(ISNUMBER($D97)),NOT(ISNUMBER(INDEX(Settings!$E$4:$E$80,MATCH($E97,Settings!$A$4:$A$80,0))))),"No",IF($D97>INDEX(Settings!$E$4:$E$80,MATCH($E97,Settings!$A$4:$A$80,0)),"Yes","No")),"")) -> No | H97: =IFERROR(TRIM(INDEX('Raw Data'!$S$5:$S$400,MATCH($B97,'Raw Data'!$H$5:$H$400,0))),"") -> MY26B016494, RMN4MA/MY26B016536
A98: =IFERROR(INDEX('Raw Data'!$D$5:$D$400,MATCH($B98,'Raw Data'!$H$5:$H$400,0)),"") -> 46185.326 | B98: WO-0589876 | C98: =IFERROR(TRIM(INDEX('Raw Data'!$J$5:$J$400,MATCH($B98,'Raw Data'!$H$5:$H$400,0))),"") -> Dollar General #22982 | D98: =IFERROR(INDEX('Store List'!$B$4:$B$300,MATCH($C98,'Store List'!$A$4:$A$300,0)),"") -> 46126 | E98: DG Installation issue | F98: All freedom/MB cases in store are disconnected | G98: =IF($E98="","",IFERROR(IF(OR(NOT(ISNUMBER($D98)),NOT(ISNUMBER(INDEX(Settings!$E$4:$E$80,MATCH($E98,Settings!$A$4:$A$80,0))))),"No",IF($D98>INDEX(Settings!$E$4:$E$80,MATCH($E98,Settings!$A$4:$A$80,0)),"Yes","No")),"")) -> No | H98: =IFERROR(TRIM(INDEX('Raw Data'!$S$5:$S$400,MATCH($B98,'Raw Data'!$H$5:$H$400,0))),"") -> RLN3MA/MY26B016502, MY26B016013, RLN4MA/MY26B014967
A99: =IFERROR(INDEX('Raw Data'!$D$5:$D$400,MATCH($B99,'Raw Data'!$H$5:$H$400,0)),"") -> 46185.283 | B99: WO-0590766 | C99: =IFERROR(TRIM(INDEX('Raw Data'!$J$5:$J$400,MATCH($B99,'Raw Data'!$H$5:$H$400,0))),"") -> Dollar General #21778 | D99: =IFERROR(INDEX('Store List'!$B$4:$B$300,MATCH($C99,'Store List'!$A$4:$A$300,0)),"") -> 46148 | E99: Drain tube blocked | F99: Has been getting good defrost for sure. Case temp is good too. No info from tech. Only thing I can think of that can cause water leak is blocked drain tube | G99: =IF($E99="","",IFERROR(IF(OR(NOT(ISNUMBER($D99)),NOT(ISNUMBER(INDEX(Settings!$E$4:$E$80,MATCH($E99,Settings!$A$4:$A$80,0))))),"No",IF($D99>INDEX(Settings!$E$4:$E$80,MATCH($E99,Settings!$A$4:$A$80,0)),"Yes","No")),"")) -> No | H99: =IFERROR(TRIM(INDEX('Raw Data'!$S$5:$S$400,MATCH($B99,'Raw Data'!$H$5:$H$400,0))),"") -> RLN3MA/MY26D028107
A100: =IFERROR(INDEX('Raw Data'!$D$5:$D$400,MATCH($B100,'Raw Data'!$H$5:$H$400,0)),"") -> 46185.274 | B100: WO-0589851 | C100: =IFERROR(TRIM(INDEX('Raw Data'!$J$5:$J$400,MATCH($B100,'Raw Data'!$H$5:$H$400,0))),"") -> Dollar General #22281 | D100: =IFERROR(INDEX('Store List'!$B$4:$B$300,MATCH($C100,'Store List'!$A$4:$A$300,0)),"") -> 46118 | E100: Communication problem | F100: Comm loss. All cases lost connection at the same time on all cases | G100: =IF($E100="","",IFERROR(IF(OR(NOT(ISNUMBER($D100)),NOT(ISNUMBER(INDEX(Settings!$E$4:$E$80,MATCH($E100,Settings!$A$4:$A$80,0))))),"No",IF($D100>INDEX(Settings!$E$4:$E$80,MATCH($E100,Settings!$A$4:$A$80,0)),"Yes","No")),"")) -> No | H100: =IFERROR(TRIM(INDEX('Raw Data'!$S$5:$S$400,MATCH($B100,'Raw Data'!$H$5:$H$400,0))),"") -> RLN2MA/MY26C019876, MY26B016513, MY26B16019
A101: =IFERROR(INDEX('Raw Data'!$D$5:$D$400,MATCH($B101,'Raw Data'!$H$5:$H$400,0)),"") -> 46184.377 | B101: WO-0588967 | C101: =IFERROR(TRIM(INDEX('Raw Data'!$J$5:$J$400,MATCH($B101,'Raw Data'!$H$5:$H$400,0))),"") -> Dollar General #22286 | D101: =IFERROR(INDEX('Store List'!$B$4:$B$300,MATCH($C101,'Store List'!$A$4:$A$300,0)),"") -> 46099 | E101: Door Torque | F101: Eng sent this. Tech didn’t do any air leak testing which is why he was sent in the first place. He adjusted the defrost time but I have seen 45min defrost on this case from before he came in. There are some remote defrost changes done from pulse on jun 3. I'll check with Chris tomorrow. | G101: =IF($E101="","",IFERROR(IF(OR(NOT(ISNUMBER($D101)),NOT(ISNUMBER(INDEX(Settings!$E$4:$E$80,MATCH($E101,Settings!$A$4:$A$80,0))))),"No",IF($D101>INDEX(Settings!$E$4:$E$80,MATCH($E101,Settings!$A$4:$A$80,0)),"Yes","No")),"")) -> No | H101: =IFERROR(TRIM(INDEX('Raw Data'!$S$5:$S$400,MATCH($B101,'Raw Data'!$H$5:$H$400,0))),"") -> RLN2MA/MY26B014938
A102: =IFERROR(INDEX('Raw Data'!$D$5:$D$400,MATCH($B102,'Raw Data'!$H$5:$H$400,0)),"") -> 46184.052 | B102: WO-5089345 | C102: =IFERROR(TRIM(INDEX('Raw Data'!$J$5:$J$400,MATCH($B102,'Raw Data'!$H$5:$H$400,0))),"") -> Dollar General #16435 | D102: =IFERROR(INDEX('Store List'!$B$4:$B$300,MATCH($C102,'Store List'!$A$4:$A$300,0)),"") -> 46106 | E102: DG Installation issue | F102: All cases (Freedom/Microblock) had power loss starting April 1st. Tech was able to get the power back on for the microblock cases but freedom still does not show any data. Tech's comments were that DG should have their contractors come take a look at the electrical | G102: =IF($E102="","",IFERROR(IF(OR(NOT(ISNUMBER($D102)),NOT(ISNUMBER(INDEX(Settings!$E$4:$E$80,MATCH($E102,Settings!$A$4:$A$80,0))))),"No",IF($D102>INDEX(Settings!$E$4:$E$80,MATCH($E102,Settings!$A$4:$A$80,0)),"Yes","No")),"")) -> No | H102: =IFERROR(TRIM(INDEX('Raw Data'!$S$5:$S$400,MATCH($B102,'Raw Data'!$H$5:$H$400,0))),"") -> RMN4MA/MY26B013841
A103: =IFERROR(INDEX('Raw Data'!$D$5:$D$400,MATCH($B103,'Raw Data'!$H$5:$H$400,0)),"") -> 46184 | B103: WO-0589359 | C103: =IFERROR(TRIM(INDEX('Raw Data'!$J$5:$J$400,MATCH($B103,'Raw Data'!$H$5:$H$400,0))),"") -> Dollar General #21135 | D103: =IFERROR(INDEX('Store List'!$B$4:$B$300,MATCH($C103,'Store List'!$A$4:$A$300,0)),"") -> 46106 | E103: Door Torque | F103: Tech had to adjust door torque on 3 doors MT Case. The drain pan was full of water (probably because of excessive humidity into the case). The compressor discharge seems to be steady from the beginning. Don’t see any issues | G103: =IF($E103="","",IFERROR(IF(OR(NOT(ISNUMBER($D103)),NOT(ISNUMBER(INDEX(Settings!$E$4:$E$80,MATCH($E103,Settings!$A$4:$A$80,0))))),"No",IF($D103>INDEX(Settings!$E$4:$E$80,MATCH($E103,Settings!$A$4:$A$80,0)),"Yes","No")),"")) -> No | H103: =IFERROR(TRIM(INDEX('Raw Data'!$S$5:$S$400,MATCH($B103,'Raw Data'!$H$5:$H$400,0))),"") -> RMN3MA/MY26B016480
A104: =IFERROR(INDEX('Raw Data'!$D$5:$D$400,MATCH($B104,'Raw Data'!$H$5:$H$400,0)),"") -> 46183 | B104: WO-0588157 | C104: =IFERROR(TRIM(INDEX('Raw Data'!$J$5:$J$400,MATCH($B104,'Raw Data'!$H$5:$H$400,0))),"") -> Dollar General # 13069 | D104: =IFERROR(INDEX('Store List'!$B$4:$B$300,MATCH($C104,'Store List'!$A$4:$A$300,0)),"") -> 46127 | E104: Door not closed (Overnight) | F104: Worked perfectly fine until the door never got closed on Jun 9th. Door Closed on jun 10th and its working fine after that | G104: =IF($E104="","",IFERROR(IF(OR(NOT(ISNUMBER($D104)),NOT(ISNUMBER(INDEX(Settings!$E$4:$E$80,MATCH($E104,Settings!$A$4:$A$80,0))))),"No",IF($D104>INDEX(Settings!$E$4:$E$80,MATCH($E104,Settings!$A$4:$A$80,0)),"Yes","No")),"")) -> No | H104: =IFERROR(TRIM(INDEX('Raw Data'!$S$5:$S$400,MATCH($B104,'Raw Data'!$H$5:$H$400,0))),"") -> RMN4MA/MY26B014985
A105: =IFERROR(INDEX('Raw Data'!$D$5:$D$400,MATCH($B105,'Raw Data'!$H$5:$H$400,0)),"") -> 46183 | B105: WO-0588762 | C105: =IFERROR(TRIM(INDEX('Raw Data'!$J$5:$J$400,MATCH($B105,'Raw Data'!$H$5:$H$400,0))),"") -> Dollar General #14104 | D105: =IFERROR(INDEX('Store List'!$B$4:$B$300,MATCH($C105,'Store List'!$A$4:$A$300,0)),"") -> 46105 | E105: Door Gasket | F105: Data looks okay. Pulling down to -10 pretty much and defrost is about 32. Could be icing. Notes say improper door seal. Could be the door gasket. And they also say waiting for parts so may be new gaskets were ordered? | G105: =IF($E105="","",IFERROR(IF(OR(NOT(ISNUMBER($D105)),NOT(ISNUMBER(INDEX(Settings!$E$4:$E$80,MATCH($E105,Settings!$A$4:$A$80,0))))),"No",IF($D105>INDEX(Settings!$E$4:$E$80,MATCH($E105,Settings!$A$4:$A$80,0)),"Yes","No")),"")) -> No | H105: =IFERROR(TRIM(INDEX('Raw Data'!$S$5:$S$400,MATCH($B105,'Raw Data'!$H$5:$H$400,0))),"") -> RLN2MA/MY26B015990
...

Sheet Raw Data
A1: Raw Data - paste new CRM export rows at the bottom | B1: Raw Data - paste new CRM export rows at the bottom | C1: Raw Data - paste new CRM export rows at the bottom | D1: Raw Data - paste new CRM export rows at the bottom
A3: Possible duplicate work orders: | C3: =SUMPRODUCT(('Raw Data'!$H$5:$H$400<>"")*(COUNTIF('Raw Data'!$H$5:$H$400,'Raw Data'!$H$5:$H$400)>1)) -> 4
A4: (Do Not Modify) WO Number | B4: (Do Not Modify) Row Checksum | C4: (Do Not Modify) Modified On | D4: DATE | E4: APRILS NOTES | F4: STATUS | G4: COMPLETED DATE | H4: BOS WORK ORDER | I4: BRANCH | J4: STORE | K4: CITY | L4: STATE | M4: PO | N4: CALLER | O4: PROBLEM CATEGORY | P4: REPLACEMENT PARTS | Q4: NON-WARRANTY BILLABLE | R4: FR SUBMITTED YES/NO | S4: CASE MODEL/SERIAL NUMBER | T4: PICTURES BOS | U4: Job Scope | V4: WORK SUMMARY
D5: 46209.674 | F5: Canceled | G5: 46209 | H5: WO-0608904 | I5: San Antonio, TX | J5: Dollar General #20761 | K5: Pettus | L5: TX | M5: TAVANT/PRODUCT CARE | N5: STORE CONNECT | O5: TEMPERATURE | S5: RLN2MA / MY26B013813 | U5: High Temperature Alarm | V5: Product Care Team cancelled the call
D6: 46209.641 | F6: Completed | G6: 46210 | H6: WO-0608855 | I6: Dallas, TX | J6: Dollar General #3277 | K6: Garland | L6: TX | M6: 5169188 | N6: FEXA | O6: TEMPERATURE | S6: RLN3MA / MY26D028108 | U6: Invalid Temperature Reading | V6: I found case at temp -8 down to - 10 i found left hand door not closing all the way and probably causing issues store had roped off the case i repaired torque rod and adjusted it . No other issues found with the case. Store ac is not working properly could case issues not sure.
D7: 46209.492 | E7: ETA 7/6 | F7: Scheduled | H7: WO-0608593 | I7: Kansas City, MO (Lenexa) | J7: Dollar General #1768 | K7: Nixa | L7: MO | M7: 5163557 | N7: FEXA | O7: WATER LEAKING | S7: RLN2MA / MY26D028097 | U7: Water leaking from under the unit and excessive condinsation on the doors - multiple units effected
D8: 46209.353 | F8: Canceled | H8: WO-0608327 | I8: Tulsa, OK | J8: Dollar General #21606 | K8: Porum | L8: OK | M8: TAVANT/PRODUCT CARE | N8: STORE CONNECT | O8: TEMPERATURE | S8: RLN3MA / MY26B013826 | U8: High Temperature Alarm | V8: Kindly recall the dispatch for below case, as case trends and working seems to be normal, kindly acknowledge here once it is recalled.
D9: 46206.953 | F9: Completed | G9: 46210 | H9: WO-0607313 | I9: Southern | J9: Dollar General #21375 | K9: Oxford | L9: AR | M9: 5162624 | N9: FEXA | O9: ICE BUILD UP | S9: RLN3MA / MY26B01382 | U9: There is a block of ice on the inside and top of the unit | V9: Email from Young, Bradley <Bradley.Young@hussmann.onmicrosoft.com>
D10: 46206.943 | E10: ETA 7/8 | F10: Scheduled | H10: WO-0607311 | I10: Dallas, TX | J10: Dollar General #22930 | K10: Forestburg | L10: TX | M10: 5162381 | N10: FEXA | O10: WATER LEAKING INTO UNIT | S10: RLN4MA / MY26B014974 | U10: There is water running into the unit and down the shelves and freezing
D11: 46206.611 | F11: Completed | H11: WO-0607008 | I11: Southern | J11: Dollar General #21838 | K11: Belle Chasse | L11: LA | M11: TAVANT/PRODUCT CARE | N11: STORE CONNECT | O11: TEMPERATURE | S11: RLN3MA / MY26E039365 | U11: High Temperature Alarm | V11: Found ice dripping from top of cabinet. Checked to make sure the drain was clear. Removed top plate to inspect where water was coming from. Found spray foam and butyl had overflowed into airway and had ice forming on it and wicking water down to cabinet. Removed overflow and all ice. Observed for 45 minutes to ensure it didn't continue leaking. Observed defrost and proper drain function.
D12: 46206.036 | E12: Pinged Sarah for eta | F12: Send New Tech | H12: WO-0606554 | I12: Houston, TX | J12: Dollar General #14858 | K12: Houston | L12: TX | M12: TAVANT/PRODUCT CARE | N12: STORE CONNECT | O12: TEMPERATURE | S12: RLN2MA / MY26B016475 | U12: High Temperature Alarm
D13: 46206 | E13: Parts ordered and tech returning with propane | F13: Done - Send New Tech | H13: WO-0607304 | I13: Houston, TX | J13: Dollar General #22408 | K13: Angelton | L13: TX | M13: 5162382 | N13: FEXA | O13: TEMPERATURE | S13: RMN5MA/MY26E03940 | U13: Invalid Temperature Reading | V13: 7/7/2026 .Tech support called me after I left. 7/7/2026 One of the units might be under charged so they asked me to go back with some propaneChecked in with manager. Located 5 door case. Found unit at temp. Connected to both controllers. Found all sensors reading properly. Tried to get with tech support but couldnt get a hold of them. Found 1 torque rod and master that need to repaced. Got with andrew miller we checked all sensors . Will return when parts come in
D14: 46205.919 | F14: Canceled | G14: 46206 | H14: WO-0606498 | I14: Bolingbrook, IL | J14: Dollar General #8773 | K14: South Bend | L14: IN | M14: TAVANT/PRODUCT CARE | N14: STORE CONNECT | O14: TEMPERATURE | S14: RLN3MA / MY26B016492 | U14: High Temperature Alarm | V14: 7/3/2026 2:02AM Please recall the dispatch request, as the case has started returning to normal. Regards,Product Care Team
D15: 46205 | F15: Completed | G15: 46210 | H15: WO-0605720 | I15: Dallas, TX | J15: Dollar General #21664 | K15: Jacksonville | L15: TX | M15: TAVANT/PRODUCT CARE | N15: STORE CONNECT | O15: TEMPERATURE | S15: RMN5MA / MY26D033044 | U15: High Temperature Alarm | V15: 07/02/26; Check new cases and found the new case, SN MY26D033044 warm in the left end. Case has two condensing units. Pull inside top cover to access the evap, evap clear. Condensing units are R290. Discharge temp feels low at the condenser inlet. Leak check unit, found no leaks. Will have to pick up an R290 charging kit and return. Spoke with the manager about it and they are fine. 07/06/26; Pick up R290 kit in Longview and return to the store. Install piercing valveson liquid and suction. Hookup hoses and vacuum pump, vacuum pump locked up. Pick up new vacuum pump. 07/07/26; Return to store. Activate piercing valves and pull vacuum. Leave unit on vacuum for an hour, vacuum stayed at 30". Weigh in 3.5 oz of R290. Discharge temp at condenser is at 110°F. Suction at 50# and discharge at 140#. Case temp droped to setpoint and cycled.
D16: 46205 | E16: ETA is 7/17 | F16: Return Needed | H16: WO-0606044 | I16: Denver, CO | J16: Dollar General #21938 | K16: Olathe | L16: CO | M16: TAVANT/Tim Smith (Installation) | N16: INTERNAL | O16: HUMIDITY SENSOR | V16: 07/02/26; Check new cases and found the new case, SN MY26D033044 warm in the left end. Case has two condensing units. Pull inside top cover to access the evap, evap clear. Condensing units are R290. Discharge temp feels low at the condenser inlet. Leak check unit, found no leaks. Will have to pick up an R290 charging kit and return. Spoke with the manager about it and they are fine. 07/06/26; Pick up R290 kit in Longview and return to the store. Install piercing valveson liquid and suction. Hookup hoses and vacuum pump, vacuum pump locked up. Pick up new vacuum pump. 07/07/26; Return to store. Activate piercing valves and pull vacuum. Leave unit on vacuum for an hour, vacuum stayed at 30". Weigh in 3.5 oz of R290. Discharge temp at condenser is at 110°F. Suction at 50# and discharge at 140#. Case temp droped to setpoint and cycled.
D17: 46205 | F17: Completed | G17: 46205 | H17: WO-0605513 | I17: Houston, TX | J17: Dollar General #22408 | K17: Angleton | L17: TX | M17: TAVANT/PRODUCT CARE | N17: STORE CONNECT | O17: TEMPERATURE | S17: RLN3MA / MY26F047534 | U17: High Temperature Alarm | V17: Checked in with manager. Located self contained unit. Found unit at -4 degrees. Right side condenser was not running. Connected to controller. Controller was calling for comp. Started going thru control wiring. Found a wiring issue. Repaired wiring. Started condenser up. Unit dropped to temp. Checked operation of unit. All okay work complete
D18: 46203 | F18: Completed | G18: 46205 | H18: WO-0603741 | I18: Bolingbrook, IL | J18: Dollar General #20597 | K18: Chicago | L18: IL | M18: TAVANT/PRODUCT CARE | N18: STORE CONNECT | O18: TEMPERATURE | S18: RLN3MA / MY26B016493 | U18: High Temperature Alarm | V18: 7/1/26 DE Arrived on site and checked in. On site for reach in freezer running warm. Case controllers were reading -8 and -4 upn arrival. Case went into defrost immediately after arrival. Let case run through its natural defrost cycle. After defrost, let case try to pull down to temp. Customers kept opening doors so case was struggling to pull down to temp. Doors were finally left closed long enough for case to pull down. Case temping at -.5 and .1 and still dropping upon departure. No issue found at this time. Cleaned up work area and checked out with manager Sylvia.
D19: 46203 | F19: Canceled | G19: 46204 | H19: WO-0603718 | I19: Southern | J19: Dollar General #13069 | K19: Laurel | L19: MS | M19: TAVANT/PRODUCT CARE | N19: STORE CONNECT | O19: TEMPERATURE | S19: RLN3MA / MY26B016491 | U19: High Temperature Alarm | V19: 7/1 Kindly recall the dispatch for below case, as case trends and working seems to be normal, kindly acknowledge here once it is recalled. From Product Care 6/30 Roll call for AM as store closes in 35 minutes
D20: 46203 | F20: Completed | G20: 46203 | H20: WO-0602689 | I20: Houston, TX | J20: Dollar General #20440 | K20: Sheridan | L20: TX | M20: TAVANT/PRODUCT CARE | N20: STORE CONNECT | O20: TEMPERATURE | S20: RLN3MA / MY26D032603 | U20: High Temperature Alarm | V20: 7/1 checked in with manager . Located rif self contained unit. Found unit at 18 degrees. Found ice build up on frame of case not allowing doors to close properly. Removed ice from frame , case started dropping to temp. Started looking into frame heater. Located anti sweat contoller in top left panel of case. Found good voltage coming in and out of contoller. Started tracing wiring for frame heater. Had to go wire for wire to locate frame heater. Found that frame heater wasnt wired properly. Fixed wiring. Frame heater started pulling correct amps , ice melted off frame. Checked operation of unit. Units are charged properly. Tried to check deforst but controllers were locked out. Had to get with tech support to download the correct app for carel controllers. Tested defrost. Had to install a self tapper on condenser because ribbits had come loose . All okay. Work complete
D21: 46202 | E21: Pinged Heidi - ETA was 7/6 | F21: Unscheduled | H21: WO-0601570 | I21: Tulsa, OK | J21: Dollar General #22149 | K21: Anton | L21: TX | M21: TAVANT/PRODUCT CARE | N21: STORE CONNECT | O21: TEMPERATURE | S21: RLN2MA / MY26B014945 | U21: High Temperature Alarm
D22: 46200.148 | F22: Completed | G22: 46200 | H22: WO-0600724 | I22: Southern | J22: Dollar General #20100 | K22: Paulina | L22: LA | M22: TAVANT/PRODUCT CARE | N22: STORE CONNECT | O22: TEMPERATURE | S22: RLN2MA MY26D029644 | U22: High Temperature Alarm | V22: Checked case and found that the evaporator coil was iced up and it was because there was a box of product that was keeping the door open, so after moving the box and closing the door i had to run the case in multiple defrost. After that case came back down yo temperature and its now running normally.
D23: 46199.431 | F23: Send New Tech | H23: WO-0599879 | I23: Houston, TX | J23: Dollar General #21359 | K23: Orange | L23: TX | M23: 5134984 | N23: FEXA | O23: TEMPERATURE | S23: RLN3MA / MY26B016014 | U23: Ice cream is melting and product damaged, water leaking under unit | V23: 6/26/26 Freezer iced up due to high humidity in area.customer removed all product then i deiced case.defrost heaters working properly.i also cleaned drain pan assembly.also cleaned condenser coils.then put unit it online.frerzer maintaining temperature -8 degrees
D24: 46199.417 | F24: Completed | G24: 46200 | H24: WO-0599854 | I24: Houston, TX | J24: Dollar General #20440 | K24: Sheridan | L24: TX | M24: 5140629 | N24: FEXA | O24: TEMPERATURE | S24: RLN3MA/ MY26D032603 | U24: Cooler keeps freezing up, causing door to form ice and it is not closing | V24: 6/26/26 Arrived on site checked in with manager. Found 3 door case with some ice building up at bottom of door. Removed ice pulled gaskets and set outside in the sun to warm up. Reinstalled and adjusted torque rods on Doors. Doors seem to be Sealing better and can not feel any air leaks. After talking to non-mechanical technician cases may not be leveled correctly. Checked with makeshift plumber Bob and cases seem to be leaning forward. Non-mechanical technicians or installing contractor may need to check level on cases. Cases are out of alarm at this time. Checked out with store m o d work order complete.
D25: 46199.177 | F25: Completed | G25: 46200 | H25: WO-0600225 | I25: Southern | J25: Dollar General #10520 | K25: Youngsville | L25: LA | M25: TAVANT/PRODUCT CARE | N25: STORE CONNECT | O25: TEMPERATURE | S25: RLN3MA / MY26E039362 | U25: High Temperature Alarm | V25: 6/27/26 Service call for frozen food micro blocks high temp. Drove to site, checked in, gained access to cases, all 3 micro blocks are working as they should with no alarm, and cases are at setpoint. Serial: MY26D029643 MODEL ID: RLN2MA MODEL ID: RLN3MA SERIAL: MY26E039362
D26: 46198.497 | F26: Completed | G26: 46199 | H26: WO-0599278 | I26: Southern | J26: Dollar General #13009 | K26: Wake Village | L26: TX | M26: TAVANT/PRODUCT CARE | N26: STORE CONNECT | O26: TEMPERATURE | S26: RLN2MA / MY26C019875 | U26: High Temperature Alarm | V26: 6/26/26 Arrived onsite to service Hussmann reach-in case. Recovered the existing R-290 refrigerant charge, pulled the system into a deep vacuum, and recharged the system with 3.5 oz of R-290. Restarted the unit and verified proper operation. Case temperature is currently -7°F and maintaining temperature as designed. Unit operating normally at this time. 6/25/26- inspected the system. Checked the airflow. Checked that the compressor was running. Determined that the system was low on R290. Will have Dave return tomorrow to gas up the system.
D27: 46198.312 | F27: Completed | G27: 46199 | H27: WO-0599624 | I27: Southern | J27: Dollar General #21838 | K27: Belle Chasse | L27: LA | M27: TAVANT/PRODUCT CARE | N27: STORE CONNECT | O27: TEMPERATURE | S27: RMN4MA/MY26E039403 | U27: High Temperature Alarm | V27: 6/26 Please recall the dispatch requst, as the case has started returning to normal. Regards, Product Care Team 6/25When i got to site i found the evaporator was iced up because the vendor had the doors open as he was installing sliders and fillling it with product, So i tested defrost out and its working normally the case will recover when they are done loading the case
D28: 46198.151 | F28: Completed | G28: 46198 | H28: WO-0599522 | I28: Bolingbrook, IL | J28: Dollar General #20597 | K28: Chicago | L28: IL | M28: TAVANT/PRODUCT CARE | N28: STORE CONNECT | O28: COIL ICING | S28: RLN3MA/MY26B016493 | U28: We are observing a coil icing | V28: 6/25/26 AN Model# RLN3MA Serial# MY26B016493 Drove to site. Arrived on site. Call for frozen 3 door icing up. Found right most door had gasket off at the bottom of the door keeping door open causing moisture to enter into case. Ice was forming on ceiling of case. Reinstalled gasket. Cleared ice forming on door frame. Door is now closing proper. Forced both controllers through multiple defrosts to clear any frost from coils. Cleared as much ice and moisture as possible. Monitored temps. Temps are dropping. At 0 degrees and still dropping. Cleaned up work area. Work complete
D29: 46197.197 | F29: Completed | G29: 46198 | H29: WO-0598739 | I29: RPM/Strategic Accounts | J29: Dollar General #6987 | K29: Pinetop | L29: AZ | M29: 5129550 | N29: FEXA | O29: TEMPERATURE | S29: RMN4MA/MY26E039399 | U29: I spoke with Marie (SM) and she said temperature seemed warm and product didn't look good and the temperature gauge was not working. | V29: Sub sending in tech notes
D30: 46196.488 | F30: Completed | G30: 46199 | H30: WO-0597607 | I30: RPM/Strategic Accounts | J30: Dollar General #21342 | K30: Klamath Falls | L30: OR | M30: 5130014 | N30: FEXA | O30: ICE BUILD UP | S30: RLN3MA/MY26B016018 | U30: Major Ice build up on the doors and leaking water on floor | V30: Sub confirms complete and will send in tech notes
D31: 46196.419 | F31: Completed | G31: 46196 | H31: WO-0597498 | I31: Phoenix, AZ | J31: Dollar General #22864 | K31: Tucson | L31: AZ | M31: 5119317 | N31: FEXA | O31: TEMPERATURE | S31: RMN5MA/MY26B016552 | U31: Not Keeping Temperature | V31: Arrived on site and checked in with mod. Cooler reach in at temp upon arrival. Pulled product and panels. Coil free and clear of ice. Fans working. Compressor running. Condenser fan running and clear of dust and debris. Solenoid operational. Superheat ok. Dixell controller working. Correct amount of defrost and defrost time set. Changed high temp alarm from 47° to 65°. Job complete
D32: 46195.463 | F32: Completed | G32: 46195 | H32: WO-0596795 | I32: Southern | J32: Dollar General #20100 | K32: Paulina | L32: LA | M32: TAVANT/PRODUCT CARE | N32: STORE CONNECT | O32: TEMPERATURE | S32: RMN4MA / MY26E039404 | U32: High Temperature alarm | V32: On arrival case was not temping high, checked airflow and confirmed it was good, checked condensing unit and cleaned the small layer of dust I noticed. Also tensioned doors after noticing they do not close by themselves after opening.
D33: 46192.471 | E33: Scheduled for 6/26 return (DG Manager requested return to check on it) | F33: Return Needed | H33: WO-0595748 | I33: Phoenix, AZ | J33: Dollar General #22286 | K33: Arizona City | L33: AZ | M33: 5123730 | N33: FEXA | S33: RLN2MA /MY26B014938 | U33: Not Working at All - Temp is failing, Ice Cream Melting, Product Damaged | V33: Arrived at store checked in with manager checked 2dr freezer and case was running at -6°F talked to manager amd he dont like how temp spikes up 6-8°af after opening door for 10-15 sec case dropps to temp after door closes. Called tech support and spoke with Erik we went through all perameters and chexked temp graph we did find the case is going into 2 defroat back to back. Erik ssaid it ahould be a program issue and that they coulsld do the changes remotely. Case was running at -7° when i left store.
D34: 46191.436 | F34: Completed | G34: 46192 | H34: WO-0594944 | I34: Phoenix, AZ | J34: Dollar General #22286 | K34: Arizona City | L34: AZ | M34: 5125380 | N34: FEXA | O34: TEMPERATURE | S34: RMN5MA/MY26B016552 | U34: High temperature alarm | V34: 6/19 Arrived at store checked in with manager looked for case mentioned on work summary RMN5MA MY26B016552 and there is no case in store with this model# and serial#. Store did have a issue with a 2dr freezer manager said case was to warm during defrost and temp got upto 48°F and took a long time to drop. Case was running at -9°F when i arrived. Checked defrost perameters and found it was programmed for defroat interval of 6hrs changed that to every 8hrs also found max defrost duration set to 60 min changed that to 25 min also end defrost temp was set to 45° changed that to 36°F after making changes ran system throu a defrost cycle ansd monitored case temp did not go higher then 36°F and after defrost case dropped temp case is running at -5°F when i left store. No other issues present at time of departure Arrived onsite 06/18/26, checked in with manager on duty. Gained access to case model # RMNAMA serial # MY26B014985. Found temp at 41°. Manager stated that the door had been left open all night because door wouldn't close on its own. Adjusted door to close on its own. Allowed to cool down. Temp dropped to 37° and stalled. Removed inside rop panel to expose evaporator and fans. Fans are operational and there is no ice visible on coils. Reassembled and forced defrost incase there is any ice i couldn't see. Allowed to complete defrost. Refrigeration restarted. Case began to pull down to 35.7, until case attached satisfied. Then temp went up to 36°. Will return for further diagnosis.
D35: 46191.278 | F35: Completed | G35: 46192 | H35: WO-0594225 | I35: Tulsa, OK | J35: Dollar General #14386 | K35: Norman | L35: OK | M35: TAVANT/PRODUCT CARE | N35: STORE CONNECT | O35: TEMPERATURE | S35: RLN2MA MY26B016452 | U35: High temperature alarm | V35: arrived onsite and assited tech in the removal of faulty micro block and installation on new all checks good Found unit temp at 58°f pull refrigerant out pulled vacuum and recharged 100g of r290 unit still not cooling properly called tech support on unit and they will send new unit to replace this one Returned to install new unit watched temp drop new unit working properly and re addressed to communicate with sc pulse
D36: 46191.089 | E36: Tech was onsite 6/18 per his notes he must return | F36: Return Needed | H36: WO-0594191 | I36: Southern | J36: Dollar General # 13070 | K36: Laurel | L36: MS | M36: TAVANT/PRODUCT CARE | N36: STORE CONNECT | O36: TEMPERATURE | S36: RMN4MA/MY26B014986 | U36: High temperature alarm
D37: 46189.152 | F37: Completed | G37: 46189 | H37: WO-0593126 | I37: Phoenix, AZ | J37: Dollar General #22286 | K37: Arizona City | L37: AZ | M37: 5108840 | N37: FEXA | O37: TEMPERATURE | S37: RLN2MA MY26B014938 | U37: Ice Cream is melting | V37: Checked in with management upon arrival. Found unit down to temp at -6.0, pulled top panel to inspect the EVAP. It had no ice build up. Inspected the controller parameters. Found it has a defrost pre set of 45 min with a temp termination of 45F (7.2C), lowered the time to 20 min and 37F (2.7C). Put unit back together. Ran through a defrost cycle to verify. No further issues found. Unit temped -2 F before departure.
D38: 46189.097 | F38: Completed | G38: 46189 | H38: WO-0592610 | I38: San Antonio, TX | J38: Dollar General #20761 | K38: Pettus | L38: TX | M38: TAVANT/PRODUCT CARE | N38: STORE CONNECT | O38: TEMPERATURE | S38: RLN2MA MY26B013813 | U38: High Temperature alarm | V38: I confirned unit was above temp at approx 16⁰F upon arrival. I verified controller, compressor and both condenser (1) and evaporator (2) fans were function. I confirmed coils were iced up. Checked with Hussmann to confirm theory of operation. I believe a power issue might have caused some controller issue because after a reset the defrost intiated (hot gas) without issue. I maually cleaned coil. I also sealed cracks/opening in the semas of the block. Issue is resolved.
D39: 46188.451 | F39: Completed | G39: 46196 | H39: WO-0592045 | I39: Tulsa, OK | J39: Dollar General #23988 | K39: Kingfisher | L39: OK | M39: TAVANT/PRODUCT CARE/5110636 | N39: STORE CONNECT/FEXA | O39: TEMPERATURE | S39: RLN2MA MY26C025304 | U39: High temperature alarm | V39: 6/23 arrived onsite and replaed hot gas solenoid coil, ran coil thru factory wire casing, turned case, waistedf for case to get to decent temp for system to allow me to put through defrost and test solenoid, ran defrost solenoid worked, made sure temp got down to temp all checks good 6/16 arrived onsite foumd case evaporator iced up, after troubleshooting found hot gas solenoid coil not working has power but not energizing, case still under warranty, spoke to shane he will be filling out and providing the form for performance parts warranty, turned off case will return once part arrived to fix and turn on
D40: 46188.447 | F40: Completed | G40: 46188 | H40: WO-0592039 | I40: Houston, TX | J40: Dollar General #20107 | K40: Baytown | L40: TX | M40: TAVANT/PRODUCT CARE | N40: STORE CONNECT | O40: TEMPERATURE | S40: RMN3MA MY26C025312 | U40: High temperature alarm | V40: 06-15-26 juan olvera technician dispatch send me one service call for the deer and milk case midel RMN3MA, serial number MY26C025312, first i drove to site job upon arrival check-in with manager, for next i found the case and set up the ladder to check the cases compressor, the case is working, i check the airflow, the coil, case temperature, compressors, and the door, i did not found anything wrong the case is working at 34 Fahrenheit, the defrost is working, condenser fan is working during refrigeration mode, for last i submit pictures in document and I explain to the manager my performance further more this call is complete.
D41: 46186.342 | F41: Completed | G41: 46186 | H41: WO-0590801 | I41: Phoenix, AZ | J41: Dollar General #13396 | K41: Coolidge | L41: AZ | M41: TAVANT/PRODUCT CARE | N41: STORE CONNECT | O41: TEMPERATURE | S41: RLN2MA/MY26B016003 | T41: X | U41: High Temperature alarm on cases | V41: Arrived at store checked in with manager checked microblock high temp alarm. After troubleshooting found a 2dr freezer microblock running at 10°F. Ran system through a defrost cycle and cleared out all frost that was on evaperator. Monitored unit after defrost. I did notice condenser temp was running arounf 140°F the store has no AC the are using portable ac units and store is really warm. Removed the trim covering condenser and condenser temp dropped to 129°F and temp inside case started to drop a little faster. Case is dropping case got down to 4°F but customers keep openning the doors and temps goes right up.
D42: 46185.452 | F42: Completed | G42: 46186 | H42: WO-0590856 | I42: Phoenix, AZ | J42: Dollar General #22286 | K42: Arizona City | L42: AZ | M42: 5097913 | N42: FEXA | O42: TEMPERATURE | S42: RMN4MA/MY26B016036 | T42: X | U42: Freezer is shifting temperatures rapidly and ice cream is soft. Current at 16 degrees and warming. Need a tech sent asap! Thank you. | V42: System was in Defrost mode, and case at 36f° when arrived, checked system for airflow and was low, I set system to another defrost to clear up, I also checked parameters and compare it to another case. I found dp1 at 60 min and dp2 at 45 min, so sinve these is hot gas I set it dp1 25 and dp2 at45, also dt1 and dt2 both where 48. Once defrost completed system returned to normal operation and I monitor temp drop til system rwached -1 we have good air flow and with the adjustment these case should be running accordenly now, I checked case was sealed and not getting moisture feom any where on top of case where system is set, no further issues upon departure. System went into eco mode at 2f° so I removed it from it.
D43: 46185.39 | E43: ON HOLD | F43: Unscheduled | H43: WO-0589971 | I43: Bolingbrook, Il | J43: Dollar General #11509 | K43: Harvey | L43: IL | M43: TAVANT/PRODUCT CARE | N43: STORE CONNECT | O43: COMMUNICATION | S43: MY26B016494, RMN4MA/MY26B016536 | U43: Communication loss on cases
D44: 46185.326 | E44: ON HOLD | F44: Unscheduled | H44: WO-0589876 | J44: Dollar General #22982 | K44: Ropesville | L44: TX | M44: TAVANT/PRODUCT CARE | N44: STORE CONNECT | O44: COMMUNICATION | S44: RLN3MA/MY26B016502, MY26B016013, RLN4MA/MY26B014967 | U44: Communication loss on cases
D45: 46185.283 | E45: ETA 6/15 | F45: Unscheduled | H45: WO-0590766 | I45: Dallas, TX | J45: Dollar General #21778 | K45: Kaufman | L45: TX | M45: 5097125 | N45: FEXA | O45: WATER LEAKING | S45: RLN3MA/MY26D028107 | U45: Water is pouring down inside from the top - this has already been fixed once
D46: 46185.274 | E46: ON HOLD | F46: Unscheduled | H46: WO-0589851 | J46: Dollar General #22281 | K46: Hamlet | L46: IN | M46: TAVANT/PRODUCT CARE | N46: STORE CONNECT | O46: COMMUNICATION | S46: RLN2MA/MY26C019876, MY26B016513, MY26B16019 | U46: Communication loss on cases
D47: 46184.377 | F47: Completed | G47: 46185 | H47: WO-0588967 | I47: Phoenix, AZ | J47: Dollar General #22286 | K47: Arizona City | L47: AZ | M47: TAVANT/PRODUCT CARE | N47: STORE CONNECT | O47: AIR LEAK IMPROPER DOOR SEAL | S47: RLN2MA/MY26B014938 | T47: X | U47: having trouble with door leak impacting cooling performance | V47: Arrived on site, checked in with manager. Found 2 door icecream case specified in WO description struggling to maintain setpoint with massive temperature swings when door is opened due to poor airlfow caused by a partially iced up evap coil. Ran system through 2 manual defrost cycles in order to completely clear this ice build up and reestablish proper airflow. Found cause of this to be that the defrost time was 15mins instead of 45mins and the termination temp was set at 38°F not 48°F as manufacturer recommended. Made these changes to manufacturer recommendations. Stayed and monitored system after defrost to ensure proper operation. Case is now running at and maintaning setpoint. No further issues found
D48: 46184.052 | E48: HAVE SUZANNE TAKE A LOOK | F48: Completed | G48: 46185 | H48: WO-5089345 | I48: Phoenix, AZ | J48: Dollar General #16435 | K48: Tuba City | L48: AZ | M48: 5092946 | N48: FEXA | O48: ELECTRICAL | S48: RMN4MA/MY26B013841 | U48: Issue with eletric, need technician to return to reset | V48: Return to power on units. New case powered on and achieved desired temp. All existing equipmwnt would not power back on and requires dollar general contractor to diagnose.
D49: 46184 | F49: Completed | G49: 46185 | H49: WO-0589359 | I49: Houston, TX | J49: Dollar General #21135 | K49: La Marque | L49: TX | M49: 5092945 | N49: FEXA | O49: WATER LEAKING | S49: RMN3MA/MY26B016480 | T49: X | U49: Water is leaking under unit | V49: 06-12-26 juan olvera tech dispatch send me one emergency service call for the beer case leaking water, first I drove to site job upon arrival check-in with manager, for next i remove the bottom panel to check where the water is coming from, the bottom of the case is clear, then i check the drain pan on top of the case and i found the drain pan full of water, so the wayer leaks because drains from the top to bottom, i drain the drain pan and i clean all the remain of the water, then i adjust the door torque rod for all 3 door the same beer case, also there was another water leak for the next frozen food case, i fix that water leak, the pump water hose was disconnect i explain to the manager the second case was not part of the call, for last i explain to the manager my performance, i submit pictures in document and this call is complete.
D50: 46183 | E50: ETA 6/10 | F50: Scheduled | H50: WO-0588157 | I50: Southern | J50: Dollar General # 13069 | K50: Laurel | L50: MS | M50: TAVANT/PRODUCT CARE | N50: STORE CONNECT | O50: TEMPERATURE | S50: RMN4MA/MY26B014985 | U50: High temperature alarm
D51: 46183 | E51: ETA 6/11 | F51: Materials Needed | H51: WO-0588762 | I51: Phoenix, AZ | J51: Dollar General #14104 | K51: Tucson | L51: AZ | M51: TAVANT/PRODUCT CARE | N51: STORE CONNECT | O51: AIR LEAK IMPROPER DOOR SEAL | S51: RLN2MA/MY26B015990 | U51: Frozen food 2 door having trouble with door leak impacting cooling performance
D52: 46183 | E52: ETA 6/10 | F52: Scheduled | H52: WO-0588157 | I52: Southern | J52: Dollar General # 13069 | K52: Laurel | L52: MS | M52: TAVANT/PRODUCT CARE | N52: STORE CONNECT | O52: TEMPERATURE | S52: RMN4MA/MY26B014985 | U52: High temperature alarm
D53: 46182.395 | F53: Completed | G53: 46183 | H53: WO-0587865 | I53: Davenport, IA | J53: Dollar General #14341 | K53: South Perkin | L53: IL | M53: TAVANT/PRODUCT CARE | N53: STORE CONNECT | O53: TEMPERATURE | S53: RLN3MA/MY26B016495 | U53: High Temperature Alarm | V53: Checked ice cream freezer and new unit installed had no air flow. Evaporator has thick ice build-up. Checked defrost operation and was not passing power to hot gas defrost solenoid. Went through wiring and found both wires to naturals. Fixed wiring to power and ran through several defrost. Cleared ice buildup and cleaned water out of case. Put back together and back working in normal operation.
D54: 46182.188 | F54: Unscheduled | H54: WO-0587673 | I54: Tulsa, OK | J54: Dollar General #22799 | K54: Amarillo | L54: TX | M54: 5086405 | N54: FEXA | O54: WATER LEAKING | S54: RLN3MA/MY26B016006 | U54: Water is collecting in the top of the cooler as well as inside the cooler. Lights go on and off they do not stay on.
D55: 46181.537 | F55: Scheduled | H55: WO-0586550 | I55: Kansas City, MO (Lenexa) | J55: Dollar General #2600 | K55: Quincy | L55: IL | M55: 5082583 | N55: FEXA | O55: TEMPERATURE | S55: RMN3MA/MY26D026820 | U55: Not keeping the specified temperature, keeps going up and down
D56: 46181.424 | E56: Door Gasket Needed | F56: Materials Needed | H56: WO-0586308 | I56: Houston, TX | J56: Dollar General #20654 | K56: Alvin | L56: TX | M56: TAVANT/PRODUCT CARE | N56: STORE CONNECT | O56: TEMPERATURE | S56: RLN2MA/MY26B016474 | U56: High Temperature Alarm
D57: 46181.335 | E57: 6/10 spoke with dispatcher they are trying to find a tech | F57: Scheduled | H57: WO-0586957 | I57: San Antonio, TX | J57: Dollar General #20761 | K57: Pettus | L57: TX | M57: 5084774 | N57: FEXA | O57: LOW REFRIGERANT ALARM | S57: RMN4MA/MY26B016036 | U57: Observing low refrigerant operating condition
D58: 46181.537 | F58: Unscheduled | H58: WO-0586550 | I58: Kansas City, MO (Lenexa) | J58: Dollar General #2600 | K58: Quincy | L58: IL | M58: 5082583 | N58: FEXA | O58: TEMPERATURE | S58: RMN3MA/MY26D026820 | U58: Not keeping the specified temperature, keeps going up and down
D59: 46180.356 | F59: In Progress | H59: WO-0585699 | I59: Dallas, TX | J59: Dollar General #3277 | K59: Garland | L59: TX | M59: TAVANT/PRODUCT CARE/5080714 | N59: STORE CONNECT/ FEXA | O59: TEMPERATURE | S59: RLN3MA/MY26D028108 | U59: The alarm has been active beyond the configured threshold of 60 minutes.
D60: 46179.472 | E60: DISASTER FIRE - NO BOS TICKET CREATED YET | F60: Unscheduled | H60: TBD | I60: TBD | J60: Dollar General #22711 | K60: Purvis | L60: MS | M60: 5079187 | N60: FEXA | O60: DISASTER - FIRE | Q60: X | U60: RFLN3/MY21D040973 - Unit caught fire - had to turn off | V60: 6/8 - forwarded the service request to Eileen Petito, cc'd: Daniel Whited & Amber Fischer
D61: 46178.185 | F61: In Progress | H61: WO-0584971 | I61: Kansas City, MO (Lenexa) | J61: Dollar General #1247 | K61: Trenton | L61: MO | M61: 5077040 | N61: FEXA | O61: TEMPERATURE | P61: CASSETTE | S61: RLN4MA/MY26C019909 | T61: X | U61: New unit...not holding temp | V61: 6/4: Cassette was replaced on Thursday. 6/5: received service request from DG. 6/8: Tech found cassette low on refrigerant, to return on Tuesday to complete repair
D62: 46177.499 | E62: DISASTER | F62: Unscheduled | H62: WO-0584133 | I62: Charlotte | J62: Dollar General #12955 | K62: Surfside Beach | L62: SC | M62: 5074947 | N62: FEXA | O62: DISASTER - CASE ASSESSMENT | Q62: X
D63: 46177.438 | E63: ETA 6/4 - Calculated Comfort | F63: Completed | G63: 46177 | H63: WO-0583967 | I63: RPM/Strategic Accounts | J63: Dollar General #21342 | K63: Klamath Falls | L63: OR | M63: TAVANT/PRODUCT CARE | N63: STORE CONNECT | O63: TEMPERATURE | S63: RLN2MA/MY26C019880 | U63: High Temp Alarm | V63: Here are the hand written tech notes. We have not created an invoice yet for any charges. Our tech actually found other problems on site that need attention. Freezer 10 11 and 12 are experiencing drain pump issues...these are the old freedom cases. We are requesting a work order for a return visit to replace the drain pumps. Also another work order for a follow up on the micro block freezer to check the refrigerant charge. They defrosted the frozen evaporator and checked the operation. It is operating correctly at this time. We are requesting another work order for a follow up visit at the same time we replace the pumps on the freedom cases. When our tech got there the pumps had failed to the point there was water on the floor. Thanks, Dave Calculated Comfort
D64: 46177.402 | F64: Completed | G64: 46181 | H64: WO-0584430 | I64: Kansas City, MO (Lenexa) | J64: Dollar General #21709 | K64: Eolia | L64: MO | M64: 5074861 | N64: FEXA | O64: DOOR | Q64: X | S64: RMN3MA MY26D029152 | U64: Door remains open or sparks | V64: (CS) Found the system wouldn't call for cooling. I checked to make sure the safeties were good and they were. System had freon. I went to try and change the setpoint on the controller, and it was stuck on 178 degrees. I tried to reset and change it and it wouldn't change. Controller needs replaced on this cooler. Submitted parts request for new controller. Come to find out the case is not under warranty and they need to use their normal service contractor. Job is complete on our end NOTE: naissance call on the MY26 case as someone had already fixed and Hussmann was asked to look at a non-warranty case.
D65: 46177.072 | E65: DISASTER | F65: Unscheduled | H65: WO-0584141 | I65: RPM/Strategic Accounts | J65: Dollar General #14306 | K65: Sacramento | L65: CA | M65: 5074878 | N65: FEXA | O65: DISASTER - REMOVAL DISPOSAL | Q65: X | U65: Store is closing and need refrigeration removed and disposed of.
D66: 46176.926 | E66: Internal Purposes Only | F66: Unscheduled | H66: WO-0583750 | I66: RPM/Strategic Accounts | J66: Dollar General #1247 | K66: Trenton | L66: MO | M66: TAVANT/RPM INSTALLATION | N66: SUZANNE | O66: CASSETTE, REPLACEMENT | P66: CASSETTE | S66: RMN4MA/MY26B016036 | U66: Low Refrigerant Operation Condition | V66: **Andrew Miller mentioned cassette replacement, RPM/Rob Starkey stated, failure occurred during start up & waiting for details/equipment information**
D67: 46176.403 | F67: Completed | G67: 46181 | H67: WO-0583216 | I67: Tulsa, OK | J67: Dollar General #20336 | K67: Ardmore | L67: OK | M67: 5071633 | N67: FEXA | O67: TEMPERATURE | S67: RLN2MA/MY26B015996 | U67: Flashing HA - Up to 28 degrees | V67: Case RLN2MA / S/N MY26B015996 is working correctly setpoint is -10 degreees and is at -9.0 degrees. Verified fans / lights / compressor is working correctly with no alarms present on case. Case is holding temp with no issues. Note: Nextech HVAC/R is here at store working on case next to this one.
D68: 46175.419 | F68: Completed | G68: 46181 | H68: WO-0583040 | I68: Houston, TX | J68: Dollar General #20440 | K68: Sheridan | L68: TX | M68: 5069343 | N68: FEXA | O68: ICE/FROST & LOW REFRIGERANT | S68: RLN3MA/MY26B016036 | U68: Ice build up and Low refrigerant | V68: Picked up insulation, silicone, and butyl foam from Uri. Arrived on site, spoke with Mic, and found that one door was sweating and causing the frame to ice over. Found that the anti-sweat function of that door wasn't working, but the other two were. Checked wiring and connections in the raceway and found that the heater plug wasn't fully plugged in. Once I tightened the connection, the heaters on the door started to work. Also insulated and siliconed the top of the box due to air infiltration. The case is now running and operating as designed, and cases are meeting the setpoint of -9 degrees.
D69: 46175.419 | F69: Canceled | G69: 46176 | H69: WO-0583039 | I69: Kansas City, MO (Lenexa) | J69: Dollar General #21709 | K69: Eolia | L69: MO | M69: TAVANT/PRODUCT CARE | N69: STORE CONNECT | O69: TEMPERATURE | S69: RLN2MA/MY26B016465 | U69: Hight Temperature Alarm | V69: Store Connect canceled call stating everything was normal
D70: 46172.206 | F70: Completed | G70: 46173 | H70: WO-0580974 | I70: Southern | J70: Dollar General #21415 | K70: Sulphur | L70: LA | M70: 5060356 | N70: FEXA | O70: TEMPERATURE | P70: PRODUCT LOSS - EXISTING CASES | Q70: X | U70: Invalid Temperature reading- cases running warm - RLN2MA/MY26C019877 & RLN3MA/MY26D029648 | V70: Hussmann Cooler MODEL ID: RFMN5 SERIAL NO MY20D029072 Hussmann Freezer SERIAL NO MY20D029045 MODEL ID: RFLN4 Arrived onsite and spoke with the manager. Inspected the cooler and freezer cases that were experiencing temperature issues. Found the freezer controller setpoint was incorrectly set to 32°F. Adjusted the setpoint to -8°F to match the adjacent freezer case. Syatem recovered to -7 degrees upon departure. Inspected the cooler case that was running at elevated temperatures and located a refrigerant leak at the liquid line hose flare fitting. Loosened the fitting, applied thread sealant, and retightened the connection until the leak was eliminated. Leak detector readings decreased from approximately 500 ppm to 0 ppm, confirming the repair. Added 1.5 lbs of R-448A refrigerant to the system. Upon departure, the cooler temperature recovered from 44°F to 40°F. Also found the adjacent cooler case setpoint incorrectly adjusted to 230°F; reset the controller to 34°F. The cooler temperature recovered from 68°F to 51°F prior to departure. Both cases are operating and cooling properly at this time. Due to elevated product temperatures, full temperature recovery is expected to occur overnight as the product load continues to cool. Caleb S
D71: 46172.146 | F71: Completed | G71: 46174 | H71: WO-0580946 | I71: Southern | J71: Dollar General #6372 | K71: Petal | L71: MS | M71: 5060355 | N71: FEXA | O71: TEMPERATURE | S71: RLN3MA/MY26C019883, RMN4MA/MY26B016031 | U71: Not Keeping Specified Temp | V71: RMNAMA Serial #MY26B01603, cycled power to both units. Units back online, temps ok. RLN3MA Serial #MY26C019883, cycled power to units, back online. Temps ok.
D72: 46171.399 | F72: Completed | G72: 46171 | H72: WO-0580073 | I72: Houston, TX | J72: Dollar General #20582 | K72: Houston | L72: TX | M72: TAVANT/PRODUCT CARE | N72: STORE CONNECT | O72: TEMPERATURE | S72: RLN3MA/MY26B014956 | U72: High Temperature alarm | V72: Arrived on site checked in with manager. Found frozen food case running warm but not in alarm. After further inspection found left door not closing properly. Adjusted door and it is now closing as intended. Also noticed ice build up on left hand return air penetration. Ran both condensing units through defrost and removed ice. Checked top of case and found wet spot between micro block and top of case. Cleaned water and use silicone to seal between case and micro block. Put case back together and waited for case to reach set point. Checked out with manager work order complete
D73: 46171.192 | E73: ETA is 6/1 | F73: Scheduled | H73: WO-0580512 | I73: Davenport, IA | J73: Dollar General #14347 | K73: South Perkin | L73: IL | M73: TAVANT/ANDREW MILLER | N73: ANDREW MILLER | O73: WATER ICING ISSUE
D74: 46168.522 | E74: DISASTER | F74: Unscheduled | H74: WO-0578039 | I74: RPM/Strategic Accounts | J74: Dollar General #12799 | K74: Wichita | L74: KS | M74: 4988413 | N74: FEXA | O74: DISASTER - MOVE CASES | Q74: X | U74: Below are the details for a new service call. o Site Name/#: Dollar General 12799 o Address: 1624 E Central Ave Wichita, KS o Store Hours: 8am – 9pm (store will not stay past closing) o NTE: $1,500 o PO: 4988413 o Problem: Check In/Out with Store **need this 5 door Hussmann cooler unit moved out 4-5 ft in order to complete interior repairs. Units need to stay powered on, if possible. Building has large hole on the side of building. Coolers in front of large hole no one can get in form hole, but maybe an animal could. Manager on Duty OBTAIN A SIGNATURE ON SERVICE TICKET & NOTE FIRST AND LAST NAME. Hussmann Equipment ONLY: <insert issue> Tech can work on multiple Hussmann Cases with one ticket, confirm all cases are operating or diagnose before leaving the store. Tech must list or take pictures of the data tag of all equipment model/serial number repaired on service ticket and provide a detail work summary of each equipment repaired. If you need assistance, please contact Hussmann Technical Support @ 800-922-1919, option #3. If Parts are needed, contact Hussmann Warranty Parts @ 855-487-7778, option #6 – state it’s for Dollar General Copeland compressors are under warranty over the counter through United or Copeland Distributor. Sanhua TXV replacement is not available – source Sporlan. If parts are not available & have long lead time, send us an e-mail @ dg.service@hussmann.com to help locate. Invoices must be sent within 30 days of repair completion date to both April.marolf@hussmann.com and the dg.service@hussmann.com emails. Send repair status with a brief work summary BEFORE leaving the location to dg.service@hussmann.com. If you have any questions, contact us at @ dg.service@hussmann.com Troubleshooting Process Step 1 - Start with documentation located within case Operation Manual & Data Sheet with the case. Step 2 - Scan Hussmann QR Code located on model/serial plate Type serial number of case and follow navigation for product sheets, data sheets, and manuals Step 3 – Scan BOX QR Code for Box account Carries in depth support - parameters, controller guides etc. Step 4 - Contact technical support - direct line #866-785-8499 Tech support will escalate to our Field Equipment Team if issue cannot be resolved – tech support does not provide NTE/OT approval A qr code on a white background AI-generated content may be incorrect. A qr code with a box AI-generated content may be incorrect.
D75: 46165.392 | F75: Completed | G75: 46165 | H75: WO-0576129 | I75: Houston, TX | J75: Dollar General #6996 | K75: Baytown | L75: TX | M75: TAVANT/PRODUCT CARE | N75: STORE CONNECT | O75: TEMPERATURE | S75: RMN4MA/MY26D028118 | U75: High Temperature Alarm | V75: 5/23/26 Checked in with management , walked store and found a cases at temp , checked all cases ID tag to verify case called in running warm , located case and found case at temp , checked air flow , spoke with management and found out store experienced a power outage do to storm , all case back online and at temp , all checks out at this time.
D76: 46164.331 | E76: 6/8 Tech scheduled for 6/18 6/2 Andrew is sending parts to tech 6/1 checked with brach. Tech reached out to Andrew 5/22 and is waiting for response. Pinged Andrew. | F76: In Progress | H76: WO-0575409 | I76: Phoenix, AZ | J76: Dollar General #10339 | K76: Casa Grande | L76: AZ | M76: 5036631 | N76: FEXA | O76: TEMPERATURE | S76: RLN2MA/MY26B016459 (same case from 5/5) | U76: 5/22 @ 7:57am - Check In/Out with Store Manager on Duty & Obtain Signature Hussmann R290 Microblock Equipment ONLY: RLN2MA, MY26B016459 Not working at all. • TECH must obtain a photo of the equipment tag that includes MODEL & SERIAL number on the CASE & CONDENSING UNIT (Tecumseh) • Tech can only work on multiple Hussmann R290 cases with one ticket, confirm all cases are operating or diagnose before leaving the store. • DO NOT work on existing cases, communicate to the Store MOD to place call with their service vendor. • Tech must list or take pictures of the data tag of all equipment model/serial number repaired on service ticket and provide a detail work summary of each equipment repaired. • If you need assistance, please contact the following Hussmann Technical Support Team @ 866-785-8499 or the following: 1. Todd Green @ 210-346-0005 2. Jeff Fosnaugh @ 314-501-8736 3. Andrew Miller @ 314-501-8698 • Hussmann Performance Parts @ 855-487-7778, option #3 – Warranty • Tecumseh compressor warranty – supply house will provide warranty tag to fill out & obtain a copy for office. Must purchase the compressor & file warranty claim. • If parts are not available & have long lead time, send an e-mail @ dg.service@hussmann.com to help locate. • Invoice MUST be submitted within 45 days of repair completion date to TAVANT. For support with warranty claim @ 800-398-7402, option #4 or hussmannwarrantyclaims@hussmann.com Send repair status with a brief work summary BEFORE leaving the location & contact to dg.service@hussmann.com. If you have any questions, contact us at @ dg.service@hussmann.com Troubleshooting Process Step 1 - Start with documentation located within case • Operation Manual & Data Sheet with the case. Step 2 - Scan Hussmann QR Code located on model/serial plate • Type serial number of case and follow navigation for product sheets, data sheets, and manuals Step 3 – Scan BOX QR Code for Box account • Carries in depth support - parameters, controller guides etc. Step 4 - Contact technical support - direct line #866-785-8499 • Tech support will escalate to our Field Equipment Team if issue cannot be resolved – tech support does not provide NTE/OT approval. | V76: Found 2 door freezer high temp at 33 degrees. Found no air flow to case. Found evaporater iced up. Ran system theough serveral defost and used hot water from spray pump. Found case not draining. Drain line was plugged with foam spray inside drain line. Was able to remove with long screwdriver. All defrost operations working properly. Found right door gasket laying over and not sealing properly Need new door gasket. Possible micro block may need new seal around cabinet. Got unit back on line and monitored temps. D/A 5.3 degrees and dropping. Alarm clear on departure. Need to f/u on system to make sure system is defrosting properly
D77: 46164.252 | F77: Completed | G77: 46164 | H77: WO-0575297 | I77: Phoenix, AZ | J77: Dollar General #19997 | K77: Buckeye | L77: AZ | M77: TAVANT/PRODUCTCARE | N77: STORE CONNECT | O77: DOOR | S77: RMN4MA/MY26B016517 | T77: YES | U77: 5/22 @ 6:07am - Response : Priority: P1-Immediate Job Scope: HIGH TEMPERATURE Tech must obtain a photo of the equipment tag that includes Model & Serial Number on the Case and Condensing Unit (Tecumseh). Please review and Confirm the Checklist items below: We are observing a High Temperature Alarm on the Serial number MY26B016517, RMN4MA, Left & Center/Right Microblock case at the above-mentioned location. The alarm has been active beyond the configured threshold of 60 minutes. The store is currently operational and fully stocked with products. If this condition is not addressed immediately, it may result in product loss, food safety risk, and significant store operational impact, potentially leading to customer dissatisfaction. To prevent any product loss and ensure continued store operations, we request an immediate P1 (Critical) level site visit. Checklist: • Inspect the evaporator coil for ice or frost accumulation • Verify the evaporator fan is active and running properly • Confirm airflow direction and un-obstructed air circulation • If ice is present: Perform a manual defrost to fully clear the evaporator coil • Verify Hot Gas Valve operation during defrosts • Confirm the condenser fan turns OFF during defrost • Verify the refrigerant charge level • If low, charge the system to the manufacturer-recommended level | V77: Found left side of case high temp alarm. Found left door open on arrival. Had to adjust torque rod to get door to close properly. Monitored temps. D/A 38 degrees and dropping. Alarms clear on departure Resource: Ramond Ramirez Found left side of case high temp alarm. Found left door open on arrival. Had to adjust torque rod to get door to close properly. Monitored temps. D/A 38 degrees and dropping. Alarms clear on departure Resource: Ramond Ramirez
D78: 46162.528 | F78: Completed | G78: 46163 | H78: WO-0573996 | I78: Houston, TX | J78: Dollar General #20107 | K78: Baytown | L78: TX | M78: 5031411 | N78: FEXA | O78: CAREL CONTROLLER, PROBES | P78: PRODUCT LOSS - 2 LT, ICE CREAM | S78: RLN2MA/MY26B015992 (not pulling up in PP) | U78: Not working at all - all the ice cream is melted | V78: 5/21/26 I arrived and spoke with the manager. Read the alarms on the carel aplica mobile app, alarms listed were probe 1, probe 2, & control probe fault. Called Hussmann tech support. Found, the probe 1, probe 2, & control probe— plug disconnected from the controller. Disconnected the power to the unit, plugged in that said- plug to the respective receptacle on the controller, reconnected the power, watched the case pull down, currently the case is at 0.5° Fahrenheit, no longer in alarm, and pulling down to temperature setpoint. Remounted and re-fastened the cover over the control box. Cassette Model# ALX44U-DS3B01 Serial# 04E0226121673 Case Model# RLN2MA Serial# MY26B015992
D79: 46162.097 | E79: Suzanne Finding Someone to Run | F79: Unscheduled | H79: WO-0574005 | I79: RPM/Strategic Accounts | J79: Dollar General #21223 | K79: Santa Anna | L79: TX | M79: 5031586 | N79: FEXA | O79: ICE/FROST | S79: RLN2MA MY26B014946 | U79: Starting to Drip Frozen
D80: 46160.247 | F80: Completed | G80: 46161 | H80: WO-0572389 | I80: Kansas City, MO (Lenexa) | J80: Dollar General #7231 | K80: Springfield | L80: MO | M80: 5021320 | N80: FEXA | O80: NOISE | Q80: X | U80: Case is making a beeping sound | V80: Checked in with manager. Upon arrivial i found only one case not operating and it is a medium temp case. The serial number is not a MY26 it is a MY19. I talked to hussmann warranty department and found out this case is NOT under warranty. I was instructed to not work on this unit because its not under warranty.
D81: 46159.354 | F81: Completed | G81: 46159 | H81: WO-0571130 | I81: Bolingbrook, IL | J81: Dollar General #20597 | K81: Chicago | L81: IL | M81: TAVANT/PRODUCT CARE | N81: STORE CONNECT | O81: TEMPERATURE | S81: RLN3MA/MY26B016493 | T81: YES | U81: Response : Priority: P1-Immediate(0-24 Hours) Job Scope: HIGH TEMPERATURE We are observing a High Temperature Alarm on the Serial number MY26B016493, RLN3MA, Left/Center/Right Microblock case at the above-mentioned location. The alarm has been active beyond the configured threshold of 60 minutes. | V81: Drove to store, checked in with manager. On site for 3 door frozen unit running warm. Upon inspection found center door being held open by right hand door door heater wire bushing that hand come out of door frame. Reinstalled. Cleared ice around door. Door now closing properly forced defrost on both units to clear any frost build up on evaporator. Coils clear, defrost operation normal. Case now has good airflow. And at setpoint. Work complete.
D82: 46158.421 | F82: Completed | G82: 46157 | H82: WO-0570321 | I82: Dallas, TX | J82: Dollar General #21778 | K82: Kaufman | L82: TX | M82: 5012792 | N82: FEXA | O82: WATER LEAK | S82: RLN3MA/MY26D028107 | U82: Leaking Water and forming on all products inside | V82: May 18 2026. Checked in with manager kelly hunter. Work order was for water leaking inside the case. Located case. Verified case was microblock and took pictures of case and condensing unit data tags. Saw that there was ice on one of the glass doors as well as on the shelves and the ceiling of the case. Verified door heaters were operational. Cleared ice from the door. I then removed the ceiling to see where water might be coming from. Found ice buildup underneath where the drain line leaves the case and goes to the condensate pan under the condensing unit. Checked condensing unit. Found a pile of bolts and screws inside the condensate pan blocking the drain line. Removed the obstruction then put case in defrost. Defrost operational. I found water leaking out from the area where the drain leaves the evaporator. Used silicone sealant to seal around the area. Water stopped. I then took case out of defrost. Had manager remove product from shelves so i could clear the ice off. Put case back together. No other issues found. Checked out with m.o.d
D83: 46157.117 | F83: Completed | G83: 46162 | H83: WO-0570508 | I83: Kansas City, MO (Lenexa) | J83: Dollar General #14928 | K83: Nixa | L83: MO | M83: TAVANT/PRODUCT CARE/INSTALLATION | N83: RPM/ROB S. | O83: ELECTRICAL | S83: RLN2MA/MY26D02809, RLN3MA/MY26D03141 | U83: Cases were recently installed & no longer working…customer schedule to have product delivered tomorrow.
D84: 46155.36 | F84: Completed | G84: 46160 | H84: WO-0569146 | I84: RPM/Strategic Accounts | J84: Dollar General #21130 | K84: White City | L84: OR | M84: 5008372 | N84: FEXA | O84: ICE/FROST | R84: FR54400 | S84: RLN3MA/MY26C019887 | T84: YES | U84: There is a block of ice on the inside at the top of the unit, Not keeping the specified temperature | V84: Evaporator leaked water down inside the case. We chipped off the ice out of the case. We found that the drain was pointed upwards because wire conduit was run below the drain line. We re-ran the conduit above the drain to the lower the drain tube.
D85: 46155.342 | F85: Completed | G85: 46156 | H85: WO-0568891 | I85: Southern | J85: Dollar General #21375 | K85: Oxford | L85: AR | M85: 5006558 | N85: FEXA | O85: TEMPERATURE | R85: FR54401 | S85: RLN3MA/MY26B013828 | U85: Invalid Temperature Reading | V85: Arrived to check the 3 door freezer case for being high temp. Found it running defrost far to long for being hot gas. Found the parameters on the controller were not correct. Adjusted as necessary. Pulls down much quicker after defrost now. Job complete.
D86: 46155.142 | E86: DISASTER 5/29 emailed team for an update 5/14 Jerry sent email requesting survey | F86: Accepted | H86: WO-0569339 | I86: Gulf | J86: Dollar General #25390 | K86: Homer | L86: GA | M86: 5008919 | N86: FEXA | O86: DISASTER - DAMAGED UNITS | Q86: X | R86: FR54399 | S86: RFLN4/MY23K092022, RFLN5/MY23K092026 | U86: VH & units damaged- need to dispatch for replacement; Per Nextech - The cases have been patched up as well as could be. There are still air penetrations and ice forming in different spots on the case, including the back side. The impact looks to have been sufficient that I would say that the insulation between the paneling has been broken apart. I don’t see them as fully repairable. Thanks, Kendra
D87: 46154.495 | F87: Completed | G87: 46155 | H87: WO-0568437 | I87: Phoenix, AZ | J87: Dollar General #22286 | K87: Arizona City | L87: AZ | M87: TAVANT/PRODUCT CARE - RECALL | N87: STORE CONNECT | O87: ICE/FROST | S87: RLN2MA/MY26B014938 | T87: YES | U87: RECALL - issue still persists - coil icing | V87: Arrived at store and checked in with manager. Upon arrival the case hasno visible signs of icebuild up. Opened top panel inside of the case and checked evap coil and found the top half of the coil was iced up. Ran case through multiple defrost to clear ice and defrost sensor never showed above 31 degrees. Checked over micro block unit and noticed there was alot of water coming out of the liquid line penitration. The penitration isnt fully sealed to the outside. Shut unit down. Removed microblock box over evap coil and found the end of the coil is still iced up. Deiced the rest of the coil and checked sensor locations are both correct and defrost sensor was covered in ice which explains why it wouldnt go any higher. Applied more butyl to the bottom of the box along with over the line penitrations to seal them both. Reset box over evap coil and started unit back up. Case is now back down to temp and defrost time has been adjusted to 45min from 40 minutes to help keep the coil clear.
D88: 46154.492 | F88: Completed | G88: 46156 | H88: WO-0568430 | I88: Houston, TX | J88: Dollar General #14858 | K88: Houston | L88: TX | M88: TAVANT/PRODUCT CARE - RECALL | N88: STORE CONNECT | O88: REFRIGERANT, LEAK | S88: RLN3MA/MY26B016004 | T88: YES | U88: RECALL - issue still persists - lack of refrigerant | V88: Checked in. Located case matching serial number from work order. Found 3 door rif at -5 degrees on both controllers. Found no alarms. Could not leak check due to unit is R290 and my leak detector does not have the sensor for it. At e2 did not see any refrigerant leak alarms. There were no active alarms on controller. Spoke with manager, per manager wo was for an older system, breakfast case. That case was at temp. Advised them to open a separate wo for that case and serial number. RIF is operating as of now.
D89: 46154.49 | F89: Completed | G89: 46155 | H89: WO-0568428 | I89: Phoenix, AZ | J89: Dollar General #22613 | K89: Hereford | L89: AZ | M89: TAVANT/PRODUCT CARE - RECALL | N89: STORE CONNECT | O89: REFRIGERANT, LEAK | S89: RLN2MA/MY26B014941 | U89: RECALL - issue still persists - lack of refrigerant | V89: Frozen meats Checked in. Located case matching serial number from work order. Found 3 door rif at -5 degrees on both controllers. Found no alarms. Could not leak check due to unit is R290 and my leak detector does not have the sensor for it. At e2 did not see any refrigerant leak alarms. There were no active alarms on controller. Spoke with manager, per manager wo was for an older system, breakfast case. That case was at temp. Advised them to open a separate wo for that case and serial number. RIF is operating as of now.
D90: 46154.485 | F90: Completed | G90: 46155 | H90: WO-0568415 | I90: Phoenix, AZ | J90: Dollar General #14104 | K90: Tucson | L90: AZ | M90: TAVANT/PRODUCT CARE - RECALL | N90: STORE CONNECT | O90: ICE/FROST | S90: RLN2MA/MY26B015990 | U90: RECALL - Issue still persists - coil icing | V90: Dwain Taylor - Tech Notes Arrived on site checked in with site manager Located unit in question documented case temp Upon arrival at −6.3° continued inspection verified airflow was adequate , clear and unobstructed continued inspection verified condenser coil is clean verified compressor was pulling correct amperage verified that unit top Evaporator cover was sealed with no loss of air flow at this time ran system through manual defrost verified operation of defrost is correct verified time of defrost and termination is correct verified restart of unit watch temperature drop temperature dropped approximately to −8.8° Found no issues with this unit at this time..
D91: 46154.272 | E91: 5/13 Per Suzanne send to Specrite 5/13 Per Ashley she is checking with management and getting a tech out | F91: Completed | G91: 46175 | H91: WO-0568707 | I91: RPM/Strategic Accounts | J91: Dollar General #31905 | K91: Grand Prairie | L91: TX | M91: DEVIN SUMMERS/TIM SMITH | N91: TIM SMITH | O91: TEMPERATURE | Q91: X | S91: RFLN3/MY24A007599, RFLN4/MY24B011485 | U91: Hussmann Freedom Line 3 total cases – out of warranty: Two Freezer Cases RFLN3/MY24A007599 – RFLN4/MY24B011485 have no digital temperature reading & don’t know what the temperature suppose to be. One Cooler Case RFMN3/MY22B019861 is reading 48 degrees and the breaker boxes are not labeled. Confirm cases are programmed, operational & correct temperature.
D92: 46154.177 | E92: 5/12 Suzanne determining who will run | F92: Completed | G92: 46175 | H92: WO-0568634 | I92: TBD | J92: Dollar General #3270 | K92: San Angelo | L92: TX | M92: TAVANT/PRODUCT CARE - RECALL | N92: STORE CONNECT | O92: REFRIGERANT, LEAK | S92: RLN3MA/ MY26B016488, CENTER/RIGHT | U92: RECALL - issue still persists - lack of refrigerant | V92: Per Suzanne - Store reports no issues, close ticket
D93: 46152.156 | F93: Completed | G93: 46152 | H93: WO-0567300 | I93: Phoenix, AZ | J93: Dollar General #22864 | K93: Tucson | L93: AZ | M93: TAVANT/PRODUCTCARE | N93: STORE CONNECT | O93: TEMPERATURE | S93: RLN3MA/MY26B014958 | U93: RLN3MA MY26B014958 ALARM SHOWING HIGH TEMPERATURE | V93: Arrived manager stated the line up on the east side of wall frozen foods is not hold temp also the right corner 4 door case with 2 condensors. Checked the set points for the right corner line up and they were all set to 23 degrees. Went into control and placed set point based off manufacture recommendations -5. Temps started to come down. The corner 4 door case the controller kept on reading 0000. Tried to get through controller to enter passcode to view set points was unable to set set points at time went ahead and disconnected controller and reconnected then display came on and worked to change set point to -5. Temps on that case began to come down. Condensor fans are spinning along with evap fans. Did not see potential leaks used leak detector. Placed into manuel defrost and condensor fans shut off. Cleaned condensor coils with nitrogen on all condensors on right wall line up and 4 door right corner case
D94: 46150.383 | F94: Completed | G94: 46150 | H94: WO-0566374 | I94: Grand Rapids, MI | J94: Dollar General #20639 | K94: South Bend | L94: IN | M94: TAVANT/PRODUCT CARE | N94: STORE CONNECT | O94: TEMPERATURE | S94: RLN3MA/MY26B016016 | T94: YES | U94: HIGH TEMPERATURE | V94: When I arrived the cases were at 5 degrees. Checked for air obstruction and it seemed to be fine. One of the doors was not tensioned and there was reason to believe it was left open which caused the alarm. I tightened the door so it now closes properly and the cases were -3 when I left.
D95: 46148 | F95: Completed | G95: 46150 | H95: WO-0565337 | I95: Tulsa, OK | J95: Dollar General #21606 | K95: Porum | L95: OK | M95: TAVANT/PRODUCT CARE | N95: STORE CONNECT | O95: TEMPERATURE | P95: PRODUCT LOSS - 3 LT, FROZEN FOOD | S95: RLN3MA MY26B013826 | U95: HIGH TEMPERATURE Product line Serial Number Module Assets Model Alt Name: Microblock MY26B013826 Left RLN3MA Frozen food 5 Center/Right | V95: 5/8 Arrived on site and checked in. Unit had cleared a lot of water and was tmde iced. Turned back on and turned back on lights and antisweats. Unit pulled right down to temp, cycling normally. Has defrost operating normally. Spoke with jeff and decided that if unit ices up again in the future we will replace removable deck unit with a new one. WO complete. 5/7 Tried to de ice system but there is significant ice build up on coil. Due to design of microblock units i could not manually de ice. Had to shut off unit and will return on Friday morning to turn back on after ice has melted out.
D96: 46147.452 | F96: Completed | G96: 46148 | H96: WO-0564555 | I96: Phoenix, AZ | J96: Dollar General #10339 | K96: Casa Grande | L96: AZ | M96: TAVANT/PRODUCT CARE | N96: STORE CONNECT | O96: TEMPERATURE | S96: RLN2MA MY26B016459 | U96: We are observing a High Temperature Alarm on the Serial number MY26B016459, RLN2MA, Left Microblock case at the above-mentioned location. The alarm has been active beyond the configured threshold of 60 minutes. | V96: 5/5 Arrived at store and checked in with manager. Made my way back to new 2door microblock freezer. Found it was running warm due to all the product stuck inside the case. All the product is blocking the air flow. Store had to over load the case due to the one of the 3 door freezers being down. Also the cant use their over flow freezer in the back room because the electrician changed the outlet for it from a twist lock to a normal 3 prong plug. Ran case through 2 long defrost to male sure the evap coil is clear of ice. Temp is at 10 degrees upon departure. Will follow back up once new controller for the down 3 door arrives.
D97: 46147 | F97: Completed | G97: 46148 | H97: WO-0564924 | I97: Phoenix, AZ | J97: Dollar General #13631 | K97: Quartzsite | L97: AZ | M97: TAVANT/J BUDIK | N97: RPM/SUZANNE B. | O97: NUISANCE | S97: RMN4MA/MY26D028116 | T97: YES | U97: Hussmann R290 Microblock Case: Beverage Case – RMN4MA, possible undercharged and/or refrigerant leak. Tech must pick up R290 before heading to store. | V97: Upon arrival found everything working proper, customer stated someone was here this morning and was doing something on top but didn't know who or what, leak checked eberything and no leaks found. Monitored operation for a dozen cycles and both condensers turn on @40* and shut off @30*, checked all electrical connections, evaporator coils and motors, checked condenser coils and motors. Refrigeration cycle from 40* to 31* is 4.5 minutes. All pictures are attached in BOS.
D98: 46144.319 | E98: Installation Team handled | F98: Completed | G98: 46147 | H98: WO-0563528 | I98: Phoenix, AZ | J98: Dollar General #13396 | K98: Coolidge | L98: AZ | M98: 4983001 | N98: FEXA | O98: CASSETTE | P98: BMS PLUG | S98: RLN2MA MY26B016003 | U98: Not working at all. Lights on unit warm inside. | V98: 5/5There’s been some miscommunication from the factory to installation team for this location… Please DO NOT order BMS plug, this will be addressed by the Installation Team. Close out ticket, submit to Tavant: add note to description of claim – Sales/Factory did not add the BMS Plug to 2 Door Case replacement shipment & another order was placed without knowledge to service team before customer placed the service request. 5/4 Arrived at store and checked in with manager. Made my way over to hussmann 2 door freezer. Found the breaker on the electrical box was turned off. The installer also removed the BMS plug for the sensor/communication wire and I believe that is why they left the breaker off. Turned breaker on and monitored case and it has dropped down to 0.6 degrees and still dropping. Cycled case through defrost as well no issues found. Will get new BMS plug ordered and follow up to replace.
A99: 59e6d1e0-4743-f111-88b4-70a8a59001d5 | B99: 5fwVqsBfxF8ffzogfVx71CXSfzifEdaEI+87xbb0fc8BN+hr8nDT75EadCNoX1zp9qeQGF4pvNVVteaRvrNdpQ== | C99: 46141.62 | D99: 46140.597 | E99: DISASTER 5/29 sent email to team for update 4/29 Jerry creating quote | F99: Pending Quote | H99: WO-0561350 | I99: RPM/Strategic Accounts | J99: Dollar General #24243 | K99: Starkville | L99: MS | M99: 4971334 | N99: FEXA | O99: DISASTER: CASE(s) REPLACEMENT & INSTALLATION | P99: CASES | Q99: X | U99: Dollar General requesting Hussman's Assistance: Due to car hit damage, Nextech has advised: ALL 3 Of Units needing replacements RIF1 HUSSMAN MY22H084731 RFLN5 RIF 2 HUSSMAN MY22K088659 RFLN4 RIC4 HUSSMAN MY22K090785 RFMN4 Please dispatch for replacement. Thanks, Kendra
A100: 1470bcbf-3b43-f111-88b4-70a8a59001d5 | B100: E7KM7qXbsdfpvfJwveq/VdTqahZc/5yTtZlwSarywFxAfNNnQ1wzrL3nfHYG8LqLe0EyU4cbgT8pXadn/6cucg== | C100: 46142.744 | D100: 46140.536 | E100: CASE ASSESSMENT ETA is July 5/8 Quote entered into FEXA & APPROVED 5/1 Tech did assessment, waiting on quote or further direction | F100: Materials Ordered | H100: WO-0561294 | I100: Charlotte, NC | J100: Dollar General #9929 | K100: Townville | L100: SC | M100: 4970415 | N100: FEXA | O100: CASE ASSESSMENT | Q100: X | U100: Hussmann Cases – 5 qty Cases: RFLN4/MY23f057380 ~ RFMN4/MY23h081991 ~ RFLN4/MY23C028835 Ice cream ~ IDF5SM8TE/MY23g064419 Open Air Meat & IDF5SM12TE/MY23HO73441 Open Air produce: Tech must perform a thorough inspection of each case, take pictures of any damage/findings (water leak/refrigerant leak/damage, ect…) and list repairs needed for each case. Look below for items to check for on the cases and previous repairs performed by others. Any questions, contact Suzanne/Hussmann Account Manager @ 206-255-7674. Items to look at: - Store temperature & Humidity by the cases - Any air from vents/door on the Open-Air Cases - Check case temperatures - Defrost - Programming of controller, ensure it’s program to spec - Product is below the product line/not blocking vents - Reach in doors closing/sealing properly & gasket in good condition - Condensate drain/pan conditions - List repairs needed for each case, need to submit proposal - Tech MUST take pictures of any damage/findings (leaking water, refrigerant leak, damage to case, ect…) • IDF5SM12TE/MY23HO73441 Open Air cooler produce? o 11/19/24-11/21 replaced fan blade o 11/29/24-12/16 compressor o 2/12/25-2/12 condensate pump line clogged o 3/24/25-3/26 condensate pump line air bubble o 5/15/25-5/16 water leaking. Tech found nothing. o 5/31/25-6/5 frozen over and making noise. o 6/22/25-6/27 frozen due to fan shroud off. o 7/3/25-7/7 fan clanging and water leaking. Cleared tubing again o 7/12/25-7/15 water pan full again. Tech shortened hose again o 7/15/25-7/16 duplicate o 7/30/25-8/6 cooler basin full of water AGAIN o 8/8/25-8/11 replaced condensate pump o 10/30/25-11/18 leaking. Replaced condensate pump o 3/12/26-3/16 leaking. Replaced condensate pump o 4/15/26 tech found unit leaking and fixed on site same day. • IDF5SM8TE/MY23g064419 Open Air meat cooler o 2/19/26-2/20/26 water leak. Condensate pump cleaned and tubes. o 4/14/26-4/16/26 pump replacement • RFLN4/MY23C028835 Ice cream walk in o 7/12/25-7/27 replaced terminal o 8/11/25-8/13 replaced contactor and controller o 8/28/25-8/30-8/29 ice build up between doors. o 10/31/25-11/6 ice build up between doors. Rewired. o 11/14/25-11/18 replaced condensate pump o 1/15/26-1/19 tightened wires. Puddles and freezing o 3/1/26-3/12 replace door frame heaters o 3/16/26-3/19 not holding temp. fixed wiring o 4/6/26 open ticket. Replacing frame heater leaking. • RFLN4/MY23f057380 • RFMN4/MY23h081991
A101: d4d7c48b-4642-f111-88b5-000d3a57f875 | B101: 6ijwTb/9fTwly/teL3uyRmAyl9r2IiwPgeyuu995of7NElE4XxQP0ThQqA9kfwKEQdf3Zf7iKyrWaFaPq4z9vA== | C101: 46142.591 | D101: 46139.317 | E101: Emailed Branch to close ticket | F101: Completed | G101: 46150 | H101: WO-0560039 | I101: Houston, TX | J101: Dollar General #20582 | K101: Houston | L101: TX | M101: 4967141 | N101: FEXA | O101: WATER LEAK & DOOR | P101: DOOR REPLACEMENT - WARRANTY | S101: RLN2MA/MY26B016475 | U101: 3 units REG* RLN2MA- MY26B016476 Leaking. Tech MUST obtain Store Temperature & Humidity Readings. Take picture or write in ticket the CASE & CONDENSING UNIT equipment tag (model & serial #). o Store Hours: 8am – 9pm (store will not stay past closing) o Overtime Approved: NO o Problem: Check In/Out with Store Manager on Duty & Obtain Signature Hussmann R290 Microblock Equipment ONLY: RLN2MA- MY26B016476 Leaking. Tech can only work on multiple Hussmann R290 cases with one ticket, confirm all cases are operating or diagnose before leaving the store. • DO NOT work on existing cases, communicate to the Store MOD to place call with their service vendor. • Tech must list or take pictures of the data tag of all equipment model/serial number repaired on service ticket and provide a detail work summary of each equipment repaired. • If you need assistance, please contact the following Hussmann Technical Support Team @ 866-785-8499 or the following: 1) Todd Green @ 210-346-0005 2) Jeff Fosnaugh @ 314-501-8736 3) Andrew Miller @ 314-501-8698 • Hussmann Performance Parts @ 855-487-7778, option #3 – Warranty • Tecumseh compressor warranty – supply house will provide warranty tag to fill out & obtain a copy for office. Must purchase the compressor & file warranty claim. • If parts are not available & have long lead time, send an e-mail @ dg.service@hussmann.com to help locate. • Invoice MUST be submitted within 45 days of repair completion date to TAVANT. For support with warranty claim @ 800-398-7402, option #4 or hussmannwarrantyclaims@hussmann.com Send repair status with a brief work summary BEFORE leaving the location & contact to dg.service@hussmann.com. If you have any questions, contact us at @ dg.service@hussmann.com Troubleshooting Process Step 1 - Start with documentation located within case • Operation Manual & Data Sheet with the case. Step 2 - Scan Hussmann QR Code located on model/serial plate • Type serial number of case and follow navigation for product sheets, data sheets, and manuals Step 3 – Scan BOX QR Code for Box account • Carries in depth support - parameters, controller guides etc. Step 4 - Contact technical support - direct line #866-785-8499 • Tech support will escalate to our Field Equipment Team if issue cannot be resolved – tech support does not provide NTE/OT approval. Problem: MY26B014956 "Leaking Check In/Out with Store Manager on Duty & Obtain Signature Hussmann R290 Microblock Equipment ONLY: Model#: RLN3 Serial # MY26B014956 "Leaking Factory Order #: 901021 Ship Date: 2026-00-23 • TECH must obtain a photo of the equipment tag that includes MODEL & SERIAL number on the CASE & CONDENSING UNIT (Tecumseh) • Tech can only work on multiple Hussmann R290 cases with one ticket, confirm all cases are operating or diagnose before leaving the store. • DO NOT work on existing cases, communicate to the Store MOD to place call with their service vendor. • Tech must list or take pictures of the data tag of all equipment model/serial number repaired on service ticket and provide a detail work summary of each equipment repaired. • If you need assistance, please contact the following Hussmann Technical Support Team @ 866-785-8499 or the following: 1) Todd Green @ 210-346-0005 2) Jeff Fosnaugh @ 314-501-8736 3) Andrew Miller @ 314-501-8698 • Hussmann Performance Parts @ 855-487-7778, option #3 – Warranty • Tecumseh compressor warranty – supply house will provide warranty tag to fill out & obtain a copy for office. Must purchase the compressor & file warranty claim. • If parts are not available & have long lead time, send an e-mail @ dg.service@hussmann.com to help locate. • Invoice MUST be submitted within 45 days of repair completion date to TAVANT. For support with warranty claim @ 800-398-7402, option #4 or hussmannwarrantyclaims@hussmann.com Send repair status with a brief work summary BEFORE leaving the location & contact to dg.service@hussmann.com. If you have any questions, contact us at @ dg.service@hussmann.com Troubleshooting Process Step 1 - Start with documentation located within case • Operation Manual & Data Sheet with the case. Step 2 - Scan Hussmann QR Code located on model/serial plate • Type serial number of case and follow navigation for product sheets, data sheets, and manuals Step 3 – Scan BOX QR Code for Box account • Carries in depth support - parameters, controller guides etc. | V101: 5/Helped tech Ray Rueda check out self contain cases leaking water , case kn back wall leaking water do to built up ice and gap between end panel and bottom of case bottom and case on side wall leaking water condensation down wall do to split insulation , reglued insulation and taped with insulation tape. ***Unable to check out of call*** 4/30Arrived onsite checked in with the store manager after talking withanager found case that were leaking had to use 6ft ladder to get on top of cases to checked drains and drain pans after looking at units found one unit to have a broke insulation on the suction line insulating was ripped had water build up and would run down the back wall onto the floore making big puddle of water so pulled back line fixed insulation with glue and insulation tape found other case to be leaking air on the outside that is leaking air from the inside blowing -10 defree air on outside panel causing it to sweat and make a ice ball on outsode of case all pucs are attached to wo will need to return with caulkinh and seal case properly were there will be no air escaping from unit causeing outsode to sweat and make water on floore will need to get with manager to see if install crew needs to return to properly seal case Resource: Ray Rueda
...

Sheet Settings
A1: Root Cause Settings - dropdown source and clean-point rules
A3: Root Cause | B3: Group | C3: Owner | D3: Status | E3: Clean-Point Date | F3: Clean-Point Serial | G3: Display Order | H3: Cause Color (hex) | I3: Group Color (hex)
A4: Ref. leak/ Low charge | B4: Ref. leak/ Low charge | C4: Tecumseh | D4: Closed | E4: 46132 | G4: 1 | H4: 70AD47 | I4: 70AD47
A5: Door Torque | B5: Doors | C5: Hussmann MTY | D5: Closed | E5: 46178 | G5: 2 | H5: FFC000 | I5: FFC000
A6: Door Gasket | B6: Doors | C6: HSM MTY/RPM | D6: Closed | E6: 46178 | F6: NA | G6: 3 | H6: FFC000 | I6: FFC000
A7: Door frame heater | B7: Doors | C7: HSM MTY | D7: Closed | E7: 46178 | F7: NA | G7: 4 | H7: FFC000 | I7: FFC000
A8: Door Torsion rod | B8: Doors | C8: HSM MTY/RPM | D8: Closed | E8: 46178 | F8: NA | G8: 5 | H8: FFC000 | I8: FFC000
A9: Door not closed (Overnight) | B9: Doors | C9: HSM MTY/ RPM | D9: Closed | E9: 46178 | G9: 6 | H9: FFC000 | I9: FFC000
A10: Door - general | B10: Doors | C10: HSM | D10: Closed | E10: 46178 | F10: NA | G10: 7 | H10: FFC000 | I10: FFC000
A11: Drain tube blocked | B11: Drain tube blocked | C11: Tecumseh | D11: Closed | E11: 46213 | F11: 04G0926122771 | G11: 8 | H11: 4472C4 | I11: 4472C4
A12: Wrong / Loose wiring | B12: Wrong / Loose wiring | C12: Tecumseh | D12: Closed | E12: 46108 | G12: 9 | H12: ED7D31 | I12: ED7D31
A13: Communication problem | B13: Communication problem | C13: RPM | D13: Open | E13: 46191 | F13: NA | G13: 10 | H13: 5B9BD5 | I13: 5B9BD5
A14: High Store RH | B14: High Store RH | C14: DG | D14: Closed | E14: 46171 | F14: NA | G14: 11 | H14: A5A5A5 | I14: A5A5A5
A15: Enclosure Seal | B15: Enclosure Seal | C15: Tecumseh | D15: Closed | E15: 46135 | G15: 12 | H15: 264478 | I15: 264478
A16: Component Failure | B16: Component Failure | C16: Tecumseh | D16: TBD | G16: 13 | H16: 9E480E | I16: 9E480E
A17: Defrost Sync | B17: Defrost Sync | C17: HSM BGN | D17: Closed | E17: 46185 | F17: NA | G17: 14 | H17: 636363 | I17: 636363
A18: False Alarm | B18: False Alarm | C18: HSM BGN | D18: Closed | E18: 46164 | F18: NA | G18: 15 | H18: 997300 | I18: 997300
A19: Setpoint change | B19: Setpoint change | C19: Tecumseh | D19: Closed | E19: 46097 | G19: 16 | H19: 2.55e+93 | I19: 2.55e+93
A20: Overstocking | B20: Overstocking | C20: DG | D20: Closed | E20: 46171 | G20: 17 | H20: 43682B | I20: 43682B
A21: Case End Seal | B21: Case End Seal | C21: HSM MTY | D21: Closed | E21: 46171 | G21: 18 | H21: 698ED0 | I21: 698ED0
A22: Return Air blocked | B22: Return Air blocked | C22: DG | D22: Closed | E22: 46171 | F22: NA | G22: 19 | H22: F1975A | I22: F1975A
A23: Unidentified air leak | B23: Unidentified air leak | C23: HSM BGN | D23: Open | E23: 46189 | F23: NA | G23: 20 | H23: B7B7B7 | I23: B7B7B7
A24: Freedom | B24: Freedom | C24: NA | D24: Closed | F24: NA | G24: 21 | H24: 1F4E79 | I24: 1F4E79
A25: Heavy case load | B25: Heavy case load | C25: DG | D25: Closed | E25: 46171 | F25: NA | G25: 22 | H25: C00000 | I25: C00000
A26: DG Installation issue | B26: DG Installation issue | C26: RPM | D26: Closed | E26: 46171 | F26: NA | G26: 23 | H26: 7030A0 | I26: 7030A0
A27: Unknown | B27: Unknown | C27: NA | D27: Open | F27: NA | G27: 24 | H27: 2E75B6 | I27: 2E75B6
A28: Program change - Hussmann | B28: Program change - Hussmann | C28: HSM BGN | D28: Open | E28: 46171 | F28: NA | G28: 25 | H28: BF9000 | I28: BF9000
A29: Wrong program | B29: Wrong program | C29: Tecumseh | D29: Open | F29: NA | G29: 26 | H29: 2.55e+93 | I29: 2.55e+93
A63: T-S2 Constants
A64: Label | B64: Value | C64: Name
A65: Max Summary rows | B65: 240 | C65: set_maxSummaryRow
A66: Max Raw rows | B66: 400 | C66: set_maxRawRow
A67: Max causes | B67: 80 | C67: set_maxCauses
A68: Weeks shown | B68: 20 | C68: set_weeksShown
A69: Tiebreak divisor | B69: 100000 | C69: set_tiebreakDivisor
A73: T-S3 Serial prefixes
A74: Prefix
A75: RLN2MA
A76: RLN3MA
A77: RLN4MA
A78: RMN4MA
A79: RMN3MA
A80: RMN5MA

Sheet Store List
A1: Store List - one row per store with commission date
A3: DG Store # | B3: Store Commission Date | C3: City | D3: State | E3: Notes
A4: Dollar General #13338 | B4: 46092 | C4: McRae | D4: AR
A5: Dollar General #20876 | B5: 46112 | C5: Elaine | D5: AR
A6: Dollar General #21375 | B6: 46091 | C6: Oxford | D6: AR
A7: Dollar General #22515 | B7: 46090 | C7: Fort Smith | D7: AR
A8: Dollar General #6827 | B8: 46086 | C8: Conway | D8: AR
A9: DOLLAR GENERAL #10369 | B9: 46106 | C9: Ajo | D9: AZ
A10: Dollar General #10339 | B10: 46141 | C10: Casa Grande | D10: AZ
A11: Dollar General #13396 | B11: 46141 | C11: Coolidge | D11: AZ
A12: Dollar General #13631 | B12: 46147 | C12: Quartzsite | D12: AZ
A13: Dollar General #14104 | B13: 46105 | C13: Tucson | D13: AZ
A14: Dollar General #16435 | B14: 46106 | C14: Tuba City | D14: AZ
A15: Dollar General #19997 | B15: 46142 | C15: Buckeye | D15: AZ
... A72: Dollar General 22799 | B72: 46099 | C72: Amarillo | D72: TX
A73: Unknown legacy store | B73: 46085
A74: Dollar general #21257 | B74: 46211 | C74: Kankakee | D74: IL
A75: Dollar General #22187 | B75: 46213 | C75: Essex | D75: IL
A76: Dollar General 21548 | B76: 46214 | C76: Wills Point | D76: TX
A77: Dollar General #10095 | B77: 46215 | C77: Noonday | D77: TX
A78: Dollar General #20339 | B78: 46212 | C78: Porter | D78: TX
A79: Dollar General #05805 | B79: 46212 | C79: New Caney | D79: TX
A80: Dollar General #22040 | B80: 46212 | C80: Midland City | D80: AL
A81: Dollar General #21303 | B81: 46210 | C81: Rangely | D81: CO
A82: Dollar General #12959 | B82: 46211 | C82: Houston | D82: TX
A83: Dollar General #11114 | B83: 46211 | C83: Delta | D83: UT
A84: Dollar General #12377 | B84: 46211 | C84: Baytown | D84: TX
A85: Dollar General #2606 | B85: 46209 | C85: Logansport | D85: IN
... A154: Dollar General #31839 | B154: 46155 | C154: Jacksonville | D154: AL
A155: Dollar General #13953 | C155: Allen | D155: OK
A156: Dollar General #06559 | C156: Gardendale | D156: AL
A157: Dollar General #06314 | C157: Northport | D157: AL
A158: Dollar General #06550 | B158: 46147 | C158: Jacinto | D158: TX
A159: Dollar General #13693 | C159: Maryland Heights | D159: MO
A160: Dollar General #21829 | C160: Hazelwood | D160: MO
A161: Dollar General #24159 | C161: Herculaneum | D161: MO
A162: Dollar General #21783 | C162: East Bethel | D162: MN
A163: Dollar General #00279 | C163: Fouke | D163: AR
A164: Dollar General #22107 | B164: 46160 | C164: Waubun | D164: MN
A165: Dollar General #09806 | B165: 45553 | C165: Scottsville | D165: KY
A166: Dollar General #25692 | C166: Charlotte | D166: NC
A167: Dollar General #08790 | C167: Lafayette | D167: LA
A168: Dollar General #30977 | B168: 45531 | C168: Scottsboro | D168: AL
A169: Dollar General #10884 | B169: 45524 | C169: Cullman | D169: AL
A170: Dollar General #03217 | B170: 45502 | C170: Lillington | D170: NC
A171: Dollar General #02332 | B171: 45531 | C171: Sylacauga | D171: AL
A172: Dollar General #03000 | C172: Florissant | D172: MO
A173: Dollar General #06026 | C173: Overland | D173: MO

Sheet Calc_Weekly
A1: T-W1/T-W2/T-W3 Weekly pivots
A2: Three stacked pivots: commission week by root cause, call week by root cause, and commission week by group. Week rows remain capped by Settings!Weeks shown.
A3: Commission week by root cause
B4: Group | C4: =Settings!B4 -> Ref. leak/ Low charge | D4: =Settings!B5 -> Doors | E4: =Settings!B6 -> Doors | F4: =Settings!B7 -> Doors | G4: =Settings!B8 -> Doors | H4: =Settings!B9 -> Doors | I4: =Settings!B10 -> Doors | J4: =Settings!B11 -> Drain tube blocked | K4: =Settings!B12 -> Wrong / Loose wiring | L4: =Settings!B13 -> Communication problem | M4: =Settings!B14 -> High Store RH | N4: =Settings!B15 -> Enclosure Seal | O4: =Settings!B16 -> Component Failure | P4: =Settings!B17 -> Defrost Sync | Q4: =Settings!B18 -> False Alarm | R4: =Settings!B19 -> Setpoint change | S4: =Settings!B20 -> Overstocking | T4: =Settings!B21 -> Case End Seal | U4: =Settings!B22 -> Return Air blocked | V4: =Settings!B23 -> Unidentified air leak | W4: =Settings!B24 -> Freedom | X4: =Settings!B25 -> Heavy case load | Y4: =Settings!B26 -> DG Installation issue | Z4: =Settings!B27 -> Unknown | AA4: =Settings!B28 -> Program change - Hussmann | AB4: =Settings!B29 -> Wrong program | AC4: =Settings!B30 -> 0 | AD4: =Settings!B31 -> 0 | AE4: =Settings!B32 -> 0 | AF4: =Settings!B33 -> 0 | AG4: =Settings!B34 -> 0 | AH4: =Settings!B35 -> 0 | AI4: =Settings!B36 -> 0 | AJ4: =Settings!B37 -> 0 | AK4: =Settings!B38 -> 0 | AL4: =Settings!B39 -> 0 | AM4: =Settings!B40 -> 0 | AN4: =Settings!B41 -> 0 | AO4: =Settings!B42 -> 0 | AP4: =Settings!B43 -> 0 | AQ4: =Settings!B44 -> 0 | AR4: =Settings!B45 -> 0 | AS4: =Settings!B46 -> 0 | AT4: =Settings!B47 -> 0 | AU4: =Settings!B48 -> 0 | AV4: =Settings!B49 -> 0 | AW4: =Settings!B50 -> 0 | AX4: =Settings!B51 -> 0 | AY4: =Settings!B52 -> 0 | AZ4: =Settings!B53 -> 0 | BA4: =Settings!B54 -> 0 | BB4: =Settings!B55 -> 0 | BC4: =Settings!B56 -> 0 | BD4: =Settings!B57 -> 0 | BE4: =Settings!B58 -> 0 | BF4: =Settings!B59 -> 0
A5: Week Start | B5: Root Cause | C5: =Settings!A4 -> Ref. leak/ Low charge | D5: =Settings!A5 -> Door Torque | E5: =Settings!A6 -> Door Gasket | F5: =Settings!A7 -> Door frame heater | G5: =Settings!A8 -> Door Torsion rod | H5: =Settings!A9 -> Door not closed (Overnight) | I5: =Settings!A10 -> Door - general | J5: =Settings!A11 -> Drain tube blocked | K5: =Settings!A12 -> Wrong / Loose wiring | L5: =Settings!A13 -> Communication problem | M5: =Settings!A14 -> High Store RH | N5: =Settings!A15 -> Enclosure Seal | O5: =Settings!A16 -> Component Failure | P5: =Settings!A17 -> Defrost Sync | Q5: =Settings!A18 -> False Alarm | R5: =Settings!A19 -> Setpoint change | S5: =Settings!A20 -> Overstocking | T5: =Settings!A21 -> Case End Seal | U5: =Settings!A22 -> Return Air blocked | V5: =Settings!A23 -> Unidentified air leak | W5: =Settings!A24 -> Freedom | X5: =Settings!A25 -> Heavy case load | Y5: =Settings!A26 -> DG Installation issue | Z5: =Settings!A27 -> Unknown | AA5: =Settings!A28 -> Program change - Hussmann | AB5: =Settings!A29 -> Wrong program | AC5: =Settings!A30 -> 0 | AD5: =Settings!A31 -> 0 | AE5: =Settings!A32 -> 0 | AF5: =Settings!A33 -> 0 | AG5: =Settings!A34 -> 0 | AH5: =Settings!A35 -> 0 | AI5: =Settings!A36 -> 0 | AJ5: =Settings!A37 -> 0 | AK5: =Settings!A38 -> 0 | AL5: =Settings!A39 -> 0 | AM5: =Settings!A40 -> 0 | AN5: =Settings!A41 -> 0 | AO5: =Settings!A42 -> 0 | AP5: =Settings!A43 -> 0 | AQ5: =Settings!A44 -> 0 | AR5: =Settings!A45 -> 0 | AS5: =Settings!A46 -> 0 | AT5: =Settings!A47 -> 0 | AU5: =Settings!A48 -> 0 | AV5: =Settings!A49 -> 0 | AW5: =Settings!A50 -> 0 | AX5: =Settings!A51 -> 0 | AY5: =Settings!A52 -> 0 | AZ5: =Settings!A53 -> 0 | BA5: =Settings!A54 -> 0 | BB5: =Settings!A55 -> 0 | BC5: =Settings!A56 -> 0 | BD5: =Settings!A57 -> 0 | BE5: =Settings!A58 -> 0 | BF5: =Settings!A59 -> 0
A6: =MIN(Summary!$D$5:$D$241)-WEEKDAY(MIN(Summary!$D$5:$D$241),2)+1 -> 46083 | B6: =TEXT(A6,"mmm d") -> Mar 2 | C6: =IF(C5="","",COUNTIFS(Summary!$E$5:$E$241,C5,Summary!$D$5:$D$241,">="&$A6,Summary!$D$5:$D$241,"<"&$A6+7)) -> 0 | D6: =IF(D5="","",COUNTIFS(Summary!$E$5:$E$241,D5,Summary!$D$5:$D$241,">="&$A6,Summary!$D$5:$D$241,"<"&$A6+7)) -> 0 | E6: =IF(E5="","",COUNTIFS(Summary!$E$5:$E$241,E5,Summary!$D$5:$D$241,">="&$A6,Summary!$D$5:$D$241,"<"&$A6+7)) -> 0 | F6: =IF(F5="","",COUNTIFS(Summary!$E$5:$E$241,F5,Summary!$D$5:$D$241,">="&$A6,Summary!$D$5:$D$241,"<"&$A6+7)) -> 0 | G6: =IF(G5="","",COUNTIFS(Summary!$E$5:$E$241,G5,Summary!$D$5:$D$241,">="&$A6,Summary!$D$5:$D$241,"<"&$A6+7)) -> 0 | H6: =IF(H5="","",COUNTIFS(Summary!$E$5:$E$241,H5,Summary!$D$5:$D$241,">="&$A6,Summary!$D$5:$D$241,"<"&$A6+7)) -> 1 | I6: =IF(I5="","",COUNTIFS(Summary!$E$5:$E$241,I5,Summary!$D$5:$D$241,">="&$A6,Summary!$D$5:$D$241,"<"&$A6+7)) -> 1 | J6: =IF(J5="","",COUNTIFS(Summary!$E$5:$E$241,J5,Summary!$D$5:$D$241,">="&$A6,Summary!$D$5:$D$241,"<"&$A6+7)) -> 1 | ... BF6: =IF(BF5="","",COUNTIFS(Summary!$E$5:$E$241,BF5,Summary!$D$5:$D$241,">="&$A6,Summary!$D$5:$D$241,"<"&$A6+7)) -> 0
A7: =A6+7 -> 46090 | B7: =TEXT(A7,"mmm d") -> Mar 9 | C7: =IF(C5="","",COUNTIFS(Summary!$E$5:$E$241,C5,Summary!$D$5:$D$241,">="&$A7,Summary!$D$5:$D$241,"<"&$A7+7)) -> 0 | D7: =IF(D5="","",COUNTIFS(Summary!$E$5:$E$241,D5,Summary!$D$5:$D$241,">="&$A7,Summary!$D$5:$D$241,"<"&$A7+7)) -> 1 | E7: =IF(E5="","",COUNTIFS(Summary!$E$5:$E$241,E5,Summary!$D$5:$D$241,">="&$A7,Summary!$D$5:$D$241,"<"&$A7+7)) -> 0 | F7: =IF(F5="","",COUNTIFS(Summary!$E$5:$E$241,F5,Summary!$D$5:$D$241,">="&$A7,Summary!$D$5:$D$241,"<"&$A7+7)) -> 0 | G7: =IF(G5="","",COUNTIFS(Summary!$E$5:$E$241,G5,Summary!$D$5:$D$241,">="&$A7,Summary!$D$5:$D$241,"<"&$A7+7)) -> 0 | H7: =IF(H5="","",COUNTIFS(Summary!$E$5:$E$241,H5,Summary!$D$5:$D$241,">="&$A7,Summary!$D$5:$D$241,"<"&$A7+7)) -> 2 | I7: =IF(I5="","",COUNTIFS(Summary!$E$5:$E$241,I5,Summary!$D$5:$D$241,">="&$A7,Summary!$D$5:$D$241,"<"&$A7+7)) -> 1 | J7: =IF(J5="","",COUNTIFS(Summary!$E$5:$E$241,J5,Summary!$D$5:$D$241,">="&$A7,Summary!$D$5:$D$241,"<"&$A7+7)) -> 1 | ... BF7: =IF(BF5="","",COUNTIFS(Summary!$E$5:$E$241,BF5,Summary!$D$5:$D$241,">="&$A7,Summary!$D$5:$D$241,"<"&$A7+7)) -> 0
A8: =A7+7 -> 46097 | B8: =TEXT(A8,"mmm d") -> Mar 16 | C8: =IF(C5="","",COUNTIFS(Summary!$E$5:$E$241,C5,Summary!$D$5:$D$241,">="&$A8,Summary!$D$5:$D$241,"<"&$A8+7)) -> 3 | D8: =IF(D5="","",COUNTIFS(Summary!$E$5:$E$241,D5,Summary!$D$5:$D$241,">="&$A8,Summary!$D$5:$D$241,"<"&$A8+7)) -> 3 | E8: =IF(E5="","",COUNTIFS(Summary!$E$5:$E$241,E5,Summary!$D$5:$D$241,">="&$A8,Summary!$D$5:$D$241,"<"&$A8+7)) -> 0 | F8: =IF(F5="","",COUNTIFS(Summary!$E$5:$E$241,F5,Summary!$D$5:$D$241,">="&$A8,Summary!$D$5:$D$241,"<"&$A8+7)) -> 1 | G8: =IF(G5="","",COUNTIFS(Summary!$E$5:$E$241,G5,Summary!$D$5:$D$241,">="&$A8,Summary!$D$5:$D$241,"<"&$A8+7)) -> 0 | H8: =IF(H5="","",COUNTIFS(Summary!$E$5:$E$241,H5,Summary!$D$5:$D$241,">="&$A8,Summary!$D$5:$D$241,"<"&$A8+7)) -> 1 | I8: =IF(I5="","",COUNTIFS(Summary!$E$5:$E$241,I5,Summary!$D$5:$D$241,">="&$A8,Summary!$D$5:$D$241,"<"&$A8+7)) -> 1 | J8: =IF(J5="","",COUNTIFS(Summary!$E$5:$E$241,J5,Summary!$D$5:$D$241,">="&$A8,Summary!$D$5:$D$241,"<"&$A8+7)) -> 0 | ... BF8: =IF(BF5="","",COUNTIFS(Summary!$E$5:$E$241,BF5,Summary!$D$5:$D$241,">="&$A8,Summary!$D$5:$D$241,"<"&$A8+7)) -> 0
A9: =A8+7 -> 46104 | B9: =TEXT(A9,"mmm d") -> Mar 23 | C9: =IF(C5="","",COUNTIFS(Summary!$E$5:$E$241,C5,Summary!$D$5:$D$241,">="&$A9,Summary!$D$5:$D$241,"<"&$A9+7)) -> 0 | D9: =IF(D5="","",COUNTIFS(Summary!$E$5:$E$241,D5,Summary!$D$5:$D$241,">="&$A9,Summary!$D$5:$D$241,"<"&$A9+7)) -> 3 | E9: =IF(E5="","",COUNTIFS(Summary!$E$5:$E$241,E5,Summary!$D$5:$D$241,">="&$A9,Summary!$D$5:$D$241,"<"&$A9+7)) -> 2 | F9: =IF(F5="","",COUNTIFS(Summary!$E$5:$E$241,F5,Summary!$D$5:$D$241,">="&$A9,Summary!$D$5:$D$241,"<"&$A9+7)) -> 0 | G9: =IF(G5="","",COUNTIFS(Summary!$E$5:$E$241,G5,Summary!$D$5:$D$241,">="&$A9,Summary!$D$5:$D$241,"<"&$A9+7)) -> 0 | H9: =IF(H5="","",COUNTIFS(Summary!$E$5:$E$241,H5,Summary!$D$5:$D$241,">="&$A9,Summary!$D$5:$D$241,"<"&$A9+7)) -> 1 | I9: =IF(I5="","",COUNTIFS(Summary!$E$5:$E$241,I5,Summary!$D$5:$D$241,">="&$A9,Summary!$D$5:$D$241,"<"&$A9+7)) -> 0 | J9: =IF(J5="","",COUNTIFS(Summary!$E$5:$E$241,J5,Summary!$D$5:$D$241,">="&$A9,Summary!$D$5:$D$241,"<"&$A9+7)) -> 1 | ... BF9: =IF(BF5="","",COUNTIFS(Summary!$E$5:$E$241,BF5,Summary!$D$5:$D$241,">="&$A9,Summary!$D$5:$D$241,"<"&$A9+7)) -> 0
A10: =A9+7 -> 46111 | B10: =TEXT(A10,"mmm d") -> Mar 30 | C10: =IF(C5="","",COUNTIFS(Summary!$E$5:$E$241,C5,Summary!$D$5:$D$241,">="&$A10,Summary!$D$5:$D$241,"<"&$A10+7)) -> 0 | D10: =IF(D5="","",COUNTIFS(Summary!$E$5:$E$241,D5,Summary!$D$5:$D$241,">="&$A10,Summary!$D$5:$D$241,"<"&$A10+7)) -> 0 | E10: =IF(E5="","",COUNTIFS(Summary!$E$5:$E$241,E5,Summary!$D$5:$D$241,">="&$A10,Summary!$D$5:$D$241,"<"&$A10+7)) -> 0 | F10: =IF(F5="","",COUNTIFS(Summary!$E$5:$E$241,F5,Summary!$D$5:$D$241,">="&$A10,Summary!$D$5:$D$241,"<"&$A10+7)) -> 0 | G10: =IF(G5="","",COUNTIFS(Summary!$E$5:$E$241,G5,Summary!$D$5:$D$241,">="&$A10,Summary!$D$5:$D$241,"<"&$A10+7)) -> 0 | H10: =IF(H5="","",COUNTIFS(Summary!$E$5:$E$241,H5,Summary!$D$5:$D$241,">="&$A10,Summary!$D$5:$D$241,"<"&$A10+7)) -> 0 | I10: =IF(I5="","",COUNTIFS(Summary!$E$5:$E$241,I5,Summary!$D$5:$D$241,">="&$A10,Summary!$D$5:$D$241,"<"&$A10+7)) -> 0 | J10: =IF(J5="","",COUNTIFS(Summary!$E$5:$E$241,J5,Summary!$D$5:$D$241,">="&$A10,Summary!$D$5:$D$241,"<"&$A10+7)) -> 0 | ... BF10: =IF(BF5="","",COUNTIFS(Summary!$E$5:$E$241,BF5,Summary!$D$5:$D$241,">="&$A10,Summary!$D$5:$D$241,"<"&$A10+7)) -> 0
A11: =A10+7 -> 46118 | B11: =TEXT(A11,"mmm d") -> Apr 6 | C11: =IF(C5="","",COUNTIFS(Summary!$E$5:$E$241,C5,Summary!$D$5:$D$241,">="&$A11,Summary!$D$5:$D$241,"<"&$A11+7)) -> 5 | D11: =IF(D5="","",COUNTIFS(Summary!$E$5:$E$241,D5,Summary!$D$5:$D$241,">="&$A11,Summary!$D$5:$D$241,"<"&$A11+7)) -> 0 | E11: =IF(E5="","",COUNTIFS(Summary!$E$5:$E$241,E5,Summary!$D$5:$D$241,">="&$A11,Summary!$D$5:$D$241,"<"&$A11+7)) -> 0 | F11: =IF(F5="","",COUNTIFS(Summary!$E$5:$E$241,F5,Summary!$D$5:$D$241,">="&$A11,Summary!$D$5:$D$241,"<"&$A11+7)) -> 0 | G11: =IF(G5="","",COUNTIFS(Summary!$E$5:$E$241,G5,Summary!$D$5:$D$241,">="&$A11,Summary!$D$5:$D$241,"<"&$A11+7)) -> 0 | H11: =IF(H5="","",COUNTIFS(Summary!$E$5:$E$241,H5,Summary!$D$5:$D$241,">="&$A11,Summary!$D$5:$D$241,"<"&$A11+7)) -> 0 | I11: =IF(I5="","",COUNTIFS(Summary!$E$5:$E$241,I5,Summary!$D$5:$D$241,">="&$A11,Summary!$D$5:$D$241,"<"&$A11+7)) -> 0 | J11: =IF(J5="","",COUNTIFS(Summary!$E$5:$E$241,J5,Summary!$D$5:$D$241,">="&$A11,Summary!$D$5:$D$241,"<"&$A11+7)) -> 0 | ... BF11: =IF(BF5="","",COUNTIFS(Summary!$E$5:$E$241,BF5,Summary!$D$5:$D$241,">="&$A11,Summary!$D$5:$D$241,"<"&$A11+7)) -> 0
A12: =A11+7 -> 46125 | B12: =TEXT(A12,"mmm d") -> Apr 13 | C12: =IF(C5="","",COUNTIFS(Summary!$E$5:$E$241,C5,Summary!$D$5:$D$241,">="&$A12,Summary!$D$5:$D$241,"<"&$A12+7)) -> 1 | D12: =IF(D5="","",COUNTIFS(Summary!$E$5:$E$241,D5,Summary!$D$5:$D$241,">="&$A12,Summary!$D$5:$D$241,"<"&$A12+7)) -> 1 | E12: =IF(E5="","",COUNTIFS(Summary!$E$5:$E$241,E5,Summary!$D$5:$D$241,">="&$A12,Summary!$D$5:$D$241,"<"&$A12+7)) -> 0 | F12: =IF(F5="","",COUNTIFS(Summary!$E$5:$E$241,F5,Summary!$D$5:$D$241,">="&$A12,Summary!$D$5:$D$241,"<"&$A12+7)) -> 0 | G12: =IF(G5="","",COUNTIFS(Summary!$E$5:$E$241,G5,Summary!$D$5:$D$241,">="&$A12,Summary!$D$5:$D$241,"<"&$A12+7)) -> 0 | H12: =IF(H5="","",COUNTIFS(Summary!$E$5:$E$241,H5,Summary!$D$5:$D$241,">="&$A12,Summary!$D$5:$D$241,"<"&$A12+7)) -> 3 | I12: =IF(I5="","",COUNTIFS(Summary!$E$5:$E$241,I5,Summary!$D$5:$D$241,">="&$A12,Summary!$D$5:$D$241,"<"&$A12+7)) -> 1 | J12: =IF(J5="","",COUNTIFS(Summary!$E$5:$E$241,J5,Summary!$D$5:$D$241,">="&$A12,Summary!$D$5:$D$241,"<"&$A12+7)) -> 1 | ... BF12: =IF(BF5="","",COUNTIFS(Summary!$E$5:$E$241,BF5,Summary!$D$5:$D$241,">="&$A12,Summary!$D$5:$D$241,"<"&$A12+7)) -> 0
A13: =A12+7 -> 46132 | B13: =TEXT(A13,"mmm d") -> Apr 20 | C13: =IF(C5="","",COUNTIFS(Summary!$E$5:$E$241,C5,Summary!$D$5:$D$241,">="&$A13,Summary!$D$5:$D$241,"<"&$A13+7)) -> 0 | D13: =IF(D5="","",COUNTIFS(Summary!$E$5:$E$241,D5,Summary!$D$5:$D$241,">="&$A13,Summary!$D$5:$D$241,"<"&$A13+7)) -> 0 | E13: =IF(E5="","",COUNTIFS(Summary!$E$5:$E$241,E5,Summary!$D$5:$D$241,">="&$A13,Summary!$D$5:$D$241,"<"&$A13+7)) -> 1 | F13: =IF(F5="","",COUNTIFS(Summary!$E$5:$E$241,F5,Summary!$D$5:$D$241,">="&$A13,Summary!$D$5:$D$241,"<"&$A13+7)) -> 1 | G13: =IF(G5="","",COUNTIFS(Summary!$E$5:$E$241,G5,Summary!$D$5:$D$241,">="&$A13,Summary!$D$5:$D$241,"<"&$A13+7)) -> 0 | H13: =IF(H5="","",COUNTIFS(Summary!$E$5:$E$241,H5,Summary!$D$5:$D$241,">="&$A13,Summary!$D$5:$D$241,"<"&$A13+7)) -> 1 | I13: =IF(I5="","",COUNTIFS(Summary!$E$5:$E$241,I5,Summary!$D$5:$D$241,">="&$A13,Summary!$D$5:$D$241,"<"&$A13+7)) -> 0 | J13: =IF(J5="","",COUNTIFS(Summary!$E$5:$E$241,J5,Summary!$D$5:$D$241,">="&$A13,Summary!$D$5:$D$241,"<"&$A13+7)) -> 1 | ... BF13: =IF(BF5="","",COUNTIFS(Summary!$E$5:$E$241,BF5,Summary!$D$5:$D$241,">="&$A13,Summary!$D$5:$D$241,"<"&$A13+7)) -> 0
A14: =A13+7 -> 46139 | B14: =TEXT(A14,"mmm d") -> Apr 27 | C14: =IF(C5="","",COUNTIFS(Summary!$E$5:$E$241,C5,Summary!$D$5:$D$241,">="&$A14,Summary!$D$5:$D$241,"<"&$A14+7)) -> 0 | D14: =IF(D5="","",COUNTIFS(Summary!$E$5:$E$241,D5,Summary!$D$5:$D$241,">="&$A14,Summary!$D$5:$D$241,"<"&$A14+7)) -> 1 | E14: =IF(E5="","",COUNTIFS(Summary!$E$5:$E$241,E5,Summary!$D$5:$D$241,">="&$A14,Summary!$D$5:$D$241,"<"&$A14+7)) -> 0 | F14: =IF(F5="","",COUNTIFS(Summary!$E$5:$E$241,F5,Summary!$D$5:$D$241,">="&$A14,Summary!$D$5:$D$241,"<"&$A14+7)) -> 0 | G14: =IF(G5="","",COUNTIFS(Summary!$E$5:$E$241,G5,Summary!$D$5:$D$241,">="&$A14,Summary!$D$5:$D$241,"<"&$A14+7)) -> 0 | H14: =IF(H5="","",COUNTIFS(Summary!$E$5:$E$241,H5,Summary!$D$5:$D$241,">="&$A14,Summary!$D$5:$D$241,"<"&$A14+7)) -> 0 | I14: =IF(I5="","",COUNTIFS(Summary!$E$5:$E$241,I5,Summary!$D$5:$D$241,">="&$A14,Summary!$D$5:$D$241,"<"&$A14+7)) -> 0 | J14: =IF(J5="","",COUNTIFS(Summary!$E$5:$E$241,J5,Summary!$D$5:$D$241,">="&$A14,Summary!$D$5:$D$241,"<"&$A14+7)) -> 1 | ... BF14: =IF(BF5="","",COUNTIFS(Summary!$E$5:$E$241,BF5,Summary!$D$5:$D$241,">="&$A14,Summary!$D$5:$D$241,"<"&$A14+7)) -> 0
A15: =A14+7 -> 46146 | B15: =TEXT(A15,"mmm d") -> May 4 | C15: =IF(C5="","",COUNTIFS(Summary!$E$5:$E$241,C5,Summary!$D$5:$D$241,">="&$A15,Summary!$D$5:$D$241,"<"&$A15+7)) -> 0 | D15: =IF(D5="","",COUNTIFS(Summary!$E$5:$E$241,D5,Summary!$D$5:$D$241,">="&$A15,Summary!$D$5:$D$241,"<"&$A15+7)) -> 1 | E15: =IF(E5="","",COUNTIFS(Summary!$E$5:$E$241,E5,Summary!$D$5:$D$241,">="&$A15,Summary!$D$5:$D$241,"<"&$A15+7)) -> 0 | F15: =IF(F5="","",COUNTIFS(Summary!$E$5:$E$241,F5,Summary!$D$5:$D$241,">="&$A15,Summary!$D$5:$D$241,"<"&$A15+7)) -> 0 | G15: =IF(G5="","",COUNTIFS(Summary!$E$5:$E$241,G5,Summary!$D$5:$D$241,">="&$A15,Summary!$D$5:$D$241,"<"&$A15+7)) -> 0 | H15: =IF(H5="","",COUNTIFS(Summary!$E$5:$E$241,H5,Summary!$D$5:$D$241,">="&$A15,Summary!$D$5:$D$241,"<"&$A15+7)) -> 2 | I15: =IF(I5="","",COUNTIFS(Summary!$E$5:$E$241,I5,Summary!$D$5:$D$241,">="&$A15,Summary!$D$5:$D$241,"<"&$A15+7)) -> 0 | J15: =IF(J5="","",COUNTIFS(Summary!$E$5:$E$241,J5,Summary!$D$5:$D$241,">="&$A15,Summary!$D$5:$D$241,"<"&$A15+7)) -> 3 | ... BF15: =IF(BF5="","",COUNTIFS(Summary!$E$5:$E$241,BF5,Summary!$D$5:$D$241,">="&$A15,Summary!$D$5:$D$241,"<"&$A15+7)) -> 0
A16: =A15+7 -> 46153 | B16: =TEXT(A16,"mmm d") -> May 11 | C16: =IF(C5="","",COUNTIFS(Summary!$E$5:$E$241,C5,Summary!$D$5:$D$241,">="&$A16,Summary!$D$5:$D$241,"<"&$A16+7)) -> 0 | D16: =IF(D5="","",COUNTIFS(Summary!$E$5:$E$241,D5,Summary!$D$5:$D$241,">="&$A16,Summary!$D$5:$D$241,"<"&$A16+7)) -> 0 | E16: =IF(E5="","",COUNTIFS(Summary!$E$5:$E$241,E5,Summary!$D$5:$D$241,">="&$A16,Summary!$D$5:$D$241,"<"&$A16+7)) -> 0 | F16: =IF(F5="","",COUNTIFS(Summary!$E$5:$E$241,F5,Summary!$D$5:$D$241,">="&$A16,Summary!$D$5:$D$241,"<"&$A16+7)) -> 0 | G16: =IF(G5="","",COUNTIFS(Summary!$E$5:$E$241,G5,Summary!$D$5:$D$241,">="&$A16,Summary!$D$5:$D$241,"<"&$A16+7)) -> 0 | H16: =IF(H5="","",COUNTIFS(Summary!$E$5:$E$241,H5,Summary!$D$5:$D$241,">="&$A16,Summary!$D$5:$D$241,"<"&$A16+7)) -> 0 | I16: =IF(I5="","",COUNTIFS(Summary!$E$5:$E$241,I5,Summary!$D$5:$D$241,">="&$A16,Summary!$D$5:$D$241,"<"&$A16+7)) -> 1 | J16: =IF(J5="","",COUNTIFS(Summary!$E$5:$E$241,J5,Summary!$D$5:$D$241,">="&$A16,Summary!$D$5:$D$241,"<"&$A16+7)) -> 0 | ... BF16: =IF(BF5="","",COUNTIFS(Summary!$E$5:$E$241,BF5,Summary!$D$5:$D$241,">="&$A16,Summary!$D$5:$D$241,"<"&$A16+7)) -> 0
A17: =A16+7 -> 46160 | B17: =TEXT(A17,"mmm d") -> May 18 | C17: =IF(C5="","",COUNTIFS(Summary!$E$5:$E$241,C5,Summary!$D$5:$D$241,">="&$A17,Summary!$D$5:$D$241,"<"&$A17+7)) -> 0 | D17: =IF(D5="","",COUNTIFS(Summary!$E$5:$E$241,D5,Summary!$D$5:$D$241,">="&$A17,Summary!$D$5:$D$241,"<"&$A17+7)) -> 1 | E17: =IF(E5="","",COUNTIFS(Summary!$E$5:$E$241,E5,Summary!$D$5:$D$241,">="&$A17,Summary!$D$5:$D$241,"<"&$A17+7)) -> 0 | F17: =IF(F5="","",COUNTIFS(Summary!$E$5:$E$241,F5,Summary!$D$5:$D$241,">="&$A17,Summary!$D$5:$D$241,"<"&$A17+7)) -> 2 | G17: =IF(G5="","",COUNTIFS(Summary!$E$5:$E$241,G5,Summary!$D$5:$D$241,">="&$A17,Summary!$D$5:$D$241,"<"&$A17+7)) -> 0 | H17: =IF(H5="","",COUNTIFS(Summary!$E$5:$E$241,H5,Summary!$D$5:$D$241,">="&$A17,Summary!$D$5:$D$241,"<"&$A17+7)) -> 0 | I17: =IF(I5="","",COUNTIFS(Summary!$E$5:$E$241,I5,Summary!$D$5:$D$241,">="&$A17,Summary!$D$5:$D$241,"<"&$A17+7)) -> 0 | J17: =IF(J5="","",COUNTIFS(Summary!$E$5:$E$241,J5,Summary!$D$5:$D$241,">="&$A17,Summary!$D$5:$D$241,"<"&$A17+7)) -> 0 | ... BF17: =IF(BF5="","",COUNTIFS(Summary!$E$5:$E$241,BF5,Summary!$D$5:$D$241,">="&$A17,Summary!$D$5:$D$241,"<"&$A17+7)) -> 0
A18: =A17+7 -> 46167 | B18: =TEXT(A18,"mmm d") -> May 25 | C18: =IF(C5="","",COUNTIFS(Summary!$E$5:$E$241,C5,Summary!$D$5:$D$241,">="&$A18,Summary!$D$5:$D$241,"<"&$A18+7)) -> 0 | D18: =IF(D5="","",COUNTIFS(Summary!$E$5:$E$241,D5,Summary!$D$5:$D$241,">="&$A18,Summary!$D$5:$D$241,"<"&$A18+7)) -> 1 | E18: =IF(E5="","",COUNTIFS(Summary!$E$5:$E$241,E5,Summary!$D$5:$D$241,">="&$A18,Summary!$D$5:$D$241,"<"&$A18+7)) -> 0 | F18: =IF(F5="","",COUNTIFS(Summary!$E$5:$E$241,F5,Summary!$D$5:$D$241,">="&$A18,Summary!$D$5:$D$241,"<"&$A18+7)) -> 0 | G18: =IF(G5="","",COUNTIFS(Summary!$E$5:$E$241,G5,Summary!$D$5:$D$241,">="&$A18,Summary!$D$5:$D$241,"<"&$A18+7)) -> 0 | H18: =IF(H5="","",COUNTIFS(Summary!$E$5:$E$241,H5,Summary!$D$5:$D$241,">="&$A18,Summary!$D$5:$D$241,"<"&$A18+7)) -> 1 | I18: =IF(I5="","",COUNTIFS(Summary!$E$5:$E$241,I5,Summary!$D$5:$D$241,">="&$A18,Summary!$D$5:$D$241,"<"&$A18+7)) -> 0 | J18: =IF(J5="","",COUNTIFS(Summary!$E$5:$E$241,J5,Summary!$D$5:$D$241,">="&$A18,Summary!$D$5:$D$241,"<"&$A18+7)) -> 0 | ... BF18: =IF(BF5="","",COUNTIFS(Summary!$E$5:$E$241,BF5,Summary!$D$5:$D$241,">="&$A18,Summary!$D$5:$D$241,"<"&$A18+7)) -> 0
A19: =A18+7 -> 46174 | B19: =TEXT(A19,"mmm d") -> Jun 1 | C19: =IF(C5="","",COUNTIFS(Summary!$E$5:$E$241,C5,Summary!$D$5:$D$241,">="&$A19,Summary!$D$5:$D$241,"<"&$A19+7)) -> 2 | D19: =IF(D5="","",COUNTIFS(Summary!$E$5:$E$241,D5,Summary!$D$5:$D$241,">="&$A19,Summary!$D$5:$D$241,"<"&$A19+7)) -> 0 | E19: =IF(E5="","",COUNTIFS(Summary!$E$5:$E$241,E5,Summary!$D$5:$D$241,">="&$A19,Summary!$D$5:$D$241,"<"&$A19+7)) -> 0 | F19: =IF(F5="","",COUNTIFS(Summary!$E$5:$E$241,F5,Summary!$D$5:$D$241,">="&$A19,Summary!$D$5:$D$241,"<"&$A19+7)) -> 0 | G19: =IF(G5="","",COUNTIFS(Summary!$E$5:$E$241,G5,Summary!$D$5:$D$241,">="&$A19,Summary!$D$5:$D$241,"<"&$A19+7)) -> 0 | H19: =IF(H5="","",COUNTIFS(Summary!$E$5:$E$241,H5,Summary!$D$5:$D$241,">="&$A19,Summary!$D$5:$D$241,"<"&$A19+7)) -> 0 | I19: =IF(I5="","",COUNTIFS(Summary!$E$5:$E$241,I5,Summary!$D$5:$D$241,">="&$A19,Summary!$D$5:$D$241,"<"&$A19+7)) -> 0 | J19: =IF(J5="","",COUNTIFS(Summary!$E$5:$E$241,J5,Summary!$D$5:$D$241,">="&$A19,Summary!$D$5:$D$241,"<"&$A19+7)) -> 0 | ... BF19: =IF(BF5="","",COUNTIFS(Summary!$E$5:$E$241,BF5,Summary!$D$5:$D$241,">="&$A19,Summary!$D$5:$D$241,"<"&$A19+7)) -> 0
A20: =A19+7 -> 46181 | B20: =TEXT(A20,"mmm d") -> Jun 8 | C20: =IF(C5="","",COUNTIFS(Summary!$E$5:$E$241,C5,Summary!$D$5:$D$241,">="&$A20,Summary!$D$5:$D$241,"<"&$A20+7)) -> 0 | D20: =IF(D5="","",COUNTIFS(Summary!$E$5:$E$241,D5,Summary!$D$5:$D$241,">="&$A20,Summary!$D$5:$D$241,"<"&$A20+7)) -> 0 | E20: =IF(E5="","",COUNTIFS(Summary!$E$5:$E$241,E5,Summary!$D$5:$D$241,">="&$A20,Summary!$D$5:$D$241,"<"&$A20+7)) -> 0 | F20: =IF(F5="","",COUNTIFS(Summary!$E$5:$E$241,F5,Summary!$D$5:$D$241,">="&$A20,Summary!$D$5:$D$241,"<"&$A20+7)) -> 0 | G20: =IF(G5="","",COUNTIFS(Summary!$E$5:$E$241,G5,Summary!$D$5:$D$241,">="&$A20,Summary!$D$5:$D$241,"<"&$A20+7)) -> 0 | H20: =IF(H5="","",COUNTIFS(Summary!$E$5:$E$241,H5,Summary!$D$5:$D$241,">="&$A20,Summary!$D$5:$D$241,"<"&$A20+7)) -> 0 | I20: =IF(I5="","",COUNTIFS(Summary!$E$5:$E$241,I5,Summary!$D$5:$D$241,">="&$A20,Summary!$D$5:$D$241,"<"&$A20+7)) -> 1 | J20: =IF(J5="","",COUNTIFS(Summary!$E$5:$E$241,J5,Summary!$D$5:$D$241,">="&$A20,Summary!$D$5:$D$241,"<"&$A20+7)) -> 0 | ... BF20: =IF(BF5="","",COUNTIFS(Summary!$E$5:$E$241,BF5,Summary!$D$5:$D$241,">="&$A20,Summary!$D$5:$D$241,"<"&$A20+7)) -> 0
A21: =A20+7 -> 46188 | B21: =TEXT(A21,"mmm d") -> Jun 15 | C21: =IF(C5="","",COUNTIFS(Summary!$E$5:$E$241,C5,Summary!$D$5:$D$241,">="&$A21,Summary!$D$5:$D$241,"<"&$A21+7)) -> 0 | D21: =IF(D5="","",COUNTIFS(Summary!$E$5:$E$241,D5,Summary!$D$5:$D$241,">="&$A21,Summary!$D$5:$D$241,"<"&$A21+7)) -> 1 | E21: =IF(E5="","",COUNTIFS(Summary!$E$5:$E$241,E5,Summary!$D$5:$D$241,">="&$A21,Summary!$D$5:$D$241,"<"&$A21+7)) -> 0 | F21: =IF(F5="","",COUNTIFS(Summary!$E$5:$E$241,F5,Summary!$D$5:$D$241,">="&$A21,Summary!$D$5:$D$241,"<"&$A21+7)) -> 0 | G21: =IF(G5="","",COUNTIFS(Summary!$E$5:$E$241,G5,Summary!$D$5:$D$241,">="&$A21,Summary!$D$5:$D$241,"<"&$A21+7)) -> 0 | H21: =IF(H5="","",COUNTIFS(Summary!$E$5:$E$241,H5,Summary!$D$5:$D$241,">="&$A21,Summary!$D$5:$D$241,"<"&$A21+7)) -> 1 | I21: =IF(I5="","",COUNTIFS(Summary!$E$5:$E$241,I5,Summary!$D$5:$D$241,">="&$A21,Summary!$D$5:$D$241,"<"&$A21+7)) -> 0 | J21: =IF(J5="","",COUNTIFS(Summary!$E$5:$E$241,J5,Summary!$D$5:$D$241,">="&$A21,Summary!$D$5:$D$241,"<"&$A21+7)) -> 0 | ... BF21: =IF(BF5="","",COUNTIFS(Summary!$E$5:$E$241,BF5,Summary!$D$5:$D$241,">="&$A21,Summary!$D$5:$D$241,"<"&$A21+7)) -> 0
A22: =A21+7 -> 46195 | B22: =TEXT(A22,"mmm d") -> Jun 22 | C22: =IF(C5="","",COUNTIFS(Summary!$E$5:$E$241,C5,Summary!$D$5:$D$241,">="&$A22,Summary!$D$5:$D$241,"<"&$A22+7)) -> 0 | D22: =IF(D5="","",COUNTIFS(Summary!$E$5:$E$241,D5,Summary!$D$5:$D$241,">="&$A22,Summary!$D$5:$D$241,"<"&$A22+7)) -> 0 | E22: =IF(E5="","",COUNTIFS(Summary!$E$5:$E$241,E5,Summary!$D$5:$D$241,">="&$A22,Summary!$D$5:$D$241,"<"&$A22+7)) -> 0 | F22: =IF(F5="","",COUNTIFS(Summary!$E$5:$E$241,F5,Summary!$D$5:$D$241,">="&$A22,Summary!$D$5:$D$241,"<"&$A22+7)) -> 0 | G22: =IF(G5="","",COUNTIFS(Summary!$E$5:$E$241,G5,Summary!$D$5:$D$241,">="&$A22,Summary!$D$5:$D$241,"<"&$A22+7)) -> 0 | H22: =IF(H5="","",COUNTIFS(Summary!$E$5:$E$241,H5,Summary!$D$5:$D$241,">="&$A22,Summary!$D$5:$D$241,"<"&$A22+7)) -> 0 | I22: =IF(I5="","",COUNTIFS(Summary!$E$5:$E$241,I5,Summary!$D$5:$D$241,">="&$A22,Summary!$D$5:$D$241,"<"&$A22+7)) -> 0 | J22: =IF(J5="","",COUNTIFS(Summary!$E$5:$E$241,J5,Summary!$D$5:$D$241,">="&$A22,Summary!$D$5:$D$241,"<"&$A22+7)) -> 0 | ... BF22: =IF(BF5="","",COUNTIFS(Summary!$E$5:$E$241,BF5,Summary!$D$5:$D$241,">="&$A22,Summary!$D$5:$D$241,"<"&$A22+7)) -> 0
A23: =A22+7 -> 46202 | B23: =TEXT(A23,"mmm d") -> Jun 29 | C23: =IF(C5="","",COUNTIFS(Summary!$E$5:$E$241,C5,Summary!$D$5:$D$241,">="&$A23,Summary!$D$5:$D$241,"<"&$A23+7)) -> 0 | D23: =IF(D5="","",COUNTIFS(Summary!$E$5:$E$241,D5,Summary!$D$5:$D$241,">="&$A23,Summary!$D$5:$D$241,"<"&$A23+7)) -> 0 | E23: =IF(E5="","",COUNTIFS(Summary!$E$5:$E$241,E5,Summary!$D$5:$D$241,">="&$A23,Summary!$D$5:$D$241,"<"&$A23+7)) -> 0 | F23: =IF(F5="","",COUNTIFS(Summary!$E$5:$E$241,F5,Summary!$D$5:$D$241,">="&$A23,Summary!$D$5:$D$241,"<"&$A23+7)) -> 0 | G23: =IF(G5="","",COUNTIFS(Summary!$E$5:$E$241,G5,Summary!$D$5:$D$241,">="&$A23,Summary!$D$5:$D$241,"<"&$A23+7)) -> 1 | H23: =IF(H5="","",COUNTIFS(Summary!$E$5:$E$241,H5,Summary!$D$5:$D$241,">="&$A23,Summary!$D$5:$D$241,"<"&$A23+7)) -> 0 | I23: =IF(I5="","",COUNTIFS(Summary!$E$5:$E$241,I5,Summary!$D$5:$D$241,">="&$A23,Summary!$D$5:$D$241,"<"&$A23+7)) -> 0 | J23: =IF(J5="","",COUNTIFS(Summary!$E$5:$E$241,J5,Summary!$D$5:$D$241,">="&$A23,Summary!$D$5:$D$241,"<"&$A23+7)) -> 0 | ... BF23: =IF(BF5="","",COUNTIFS(Summary!$E$5:$E$241,BF5,Summary!$D$5:$D$241,">="&$A23,Summary!$D$5:$D$241,"<"&$A23+7)) -> 0
A24: =A23+7 -> 46209 | B24: =TEXT(A24,"mmm d") -> Jul 6 | C24: =IF(C5="","",COUNTIFS(Summary!$E$5:$E$241,C5,Summary!$D$5:$D$241,">="&$A24,Summary!$D$5:$D$241,"<"&$A24+7)) -> 0 | D24: =IF(D5="","",COUNTIFS(Summary!$E$5:$E$241,D5,Summary!$D$5:$D$241,">="&$A24,Summary!$D$5:$D$241,"<"&$A24+7)) -> 0 | E24: =IF(E5="","",COUNTIFS(Summary!$E$5:$E$241,E5,Summary!$D$5:$D$241,">="&$A24,Summary!$D$5:$D$241,"<"&$A24+7)) -> 0 | F24: =IF(F5="","",COUNTIFS(Summary!$E$5:$E$241,F5,Summary!$D$5:$D$241,">="&$A24,Summary!$D$5:$D$241,"<"&$A24+7)) -> 0 | G24: =IF(G5="","",COUNTIFS(Summary!$E$5:$E$241,G5,Summary!$D$5:$D$241,">="&$A24,Summary!$D$5:$D$241,"<"&$A24+7)) -> 0 | H24: =IF(H5="","",COUNTIFS(Summary!$E$5:$E$241,H5,Summary!$D$5:$D$241,">="&$A24,Summary!$D$5:$D$241,"<"&$A24+7)) -> 1 | I24: =IF(I5="","",COUNTIFS(Summary!$E$5:$E$241,I5,Summary!$D$5:$D$241,">="&$A24,Summary!$D$5:$D$241,"<"&$A24+7)) -> 0 | J24: =IF(J5="","",COUNTIFS(Summary!$E$5:$E$241,J5,Summary!$D$5:$D$241,">="&$A24,Summary!$D$5:$D$241,"<"&$A24+7)) -> 1 | ... BF24: =IF(BF5="","",COUNTIFS(Summary!$E$5:$E$241,BF5,Summary!$D$5:$D$241,">="&$A24,Summary!$D$5:$D$241,"<"&$A24+7)) -> 0
A25: =A24+7 -> 46216 | B25: =TEXT(A25,"mmm d") -> Jul 13 | C25: =IF(C5="","",COUNTIFS(Summary!$E$5:$E$241,C5,Summary!$D$5:$D$241,">="&$A25,Summary!$D$5:$D$241,"<"&$A25+7)) -> 0 | D25: =IF(D5="","",COUNTIFS(Summary!$E$5:$E$241,D5,Summary!$D$5:$D$241,">="&$A25,Summary!$D$5:$D$241,"<"&$A25+7)) -> 0 | E25: =IF(E5="","",COUNTIFS(Summary!$E$5:$E$241,E5,Summary!$D$5:$D$241,">="&$A25,Summary!$D$5:$D$241,"<"&$A25+7)) -> 0 | F25: =IF(F5="","",COUNTIFS(Summary!$E$5:$E$241,F5,Summary!$D$5:$D$241,">="&$A25,Summary!$D$5:$D$241,"<"&$A25+7)) -> 0 | G25: =IF(G5="","",COUNTIFS(Summary!$E$5:$E$241,G5,Summary!$D$5:$D$241,">="&$A25,Summary!$D$5:$D$241,"<"&$A25+7)) -> 0 | H25: =IF(H5="","",COUNTIFS(Summary!$E$5:$E$241,H5,Summary!$D$5:$D$241,">="&$A25,Summary!$D$5:$D$241,"<"&$A25+7)) -> 0 | I25: =IF(I5="","",COUNTIFS(Summary!$E$5:$E$241,I5,Summary!$D$5:$D$241,">="&$A25,Summary!$D$5:$D$241,"<"&$A25+7)) -> 0 | J25: =IF(J5="","",COUNTIFS(Summary!$E$5:$E$241,J5,Summary!$D$5:$D$241,">="&$A25,Summary!$D$5:$D$241,"<"&$A25+7)) -> 0 | ... BF25: =IF(BF5="","",COUNTIFS(Summary!$E$5:$E$241,BF5,Summary!$D$5:$D$241,">="&$A25,Summary!$D$5:$D$241,"<"&$A25+7)) -> 0
A26: =A25+7 -> 46223 | B26: =TEXT(A26,"mmm d") -> Jul 20 | C26: =IF(C5="","",COUNTIFS(Summary!$E$5:$E$241,C5,Summary!$D$5:$D$241,">="&$A26,Summary!$D$5:$D$241,"<"&$A26+7)) -> 0 | D26: =IF(D5="","",COUNTIFS(Summary!$E$5:$E$241,D5,Summary!$D$5:$D$241,">="&$A26,Summary!$D$5:$D$241,"<"&$A26+7)) -> 0 | E26: =IF(E5="","",COUNTIFS(Summary!$E$5:$E$241,E5,Summary!$D$5:$D$241,">="&$A26,Summary!$D$5:$D$241,"<"&$A26+7)) -> 0 | F26: =IF(F5="","",COUNTIFS(Summary!$E$5:$E$241,F5,Summary!$D$5:$D$241,">="&$A26,Summary!$D$5:$D$241,"<"&$A26+7)) -> 0 | G26: =IF(G5="","",COUNTIFS(Summary!$E$5:$E$241,G5,Summary!$D$5:$D$241,">="&$A26,Summary!$D$5:$D$241,"<"&$A26+7)) -> 0 | H26: =IF(H5="","",COUNTIFS(Summary!$E$5:$E$241,H5,Summary!$D$5:$D$241,">="&$A26,Summary!$D$5:$D$241,"<"&$A26+7)) -> 0 | I26: =IF(I5="","",COUNTIFS(Summary!$E$5:$E$241,I5,Summary!$D$5:$D$241,">="&$A26,Summary!$D$5:$D$241,"<"&$A26+7)) -> 0 | J26: =IF(J5="","",COUNTIFS(Summary!$E$5:$E$241,J5,Summary!$D$5:$D$241,">="&$A26,Summary!$D$5:$D$241,"<"&$A26+7)) -> 0 | ... BF26: =IF(BF5="","",COUNTIFS(Summary!$E$5:$E$241,BF5,Summary!$D$5:$D$241,">="&$A26,Summary!$D$5:$D$241,"<"&$A26+7)) -> 0
A27: =A26+7 -> 46230 | B27: =TEXT(A27,"mmm d") -> Jul 27 | C27: =IF(C5="","",COUNTIFS(Summary!$E$5:$E$241,C5,Summary!$D$5:$D$241,">="&$A27,Summary!$D$5:$D$241,"<"&$A27+7)) -> 0 | D27: =IF(D5="","",COUNTIFS(Summary!$E$5:$E$241,D5,Summary!$D$5:$D$241,">="&$A27,Summary!$D$5:$D$241,"<"&$A27+7)) -> 0 | E27: =IF(E5="","",COUNTIFS(Summary!$E$5:$E$241,E5,Summary!$D$5:$D$241,">="&$A27,Summary!$D$5:$D$241,"<"&$A27+7)) -> 0 | F27: =IF(F5="","",COUNTIFS(Summary!$E$5:$E$241,F5,Summary!$D$5:$D$241,">="&$A27,Summary!$D$5:$D$241,"<"&$A27+7)) -> 0 | G27: =IF(G5="","",COUNTIFS(Summary!$E$5:$E$241,G5,Summary!$D$5:$D$241,">="&$A27,Summary!$D$5:$D$241,"<"&$A27+7)) -> 0 | H27: =IF(H5="","",COUNTIFS(Summary!$E$5:$E$241,H5,Summary!$D$5:$D$241,">="&$A27,Summary!$D$5:$D$241,"<"&$A27+7)) -> 0 | I27: =IF(I5="","",COUNTIFS(Summary!$E$5:$E$241,I5,Summary!$D$5:$D$241,">="&$A27,Summary!$D$5:$D$241,"<"&$A27+7)) -> 0 | J27: =IF(J5="","",COUNTIFS(Summary!$E$5:$E$241,J5,Summary!$D$5:$D$241,">="&$A27,Summary!$D$5:$D$241,"<"&$A27+7)) -> 0 | ... BF27: =IF(BF5="","",COUNTIFS(Summary!$E$5:$E$241,BF5,Summary!$D$5:$D$241,">="&$A27,Summary!$D$5:$D$241,"<"&$A27+7)) -> 0
A28: =A27+7 -> 46237 | B28: =TEXT(A28,"mmm d") -> Aug 3 | C28: =IF(C5="","",COUNTIFS(Summary!$E$5:$E$241,C5,Summary!$D$5:$D$241,">="&$A28,Summary!$D$5:$D$241,"<"&$A28+7)) -> 0 | D28: =IF(D5="","",COUNTIFS(Summary!$E$5:$E$241,D5,Summary!$D$5:$D$241,">="&$A28,Summary!$D$5:$D$241,"<"&$A28+7)) -> 0 | E28: =IF(E5="","",COUNTIFS(Summary!$E$5:$E$241,E5,Summary!$D$5:$D$241,">="&$A28,Summary!$D$5:$D$241,"<"&$A28+7)) -> 0 | F28: =IF(F5="","",COUNTIFS(Summary!$E$5:$E$241,F5,Summary!$D$5:$D$241,">="&$A28,Summary!$D$5:$D$241,"<"&$A28+7)) -> 0 | G28: =IF(G5="","",COUNTIFS(Summary!$E$5:$E$241,G5,Summary!$D$5:$D$241,">="&$A28,Summary!$D$5:$D$241,"<"&$A28+7)) -> 0 | H28: =IF(H5="","",COUNTIFS(Summary!$E$5:$E$241,H5,Summary!$D$5:$D$241,">="&$A28,Summary!$D$5:$D$241,"<"&$A28+7)) -> 0 | I28: =IF(I5="","",COUNTIFS(Summary!$E$5:$E$241,I5,Summary!$D$5:$D$241,">="&$A28,Summary!$D$5:$D$241,"<"&$A28+7)) -> 0 | J28: =IF(J5="","",COUNTIFS(Summary!$E$5:$E$241,J5,Summary!$D$5:$D$241,">="&$A28,Summary!$D$5:$D$241,"<"&$A28+7)) -> 0 | ... BF28: =IF(BF5="","",COUNTIFS(Summary!$E$5:$E$241,BF5,Summary!$D$5:$D$241,">="&$A28,Summary!$D$5:$D$241,"<"&$A28+7)) -> 0
A29: =A28+7 -> 46244 | B29: =TEXT(A29,"mmm d") -> Aug 10 | C29: =IF(C5="","",COUNTIFS(Summary!$E$5:$E$241,C5,Summary!$D$5:$D$241,">="&$A29,Summary!$D$5:$D$241,"<"&$A29+7)) -> 0 | D29: =IF(D5="","",COUNTIFS(Summary!$E$5:$E$241,D5,Summary!$D$5:$D$241,">="&$A29,Summary!$D$5:$D$241,"<"&$A29+7)) -> 0 | E29: =IF(E5="","",COUNTIFS(Summary!$E$5:$E$241,E5,Summary!$D$5:$D$241,">="&$A29,Summary!$D$5:$D$241,"<"&$A29+7)) -> 0 | F29: =IF(F5="","",COUNTIFS(Summary!$E$5:$E$241,F5,Summary!$D$5:$D$241,">="&$A29,Summary!$D$5:$D$241,"<"&$A29+7)) -> 0 | G29: =IF(G5="","",COUNTIFS(Summary!$E$5:$E$241,G5,Summary!$D$5:$D$241,">="&$A29,Summary!$D$5:$D$241,"<"&$A29+7)) -> 0 | H29: =IF(H5="","",COUNTIFS(Summary!$E$5:$E$241,H5,Summary!$D$5:$D$241,">="&$A29,Summary!$D$5:$D$241,"<"&$A29+7)) -> 0 | I29: =IF(I5="","",COUNTIFS(Summary!$E$5:$E$241,I5,Summary!$D$5:$D$241,">="&$A29,Summary!$D$5:$D$241,"<"&$A29+7)) -> 0 | J29: =IF(J5="","",COUNTIFS(Summary!$E$5:$E$241,J5,Summary!$D$5:$D$241,">="&$A29,Summary!$D$5:$D$241,"<"&$A29+7)) -> 0 | ... BF29: =IF(BF5="","",COUNTIFS(Summary!$E$5:$E$241,BF5,Summary!$D$5:$D$241,">="&$A29,Summary!$D$5:$D$241,"<"&$A29+7)) -> 0
A30: =A29+7 -> 46251 | B30: =TEXT(A30,"mmm d") -> Aug 17 | C30: =IF(C5="","",COUNTIFS(Summary!$E$5:$E$241,C5,Summary!$D$5:$D$241,">="&$A30,Summary!$D$5:$D$241,"<"&$A30+7)) -> 0 | D30: =IF(D5="","",COUNTIFS(Summary!$E$5:$E$241,D5,Summary!$D$5:$D$241,">="&$A30,Summary!$D$5:$D$241,"<"&$A30+7)) -> 0 | E30: =IF(E5="","",COUNTIFS(Summary!$E$5:$E$241,E5,Summary!$D$5:$D$241,">="&$A30,Summary!$D$5:$D$241,"<"&$A30+7)) -> 0 | F30: =IF(F5="","",COUNTIFS(Summary!$E$5:$E$241,F5,Summary!$D$5:$D$241,">="&$A30,Summary!$D$5:$D$241,"<"&$A30+7)) -> 0 | G30: =IF(G5="","",COUNTIFS(Summary!$E$5:$E$241,G5,Summary!$D$5:$D$241,">="&$A30,Summary!$D$5:$D$241,"<"&$A30+7)) -> 0 | H30: =IF(H5="","",COUNTIFS(Summary!$E$5:$E$241,H5,Summary!$D$5:$D$241,">="&$A30,Summary!$D$5:$D$241,"<"&$A30+7)) -> 0 | I30: =IF(I5="","",COUNTIFS(Summary!$E$5:$E$241,I5,Summary!$D$5:$D$241,">="&$A30,Summary!$D$5:$D$241,"<"&$A30+7)) -> 0 | J30: =IF(J5="","",COUNTIFS(Summary!$E$5:$E$241,J5,Summary!$D$5:$D$241,">="&$A30,Summary!$D$5:$D$241,"<"&$A30+7)) -> 0 | ... BF30: =IF(BF5="","",COUNTIFS(Summary!$E$5:$E$241,BF5,Summary!$D$5:$D$241,">="&$A30,Summary!$D$5:$D$241,"<"&$A30+7)) -> 0
A31: =A30+7 -> 46258 | B31: =TEXT(A31,"mmm d") -> Aug 24 | C31: =IF(C5="","",COUNTIFS(Summary!$E$5:$E$241,C5,Summary!$D$5:$D$241,">="&$A31,Summary!$D$5:$D$241,"<"&$A31+7)) -> 0 | D31: =IF(D5="","",COUNTIFS(Summary!$E$5:$E$241,D5,Summary!$D$5:$D$241,">="&$A31,Summary!$D$5:$D$241,"<"&$A31+7)) -> 0 | E31: =IF(E5="","",COUNTIFS(Summary!$E$5:$E$241,E5,Summary!$D$5:$D$241,">="&$A31,Summary!$D$5:$D$241,"<"&$A31+7)) -> 0 | F31: =IF(F5="","",COUNTIFS(Summary!$E$5:$E$241,F5,Summary!$D$5:$D$241,">="&$A31,Summary!$D$5:$D$241,"<"&$A31+7)) -> 0 | G31: =IF(G5="","",COUNTIFS(Summary!$E$5:$E$241,G5,Summary!$D$5:$D$241,">="&$A31,Summary!$D$5:$D$241,"<"&$A31+7)) -> 0 | H31: =IF(H5="","",COUNTIFS(Summary!$E$5:$E$241,H5,Summary!$D$5:$D$241,">="&$A31,Summary!$D$5:$D$241,"<"&$A31+7)) -> 0 | I31: =IF(I5="","",COUNTIFS(Summary!$E$5:$E$241,I5,Summary!$D$5:$D$241,">="&$A31,Summary!$D$5:$D$241,"<"&$A31+7)) -> 0 | J31: =IF(J5="","",COUNTIFS(Summary!$E$5:$E$241,J5,Summary!$D$5:$D$241,">="&$A31,Summary!$D$5:$D$241,"<"&$A31+7)) -> 0 | ... BF31: =IF(BF5="","",COUNTIFS(Summary!$E$5:$E$241,BF5,Summary!$D$5:$D$241,">="&$A31,Summary!$D$5:$D$241,"<"&$A31+7)) -> 0
A32: =A31+7 -> 46265 | B32: =TEXT(A32,"mmm d") -> Aug 31 | C32: =IF(C5="","",COUNTIFS(Summary!$E$5:$E$241,C5,Summary!$D$5:$D$241,">="&$A32,Summary!$D$5:$D$241,"<"&$A32+7)) -> 0 | D32: =IF(D5="","",COUNTIFS(Summary!$E$5:$E$241,D5,Summary!$D$5:$D$241,">="&$A32,Summary!$D$5:$D$241,"<"&$A32+7)) -> 0 | E32: =IF(E5="","",COUNTIFS(Summary!$E$5:$E$241,E5,Summary!$D$5:$D$241,">="&$A32,Summary!$D$5:$D$241,"<"&$A32+7)) -> 0 | F32: =IF(F5="","",COUNTIFS(Summary!$E$5:$E$241,F5,Summary!$D$5:$D$241,">="&$A32,Summary!$D$5:$D$241,"<"&$A32+7)) -> 0 | G32: =IF(G5="","",COUNTIFS(Summary!$E$5:$E$241,G5,Summary!$D$5:$D$241,">="&$A32,Summary!$D$5:$D$241,"<"&$A32+7)) -> 0 | H32: =IF(H5="","",COUNTIFS(Summary!$E$5:$E$241,H5,Summary!$D$5:$D$241,">="&$A32,Summary!$D$5:$D$241,"<"&$A32+7)) -> 0 | I32: =IF(I5="","",COUNTIFS(Summary!$E$5:$E$241,I5,Summary!$D$5:$D$241,">="&$A32,Summary!$D$5:$D$241,"<"&$A32+7)) -> 0 | J32: =IF(J5="","",COUNTIFS(Summary!$E$5:$E$241,J5,Summary!$D$5:$D$241,">="&$A32,Summary!$D$5:$D$241,"<"&$A32+7)) -> 0 | ... BF32: =IF(BF5="","",COUNTIFS(Summary!$E$5:$E$241,BF5,Summary!$D$5:$D$241,">="&$A32,Summary!$D$5:$D$241,"<"&$A32+7)) -> 0
A33: =A32+7 -> 46272 | B33: =TEXT(A33,"mmm d") -> Sep 7 | C33: =IF(C5="","",COUNTIFS(Summary!$E$5:$E$241,C5,Summary!$D$5:$D$241,">="&$A33,Summary!$D$5:$D$241,"<"&$A33+7)) -> 0 | D33: =IF(D5="","",COUNTIFS(Summary!$E$5:$E$241,D5,Summary!$D$5:$D$241,">="&$A33,Summary!$D$5:$D$241,"<"&$A33+7)) -> 0 | E33: =IF(E5="","",COUNTIFS(Summary!$E$5:$E$241,E5,Summary!$D$5:$D$241,">="&$A33,Summary!$D$5:$D$241,"<"&$A33+7)) -> 0 | F33: =IF(F5="","",COUNTIFS(Summary!$E$5:$E$241,F5,Summary!$D$5:$D$241,">="&$A33,Summary!$D$5:$D$241,"<"&$A33+7)) -> 0 | G33: =IF(G5="","",COUNTIFS(Summary!$E$5:$E$241,G5,Summary!$D$5:$D$241,">="&$A33,Summary!$D$5:$D$241,"<"&$A33+7)) -> 0 | H33: =IF(H5="","",COUNTIFS(Summary!$E$5:$E$241,H5,Summary!$D$5:$D$241,">="&$A33,Summary!$D$5:$D$241,"<"&$A33+7)) -> 0 | I33: =IF(I5="","",COUNTIFS(Summary!$E$5:$E$241,I5,Summary!$D$5:$D$241,">="&$A33,Summary!$D$5:$D$241,"<"&$A33+7)) -> 0 | J33: =IF(J5="","",COUNTIFS(Summary!$E$5:$E$241,J5,Summary!$D$5:$D$241,">="&$A33,Summary!$D$5:$D$241,"<"&$A33+7)) -> 0 | ... BF33: =IF(BF5="","",COUNTIFS(Summary!$E$5:$E$241,BF5,Summary!$D$5:$D$241,">="&$A33,Summary!$D$5:$D$241,"<"&$A33+7)) -> 0
